Workbook

Sheet ReadMe
B2: FRTB IMA — Full Revaluation PnL Vectors for Expected Shortfall (ES)
B3: Illustrative workbook — trade 123456, valuation date 7/23/2026. Demonstrates the mechanics of a full-revaluation Stressed PnL vector: PnL = StressedNPV − BaseNPV, built curve-by-curve and then combined cross-risk-class.
B5: Purpose
B6: Illustrate, end to end, how a full-reval ES PnL vector is constructed: base curve objects → shocked curve objects (10 scenarios, stress date 20-Nov-2008) → base/stressed NPV via full reval → PnL vector, both cross-risk-class and isolated by risk class (IR / Credit / FX).
B8: Tabs
B9: Trade_Info | Base_Curves | Curve_Shocks_bps | Curve_Shift_Illustration | Shocked_Curves_DF | SABR_Base | SABR_Shocks | SABR_Shocked | NPV_Engine | PnL_Summary
B11: Curve shift mechanic
B12: gxlCurveDiscShift is simulated with a sequential (cascading) bootstrap: the simple forward rate implied by the BASE curve between consecutive tenors is bumped by the scenario shock (bps), and the SHOCKED discount factor for tenor i is solved from the SHOCKED discount factor at tenor i-1 (not the base one). 3M is bumped first; 6M relies on the bumped 3M; and so on to 30Y — exactly mirroring the described gxlCurveDiscShift behaviour.
B14: SABR surface mechanic
B15: Each of ATM / RHO / NU is a 10x10 grid (expiry x tenor). Each scenario applies a parameter-level shock size to every grid point, scaled by a per-cell Sensitivity Factor grid (captures the typical stress-period pattern of larger moves at short expiries/tenors). The result is a full shocked vol surface per parameter per scenario, exactly as gxlCurveDiscShift-style functions return a shocked object for curves.
B17: NPV engine
B18: NPV is an ILLUSTRATIVE simplified full-reval pricer (not a production pricer) that consumes: SOFR/ESTRN discount factors (IR discounting), the SABR ATM grid point matching the trade's expiry/tenor (IR_VOL / optionality), Treasury/Agency_FNMA/Eur_Govt discount factors (Credit spread proxy), and the EURUSD curve (FX discount/forward proxy). Base NPV = pricer with ALL curves at BASE. Stressed NPV = pricer with the relevant curve set SHOCKED for scenario s.
... B27: All curve levels, shock sizes and SABR parameters are illustrative placeholder assumptions chosen for demonstration purposes only — they are not calibrated to actual 20-Nov-2008 market data and this is not a production pricing/risk engine.

Sheet Trade_Info
A1: Trade & Valuation Info
A3: Trade ID | B3: 123456
A4: Valuation Date | B4: 7/23/2026
A5: Stress / Shock anchor date | B5: 11/20/2008
A6: Number of scenarios | B6: 10
A7: Notional (USD) | B7: 10000000
A8: Product | B8: EUR-underlying payer swaption vs USD-collateral discounting
A9: Representative discounting tenor | B9: 1Y
A10: Representative SABR grid point (Expiry x Tenor) | B10: 1Y x 10Y
A12: Curve list, MDO used, and risk-class mapping
A13: Curve (MDO) | B13: Risk Class | C13: Notes
A14: Agency_FNMA | B14: Credit | C14: Credit — GSE/agency spread curve
A15: Eur_Govt | B15: Credit | C15: Credit — EUR sovereign curve
A16: SOFR | B16: IR | C16: IR_RATE — USD OIS/SOFR discounting curve
A17: Treasury | B17: Credit | C17: Credit — US Treasury (sovereign benchmark) curve
A18: Sabr_Swaption | B18: IR | C18: IR_VOL — SABR surface (ATM, RHO, NU); handled on SABR_* tabs
A19: EURUSD | B19: FX | C19: FX_RATE — EUR/USD FX curve
A20: ESTRN | B20: IR | C20: IR — EUR €STR discounting curve

Sheet Base_Curves
A1: Base Curve Objects — Discount Factors (as of 7/23/2026)
A3: Curve | B3: Risk Class | C3: 3M | D3: 6M | E3: 1Y | F3: 2Y | G3: 3Y | H3: 5Y | I3: 10Y | J3: 20Y | K3: 30Y
A4: Tenor Date | C4: 10/23/2026 | D4: 1/23/2027 | E4: 7/23/2027 | F4: 7/23/2028 | G4: 7/23/2029 | H4: 7/23/2031 | I4: 7/23/2036 | J4: 7/23/2046 | K4: 7/23/2056
A5: Year Frac (t) | C5: 0.25 | D5: 0.5 | E5: 1 | F5: 2 | G5: 3 | H5: 5 | I5: 10 | J5: 20 | K5: 30
A6: SOFR | B6: IR | C6: 0.989298 | D6: 0.978693 | E6: 0.957768 | F6: 0.917044 | G6: 0.877788 | H6: 0.803523 | I6: 0.640824 | J6: 0.410656 | K6: 0.263158
A7: ESTRN | B7: IR | C7: 0.992271 | D7: 0.984583 | E7: 0.96933 | F7: 0.939319 | G7: 0.909964 | H7: 0.85321 | I7: 0.722527 | J7: 0.522046 | K7: 0.377192
A8: Treasury | B8: Credit | C8: 0.989546 | D8: 0.979182 | E8: 0.958726 | F8: 0.91888 | G8: 0.880425 | H8: 0.80755 | I8: 0.647265 | J8: 0.418952 | K8: 0.271173
A9: Agency_FNMA | B9: Credit | C9: 0.988557 | D9: 0.977226 | E9: 0.954899 | F9: 0.911558 | G9: 0.869924 | H9: 0.79156 | I9: 0.621885 | J9: 0.386741 | K9: 0.240508
A10: Eur_Govt | B10: Credit | C10: 0.991775 | D10: 0.983598 | E10: 0.967393 | F10: 0.935569 | G10: 0.904521 | H10: 0.84472 | I10: 0.70822 | J10: 0.501576 | K10: 0.355226
A11: EURUSD | B11: FX | C11: 0.990041 | D11: 0.980162 | E11: 0.960645 | F11: 0.922563 | G11: 0.885724 | H11: 0.815666 | I11: 0.66034 | J11: 0.436049 | K11: 0.287941
A13: Note: base DF values are illustrative placeholder inputs (blue), not calibrated to a real curve build.

Sheet Curve_Shocks_bps
A1: Shock Vectors — Forward-Rate Shock (bps) per Tenor, 10 Scenarios, Stress Anchor 20-Nov-2008
A3: Scenario 1 | C3: 3M | D3: 6M | E3: 1Y | F3: 2Y | G3: 3Y | H3: 5Y | I3: 10Y | J3: 20Y | K3: 30Y
A4: SOFR | B4: IR | C4: -40.9 | D4: 34.3 | E4: 31.4 | F4: -21.7 | G4: -13 | H4: 6.1 | I4: 2.9 | J4: 2.1 | K4: 1.2
A5: ESTRN | B5: IR | C5: -35.5 | D5: 31.9 | E5: 24.1 | F5: 18.3 | G5: -8.9 | H5: 5.7 | I5: 2.8 | J5: 1.3 | K5: 0.6
A6: Treasury | B6: Credit | C6: 49.9 | D6: 46.7 | E6: -34.6 | F6: 21.6 | G6: 13 | H6: 7.2 | I6: 4.1 | J6: 1.9 | K6: 1.2
A7: Agency_FNMA | B7: Credit | C7: 75.2 | D7: 60.7 | E7: 51.5 | F7: 44.3 | G7: 26.8 | H7: 15.7 | I7: -6.2 | J7: 3.8 | K7: 2.5
A8: Eur_Govt | B8: Credit | C8: 64.8 | D8: 54.8 | E8: 47.2 | F8: 28 | G8: 18.8 | H8: 10.1 | I8: 5.2 | J8: 3 | K8: -1.8
A9: EURUSD | B9: FX | C9: 23.9 | D9: 26.9 | E9: 18.9 | F9: 16.3 | G9: 11 | H9: 5.2 | I9: 3.4 | J9: 1.9 | K9: 1.2
A11: Scenario 2 | C11: 3M | D11: 6M | E11: 1Y | F11: 2Y | G11: 3Y | H11: 5Y | I11: 10Y | J11: 20Y | K11: 30Y
A12: SOFR | B12: IR | C12: 45.8 | D12: 45.7 | E12: 34.7 | F12: 25.1 | G12: 14.8 | H12: 7.9 | I12: 4.1 | J12: 2.4 | K12: 1.4
A13: ESTRN | B13: IR | C13: 34.7 | D13: 37.4 | E13: -28.1 | F13: 20.8 | G13: 10.6 | H13: 5.6 | I13: -3.3 | J13: 1.5 | K13: 0.7
A14: Treasury | B14: Credit | C14: 53 | D14: 50.5 | E14: 36.1 | F14: 29.7 | G14: 16.7 | H14: 8.5 | I14: 4.5 | J14: 2.2 | K14: 1.4
A15: Agency_FNMA | B15: Credit | C15: 79.9 | D15: -82.8 | E15: 61.9 | F15: -43.5 | G15: 33.6 | H15: 16.8 | I15: 8.2 | J15: 4.2 | K15: 3
A16: Eur_Govt | B16: Credit | C16: 72.6 | D16: -67.8 | E16: 49 | F16: 37.3 | G16: 20.2 | H16: 11.4 | I16: 5.8 | J16: 3 | K16: -2.3
A17: EURUSD | B17: FX | C17: 34 | D17: 32.1 | E17: 26.4 | F17: 16.9 | G17: -11.3 | H17: 6.8 | I17: 3.7 | J17: 2.3 | K17: 1.7
A19: Scenario 3 | C19: 3M | D19: 6M | E19: 1Y | F19: 2Y | G19: 3Y | H19: 5Y | I19: 10Y | J19: 20Y | K19: 30Y
A20: SOFR | B20: IR | C20: 53.3 | D20: 45.4 | E20: 43 | F20: 26.6 | G20: 16.2 | H20: 8.8 | I20: 4.1 | J20: 2.4 | K20: 1.8
A21: ESTRN | B21: IR | C21: -41.9 | D21: 42.4 | E21: 34 | F21: 21.7 | G21: 13.3 | H21: 6.7 | I21: 3.4 | J21: 1.8 | K21: 0.9
A22: Treasury | B22: Credit | C22: 56.8 | D22: 62.4 | E22: 40.6 | F22: 29.5 | G22: 20.7 | H22: 10.3 | I22: 5.6 | J22: 2.7 | K22: -1.8
A23: Agency_FNMA | B23: Credit | C23: 102.4 | D23: 90.6 | E23: -69.8 | F23: 49 | G23: 33.7 | H23: 20.1 | I23: 9 | J23: 5.3 | K23: -3.7
A24: Eur_Govt | B24: Credit | C24: 78.1 | D24: 64 | E24: 58.6 | F24: 41.3 | G24: -24.3 | H24: 12.2 | I24: 7.6 | J24: 3.7 | K24: -2.5
A25: EURUSD | B25: FX | C25: 34 | D25: 35.2 | E25: 30.2 | F25: -18.5 | G25: 13.9 | H25: 7.8 | I25: 4.1 | J25: 2.8 | K25: 1.9
A27: Scenario 4 | C27: 3M | D27: 6M | E27: 1Y | F27: 2Y | G27: 3Y | H27: 5Y | I27: 10Y | J27: 20Y | K27: 30Y
A28: SOFR | B28: IR | C28: 54.8 | D28: 53 | E28: 46.7 | F28: 31.2 | G28: -20.7 | H28: 10.5 | I28: 4.7 | J28: 3 | K28: 2.1
A29: ESTRN | B29: IR | C29: 45.7 | D29: 43.3 | E29: 40.5 | F29: 25.3 | G29: 16 | H29: -8.5 | I29: 4.3 | J29: 2.1 | K29: 0.9
A30: Treasury | B30: Credit | C30: 71.9 | D30: 65.5 | E30: 48.6 | F30: 33.3 | G30: 20 | H30: 12 | I30: 6.2 | J30: -2.9 | K30: 2
A31: Agency_FNMA | B31: Credit | C31: 105.6 | D31: 102.5 | E31: 81.6 | F31: 58.5 | G31: 37.2 | H31: 23.3 | I31: 10.5 | J31: 5.7 | K31: 3.6
A32: Eur_Govt | B32: Credit | C32: 88.1 | D32: 81.2 | E32: 63.7 | F32: 44.4 | G32: 29 | H32: 13.9 | I32: 8.1 | J32: 4.2 | K32: 3.1
A33: EURUSD | B33: FX | C33: -37.7 | D33: 36.1 | E33: -33.5 | F33: 21.5 | G33: 14.1 | H33: 8.9 | I33: -5.1 | J33: 3.1 | K33: 1.9
A35: Scenario 5 | C35: 3M | D35: 6M | E35: 1Y | F35: 2Y | G35: 3Y | H35: 5Y | I35: 10Y | J35: 20Y | K35: 30Y
A36: SOFR | B36: IR | C36: 62.9 | D36: -60.7 | E36: 47.7 | F36: 32.8 | G36: 22.5 | H36: 11.2 | I36: 5.8 | J36: 3.4 | K36: 2.3
A37: ESTRN | B37: IR | C37: 58.2 | D37: 49.3 | E37: 40.3 | F37: 28.6 | G37: 16.8 | H37: 8.3 | I37: 4.3 | J37: -2.2 | K37: 1.1
A38: Treasury | B38: Credit | C38: -79.3 | D38: 70.5 | E38: 54.3 | F38: 38.1 | G38: 24.5 | H38: 13.9 | I38: -6.5 | J38: 3.2 | K38: 2.3
A39: Agency_FNMA | B39: Credit | C39: 119.6 | D39: 110.7 | E39: 89.7 | F39: -65.4 | G39: 43 | H39: 23.9 | I39: -10.9 | J39: -6.7 | K39: 4.3
A40: Eur_Govt | B40: Credit | C40: 92.2 | D40: 83.3 | E40: 66.8 | F40: 47.4 | G40: 32 | H40: 17.1 | I40: -8.5 | J40: 4.1 | K40: 3.5
A41: EURUSD | B41: FX | C41: 45 | D41: 42.7 | E41: 37.5 | F41: 22.5 | G41: 15.6 | H41: 10 | I41: 5.7 | J41: 3.1 | K41: -2.3
A43: Scenario 6 | C43: 3M | D43: 6M | E43: 1Y | F43: 2Y | G43: 3Y | H43: 5Y | I43: 10Y | J43: 20Y | K43: 30Y
A44: SOFR | B44: IR | C44: 75.7 | D44: -63.1 | E44: 53.1 | F44: 38.5 | G44: -24.9 | H44: 12.4 | I44: 5.7 | J44: 3.8 | K44: 2.3
A45: ESTRN | B45: IR | C45: 62.8 | D45: 53.9 | E45: 46 | F45: 31.6 | G45: 17.2 | H45: 9.9 | I45: 5 | J45: 2.5 | K45: 1.2
A46: Treasury | B46: Credit | C46: 85.1 | D46: 78 | E46: 58.6 | F46: -44.2 | G46: 28 | H46: 14.5 | I46: -7.1 | J46: 3.8 | K46: 2.3
A47: Agency_FNMA | B47: Credit | C47: 130.3 | D47: 124.2 | E47: 96.2 | F47: 68.6 | G47: 48.3 | H47: 27.3 | I47: 12.1 | J47: 6.9 | K47: 5
A48: Eur_Govt | B48: Credit | C48: 110.1 | D48: 97.2 | E48: 81.2 | F48: 55.9 | G48: -32.8 | H48: -17.4 | I48: 9.7 | J48: 4.6 | K48: 3.6
A49: EURUSD | B49: FX | C49: 51.5 | D49: -44.7 | E49: 37.2 | F49: -25.5 | G49: 18.2 | H49: 11.6 | I49: -6.2 | J49: 3.8 | K49: 2.5
A51: Scenario 7 | C51: 3M | D51: 6M | E51: 1Y | F51: 2Y | G51: 3Y | H51: 5Y | I51: 10Y | J51: 20Y | K51: 30Y
A52: SOFR | B52: IR | C52: 78.9 | D52: -69.8 | E52: 62.6 | F52: 41.1 | G52: 25 | H52: -12.5 | I52: 6.7 | J52: -4.2 | K52: 2.7
A53: ESTRN | B53: IR | C53: 68.3 | D53: 59.6 | E53: 49.8 | F53: 35 | G53: 20.1 | H53: 10.9 | I53: 5.1 | J53: 2.7 | K53: -1.3
A54: Treasury | B54: Credit | C54: 86.8 | D54: 86.8 | E54: 63.9 | F54: 47.3 | G54: 29.7 | H54: 16.4 | I54: 8.1 | J54: 3.9 | K54: 2.7
A55: Agency_FNMA | B55: Credit | C55: -150.9 | D55: 126.7 | E55: 115.6 | F55: -77.2 | G55: 54 | H55: 30.6 | I55: -13.2 | J55: 7.5 | K55: 5.2
A56: Eur_Govt | B56: Credit | C56: 112.9 | D56: 109.9 | E56: 90.5 | F56: 60.6 | G56: 34.9 | H56: 19.7 | I56: 11.1 | J56: 5.3 | K56: -4
A57: EURUSD | B57: FX | C57: 51.8 | D57: 51.2 | E57: 41.4 | F57: 28.3 | G57: 20.6 | H57: 11.8 | I57: 6.5 | J57: 3.9 | K57: 2.8
A59: Scenario 8 | C59: 3M | D59: 6M | E59: 1Y | F59: 2Y | G59: 3Y | H59: 5Y | I59: 10Y | J59: 20Y | K59: 30Y
A60: SOFR | B60: IR | C60: 86.2 | D60: 75.9 | E60: 66.2 | F60: 44.1 | G60: 28.8 | H60: 14.2 | I60: 6.8 | J60: 4.3 | K60: 2.8
A61: ESTRN | B61: IR | C61: -71.9 | D61: 67.9 | E61: -54.1 | F61: 37.1 | G61: 22 | H61: 11.1 | I61: 6 | J61: 2.9 | K61: 1.5
A62: Treasury | B62: Credit | C62: 104.3 | D62: 90.6 | E62: 70.8 | F62: 50.1 | G62: 30.7 | H62: 17.3 | I62: -8.6 | J62: 4.3 | K62: 2.9
A63: Agency_FNMA | B63: Credit | C63: 156.5 | D63: 138 | E63: 122.5 | F63: -88.4 | G63: 58.8 | H63: 32.6 | I63: 14.6 | J63: 9 | K63: 5.4
A64: Eur_Govt | B64: Credit | C64: 130 | D64: 119.2 | E64: 93.2 | F64: 66 | G64: 40.7 | H64: 21.4 | I64: 11.2 | J64: 5.8 | K64: 4.5
A65: EURUSD | B65: FX | C65: 56.4 | D65: 55.7 | E65: -47.7 | F65: 29.9 | G65: 22.5 | H65: 13.2 | I65: 6.8 | J65: 4.5 | K65: 2.9
A67: Scenario 9 | C67: 3M | D67: 6M | E67: 1Y | F67: 2Y | G67: 3Y | H67: 5Y | I67: 10Y | J67: 20Y | K67: 30Y
A68: SOFR | B68: IR | C68: 88 | D68: 82.9 | E68: 66.7 | F68: 46.5 | G68: -29.7 | H68: 16 | I68: 7.5 | J68: 4.4 | K68: 3
A69: ESTRN | B69: IR | C69: 73.1 | D69: 72.2 | E69: 56.4 | F69: 37.9 | G69: 23.4 | H69: 12 | I69: 6 | J69: 3.1 | K69: 1.6
A70: Treasury | B70: Credit | C70: 113.3 | D70: 105.1 | E70: 75.2 | F70: 54.9 | G70: 32.3 | H70: 18.5 | I70: 9 | J70: 4.7 | K70: 3.1
A71: Agency_FNMA | B71: Credit | C71: 172.5 | D71: 156.5 | E71: 132.6 | F71: 93.8 | G71: 61.2 | H71: -34.7 | I71: 15.1 | J71: -8.9 | K71: 6.2
A72: Eur_Govt | B72: Credit | C72: 139 | D72: 127.4 | E72: 103.5 | F72: 71.5 | G72: -42.4 | H72: -24.2 | I72: 12.9 | J72: 6.3 | K72: 4.8
A73: EURUSD | B73: FX | C73: 60.7 | D73: 55.6 | E73: 49 | F73: 34.5 | G73: 23.9 | H73: 13.3 | I73: 7.3 | J73: 4.6 | K73: -3
A75: Scenario 10 | C75: 3M | D75: 6M | E75: 1Y | F75: 2Y | G75: 3Y | H75: 5Y | I75: 10Y | J75: 20Y | K75: 30Y
A76: SOFR | B76: IR | C76: 102.1 | D76: 89 | E76: 71.7 | F76: 48.6 | G76: 31.7 | H76: 15.9 | I76: 8.4 | J76: 5.2 | K76: 3.4
A77: ESTRN | B77: IR | C77: -81.8 | D77: 74.2 | E77: -65.4 | F77: 40.7 | G77: 25.8 | H77: 12.7 | I77: 6.6 | J77: 3.3 | K77: -1.6
A78: Treasury | B78: Credit | C78: 119.4 | D78: 108.9 | E78: -83.3 | F78: 59.4 | G78: 35 | H78: 19 | I78: 9.6 | J78: 5.1 | K78: 3.2
A79: Agency_FNMA | B79: Credit | C79: 172.7 | D79: -159.3 | E79: 136.9 | F79: -100.5 | G79: 62.9 | H79: 35.4 | I79: -16 | J79: 10.1 | K79: 6.8
A80: Eur_Govt | B80: Credit | C80: 152.5 | D80: 127 | E80: -111.9 | F80: 76.3 | G80: 46.3 | H80: -25.9 | I80: 13.2 | J80: 6.7 | K80: -5.1
A81: EURUSD | B81: FX | C81: 63.3 | D81: 60.1 | E81: 53.5 | F81: 35.7 | G81: 24.8 | H81: -15 | I81: 8.4 | J81: 5 | K81: 3.4
A83: Shocks are hardcoded illustrative bps moves applied to forward rates (blue = raw input observations for the stress period).

Sheet Curve_Shift_Illustration
A1: gxlCurveDiscShift — Step-by-Step Illustration (Curve = SOFR, Scenario 1)
A2: Sequential / cascading bootstrap: forward rate is derived from BASE discount factors between consecutive tenors, bumped by the scenario shock (bps), then the SHOCKED discount factor is solved off the PRIOR SHOCKED discount factor (not the prior base one). 3M is shocked first and feeds into 6M, which feeds into 1Y, etc.
A4: Tenor | B4: t | C4: Base DF (prior) | D4: Base DF (current) | E4: Base Fwd Rate (simple, ann.) | F4: Shock (bps) | G4: Shocked Fwd Rate | H4: Shocked DF (current) | I4: Formula logic
A5: 3M | B5: 0.25 | C5: 1 | D5: =Base_Curves!C6 -> 0.989298 | E5: =(C5/D5-1)/(0.25-0) -> 0.043271087 | F5: =Curve_Shocks_bps!C4 -> -40.9 | G5: =E5+F5/10000 -> 0.039181087 | H5: =1/(1+G5*(0.25-0)) -> 0.99029974 | I5: Anchors at DF=1, t=0
A6: 6M | B6: 0.5 | C6: =Base_Curves!C6 -> 0.989298 | D6: =Base_Curves!D6 -> 0.978693 | E6: =(C6/D6-1)/(0.5-0.25) -> 0.04334352 | F6: =Curve_Shocks_bps!D4 -> 34.3 | G6: =E6+F6/10000 -> 0.04677352 | H6: =H5/(1+G6*(0.5-0.25)) -> 0.97885364 | I6: Uses SHOCKED DF from 3M (row above), not base
A7: 1Y | B7: 1 | C7: =Base_Curves!D6 -> 0.978693 | D7: =Base_Curves!E6 -> 0.957768 | E7: =(C7/D7-1)/(1-0.5) -> 0.043695342 | F7: =Curve_Shocks_bps!E4 -> 31.4 | G7: =E7+F7/10000 -> 0.046835342 | H7: =H6/(1+G7*(1-0.5)) -> 0.95645567 | I7: Uses SHOCKED DF from 6M (row above), not base
A8: 2Y | B8: 2 | C8: =Base_Curves!E6 -> 0.957768 | D8: =Base_Curves!F6 -> 0.917044 | E8: =(C8/D8-1)/(2-1) -> 0.044407902 | F8: =Curve_Shocks_bps!F4 -> -21.7 | G8: =E8+F8/10000 -> 0.042237902 | H8: =H7/(1+G8*(2-1)) -> 0.9176942 | I8: Uses SHOCKED DF from 1Y (row above), not base
A9: 3Y | B9: 3 | C9: =Base_Curves!F6 -> 0.917044 | D9: =Base_Curves!G6 -> 0.877788 | E9: =(C9/D9-1)/(3-2) -> 0.044721505 | F9: =Curve_Shocks_bps!G4 -> -13 | G9: =E9+F9/10000 -> 0.043421505 | H9: =H8/(1+G9*(3-2)) -> 0.87950478 | I9: Uses SHOCKED DF from 2Y (row above), not base
A10: 5Y | B10: 5 | C10: =Base_Curves!G6 -> 0.877788 | D10: =Base_Curves!H6 -> 0.803523 | E10: =(C10/D10-1)/(5-3) -> 0.046212118 | F10: =Curve_Shocks_bps!H4 -> 6.1 | G10: =E10+F10/10000 -> 0.046822118 | H10: =H9/(1+G10*(5-3)) -> 0.80419642 | I10: Uses SHOCKED DF from 3Y (row above), not base
A11: 10Y | B11: 10 | C11: =Base_Curves!H6 -> 0.803523 | D11: =Base_Curves!I6 -> 0.640824 | E11: =(C11/D11-1)/(10-5) -> 0.050778061 | F11: =Curve_Shocks_bps!I4 -> 2.9 | G11: =E11+F11/10000 -> 0.051068061 | H11: =H10/(1+G11*(10-5)) -> 0.64062025 | I11: Uses SHOCKED DF from 5Y (row above), not base
A12: 20Y | B12: 20 | C12: =Base_Curves!I6 -> 0.640824 | D12: =Base_Curves!J6 -> 0.410656 | E12: =(C12/D12-1)/(20-10) -> 0.056048858 | F12: =Curve_Shocks_bps!J4 -> 2.1 | G12: =E12+F12/10000 -> 0.056258858 | H12: =H11/(1+G12*(20-10)) -> 0.40997372 | I12: Uses SHOCKED DF from 10Y (row above), not base
A13: 30Y | B13: 30 | C13: =Base_Curves!J6 -> 0.410656 | D13: =Base_Curves!K6 -> 0.263158 | E13: =(C13/D13-1)/(30-20) -> 0.056049218 | F13: =Curve_Shocks_bps!K4 -> 1.2 | G13: =E13+F13/10000 -> 0.056169218 | H13: =H12/(1+G13*(30-20)) -> 0.2625189 | I13: Uses SHOCKED DF from 20Y (row above), not base
A15: This exact column-H formula pattern is replicated for all 6 curves x 10 scenarios on the Shocked_Curves_DF tab.

Sheet Shocked_Curves_DF
A1: Shocked Curve Objects — Discount Factors (gxlCurveDiscShift output), All Curves x 10 Scenarios
A2: Same cascading-bootstrap formula as Curve_Shift_Illustration: base forward rate (from Base_Curves) + scenario shock (bps, from Curve_Shocks_bps) = shocked forward rate; shocked DF at tenor i is solved off the SHOCKED DF at tenor i-1.
A4: Scenario 1 | C4: 3M | D4: 6M | E4: 1Y | F4: 2Y | G4: 3Y | H4: 5Y | I4: 10Y | J4: 20Y | K4: 30Y
A5: SOFR | B5: IR | C5: =1/(1+(((1/Base_Curves!C6-1)/(0.25-0))+Curve_Shocks_bps!C4/10000)*(0.25-0)) -> 0.99029974 | D5: =C5/(1+(((Base_Curves!C6/Base_Curves!D6-1)/(0.5-0.25))+Curve_Shocks_bps!D4/10000)*(0.5-0.25)) -> 0.97885364 | E5: =D5/(1+(((Base_Curves!D6/Base_Curves!E6-1)/(1-0.5))+Curve_Shocks_bps!E4/10000)*(1-0.5)) -> 0.95645567 | F5: =E5/(1+(((Base_Curves!E6/Base_Curves!F6-1)/(2-1))+Curve_Shocks_bps!F4/10000)*(2-1)) -> 0.9176942 | G5: =F5/(1+(((Base_Curves!F6/Base_Curves!G6-1)/(3-2))+Curve_Shocks_bps!G4/10000)*(3-2)) -> 0.87950478 | H5: =G5/(1+(((Base_Curves!G6/Base_Curves!H6-1)/(5-3))+Curve_Shocks_bps!H4/10000)*(5-3)) -> 0.80419642 | I5: =H5/(1+(((Base_Curves!H6/Base_Curves!I6-1)/(10-5))+Curve_Shocks_bps!I4/10000)*(10-5)) -> 0.64062025 | J5: =I5/(1+(((Base_Curves!I6/Base_Curves!J6-1)/(20-10))+Curve_Shocks_bps!J4/10000)*(20-10)) -> 0.40997372 | K5: =J5/(1+(((Base_Curves!J6/Base_Curves!K6-1)/(30-20))+Curve_Shocks_bps!K4/10000)*(30-20)) -> 0.2625189
A6: ESTRN | B6: IR | C6: =1/(1+(((1/Base_Curves!C7-1)/(0.25-0))+Curve_Shocks_bps!C5/10000)*(0.25-0)) -> 0.9931456 | D6: =C6/(1+(((Base_Curves!C7/Base_Curves!D7-1)/(0.5-0.25))+Curve_Shocks_bps!D5/10000)*(0.5-0.25)) -> 0.98467164 | E6: =D6/(1+(((Base_Curves!D7/Base_Curves!E7-1)/(1-0.5))+Curve_Shocks_bps!E5/10000)*(1-0.5)) -> 0.96826858 | F6: =E6/(1+(((Base_Curves!E7/Base_Curves!F7-1)/(2-1))+Curve_Shocks_bps!F5/10000)*(2-1)) -> 0.93662947 | G6: =F6/(1+(((Base_Curves!F7/Base_Curves!G7-1)/(3-2))+Curve_Shocks_bps!G5/10000)*(3-2)) -> 0.90814151 | H6: =G6/(1+(((Base_Curves!G7/Base_Curves!H7-1)/(5-3))+Curve_Shocks_bps!H5/10000)*(5-3)) -> 0.85059198 | I6: =H6/(1+(((Base_Curves!H7/Base_Curves!I7-1)/(10-5))+Curve_Shocks_bps!I5/10000)*(10-5)) -> 0.71945701 | J6: =I6/(1+(((Base_Curves!I7/Base_Curves!J7-1)/(20-10))+Curve_Shocks_bps!J5/10000)*(20-10)) -> 0.51934004 | K6: =J6/(1+(((Base_Curves!J7/Base_Curves!K7-1)/(30-20))+Curve_Shocks_bps!K5/10000)*(30-20)) -> 0.37507427
A7: Treasury | B7: Credit | C7: =1/(1+(((1/Base_Curves!C8-1)/(0.25-0))+Curve_Shocks_bps!C6/10000)*(0.25-0)) -> 0.98832595 | D7: =C7/(1+(((Base_Curves!C8/Base_Curves!D8-1)/(0.5-0.25))+Curve_Shocks_bps!D6/10000)*(0.5-0.25)) -> 0.97684621 | E7: =D7/(1+(((Base_Curves!D8/Base_Curves!E8-1)/(1-0.5))+Curve_Shocks_bps!E6/10000)*(1-0.5)) -> 0.95806183 | F7: =E7/(1+(((Base_Curves!E8/Base_Curves!F8-1)/(2-1))+Curve_Shocks_bps!F6/10000)*(2-1)) -> 0.91634638 | G7: =F7/(1+(((Base_Curves!F8/Base_Curves!G8-1)/(3-2))+Curve_Shocks_bps!G6/10000)*(3-2)) -> 0.87690515 | H7: =G7/(1+(((Base_Curves!G8/Base_Curves!H8-1)/(5-3))+Curve_Shocks_bps!H6/10000)*(5-3)) -> 0.80326054 | I7: =H7/(1+(((Base_Curves!H8/Base_Curves!I8-1)/(10-5))+Curve_Shocks_bps!I6/10000)*(10-5)) -> 0.64277078 | J7: =I7/(1+(((Base_Curves!I8/Base_Curves!J8-1)/(20-10))+Curve_Shocks_bps!J6/10000)*(20-10)) -> 0.41553203 | K7: =J7/(1+(((Base_Curves!J8/Base_Curves!K8-1)/(30-20))+Curve_Shocks_bps!K6/10000)*(30-20)) -> 0.26875063
A8: Agency_FNMA | B8: Credit | C8: =1/(1+(((1/Base_Curves!C9-1)/(0.25-0))+Curve_Shocks_bps!C7/10000)*(0.25-0)) -> 0.98672319 | D8: =C8/(1+(((Base_Curves!C9/Base_Curves!D9-1)/(0.5-0.25))+Curve_Shocks_bps!D7/10000)*(0.5-0.25)) -> 0.97395218 | E8: =D8/(1+(((Base_Curves!D9/Base_Curves!E9-1)/(1-0.5))+Curve_Shocks_bps!E7/10000)*(1-0.5)) -> 0.94931135 | F8: =E8/(1+(((Base_Curves!E9/Base_Curves!F9-1)/(2-1))+Curve_Shocks_bps!F7/10000)*(2-1)) -> 0.90240774 | G8: =F8/(1+(((Base_Curves!F9/Base_Curves!G9-1)/(3-2))+Curve_Shocks_bps!G7/10000)*(3-2)) -> 0.8589947 | H8: =G8/(1+(((Base_Curves!G9/Base_Curves!H9-1)/(5-3))+Curve_Shocks_bps!H7/10000)*(5-3)) -> 0.7793884 | I8: =H8/(1+(((Base_Curves!H9/Base_Curves!I9-1)/(10-5))+Curve_Shocks_bps!I7/10000)*(10-5)) -> 0.6138174 | J8: =I8/(1+(((Base_Curves!I9/Base_Curves!J9-1)/(20-10))+Curve_Shocks_bps!J7/10000)*(20-10)) -> 0.38082393 | K8: =J8/(1+(((Base_Curves!J9/Base_Curves!K9-1)/(30-20))+Curve_Shocks_bps!K7/10000)*(30-20)) -> 0.23646064
A9: Eur_Govt | B9: Credit | C9: =1/(1+(((1/Base_Curves!C10-1)/(0.25-0))+Curve_Shocks_bps!C8/10000)*(0.25-0)) -> 0.9901841 | D9: =C9/(1+(((Base_Curves!C10/Base_Curves!D10-1)/(0.5-0.25))+Curve_Shocks_bps!D8/10000)*(0.5-0.25)) -> 0.98068775 | E9: =D9/(1+(((Base_Curves!D10/Base_Curves!E10-1)/(1-0.5))+Curve_Shocks_bps!E8/10000)*(1-0.5)) -> 0.96229709 | F9: =E9/(1+(((Base_Curves!E10/Base_Curves!F10-1)/(2-1))+Curve_Shocks_bps!F8/10000)*(2-1)) -> 0.92812746 | G9: =F9/(1+(((Base_Curves!F10/Base_Curves!G10-1)/(3-2))+Curve_Shocks_bps!G8/10000)*(3-2)) -> 0.89569839 | H9: =G9/(1+(((Base_Curves!G10/Base_Curves!H10-1)/(5-3))+Curve_Shocks_bps!H8/10000)*(5-3)) -> 0.83490567 | I9: =H9/(1+(((Base_Curves!H10/Base_Curves!I10-1)/(10-5))+Curve_Shocks_bps!I8/10000)*(10-5)) -> 0.69846902 | J9: =I9/(1+(((Base_Curves!I10/Base_Curves!J10-1)/(20-10))+Curve_Shocks_bps!J8/10000)*(20-10)) -> 0.49362138 | K9: =J9/(1+(((Base_Curves!J10/Base_Curves!K10-1)/(30-20))+Curve_Shocks_bps!K8/10000)*(30-20)) -> 0.35003861
A10: EURUSD | B10: FX | C10: =1/(1+(((1/Base_Curves!C11-1)/(0.25-0))+Curve_Shocks_bps!C9/10000)*(0.25-0)) -> 0.98945569 | D10: =C10/(1+(((Base_Curves!C11/Base_Curves!D11-1)/(0.5-0.25))+Curve_Shocks_bps!D9/10000)*(0.5-0.25)) -> 0.97893077 | E10: =D10/(1+(((Base_Curves!D11/Base_Curves!E11-1)/(1-0.5))+Curve_Shocks_bps!E9/10000)*(1-0.5)) -> 0.95855049 | F10: =E10/(1+(((Base_Curves!E11/Base_Curves!F11-1)/(2-1))+Curve_Shocks_bps!F9/10000)*(2-1)) -> 0.91911276 | G10: =F10/(1+(((Base_Curves!F11/Base_Curves!G11-1)/(3-2))+Curve_Shocks_bps!G9/10000)*(3-2)) -> 0.88148062 | H10: =G10/(1+(((Base_Curves!G11/Base_Curves!H11-1)/(5-3))+Curve_Shocks_bps!H9/10000)*(5-3)) -> 0.81098155 | I10: =H10/(1+(((Base_Curves!H11/Base_Curves!I11-1)/(10-5))+Curve_Shocks_bps!I9/10000)*(10-5)) -> 0.65564525 | J10: =I10/(1+(((Base_Curves!I11/Base_Curves!J11-1)/(20-10))+Curve_Shocks_bps!J9/10000)*(20-10)) -> 0.43240635 | K10: =J10/(1+(((Base_Curves!J11/Base_Curves!K11-1)/(30-20))+Curve_Shocks_bps!K9/10000)*(30-20)) -> 0.28530953
A12: Scenario 2 | C12: 3M | D12: 6M | E12: 1Y | F12: 2Y | G12: 3Y | H12: 5Y | I12: 10Y | J12: 20Y | K12: 30Y
A13: SOFR | B13: IR | C13: =1/(1+(((1/Base_Curves!C6-1)/(0.25-0))+Curve_Shocks_bps!C12/10000)*(0.25-0)) -> 0.98817864 | D13: =C13/(1+(((Base_Curves!C6/Base_Curves!D6-1)/(0.5-0.25))+Curve_Shocks_bps!D12/10000)*(0.5-0.25)) -> 0.97648197 | E13: =D13/(1+(((Base_Curves!D6/Base_Curves!E6-1)/(1-0.5))+Curve_Shocks_bps!E12/10000)*(1-0.5)) -> 0.95398447 | F13: =E13/(1+(((Base_Curves!E6/Base_Curves!F6-1)/(2-1))+Curve_Shocks_bps!F12/10000)*(2-1)) -> 0.9112314 | G13: =F13/(1+(((Base_Curves!F6/Base_Curves!G6-1)/(3-2))+Curve_Shocks_bps!G12/10000)*(3-2)) -> 0.87099034 | H13: =G13/(1+(((Base_Curves!G6/Base_Curves!H6-1)/(5-3))+Curve_Shocks_bps!H12/10000)*(5-3)) -> 0.79614896 | I13: =H13/(1+(((Base_Curves!H6/Base_Curves!I6-1)/(10-5))+Curve_Shocks_bps!I12/10000)*(10-5)) -> 0.63390669 | J13: =I13/(1+(((Base_Curves!I6/Base_Curves!J6-1)/(20-10))+Curve_Shocks_bps!J12/10000)*(20-10)) -> 0.40559941 | K13: =J13/(1+(((Base_Curves!J6/Base_Curves!K6-1)/(30-20))+Curve_Shocks_bps!K12/10000)*(30-20)) -> 0.25968464
A14: ESTRN | B14: IR | C14: =1/(1+(((1/Base_Curves!C7-1)/(0.25-0))+Curve_Shocks_bps!C13/10000)*(0.25-0)) -> 0.99141759 | D14: =C14/(1+(((Base_Curves!C7/Base_Curves!D7-1)/(0.5-0.25))+Curve_Shocks_bps!D13/10000)*(0.5-0.25)) -> 0.98282438 | E14: =D14/(1+(((Base_Curves!D7/Base_Curves!E7-1)/(1-0.5))+Curve_Shocks_bps!E13/10000)*(1-0.5)) -> 0.9689389 | F14: =E14/(1+(((Base_Curves!E7/Base_Curves!F7-1)/(2-1))+Curve_Shocks_bps!F13/10000)*(2-1)) -> 0.93705128 | G14: =F14/(1+(((Base_Curves!F7/Base_Curves!G7-1)/(3-2))+Curve_Shocks_bps!G13/10000)*(3-2)) -> 0.90683595 | H14: =G14/(1+(((Base_Curves!G7/Base_Curves!H7-1)/(5-3))+Curve_Shocks_bps!H13/10000)*(5-3)) -> 0.84938506 | I14: =H14/(1+(((Base_Curves!H7/Base_Curves!I7-1)/(10-5))+Curve_Shocks_bps!I13/10000)*(10-5)) -> 0.72029436 | J14: =I14/(1+(((Base_Curves!I7/Base_Curves!J7-1)/(20-10))+Curve_Shocks_bps!J13/10000)*(20-10)) -> 0.51986943 | K14: =J14/(1+(((Base_Curves!J7/Base_Curves!K7-1)/(30-20))+Curve_Shocks_bps!K13/10000)*(30-20)) -> 0.37542949
A15: Treasury | B15: Credit | C15: =1/(1+(((1/Base_Curves!C8-1)/(0.25-0))+Curve_Shocks_bps!C14/10000)*(0.25-0)) -> 0.98825026 | D15: =C15/(1+(((Base_Curves!C8/Base_Curves!D8-1)/(0.5-0.25))+Curve_Shocks_bps!D14/10000)*(0.5-0.25)) -> 0.97667968 | E15: =D15/(1+(((Base_Curves!D8/Base_Curves!E8-1)/(1-0.5))+Curve_Shocks_bps!E14/10000)*(1-0.5)) -> 0.95458892 | F15: =E15/(1+(((Base_Curves!E8/Base_Curves!F8-1)/(2-1))+Curve_Shocks_bps!F14/10000)*(2-1)) -> 0.9123179 | G15: =F15/(1+(((Base_Curves!F8/Base_Curves!G8-1)/(3-2))+Curve_Shocks_bps!G14/10000)*(3-2)) -> 0.87274104 | H15: =G15/(1+(((Base_Curves!G8/Base_Curves!H8-1)/(5-3))+Curve_Shocks_bps!H14/10000)*(5-3)) -> 0.79925579 | I15: =H15/(1+(((Base_Curves!H8/Base_Curves!I8-1)/(10-5))+Curve_Shocks_bps!I14/10000)*(10-5)) -> 0.63946383 | J15: =I15/(1+(((Base_Curves!I8/Base_Curves!J8-1)/(20-10))+Curve_Shocks_bps!J14/10000)*(20-10)) -> 0.41331402 | K15: =J15/(1+(((Base_Curves!J8/Base_Curves!K8-1)/(30-20))+Curve_Shocks_bps!K14/10000)*(30-20)) -> 0.26728153
A16: Agency_FNMA | B16: Credit | C16: =1/(1+(((1/Base_Curves!C9-1)/(0.25-0))+Curve_Shocks_bps!C15/10000)*(0.25-0)) -> 0.9866088 | D16: =C16/(1+(((Base_Curves!C9/Base_Curves!D9-1)/(0.5-0.25))+Curve_Shocks_bps!D15/10000)*(0.5-0.25)) -> 0.97729995 | E16: =D16/(1+(((Base_Curves!D9/Base_Curves!E9-1)/(1-0.5))+Curve_Shocks_bps!E15/10000)*(1-0.5)) -> 0.95209186 | F16: =E16/(1+(((Base_Curves!E9/Base_Curves!F9-1)/(2-1))+Curve_Shocks_bps!F15/10000)*(2-1)) -> 0.91266819 | G16: =F16/(1+(((Base_Curves!F9/Base_Curves!G9-1)/(3-2))+Curve_Shocks_bps!G15/10000)*(3-2)) -> 0.86819957 | H16: =G16/(1+(((Base_Curves!G9/Base_Curves!H9-1)/(5-3))+Curve_Shocks_bps!H15/10000)*(5-3)) -> 0.78758301 | I16: =H16/(1+(((Base_Curves!H9/Base_Curves!I9-1)/(10-5))+Curve_Shocks_bps!I15/10000)*(10-5)) -> 0.61677378 | J16: =I16/(1+(((Base_Curves!I9/Base_Curves!J9-1)/(20-10))+Curve_Shocks_bps!J15/10000)*(20-10)) -> 0.38256318 | K16: =J16/(1+(((Base_Curves!J9/Base_Curves!K9-1)/(30-20))+Curve_Shocks_bps!K15/10000)*(30-20)) -> 0.23746685
A17: Eur_Govt | B17: Credit | C17: =1/(1+(((1/Base_Curves!C10-1)/(0.25-0))+Curve_Shocks_bps!C16/10000)*(0.25-0)) -> 0.98999294 | D17: =C17/(1+(((Base_Curves!C10/Base_Curves!D10-1)/(0.5-0.25))+Curve_Shocks_bps!D16/10000)*(0.5-0.25)) -> 0.9834839 | E17: =D17/(1+(((Base_Curves!D10/Base_Curves!E10-1)/(1-0.5))+Curve_Shocks_bps!E16/10000)*(1-0.5)) -> 0.96495558 | F17: =E17/(1+(((Base_Curves!E10/Base_Curves!F10-1)/(2-1))+Curve_Shocks_bps!F16/10000)*(2-1)) -> 0.9298575 | G17: =F17/(1+(((Base_Curves!F10/Base_Curves!G10-1)/(3-2))+Curve_Shocks_bps!G16/10000)*(3-2)) -> 0.89724675 | H17: =G17/(1+(((Base_Curves!G10/Base_Curves!H10-1)/(5-3))+Curve_Shocks_bps!H16/10000)*(5-3)) -> 0.8361463 | I17: =H17/(1+(((Base_Curves!H10/Base_Curves!I10-1)/(10-5))+Curve_Shocks_bps!I16/10000)*(10-5)) -> 0.6993314 | J17: =I17/(1+(((Base_Curves!I10/Base_Curves!J10-1)/(20-10))+Curve_Shocks_bps!J16/10000)*(20-10)) -> 0.49423084 | K17: =J17/(1+(((Base_Curves!J10/Base_Curves!K10-1)/(30-20))+Curve_Shocks_bps!K16/10000)*(30-20)) -> 0.3505951
A18: EURUSD | B18: FX | C18: =1/(1+(((1/Base_Curves!C11-1)/(0.25-0))+Curve_Shocks_bps!C17/10000)*(0.25-0)) -> 0.98920855 | D18: =C18/(1+(((Base_Curves!C11/Base_Curves!D11-1)/(0.5-0.25))+Curve_Shocks_bps!D17/10000)*(0.5-0.25)) -> 0.97856039 | E18: =D18/(1+(((Base_Curves!D11/Base_Curves!E11-1)/(1-0.5))+Curve_Shocks_bps!E17/10000)*(1-0.5)) -> 0.95783612 | F18: =E18/(1+(((Base_Curves!E11/Base_Curves!F11-1)/(2-1))+Curve_Shocks_bps!F17/10000)*(2-1)) -> 0.91837494 | G18: =F18/(1+(((Base_Curves!F11/Base_Curves!G11-1)/(3-2))+Curve_Shocks_bps!G17/10000)*(3-2)) -> 0.88266075 | H18: =G18/(1+(((Base_Curves!G11/Base_Curves!H11-1)/(5-3))+Curve_Shocks_bps!H17/10000)*(5-3)) -> 0.81182829 | I18: =H18/(1+(((Base_Curves!H11/Base_Curves!I11-1)/(10-5))+Curve_Shocks_bps!I17/10000)*(10-5)) -> 0.65625023 | J18: =I18/(1+(((Base_Curves!I11/Base_Curves!J11-1)/(20-10))+Curve_Shocks_bps!J17/10000)*(20-10)) -> 0.4326912 | K18: =J18/(1+(((Base_Curves!J11/Base_Curves!K11-1)/(30-20))+Curve_Shocks_bps!K17/10000)*(30-20)) -> 0.28540332
A20: Scenario 3 | C20: 3M | D20: 6M | E20: 1Y | F20: 2Y | G20: 3Y | H20: 5Y | I20: 10Y | J20: 20Y | K20: 30Y
A21: SOFR | B21: IR | C21: =1/(1+(((1/Base_Curves!C6-1)/(0.25-0))+Curve_Shocks_bps!C20/10000)*(0.25-0)) -> 0.98799559 | D21: =C21/(1+(((Base_Curves!C6/Base_Curves!D6-1)/(0.5-0.25))+Curve_Shocks_bps!D20/10000)*(0.5-0.25)) -> 0.97630832 | E21: =D21/(1+(((Base_Curves!D6/Base_Curves!E6-1)/(1-0.5))+Curve_Shocks_bps!E20/10000)*(1-0.5)) -> 0.95342826 | F21: =E21/(1+(((Base_Curves!E6/Base_Curves!F6-1)/(2-1))+Curve_Shocks_bps!F20/10000)*(2-1)) -> 0.91056965 | G21: =F21/(1+(((Base_Curves!F6/Base_Curves!G6-1)/(3-2))+Curve_Shocks_bps!G20/10000)*(3-2)) -> 0.87024136 | H21: =G21/(1+(((Base_Curves!G6/Base_Curves!H6-1)/(5-3))+Curve_Shocks_bps!H20/10000)*(5-3)) -> 0.79533348 | I21: =H21/(1+(((Base_Curves!H6/Base_Curves!I6-1)/(10-5))+Curve_Shocks_bps!I20/10000)*(10-5)) -> 0.63325739 | J21: =I21/(1+(((Base_Curves!I6/Base_Curves!J6-1)/(20-10))+Curve_Shocks_bps!J20/10000)*(20-10)) -> 0.40518397 | K21: =J21/(1+(((Base_Curves!J6/Base_Curves!K6-1)/(30-20))+Curve_Shocks_bps!K20/10000)*(30-20)) -> 0.25935223
A22: ESTRN | B22: IR | C22: =1/(1+(((1/Base_Curves!C7-1)/(0.25-0))+Curve_Shocks_bps!C21/10000)*(0.25-0)) -> 0.99330344 | D22: =C22/(1+(((Base_Curves!C7/Base_Curves!D7-1)/(0.5-0.25))+Curve_Shocks_bps!D21/10000)*(0.5-0.25)) -> 0.98457188 | E22: =D22/(1+(((Base_Curves!D7/Base_Curves!E7-1)/(1-0.5))+Curve_Shocks_bps!E21/10000)*(1-0.5)) -> 0.96769945 | F22: =E22/(1+(((Base_Curves!E7/Base_Curves!F7-1)/(2-1))+Curve_Shocks_bps!F21/10000)*(2-1)) -> 0.93577118 | G22: =F22/(1+(((Base_Curves!F7/Base_Curves!G7-1)/(3-2))+Curve_Shocks_bps!G21/10000)*(3-2)) -> 0.90536056 | H22: =G22/(1+(((Base_Curves!G7/Base_Curves!H7-1)/(5-3))+Curve_Shocks_bps!H21/10000)*(5-3)) -> 0.84782844 | I22: =H22/(1+(((Base_Curves!H7/Base_Curves!I7-1)/(10-5))+Curve_Shocks_bps!I21/10000)*(10-5)) -> 0.7169376 | J22: =I22/(1+(((Base_Curves!I7/Base_Curves!J7-1)/(20-10))+Curve_Shocks_bps!J21/10000)*(20-10)) -> 0.51733468 | K22: =J22/(1+(((Base_Curves!J7/Base_Curves!K7-1)/(30-20))+Curve_Shocks_bps!K21/10000)*(30-20)) -> 0.37354504
A23: Treasury | B23: Credit | C23: =1/(1+(((1/Base_Curves!C8-1)/(0.25-0))+Curve_Shocks_bps!C22/10000)*(0.25-0)) -> 0.98815749 | D23: =C23/(1+(((Base_Curves!C8/Base_Curves!D8-1)/(0.5-0.25))+Curve_Shocks_bps!D22/10000)*(0.5-0.25)) -> 0.97630095 | E23: =D23/(1+(((Base_Curves!D8/Base_Curves!E8-1)/(1-0.5))+Curve_Shocks_bps!E22/10000)*(1-0.5)) -> 0.95400896 | F23: =E23/(1+(((Base_Curves!E8/Base_Curves!F8-1)/(2-1))+Curve_Shocks_bps!F22/10000)*(2-1)) -> 0.91178104 | G23: =F23/(1+(((Base_Curves!F8/Base_Curves!G8-1)/(3-2))+Curve_Shocks_bps!G22/10000)*(3-2)) -> 0.87189384 | H23: =G23/(1+(((Base_Curves!G8/Base_Curves!H8-1)/(5-3))+Curve_Shocks_bps!H22/10000)*(5-3)) -> 0.79821677 | I23: =H23/(1+(((Base_Curves!H8/Base_Curves!I8-1)/(10-5))+Curve_Shocks_bps!I22/10000)*(10-5)) -> 0.63835164 | J23: =I23/(1+(((Base_Curves!I8/Base_Curves!J8-1)/(20-10))+Curve_Shocks_bps!J22/10000)*(20-10)) -> 0.41246187 | K23: =J23/(1+(((Base_Curves!J8/Base_Curves!K8-1)/(30-20))+Curve_Shocks_bps!K22/10000)*(30-20)) -> 0.26728357
A24: Agency_FNMA | B24: Credit | C24: =1/(1+(((1/Base_Curves!C9-1)/(0.25-0))+Curve_Shocks_bps!C23/10000)*(0.25-0)) -> 0.98606157 | D24: =C24/(1+(((Base_Curves!C9/Base_Curves!D9-1)/(0.5-0.25))+Curve_Shocks_bps!D23/10000)*(0.5-0.25)) -> 0.97258152 | E24: =D24/(1+(((Base_Curves!D9/Base_Curves!E9-1)/(1-0.5))+Curve_Shocks_bps!E23/10000)*(1-0.5)) -> 0.95361271 | F24: =E24/(1+(((Base_Curves!E9/Base_Curves!F9-1)/(2-1))+Curve_Shocks_bps!F23/10000)*(2-1)) -> 0.90609176 | G24: =F24/(1+(((Base_Curves!F9/Base_Curves!G9-1)/(3-2))+Curve_Shocks_bps!G23/10000)*(3-2)) -> 0.86193537 | H24: =G24/(1+(((Base_Curves!G9/Base_Curves!H9-1)/(5-3))+Curve_Shocks_bps!H23/10000)*(5-3)) -> 0.78143261 | I24: =H24/(1+(((Base_Curves!H9/Base_Curves!I9-1)/(10-5))+Curve_Shocks_bps!I23/10000)*(10-5)) -> 0.61176563 | J24: =I24/(1+(((Base_Curves!I9/Base_Curves!J9-1)/(20-10))+Curve_Shocks_bps!J23/10000)*(20-10)) -> 0.37919808 | K24: =J24/(1+(((Base_Curves!J9/Base_Curves!K9-1)/(30-20))+Curve_Shocks_bps!K23/10000)*(30-20)) -> 0.23636104
A25: Eur_Govt | B25: Credit | C25: =1/(1+(((1/Base_Curves!C10-1)/(0.25-0))+Curve_Shocks_bps!C24/10000)*(0.25-0)) -> 0.9898582 | D25: =C25/(1+(((Base_Curves!C10/Base_Curves!D10-1)/(0.5-0.25))+Curve_Shocks_bps!D24/10000)*(0.5-0.25)) -> 0.9801417 | E25: =D25/(1+(((Base_Curves!D10/Base_Curves!E10-1)/(1-0.5))+Curve_Shocks_bps!E24/10000)*(1-0.5)) -> 0.96122366 | F25: =E25/(1+(((Base_Curves!E10/Base_Curves!F10-1)/(2-1))+Curve_Shocks_bps!F24/10000)*(2-1)) -> 0.92590443 | G25: =F25/(1+(((Base_Curves!F10/Base_Curves!G10-1)/(3-2))+Curve_Shocks_bps!G24/10000)*(3-2)) -> 0.8972852 | H25: =G25/(1+(((Base_Curves!G10/Base_Curves!H10-1)/(5-3))+Curve_Shocks_bps!H24/10000)*(5-3)) -> 0.83605747 | I25: =H25/(1+(((Base_Curves!H10/Base_Curves!I10-1)/(10-5))+Curve_Shocks_bps!I24/10000)*(10-5)) -> 0.69873115 | J25: =I25/(1+(((Base_Curves!I10/Base_Curves!J10-1)/(20-10))+Curve_Shocks_bps!J24/10000)*(20-10)) -> 0.49356246 | K25: =J25/(1+(((Base_Curves!J10/Base_Curves!K10-1)/(30-20))+Curve_Shocks_bps!K24/10000)*(30-20)) -> 0.35017065
A26: EURUSD | B26: FX | C26: =1/(1+(((1/Base_Curves!C11-1)/(0.25-0))+Curve_Shocks_bps!C25/10000)*(0.25-0)) -> 0.98920855 | D26: =C26/(1+(((Base_Curves!C11/Base_Curves!D11-1)/(0.5-0.25))+Curve_Shocks_bps!D25/10000)*(0.5-0.25)) -> 0.97848538 | E26: =D26/(1+(((Base_Curves!D11/Base_Curves!E11-1)/(1-0.5))+Curve_Shocks_bps!E25/10000)*(1-0.5)) -> 0.9575846 | F26: =E26/(1+(((Base_Curves!E11/Base_Curves!F11-1)/(2-1))+Curve_Shocks_bps!F25/10000)*(2-1)) -> 0.92126069 | G26: =F26/(1+(((Base_Curves!F11/Base_Curves!G11-1)/(3-2))+Curve_Shocks_bps!G25/10000)*(3-2)) -> 0.88329494 | H26: =G26/(1+(((Base_Curves!G11/Base_Curves!H11-1)/(5-3))+Curve_Shocks_bps!H25/10000)*(5-3)) -> 0.81226217 | I26: =H26/(1+(((Base_Curves!H11/Base_Curves!I11-1)/(10-5))+Curve_Shocks_bps!I25/10000)*(10-5)) -> 0.65649482 | J26: =I26/(1+(((Base_Curves!I11/Base_Curves!J11-1)/(20-10))+Curve_Shocks_bps!J25/10000)*(20-10)) -> 0.43270981 | K26: =J26/(1+(((Base_Curves!J11/Base_Curves!K11-1)/(30-20))+Curve_Shocks_bps!K25/10000)*(30-20)) -> 0.28537795
A28: Scenario 4 | C28: 3M | D28: 6M | E28: 1Y | F28: 2Y | G28: 3Y | H28: 5Y | I28: 10Y | J28: 20Y | K28: 30Y
A29: SOFR | B29: IR | C29: =1/(1+(((1/Base_Curves!C6-1)/(0.25-0))+Curve_Shocks_bps!C28/10000)*(0.25-0)) -> 0.98795898 | D29: =C29/(1+(((Base_Curves!C6/Base_Curves!D6-1)/(0.5-0.25))+Curve_Shocks_bps!D28/10000)*(0.5-0.25)) -> 0.97608888 | E29: =D29/(1+(((Base_Curves!D6/Base_Curves!E6-1)/(1-0.5))+Curve_Shocks_bps!E28/10000)*(1-0.5)) -> 0.95304179 | F29: =E29/(1+(((Base_Curves!E6/Base_Curves!F6-1)/(2-1))+Curve_Shocks_bps!F28/10000)*(2-1)) -> 0.90980086 | G29: =F29/(1+(((Base_Curves!F6/Base_Curves!G6-1)/(3-2))+Curve_Shocks_bps!G28/10000)*(3-2)) -> 0.87258385 | H29: =G29/(1+(((Base_Curves!G6/Base_Curves!H6-1)/(5-3))+Curve_Shocks_bps!H28/10000)*(5-3)) -> 0.79722661 | I29: =H29/(1+(((Base_Curves!H6/Base_Curves!I6-1)/(10-5))+Curve_Shocks_bps!I28/10000)*(10-5)) -> 0.63461314 | J29: =I29/(1+(((Base_Curves!I6/Base_Curves!J6-1)/(20-10))+Curve_Shocks_bps!J28/10000)*(20-10)) -> 0.4058956 | K29: =J29/(1+(((Base_Curves!J6/Base_Curves!K6-1)/(30-20))+Curve_Shocks_bps!K28/10000)*(30-20)) -> 0.25975786
A30: ESTRN | B30: IR | C30: =1/(1+(((1/Base_Curves!C7-1)/(0.25-0))+Curve_Shocks_bps!C29/10000)*(0.25-0)) -> 0.99114737 | D30: =C30/(1+(((Base_Curves!C7/Base_Curves!D7-1)/(0.5-0.25))+Curve_Shocks_bps!D29/10000)*(0.5-0.25)) -> 0.98241285 | E30: =D30/(1+(((Base_Curves!D7/Base_Curves!E7-1)/(1-0.5))+Curve_Shocks_bps!E29/10000)*(1-0.5)) -> 0.96526908 | F30: =E30/(1+(((Base_Curves!E7/Base_Curves!F7-1)/(2-1))+Curve_Shocks_bps!F29/10000)*(2-1)) -> 0.93309617 | G30: =F30/(1+(((Base_Curves!F7/Base_Curves!G7-1)/(3-2))+Curve_Shocks_bps!G29/10000)*(3-2)) -> 0.90253671 | H30: =G30/(1+(((Base_Curves!G7/Base_Curves!H7-1)/(5-3))+Curve_Shocks_bps!H29/10000)*(5-3)) -> 0.84759699 | I30: =H30/(1+(((Base_Curves!H7/Base_Curves!I7-1)/(10-5))+Curve_Shocks_bps!I29/10000)*(10-5)) -> 0.71646924 | J30: =I30/(1+(((Base_Curves!I7/Base_Curves!J7-1)/(20-10))+Curve_Shocks_bps!J29/10000)*(20-10)) -> 0.51688483 | K30: =J30/(1+(((Base_Curves!J7/Base_Curves!K7-1)/(30-20))+Curve_Shocks_bps!K29/10000)*(30-20)) -> 0.37322022
A31: Treasury | B31: Credit | C31: =1/(1+(((1/Base_Curves!C8-1)/(0.25-0))+Curve_Shocks_bps!C30/10000)*(0.25-0)) -> 0.98778901 | D31: =C31/(1+(((Base_Curves!C8/Base_Curves!D8-1)/(0.5-0.25))+Curve_Shocks_bps!D30/10000)*(0.5-0.25)) -> 0.97586217 | E31: =D31/(1+(((Base_Curves!D8/Base_Curves!E8-1)/(1-0.5))+Curve_Shocks_bps!E30/10000)*(1-0.5)) -> 0.95320762 | F31: =E31/(1+(((Base_Curves!E8/Base_Curves!F8-1)/(2-1))+Curve_Shocks_bps!F30/10000)*(2-1)) -> 0.91068443 | G31: =F31/(1+(((Base_Curves!F8/Base_Curves!G8-1)/(3-2))+Curve_Shocks_bps!G30/10000)*(3-2)) -> 0.87090351 | H31: =G31/(1+(((Base_Curves!G8/Base_Curves!H8-1)/(5-3))+Curve_Shocks_bps!H30/10000)*(5-3)) -> 0.79706201 | I31: =H31/(1+(((Base_Curves!H8/Base_Curves!I8-1)/(10-5))+Curve_Shocks_bps!I30/10000)*(10-5)) -> 0.63727526 | J31: =I31/(1+(((Base_Curves!I8/Base_Curves!J8-1)/(20-10))+Curve_Shocks_bps!J30/10000)*(20-10)) -> 0.41326171 | K31: =J31/(1+(((Base_Curves!J8/Base_Curves!K8-1)/(30-20))+Curve_Shocks_bps!K30/10000)*(30-20)) -> 0.26714405
A32: Agency_FNMA | B32: Credit | C32: =1/(1+(((1/Base_Curves!C9-1)/(0.25-0))+Curve_Shocks_bps!C31/10000)*(0.25-0)) -> 0.98598379 | D32: =C32/(1+(((Base_Curves!C9/Base_Curves!D9-1)/(0.5-0.25))+Curve_Shocks_bps!D31/10000)*(0.5-0.25)) -> 0.97221953 | E32: =D32/(1+(((Base_Curves!D9/Base_Curves!E9-1)/(1-0.5))+Curve_Shocks_bps!E31/10000)*(1-0.5)) -> 0.94623448 | F32: =E32/(1+(((Base_Curves!E9/Base_Curves!F9-1)/(2-1))+Curve_Shocks_bps!F31/10000)*(2-1)) -> 0.89827037 | G32: =F32/(1+(((Base_Curves!F9/Base_Curves!G9-1)/(3-2))+Curve_Shocks_bps!G31/10000)*(3-2)) -> 0.85421074 | H32: =G32/(1+(((Base_Curves!G9/Base_Curves!H9-1)/(5-3))+Curve_Shocks_bps!H31/10000)*(5-3)) -> 0.77398036 | I32: =H32/(1+(((Base_Curves!H9/Base_Curves!I9-1)/(10-5))+Curve_Shocks_bps!I31/10000)*(10-5)) -> 0.60557587 | J32: =I32/(1+(((Base_Curves!I9/Base_Curves!J9-1)/(20-10))+Curve_Shocks_bps!J31/10000)*(20-10)) -> 0.37526836 | K32: =J32/(1+(((Base_Curves!J9/Base_Curves!K9-1)/(30-20))+Curve_Shocks_bps!K31/10000)*(30-20)) -> 0.23285205
A33: Eur_Govt | B33: Credit | C33: =1/(1+(((1/Base_Curves!C10-1)/(0.25-0))+Curve_Shocks_bps!C32/10000)*(0.25-0)) -> 0.9896133 | D33: =C33/(1+(((Base_Curves!C10/Base_Curves!D10-1)/(0.5-0.25))+Curve_Shocks_bps!D32/10000)*(0.5-0.25)) -> 0.97948217 | E33: =D33/(1+(((Base_Curves!D10/Base_Curves!E10-1)/(1-0.5))+Curve_Shocks_bps!E32/10000)*(1-0.5)) -> 0.9603367 | F33: =E33/(1+(((Base_Curves!E10/Base_Curves!F10-1)/(2-1))+Curve_Shocks_bps!F32/10000)*(2-1)) -> 0.92477391 | G33: =F33/(1+(((Base_Curves!F10/Base_Curves!G10-1)/(3-2))+Curve_Shocks_bps!G32/10000)*(3-2)) -> 0.89158437 | H33: =G33/(1+(((Base_Curves!G10/Base_Curves!H10-1)/(5-3))+Curve_Shocks_bps!H32/10000)*(5-3)) -> 0.83048255 | I33: =H33/(1+(((Base_Curves!H10/Base_Curves!I10-1)/(10-5))+Curve_Shocks_bps!I32/10000)*(10-5)) -> 0.69392694 | J33: =I33/(1+(((Base_Curves!I10/Base_Curves!J10-1)/(20-10))+Curve_Shocks_bps!J32/10000)*(20-10)) -> 0.48999586 | K33: =J33/(1+(((Base_Curves!J10/Base_Curves!K10-1)/(30-20))+Curve_Shocks_bps!K32/10000)*(30-20)) -> 0.3462645
A34: EURUSD | B34: FX | C34: =1/(1+(((1/Base_Curves!C11-1)/(0.25-0))+Curve_Shocks_bps!C33/10000)*(0.25-0)) -> 0.99096568 | D34: =C34/(1+(((Base_Curves!C11/Base_Curves!D11-1)/(0.5-0.25))+Curve_Shocks_bps!D33/10000)*(0.5-0.25)) -> 0.98020165 | E34: =D34/(1+(((Base_Curves!D11/Base_Curves!E11-1)/(1-0.5))+Curve_Shocks_bps!E33/10000)*(1-0.5)) -> 0.96226356 | F34: =E34/(1+(((Base_Curves!E11/Base_Curves!F11-1)/(2-1))+Curve_Shocks_bps!F33/10000)*(2-1)) -> 0.92221324 | G34: =F34/(1+(((Base_Curves!F11/Base_Curves!G11-1)/(3-2))+Curve_Shocks_bps!G33/10000)*(3-2)) -> 0.88419128 | H34: =G34/(1+(((Base_Curves!G11/Base_Curves!H11-1)/(5-3))+Curve_Shocks_bps!H33/10000)*(5-3)) -> 0.81292196 | I34: =H34/(1+(((Base_Curves!H11/Base_Curves!I11-1)/(10-5))+Curve_Shocks_bps!I33/10000)*(10-5)) -> 0.65947994 | J34: =I34/(1+(((Base_Curves!I11/Base_Curves!J11-1)/(20-10))+Curve_Shocks_bps!J33/10000)*(20-10)) -> 0.43459144 | K34: =J34/(1+(((Base_Curves!J11/Base_Curves!K11-1)/(30-20))+Curve_Shocks_bps!K33/10000)*(30-20)) -> 0.28661891
A36: Scenario 5 | C36: 3M | D36: 6M | E36: 1Y | F36: 2Y | G36: 3Y | H36: 5Y | I36: 10Y | J36: 20Y | K36: 30Y
A37: SOFR | B37: IR | C37: =1/(1+(((1/Base_Curves!C6-1)/(0.25-0))+Curve_Shocks_bps!C36/10000)*(0.25-0)) -> 0.98776137 | D37: =C37/(1+(((Base_Curves!C6/Base_Curves!D6-1)/(0.5-0.25))+Curve_Shocks_bps!D36/10000)*(0.5-0.25)) -> 0.97864201 | E37: =D37/(1+(((Base_Curves!D6/Base_Curves!E6-1)/(1-0.5))+Curve_Shocks_bps!E36/10000)*(1-0.5)) -> 0.95548798 | F37: =E37/(1+(((Base_Curves!E6/Base_Curves!F6-1)/(2-1))+Curve_Shocks_bps!F36/10000)*(2-1)) -> 0.91199677 | G37: =F37/(1+(((Base_Curves!F6/Base_Curves!G6-1)/(3-2))+Curve_Shocks_bps!G36/10000)*(3-2)) -> 0.8710808 | H37: =G37/(1+(((Base_Curves!G6/Base_Curves!H6-1)/(5-3))+Curve_Shocks_bps!H36/10000)*(5-3)) -> 0.79575158 | I37: =H37/(1+(((Base_Curves!H6/Base_Curves!I6-1)/(10-5))+Curve_Shocks_bps!I36/10000)*(10-5)) -> 0.63316178 | J37: =I37/(1+(((Base_Curves!I6/Base_Curves!J6-1)/(20-10))+Curve_Shocks_bps!J36/10000)*(20-10)) -> 0.40486374 | K37: =J37/(1+(((Base_Curves!J6/Base_Curves!K6-1)/(30-20))+Curve_Shocks_bps!K36/10000)*(30-20)) -> 0.25906435
A38: ESTRN | B38: IR | C38: =1/(1+(((1/Base_Curves!C7-1)/(0.25-0))+Curve_Shocks_bps!C37/10000)*(0.25-0)) -> 0.99084047 | D38: =C38/(1+(((Base_Curves!C7/Base_Curves!D7-1)/(0.5-0.25))+Curve_Shocks_bps!D37/10000)*(0.5-0.25)) -> 0.98196266 | E38: =D38/(1+(((Base_Curves!D7/Base_Curves!E7-1)/(1-0.5))+Curve_Shocks_bps!E37/10000)*(1-0.5)) -> 0.96483623 | F38: =E38/(1+(((Base_Curves!E7/Base_Curves!F7-1)/(2-1))+Curve_Shocks_bps!F37/10000)*(2-1)) -> 0.93238031 | G38: =F38/(1+(((Base_Curves!F7/Base_Curves!G7-1)/(3-2))+Curve_Shocks_bps!G37/10000)*(3-2)) -> 0.90177452 | H38: =G38/(1+(((Base_Curves!G7/Base_Curves!H7-1)/(5-3))+Curve_Shocks_bps!H37/10000)*(5-3)) -> 0.8442173 | I38: =H38/(1+(((Base_Curves!H7/Base_Curves!I7-1)/(10-5))+Curve_Shocks_bps!I37/10000)*(10-5)) -> 0.71361241 | J38: =I38/(1+(((Base_Curves!I7/Base_Curves!J7-1)/(20-10))+Curve_Shocks_bps!J37/10000)*(20-10)) -> 0.51642585 | K38: =J38/(1+(((Base_Curves!J7/Base_Curves!K7-1)/(30-20))+Curve_Shocks_bps!K37/10000)*(30-20)) -> 0.37283497
A39: Treasury | B39: Credit | C39: =1/(1+(((1/Base_Curves!C8-1)/(0.25-0))+Curve_Shocks_bps!C38/10000)*(0.25-0)) -> 0.99149108 | D39: =C39/(1+(((Base_Curves!C8/Base_Curves!D8-1)/(0.5-0.25))+Curve_Shocks_bps!D38/10000)*(0.5-0.25)) -> 0.9793986 | E39: =D39/(1+(((Base_Curves!D8/Base_Curves!E8-1)/(1-0.5))+Curve_Shocks_bps!E38/10000)*(1-0.5)) -> 0.95639571 | F39: =E39/(1+(((Base_Curves!E8/Base_Curves!F8-1)/(2-1))+Curve_Shocks_bps!F38/10000)*(2-1)) -> 0.91331146 | G39: =F39/(1+(((Base_Curves!F8/Base_Curves!G8-1)/(3-2))+Curve_Shocks_bps!G38/10000)*(3-2)) -> 0.87304007 | H39: =G39/(1+(((Base_Curves!G8/Base_Curves!H8-1)/(5-3))+Curve_Shocks_bps!H38/10000)*(5-3)) -> 0.79873964 | I39: =H39/(1+(((Base_Curves!H8/Base_Curves!I8-1)/(10-5))+Curve_Shocks_bps!I38/10000)*(10-5)) -> 0.64187539 | J39: =I39/(1+(((Base_Curves!I8/Base_Curves!J8-1)/(20-10))+Curve_Shocks_bps!J38/10000)*(20-10)) -> 0.41460474 | K39: =J39/(1+(((Base_Curves!J8/Base_Curves!K8-1)/(30-20))+Curve_Shocks_bps!K38/10000)*(30-20)) -> 0.26796026
A40: Agency_FNMA | B40: Credit | C40: =1/(1+(((1/Base_Curves!C9-1)/(0.25-0))+Curve_Shocks_bps!C39/10000)*(0.25-0)) -> 0.98564365 | D40: =C40/(1+(((Base_Curves!C9/Base_Curves!D9-1)/(0.5-0.25))+Curve_Shocks_bps!D39/10000)*(0.5-0.25)) -> 0.97168772 | E40: =D40/(1+(((Base_Curves!D9/Base_Curves!E9-1)/(1-0.5))+Curve_Shocks_bps!E39/10000)*(1-0.5)) -> 0.94534426 | F40: =E40/(1+(((Base_Curves!E9/Base_Curves!F9-1)/(2-1))+Curve_Shocks_bps!F39/10000)*(2-1)) -> 0.90810638 | G40: =F40/(1+(((Base_Curves!F9/Base_Curves!G9-1)/(3-2))+Curve_Shocks_bps!G39/10000)*(3-2)) -> 0.86308826 | H40: =G40/(1+(((Base_Curves!G9/Base_Curves!H9-1)/(5-3))+Curve_Shocks_bps!H39/10000)*(5-3)) -> 0.78193906 | I40: =H40/(1+(((Base_Curves!H9/Base_Curves!I9-1)/(10-5))+Curve_Shocks_bps!I39/10000)*(10-5)) -> 0.61696807 | J40: =I40/(1+(((Base_Curves!I9/Base_Curves!J9-1)/(20-10))+Curve_Shocks_bps!J39/10000)*(20-10)) -> 0.38528859 | K40: =J40/(1+(((Base_Curves!J9/Base_Curves!K9-1)/(30-20))+Curve_Shocks_bps!K39/10000)*(30-20)) -> 0.23896575
A41: Eur_Govt | B41: Credit | C41: =1/(1+(((1/Base_Curves!C10-1)/(0.25-0))+Curve_Shocks_bps!C40/10000)*(0.25-0)) -> 0.98951293 | D41: =C41/(1+(((Base_Curves!C10/Base_Curves!D10-1)/(0.5-0.25))+Curve_Shocks_bps!D40/10000)*(0.5-0.25)) -> 0.97933194 | E41: =D41/(1+(((Base_Curves!D10/Base_Curves!E10-1)/(1-0.5))+Curve_Shocks_bps!E40/10000)*(1-0.5)) -> 0.96004351 | F41: =E41/(1+(((Base_Curves!E10/Base_Curves!F10-1)/(2-1))+Curve_Shocks_bps!F40/10000)*(2-1)) -> 0.92422457 | G41: =F41/(1+(((Base_Curves!F10/Base_Curves!G10-1)/(3-2))+Curve_Shocks_bps!G40/10000)*(3-2)) -> 0.8907971 | H41: =G41/(1+(((Base_Curves!G10/Base_Curves!H10-1)/(5-3))+Curve_Shocks_bps!H40/10000)*(5-3)) -> 0.82925488 | I41: =H41/(1+(((Base_Curves!H10/Base_Curves!I10-1)/(10-5))+Curve_Shocks_bps!I40/10000)*(10-5)) -> 0.69774013 | J41: =I41/(1+(((Base_Curves!I10/Base_Curves!J10-1)/(20-10))+Curve_Shocks_bps!J40/10000)*(20-10)) -> 0.49272322 | K41: =J41/(1+(((Base_Curves!J10/Base_Curves!K10-1)/(30-20))+Curve_Shocks_bps!K40/10000)*(30-20)) -> 0.34809344
A42: EURUSD | B42: FX | C42: =1/(1+(((1/Base_Curves!C11-1)/(0.25-0))+Curve_Shocks_bps!C41/10000)*(0.25-0)) -> 0.98893952 | D42: =C42/(1+(((Base_Curves!C11/Base_Curves!D11-1)/(0.5-0.25))+Curve_Shocks_bps!D41/10000)*(0.5-0.25)) -> 0.97803788 | E42: =D42/(1+(((Base_Curves!D11/Base_Curves!E11-1)/(1-0.5))+Curve_Shocks_bps!E41/10000)*(1-0.5)) -> 0.95680489 | F42: =E42/(1+(((Base_Curves!E11/Base_Curves!F11-1)/(2-1))+Curve_Shocks_bps!F41/10000)*(2-1)) -> 0.91689389 | G42: =F42/(1+(((Base_Curves!F11/Base_Curves!G11-1)/(3-2))+Curve_Shocks_bps!G41/10000)*(3-2)) -> 0.87896483 | H42: =G42/(1+(((Base_Curves!G11/Base_Curves!H11-1)/(5-3))+Curve_Shocks_bps!H41/10000)*(5-3)) -> 0.80795336 | I42: =H42/(1+(((Base_Curves!H11/Base_Curves!I11-1)/(10-5))+Curve_Shocks_bps!I41/10000)*(10-5)) -> 0.65259036 | J42: =I42/(1+(((Base_Curves!I11/Base_Curves!J11-1)/(20-10))+Curve_Shocks_bps!J41/10000)*(20-10)) -> 0.43005126 | K42: =J42/(1+(((Base_Curves!J11/Base_Curves!K11-1)/(30-20))+Curve_Shocks_bps!K41/10000)*(30-20)) -> 0.28441241
A44: Scenario 6 | C44: 3M | D44: 6M | E44: 1Y | F44: 2Y | G44: 3Y | H44: 5Y | I44: 10Y | J44: 20Y | K44: 30Y
A45: SOFR | B45: IR | C45: =1/(1+(((1/Base_Curves!C6-1)/(0.25-0))+Curve_Shocks_bps!C44/10000)*(0.25-0)) -> 0.98744925 | D45: =C45/(1+(((Base_Curves!C6/Base_Curves!D6-1)/(0.5-0.25))+Curve_Shocks_bps!D44/10000)*(0.5-0.25)) -> 0.97839094 | E45: =D45/(1+(((Base_Curves!D6/Base_Curves!E6-1)/(1-0.5))+Curve_Shocks_bps!E44/10000)*(1-0.5)) -> 0.9549911 | F45: =E45/(1+(((Base_Curves!E6/Base_Curves!F6-1)/(2-1))+Curve_Shocks_bps!F44/10000)*(2-1)) -> 0.91102686 | G45: =F45/(1+(((Base_Curves!F6/Base_Curves!G6-1)/(3-2))+Curve_Shocks_bps!G44/10000)*(3-2)) -> 0.8741118 | H45: =G45/(1+(((Base_Curves!G6/Base_Curves!H6-1)/(5-3))+Curve_Shocks_bps!H44/10000)*(5-3)) -> 0.79834544 | I45: =H45/(1+(((Base_Curves!H6/Base_Curves!I6-1)/(10-5))+Curve_Shocks_bps!I44/10000)*(10-5)) -> 0.63525092 | J45: =I45/(1+(((Base_Curves!I6/Base_Curves!J6-1)/(20-10))+Curve_Shocks_bps!J44/10000)*(20-10)) -> 0.40609574 | K45: =J45/(1+(((Base_Curves!J6/Base_Curves!K6-1)/(30-20))+Curve_Shocks_bps!K44/10000)*(30-20)) -> 0.25985268
A46: ESTRN | B46: IR | C46: =1/(1+(((1/Base_Curves!C7-1)/(0.25-0))+Curve_Shocks_bps!C45/10000)*(0.25-0)) -> 0.99072758 | D46: =C46/(1+(((Base_Curves!C7/Base_Curves!D7-1)/(0.5-0.25))+Curve_Shocks_bps!D45/10000)*(0.5-0.25)) -> 0.98173889 | E46: =D46/(1+(((Base_Curves!D7/Base_Curves!E7-1)/(1-0.5))+Curve_Shocks_bps!E45/10000)*(1-0.5)) -> 0.96434632 | F46: =E46/(1+(((Base_Curves!E7/Base_Curves!F7-1)/(2-1))+Curve_Shocks_bps!F45/10000)*(2-1)) -> 0.93163679 | G46: =F46/(1+(((Base_Curves!F7/Base_Curves!G7-1)/(3-2))+Curve_Shocks_bps!G45/10000)*(3-2)) -> 0.90102055 | H46: =G46/(1+(((Base_Curves!G7/Base_Curves!H7-1)/(5-3))+Curve_Shocks_bps!H45/10000)*(5-3)) -> 0.84325883 | I46: =H46/(1+(((Base_Curves!H7/Base_Curves!I7-1)/(10-5))+Curve_Shocks_bps!I45/10000)*(10-5)) -> 0.7125914 | J46: =I46/(1+(((Base_Curves!I7/Base_Curves!J7-1)/(20-10))+Curve_Shocks_bps!J45/10000)*(20-10)) -> 0.51393891 | K46: =J46/(1+(((Base_Curves!J7/Base_Curves!K7-1)/(30-20))+Curve_Shocks_bps!K45/10000)*(30-20)) -> 0.37101273
A47: Treasury | B47: Credit | C47: =1/(1+(((1/Base_Curves!C8-1)/(0.25-0))+Curve_Shocks_bps!C46/10000)*(0.25-0)) -> 0.98746713 | D47: =C47/(1+(((Base_Curves!C8/Base_Curves!D8-1)/(0.5-0.25))+Curve_Shocks_bps!D46/10000)*(0.5-0.25)) -> 0.97524309 | E47: =D47/(1+(((Base_Curves!D8/Base_Curves!E8-1)/(1-0.5))+Curve_Shocks_bps!E46/10000)*(1-0.5)) -> 0.9521379 | F47: =E47/(1+(((Base_Curves!E8/Base_Curves!F8-1)/(2-1))+Curve_Shocks_bps!F46/10000)*(2-1)) -> 0.91644806 | G47: =F47/(1+(((Base_Curves!F8/Base_Curves!G8-1)/(3-2))+Curve_Shocks_bps!G46/10000)*(3-2)) -> 0.87574536 | H47: =G47/(1+(((Base_Curves!G8/Base_Curves!H8-1)/(5-3))+Curve_Shocks_bps!H46/10000)*(5-3)) -> 0.80112674 | I47: =H47/(1+(((Base_Curves!H8/Base_Curves!I8-1)/(10-5))+Curve_Shocks_bps!I46/10000)*(10-5)) -> 0.64394893 | J47: =I47/(1+(((Base_Curves!I8/Base_Curves!J8-1)/(20-10))+Curve_Shocks_bps!J46/10000)*(20-10)) -> 0.41578296 | K47: =J47/(1+(((Base_Curves!J8/Base_Curves!K8-1)/(30-20))+Curve_Shocks_bps!K46/10000)*(30-20)) -> 0.26872175
A48: Agency_FNMA | B48: Credit | C48: =1/(1+(((1/Base_Curves!C9-1)/(0.25-0))+Curve_Shocks_bps!C47/10000)*(0.25-0)) -> 0.98538384 | D48: =C48/(1+(((Base_Curves!C9/Base_Curves!D9-1)/(0.5-0.25))+Curve_Shocks_bps!D47/10000)*(0.5-0.25)) -> 0.97110848 | E48: =D48/(1+(((Base_Curves!D9/Base_Curves!E9-1)/(1-0.5))+Curve_Shocks_bps!E47/10000)*(1-0.5)) -> 0.94448209 | F48: =E48/(1+(((Base_Curves!E9/Base_Curves!F9-1)/(2-1))+Curve_Shocks_bps!F47/10000)*(2-1)) -> 0.89574796 | G48: =F48/(1+(((Base_Curves!F9/Base_Curves!G9-1)/(3-2))+Curve_Shocks_bps!G47/10000)*(3-2)) -> 0.85091386 | H48: =G48/(1+(((Base_Curves!G9/Base_Curves!H9-1)/(5-3))+Curve_Shocks_bps!H47/10000)*(5-3)) -> 0.77043468 | I48: =H48/(1+(((Base_Curves!H9/Base_Curves!I9-1)/(10-5))+Curve_Shocks_bps!I47/10000)*(10-5)) -> 0.60242459 | J48: =I48/(1+(((Base_Curves!I9/Base_Curves!J9-1)/(20-10))+Curve_Shocks_bps!J47/10000)*(20-10)) -> 0.37303815 | K48: =J48/(1+(((Base_Curves!J9/Base_Curves!K9-1)/(30-20))+Curve_Shocks_bps!K47/10000)*(30-20)) -> 0.23126731
A49: Eur_Govt | B49: Credit | C49: =1/(1+(((1/Base_Curves!C10-1)/(0.25-0))+Curve_Shocks_bps!C48/10000)*(0.25-0)) -> 0.98907496 | D49: =C49/(1+(((Base_Curves!C10/Base_Curves!D10-1)/(0.5-0.25))+Curve_Shocks_bps!D48/10000)*(0.5-0.25)) -> 0.97856192 | E49: =D49/(1+(((Base_Curves!D10/Base_Curves!E10-1)/(1-0.5))+Curve_Shocks_bps!E48/10000)*(1-0.5)) -> 0.95861205 | F49: =E49/(1+(((Base_Curves!E10/Base_Curves!F10-1)/(2-1))+Curve_Shocks_bps!F48/10000)*(2-1)) -> 0.92209199 | G49: =F49/(1+(((Base_Curves!F10/Base_Curves!G10-1)/(3-2))+Curve_Shocks_bps!G48/10000)*(3-2)) -> 0.89432728 | H49: =G49/(1+(((Base_Curves!G10/Base_Curves!H10-1)/(5-3))+Curve_Shocks_bps!H48/10000)*(5-3)) -> 0.83792341 | I49: =H49/(1+(((Base_Curves!H10/Base_Curves!I10-1)/(10-5))+Curve_Shocks_bps!I48/10000)*(10-5)) -> 0.69967661 | J49: =I49/(1+(((Base_Curves!I10/Base_Curves!J10-1)/(20-10))+Curve_Shocks_bps!J48/10000)*(20-10)) -> 0.49391631 | K49: =J49/(1+(((Base_Curves!J10/Base_Curves!K10-1)/(30-20))+Curve_Shocks_bps!K48/10000)*(30-20)) -> 0.34891167
A50: EURUSD | B50: FX | C50: =1/(1+(((1/Base_Curves!C11-1)/(0.25-0))+Curve_Shocks_bps!C49/10000)*(0.25-0)) -> 0.98878062 | D50: =C50/(1+(((Base_Curves!C11/Base_Curves!D11-1)/(0.5-0.25))+Curve_Shocks_bps!D49/10000)*(0.5-0.25)) -> 0.97999842 | E50: =D50/(1+(((Base_Curves!D11/Base_Curves!E11-1)/(1-0.5))+Curve_Shocks_bps!E49/10000)*(1-0.5)) -> 0.95873693 | F50: =E50/(1+(((Base_Curves!E11/Base_Curves!F11-1)/(2-1))+Curve_Shocks_bps!F49/10000)*(2-1)) -> 0.9229909 | G50: =F50/(1+(((Base_Curves!F11/Base_Curves!G11-1)/(3-2))+Curve_Shocks_bps!G49/10000)*(3-2)) -> 0.88458915 | H50: =G50/(1+(((Base_Curves!G11/Base_Curves!H11-1)/(5-3))+Curve_Shocks_bps!H49/10000)*(5-3)) -> 0.81288419 | I50: =H50/(1+(((Base_Curves!H11/Base_Curves!I11-1)/(10-5))+Curve_Shocks_bps!I49/10000)*(10-5)) -> 0.65974366 | J50: =I50/(1+(((Base_Curves!I11/Base_Curves!J11-1)/(20-10))+Curve_Shocks_bps!J49/10000)*(20-10)) -> 0.43456477 | K50: =J50/(1+(((Base_Curves!J11/Base_Curves!K11-1)/(30-20))+Curve_Shocks_bps!K49/10000)*(30-20)) -> 0.28648795
A52: Scenario 7 | C52: 3M | D52: 6M | E52: 1Y | F52: 2Y | G52: 3Y | H52: 5Y | I52: 10Y | J52: 20Y | K52: 30Y
A53: SOFR | B53: IR | C53: =1/(1+(((1/Base_Curves!C6-1)/(0.25-0))+Curve_Shocks_bps!C52/10000)*(0.25-0)) -> 0.98737125 | D53: =C53/(1+(((Base_Curves!C6/Base_Curves!D6-1)/(0.5-0.25))+Curve_Shocks_bps!D52/10000)*(0.5-0.25)) -> 0.97847604 | E53: =D53/(1+(((Base_Curves!D6/Base_Curves!E6-1)/(1-0.5))+Curve_Shocks_bps!E52/10000)*(1-0.5)) -> 0.95463157 | F53: =E53/(1+(((Base_Curves!E6/Base_Curves!F6-1)/(2-1))+Curve_Shocks_bps!F52/10000)*(2-1)) -> 0.91045806 | G53: =F53/(1+(((Base_Curves!F6/Base_Curves!G6-1)/(3-2))+Curve_Shocks_bps!G52/10000)*(3-2)) -> 0.86940352 | H53: =G53/(1+(((Base_Curves!G6/Base_Curves!H6-1)/(5-3))+Curve_Shocks_bps!H52/10000)*(5-3)) -> 0.79767335 | I53: =H53/(1+(((Base_Curves!H6/Base_Curves!I6-1)/(10-5))+Curve_Shocks_bps!I52/10000)*(10-5)) -> 0.63446371 | J53: =I53/(1+(((Base_Curves!I6/Base_Curves!J6-1)/(20-10))+Curve_Shocks_bps!J52/10000)*(20-10)) -> 0.40767742 | K53: =J53/(1+(((Base_Curves!J6/Base_Curves!K6-1)/(30-20))+Curve_Shocks_bps!K52/10000)*(30-20)) -> 0.26079802
A54: ESTRN | B54: IR | C54: =1/(1+(((1/Base_Curves!C7-1)/(0.25-0))+Curve_Shocks_bps!C53/10000)*(0.25-0)) -> 0.99059264 | D54: =C54/(1+(((Base_Curves!C7/Base_Curves!D7-1)/(0.5-0.25))+Curve_Shocks_bps!D53/10000)*(0.5-0.25)) -> 0.98146659 | E54: =D54/(1+(((Base_Curves!D7/Base_Curves!E7-1)/(1-0.5))+Curve_Shocks_bps!E53/10000)*(1-0.5)) -> 0.96389894 | F54: =E54/(1+(((Base_Curves!E7/Base_Curves!F7-1)/(2-1))+Curve_Shocks_bps!F53/10000)*(2-1)) -> 0.93089881 | G54: =F54/(1+(((Base_Curves!F7/Base_Curves!G7-1)/(3-2))+Curve_Shocks_bps!G53/10000)*(3-2)) -> 0.90005438 | H54: =G54/(1+(((Base_Curves!G7/Base_Curves!H7-1)/(5-3))+Curve_Shocks_bps!H53/10000)*(5-3)) -> 0.84219696 | I54: =H54/(1+(((Base_Curves!H7/Base_Curves!I7-1)/(10-5))+Curve_Shocks_bps!I53/10000)*(10-5)) -> 0.711664 | J54: =I54/(1+(((Base_Curves!I7/Base_Curves!J7-1)/(20-10))+Curve_Shocks_bps!J53/10000)*(20-10)) -> 0.51319602 | K54: =J54/(1+(((Base_Curves!J7/Base_Curves!K7-1)/(30-20))+Curve_Shocks_bps!K53/10000)*(30-20)) -> 0.37114627
A55: Treasury | B55: Credit | C55: =1/(1+(((1/Base_Curves!C8-1)/(0.25-0))+Curve_Shocks_bps!C54/10000)*(0.25-0)) -> 0.98742569 | D55: =C55/(1+(((Base_Curves!C8/Base_Curves!D8-1)/(0.5-0.25))+Curve_Shocks_bps!D54/10000)*(0.5-0.25)) -> 0.97499032 | E55: =D55/(1+(((Base_Curves!D8/Base_Curves!E8-1)/(1-0.5))+Curve_Shocks_bps!E54/10000)*(1-0.5)) -> 0.9516449 | F55: =E55/(1+(((Base_Curves!E8/Base_Curves!F8-1)/(2-1))+Curve_Shocks_bps!F54/10000)*(2-1)) -> 0.90797697 | G55: =F55/(1+(((Base_Curves!F8/Base_Curves!G8-1)/(3-2))+Curve_Shocks_bps!G54/10000)*(3-2)) -> 0.86750958 | H55: =G55/(1+(((Base_Curves!G8/Base_Curves!H8-1)/(5-3))+Curve_Shocks_bps!H54/10000)*(5-3)) -> 0.79331693 | I55: =H55/(1+(((Base_Curves!H8/Base_Curves!I8-1)/(10-5))+Curve_Shocks_bps!I54/10000)*(10-5)) -> 0.63379955 | J55: =I55/(1+(((Base_Curves!I8/Base_Curves!J8-1)/(20-10))+Curve_Shocks_bps!J54/10000)*(20-10)) -> 0.40920332 | K55: =J55/(1+(((Base_Curves!J8/Base_Curves!K8-1)/(30-20))+Curve_Shocks_bps!K54/10000)*(30-20)) -> 0.26440095
A56: Agency_FNMA | B56: Credit | C56: =1/(1+(((1/Base_Curves!C9-1)/(0.25-0))+Curve_Shocks_bps!C55/10000)*(0.25-0)) -> 0.99225746 | D56: =C56/(1+(((Base_Curves!C9/Base_Curves!D9-1)/(0.5-0.25))+Curve_Shocks_bps!D55/10000)*(0.5-0.25)) -> 0.97782229 | E56: =D56/(1+(((Base_Curves!D9/Base_Curves!E9-1)/(1-0.5))+Curve_Shocks_bps!E55/10000)*(1-0.5)) -> 0.95011547 | F56: =E56/(1+(((Base_Curves!E9/Base_Curves!F9-1)/(2-1))+Curve_Shocks_bps!F55/10000)*(2-1)) -> 0.91372538 | G56: =F56/(1+(((Base_Curves!F9/Base_Curves!G9-1)/(3-2))+Curve_Shocks_bps!G55/10000)*(3-2)) -> 0.86752173 | H56: =G56/(1+(((Base_Curves!G9/Base_Curves!H9-1)/(5-3))+Curve_Shocks_bps!H55/10000)*(5-3)) -> 0.78500269 | I56: =H56/(1+(((Base_Curves!H9/Base_Curves!I9-1)/(10-5))+Curve_Shocks_bps!I55/10000)*(10-5)) -> 0.61994787 | J56: =I56/(1+(((Base_Curves!I9/Base_Curves!J9-1)/(20-10))+Curve_Shocks_bps!J55/10000)*(20-10)) -> 0.38374648 | K56: =J56/(1+(((Base_Curves!J9/Base_Curves!K9-1)/(30-20))+Curve_Shocks_bps!K55/10000)*(30-20)) -> 0.23787651
A57: Eur_Govt | B57: Credit | C57: =1/(1+(((1/Base_Curves!C10-1)/(0.25-0))+Curve_Shocks_bps!C56/10000)*(0.25-0)) -> 0.98900649 | D57: =C57/(1+(((Base_Curves!C10/Base_Curves!D10-1)/(0.5-0.25))+Curve_Shocks_bps!D56/10000)*(0.5-0.25)) -> 0.9781869 | E57: =D57/(1+(((Base_Curves!D10/Base_Curves!E10-1)/(1-0.5))+Curve_Shocks_bps!E56/10000)*(1-0.5)) -> 0.95780838 | F57: =E57/(1+(((Base_Curves!E10/Base_Curves!F10-1)/(2-1))+Curve_Shocks_bps!F56/10000)*(2-1)) -> 0.92090259 | G57: =F57/(1+(((Base_Curves!F10/Base_Curves!G10-1)/(3-2))+Curve_Shocks_bps!G56/10000)*(3-2)) -> 0.88734725 | H57: =G57/(1+(((Base_Curves!G10/Base_Curves!H10-1)/(5-3))+Curve_Shocks_bps!H56/10000)*(5-3)) -> 0.8256437 | I57: =H57/(1+(((Base_Curves!H10/Base_Curves!I10-1)/(10-5))+Curve_Shocks_bps!I56/10000)*(10-5)) -> 0.68902015 | J57: =I57/(1+(((Base_Curves!I10/Base_Curves!J10-1)/(20-10))+Curve_Shocks_bps!J56/10000)*(20-10)) -> 0.48615346 | K57: =J57/(1+(((Base_Curves!J10/Base_Curves!K10-1)/(30-20))+Curve_Shocks_bps!K56/10000)*(30-20)) -> 0.34528159
A58: EURUSD | B58: FX | C58: =1/(1+(((1/Base_Curves!C11-1)/(0.25-0))+Curve_Shocks_bps!C57/10000)*(0.25-0)) -> 0.98877329 | D58: =C58/(1+(((Base_Curves!C11/Base_Curves!D11-1)/(0.5-0.25))+Curve_Shocks_bps!D57/10000)*(0.5-0.25)) -> 0.97766801 | E58: =D58/(1+(((Base_Curves!D11/Base_Curves!E11-1)/(1-0.5))+Curve_Shocks_bps!E57/10000)*(1-0.5)) -> 0.95626063 | F58: =E58/(1+(((Base_Curves!E11/Base_Curves!F11-1)/(2-1))+Curve_Shocks_bps!F57/10000)*(2-1)) -> 0.91586329 | G58: =F58/(1+(((Base_Curves!F11/Base_Curves!G11-1)/(3-2))+Curve_Shocks_bps!G57/10000)*(3-2)) -> 0.87755624 | H58: =G58/(1+(((Base_Curves!G11/Base_Curves!H11-1)/(5-3))+Curve_Shocks_bps!H57/10000)*(5-3)) -> 0.80639172 | I58: =H58/(1+(((Base_Curves!H11/Base_Curves!I11-1)/(10-5))+Curve_Shocks_bps!I57/10000)*(10-5)) -> 0.65111865 | J58: =I58/(1+(((Base_Curves!I11/Base_Curves!J11-1)/(20-10))+Curve_Shocks_bps!J57/10000)*(20-10)) -> 0.42885533 | K58: =J58/(1+(((Base_Curves!J11/Base_Curves!K11-1)/(30-20))+Curve_Shocks_bps!K57/10000)*(30-20)) -> 0.28266808
A60: Scenario 8 | C60: 3M | D60: 6M | E60: 1Y | F60: 2Y | G60: 3Y | H60: 5Y | I60: 10Y | J60: 20Y | K60: 30Y
A61: SOFR | B61: IR | C61: =1/(1+(((1/Base_Curves!C6-1)/(0.25-0))+Curve_Shocks_bps!C60/10000)*(0.25-0)) -> 0.98719337 | D61: =C61/(1+(((Base_Curves!C6/Base_Curves!D6-1)/(0.5-0.25))+Curve_Shocks_bps!D60/10000)*(0.5-0.25)) -> 0.97478111 | E61: =D61/(1+(((Base_Curves!D6/Base_Curves!E6-1)/(1-0.5))+Curve_Shocks_bps!E60/10000)*(1-0.5)) -> 0.95085969 | F61: =E61/(1+(((Base_Curves!E6/Base_Curves!F6-1)/(2-1))+Curve_Shocks_bps!F60/10000)*(2-1)) -> 0.90660132 | G61: =F61/(1+(((Base_Curves!F6/Base_Curves!G6-1)/(3-2))+Curve_Shocks_bps!G60/10000)*(3-2)) -> 0.86540666 | H61: =G61/(1+(((Base_Curves!G6/Base_Curves!H6-1)/(5-3))+Curve_Shocks_bps!H60/10000)*(5-3)) -> 0.79013505 | I61: =H61/(1+(((Base_Curves!H6/Base_Curves!I6-1)/(10-5))+Curve_Shocks_bps!I60/10000)*(10-5)) -> 0.62844281 | J61: =I61/(1+(((Base_Curves!I6/Base_Curves!J6-1)/(20-10))+Curve_Shocks_bps!J60/10000)*(20-10)) -> 0.40161515 | K61: =J61/(1+(((Base_Curves!J6/Base_Curves!K6-1)/(30-20))+Curve_Shocks_bps!K60/10000)*(30-20)) -> 0.25690345
A62: ESTRN | B62: IR | C62: =1/(1+(((1/Base_Curves!C7-1)/(0.25-0))+Curve_Shocks_bps!C61/10000)*(0.25-0)) -> 0.99404398 | D62: =C62/(1+(((Base_Curves!C7/Base_Curves!D7-1)/(0.5-0.25))+Curve_Shocks_bps!D61/10000)*(0.5-0.25)) -> 0.9846837 | E62: =D62/(1+(((Base_Curves!D7/Base_Curves!E7-1)/(1-0.5))+Curve_Shocks_bps!E61/10000)*(1-0.5)) -> 0.97201771 | F62: =E62/(1+(((Base_Curves!E7/Base_Curves!F7-1)/(2-1))+Curve_Shocks_bps!F61/10000)*(2-1)) -> 0.93854929 | G62: =F62/(1+(((Base_Curves!F7/Base_Curves!G7-1)/(3-2))+Curve_Shocks_bps!G61/10000)*(3-2)) -> 0.90728469 | H62: =G62/(1+(((Base_Curves!G7/Base_Curves!H7-1)/(5-3))+Curve_Shocks_bps!H61/10000)*(5-3)) -> 0.84893072 | I62: =H62/(1+(((Base_Curves!H7/Base_Curves!I7-1)/(10-5))+Curve_Shocks_bps!I61/10000)*(10-5)) -> 0.71708141 | J62: =I62/(1+(((Base_Curves!I7/Base_Curves!J7-1)/(20-10))+Curve_Shocks_bps!J61/10000)*(20-10)) -> 0.51702807 | K62: =J62/(1+(((Base_Curves!J7/Base_Curves!K7-1)/(30-20))+Curve_Shocks_bps!K61/10000)*(30-20)) -> 0.37316198
A63: Treasury | B63: Credit | C63: =1/(1+(((1/Base_Curves!C8-1)/(0.25-0))+Curve_Shocks_bps!C62/10000)*(0.25-0)) -> 0.9869993 | D63: =C63/(1+(((Base_Curves!C8/Base_Curves!D8-1)/(0.5-0.25))+Curve_Shocks_bps!D62/10000)*(0.5-0.25)) -> 0.9744779 | E63: =D63/(1+(((Base_Curves!D8/Base_Curves!E8-1)/(1-0.5))+Curve_Shocks_bps!E62/10000)*(1-0.5)) -> 0.95082457 | F63: =E63/(1+(((Base_Curves!E8/Base_Curves!F8-1)/(2-1))+Curve_Shocks_bps!F62/10000)*(2-1)) -> 0.90695199 | G63: =F63/(1+(((Base_Curves!F8/Base_Curves!G8-1)/(3-2))+Curve_Shocks_bps!G62/10000)*(3-2)) -> 0.8664475 | H63: =G63/(1+(((Base_Curves!G8/Base_Curves!H8-1)/(5-3))+Curve_Shocks_bps!H62/10000)*(5-3)) -> 0.79221527 | I63: =H63/(1+(((Base_Curves!H8/Base_Curves!I8-1)/(10-5))+Curve_Shocks_bps!I62/10000)*(10-5)) -> 0.63716998 | J63: =I63/(1+(((Base_Curves!I8/Base_Curves!J8-1)/(20-10))+Curve_Shocks_bps!J62/10000)*(20-10)) -> 0.41127317 | K63: =J63/(1+(((Base_Curves!J8/Base_Curves!K8-1)/(30-20))+Curve_Shocks_bps!K62/10000)*(30-20)) -> 0.26570402
A64: Agency_FNMA | B64: Credit | C64: =1/(1+(((1/Base_Curves!C9-1)/(0.25-0))+Curve_Shocks_bps!C63/10000)*(0.25-0)) -> 0.98474826 | D64: =C64/(1+(((Base_Curves!C9/Base_Curves!D9-1)/(0.5-0.25))+Curve_Shocks_bps!D63/10000)*(0.5-0.25)) -> 0.97015226 | E64: =D64/(1+(((Base_Curves!D9/Base_Curves!E9-1)/(1-0.5))+Curve_Shocks_bps!E63/10000)*(1-0.5)) -> 0.94234687 | F64: =E64/(1+(((Base_Curves!E9/Base_Curves!F9-1)/(2-1))+Curve_Shocks_bps!F63/10000)*(2-1)) -> 0.9072315 | G64: =F64/(1+(((Base_Curves!F9/Base_Curves!G9-1)/(3-2))+Curve_Shocks_bps!G63/10000)*(3-2)) -> 0.86096386 | H64: =G64/(1+(((Base_Curves!G9/Base_Curves!H9-1)/(5-3))+Curve_Shocks_bps!H63/10000)*(5-3)) -> 0.77878672 | I64: =H64/(1+(((Base_Curves!H9/Base_Curves!I9-1)/(10-5))+Curve_Shocks_bps!I63/10000)*(10-5)) -> 0.60836066 | J64: =I64/(1+(((Base_Curves!I9/Base_Curves!J9-1)/(20-10))+Curve_Shocks_bps!J63/10000)*(20-10)) -> 0.3762247 | K64: =J64/(1+(((Base_Curves!J9/Base_Curves!K9-1)/(30-20))+Curve_Shocks_bps!K63/10000)*(30-20)) -> 0.23318501
A65: Eur_Govt | B65: Credit | C65: =1/(1+(((1/Base_Curves!C10-1)/(0.25-0))+Curve_Shocks_bps!C64/10000)*(0.25-0)) -> 0.98858851 | D65: =C65/(1+(((Base_Curves!C10/Base_Curves!D10-1)/(0.5-0.25))+Curve_Shocks_bps!D64/10000)*(0.5-0.25)) -> 0.97754871 | E65: =D65/(1+(((Base_Curves!D10/Base_Curves!E10-1)/(1-0.5))+Curve_Shocks_bps!E64/10000)*(1-0.5)) -> 0.95705696 | F65: =E65/(1+(((Base_Curves!E10/Base_Curves!F10-1)/(2-1))+Curve_Shocks_bps!F64/10000)*(2-1)) -> 0.91970263 | G65: =F65/(1+(((Base_Curves!F10/Base_Curves!G10-1)/(3-2))+Curve_Shocks_bps!G64/10000)*(3-2)) -> 0.88569602 | H65: =G65/(1+(((Base_Curves!G10/Base_Curves!H10-1)/(5-3))+Curve_Shocks_bps!H64/10000)*(5-3)) -> 0.82384666 | I65: =H65/(1+(((Base_Curves!H10/Base_Curves!I10-1)/(10-5))+Curve_Shocks_bps!I64/10000)*(10-5)) -> 0.6874918 | J65: =I65/(1+(((Base_Curves!I10/Base_Curves!J10-1)/(20-10))+Curve_Shocks_bps!J64/10000)*(20-10)) -> 0.48490403 | K65: =J65/(1+(((Base_Curves!J10/Base_Curves!K10-1)/(30-20))+Curve_Shocks_bps!K64/10000)*(30-20)) -> 0.34232759
A66: EURUSD | B66: FX | C66: =1/(1+(((1/Base_Curves!C11-1)/(0.25-0))+Curve_Shocks_bps!C65/10000)*(0.25-0)) -> 0.98866087 | D66: =C66/(1+(((Base_Curves!C11/Base_Curves!D11-1)/(0.5-0.25))+Curve_Shocks_bps!D65/10000)*(0.5-0.25)) -> 0.97744813 | E66: =D66/(1+(((Base_Curves!D11/Base_Curves!E11-1)/(1-0.5))+Curve_Shocks_bps!E65/10000)*(1-0.5)) -> 0.96022971 | F66: =E66/(1+(((Base_Curves!E11/Base_Curves!F11-1)/(2-1))+Curve_Shocks_bps!F65/10000)*(2-1)) -> 0.91952379 | G66: =F66/(1+(((Base_Curves!F11/Base_Curves!G11-1)/(3-2))+Curve_Shocks_bps!G65/10000)*(3-2)) -> 0.88090326 | H66: =G66/(1+(((Base_Curves!G11/Base_Curves!H11-1)/(5-3))+Curve_Shocks_bps!H65/10000)*(5-3)) -> 0.80925911 | I66: =H66/(1+(((Base_Curves!H11/Base_Curves!I11-1)/(10-5))+Curve_Shocks_bps!I65/10000)*(10-5)) -> 0.65335478 | J66: =I66/(1+(((Base_Curves!I11/Base_Curves!J11-1)/(20-10))+Curve_Shocks_bps!J65/10000)*(20-10)) -> 0.43015815 | K66: =J66/(1+(((Base_Curves!J11/Base_Curves!K11-1)/(30-20))+Curve_Shocks_bps!K65/10000)*(30-20)) -> 0.28350811
A68: Scenario 9 | C68: 3M | D68: 6M | E68: 1Y | F68: 2Y | G68: 3Y | H68: 5Y | I68: 10Y | J68: 20Y | K68: 30Y
A69: SOFR | B69: IR | C69: =1/(1+(((1/Base_Curves!C6-1)/(0.25-0))+Curve_Shocks_bps!C68/10000)*(0.25-0)) -> 0.98714951 | D69: =C69/(1+(((Base_Curves!C6/Base_Curves!D6-1)/(0.5-0.25))+Curve_Shocks_bps!D68/10000)*(0.5-0.25)) -> 0.9745694 | E69: =D69/(1+(((Base_Curves!D6/Base_Curves!E6-1)/(1-0.5))+Curve_Shocks_bps!E68/10000)*(1-0.5)) -> 0.95063 | F69: =E69/(1+(((Base_Curves!E6/Base_Curves!F6-1)/(2-1))+Curve_Shocks_bps!F68/10000)*(2-1)) -> 0.90617496 | G69: =F69/(1+(((Base_Curves!F6/Base_Curves!G6-1)/(3-2))+Curve_Shocks_bps!G68/10000)*(3-2)) -> 0.86985711 | H69: =G69/(1+(((Base_Curves!G6/Base_Curves!H6-1)/(5-3))+Curve_Shocks_bps!H68/10000)*(5-3)) -> 0.79393745 | I69: =H69/(1+(((Base_Curves!H6/Base_Curves!I6-1)/(10-5))+Curve_Shocks_bps!I68/10000)*(10-5)) -> 0.63129135 | J69: =I69/(1+(((Base_Curves!I6/Base_Curves!J6-1)/(20-10))+Curve_Shocks_bps!J68/10000)*(20-10)) -> 0.40340978 | K69: =J69/(1+(((Base_Curves!J6/Base_Curves!K6-1)/(30-20))+Curve_Shocks_bps!K68/10000)*(30-20)) -> 0.25801842
A70: ESTRN | B70: IR | C70: =1/(1+(((1/Base_Curves!C7-1)/(0.25-0))+Curve_Shocks_bps!C69/10000)*(0.25-0)) -> 0.9904749 | D70: =C70/(1+(((Base_Curves!C7/Base_Curves!D7-1)/(0.5-0.25))+Curve_Shocks_bps!D69/10000)*(0.5-0.25)) -> 0.98104375 | E70: =D70/(1+(((Base_Curves!D7/Base_Curves!E7-1)/(1-0.5))+Curve_Shocks_bps!E69/10000)*(1-0.5)) -> 0.96317151 | F70: =E70/(1+(((Base_Curves!E7/Base_Curves!F7-1)/(2-1))+Curve_Shocks_bps!F69/10000)*(2-1)) -> 0.92993585 | G70: =F70/(1+(((Base_Curves!F7/Base_Curves!G7-1)/(3-2))+Curve_Shocks_bps!G69/10000)*(3-2)) -> 0.89883653 | H70: =G70/(1+(((Base_Curves!G7/Base_Curves!H7-1)/(5-3))+Curve_Shocks_bps!H69/10000)*(5-3)) -> 0.8408843 | I70: =H70/(1+(((Base_Curves!H7/Base_Curves!I7-1)/(10-5))+Curve_Shocks_bps!I69/10000)*(10-5)) -> 0.7102847 | J70: =I70/(1+(((Base_Curves!I7/Base_Curves!J7-1)/(20-10))+Curve_Shocks_bps!J69/10000)*(20-10)) -> 0.51205368 | K70: =J70/(1+(((Base_Curves!J7/Base_Curves!K7-1)/(30-20))+Curve_Shocks_bps!K69/10000)*(30-20)) -> 0.36954507
A71: Treasury | B71: Credit | C71: =1/(1+(((1/Base_Curves!C8-1)/(0.25-0))+Curve_Shocks_bps!C70/10000)*(0.25-0)) -> 0.98678016 | D71: =C71/(1+(((Base_Curves!C8/Base_Curves!D8-1)/(0.5-0.25))+Curve_Shocks_bps!D70/10000)*(0.5-0.25)) -> 0.97391298 | E71: =D71/(1+(((Base_Curves!D8/Base_Curves!E8-1)/(1-0.5))+Curve_Shocks_bps!E70/10000)*(1-0.5)) -> 0.95006942 | F71: =E71/(1+(((Base_Curves!E8/Base_Curves!F8-1)/(2-1))+Curve_Shocks_bps!F70/10000)*(2-1)) -> 0.90581695 | G71: =F71/(1+(((Base_Curves!F8/Base_Curves!G8-1)/(3-2))+Curve_Shocks_bps!G70/10000)*(3-2)) -> 0.86523089 | H71: =G71/(1+(((Base_Curves!G8/Base_Curves!H8-1)/(5-3))+Curve_Shocks_bps!H70/10000)*(5-3)) -> 0.79092934 | I71: =H71/(1+(((Base_Curves!H8/Base_Curves!I8-1)/(10-5))+Curve_Shocks_bps!I70/10000)*(10-5)) -> 0.63166495 | J71: =I71/(1+(((Base_Curves!I8/Base_Curves!J8-1)/(20-10))+Curve_Shocks_bps!J70/10000)*(20-10)) -> 0.40761461 | K71: =J71/(1+(((Base_Curves!J8/Base_Curves!K8-1)/(30-20))+Curve_Shocks_bps!K70/10000)*(30-20)) -> 0.26330637
A72: Agency_FNMA | B72: Credit | C72: =1/(1+(((1/Base_Curves!C9-1)/(0.25-0))+Curve_Shocks_bps!C71/10000)*(0.25-0)) -> 0.98436052 | D72: =C72/(1+(((Base_Curves!C9/Base_Curves!D9-1)/(0.5-0.25))+Curve_Shocks_bps!D71/10000)*(0.5-0.25)) -> 0.96932859 | E72: =D72/(1+(((Base_Curves!D9/Base_Curves!E9-1)/(1-0.5))+Curve_Shocks_bps!E71/10000)*(1-0.5)) -> 0.94108519 | F72: =E72/(1+(((Base_Curves!E9/Base_Curves!F9-1)/(2-1))+Curve_Shocks_bps!F71/10000)*(2-1)) -> 0.89039831 | G72: =F72/(1+(((Base_Curves!F9/Base_Curves!G9-1)/(3-2))+Curve_Shocks_bps!G71/10000)*(3-2)) -> 0.84479673 | H72: =G72/(1+(((Base_Curves!G9/Base_Curves!H9-1)/(5-3))+Curve_Shocks_bps!H71/10000)*(5-3)) -> 0.77358127 | I72: =H72/(1+(((Base_Curves!H9/Base_Curves!I9-1)/(10-5))+Curve_Shocks_bps!I71/10000)*(10-5)) -> 0.60417636 | J72: =I72/(1+(((Base_Curves!I9/Base_Curves!J9-1)/(20-10))+Curve_Shocks_bps!J71/10000)*(20-10)) -> 0.37781941 | K72: =J72/(1+(((Base_Curves!J9/Base_Curves!K9-1)/(30-20))+Curve_Shocks_bps!K71/10000)*(30-20)) -> 0.23405735
A73: Eur_Govt | B73: Credit | C73: =1/(1+(((1/Base_Curves!C10-1)/(0.25-0))+Curve_Shocks_bps!C72/10000)*(0.25-0)) -> 0.98836867 | D73: =C73/(1+(((Base_Curves!C10/Base_Curves!D10-1)/(0.5-0.25))+Curve_Shocks_bps!D72/10000)*(0.5-0.25)) -> 0.97713324 | E73: =D73/(1+(((Base_Curves!D10/Base_Curves!E10-1)/(1-0.5))+Curve_Shocks_bps!E72/10000)*(1-0.5)) -> 0.9561681 | F73: =E73/(1+(((Base_Curves!E10/Base_Curves!F10-1)/(2-1))+Curve_Shocks_bps!F72/10000)*(2-1)) -> 0.91836308 | G73: =F73/(1+(((Base_Curves!F10/Base_Curves!G10-1)/(3-2))+Curve_Shocks_bps!G72/10000)*(3-2)) -> 0.89154076 | H73: =G73/(1+(((Base_Curves!G10/Base_Curves!H10-1)/(5-3))+Curve_Shocks_bps!H72/10000)*(5-3)) -> 0.83637837 | I73: =H73/(1+(((Base_Curves!H10/Base_Curves!I10-1)/(10-5))+Curve_Shocks_bps!I72/10000)*(10-5)) -> 0.69745466 | J73: =I73/(1+(((Base_Curves!I10/Base_Curves!J10-1)/(20-10))+Curve_Shocks_bps!J72/10000)*(20-10)) -> 0.49175765 | K73: =J73/(1+(((Base_Curves!J10/Base_Curves!K10-1)/(30-20))+Curve_Shocks_bps!K72/10000)*(30-20)) -> 0.34709252
A74: EURUSD | B74: FX | C74: =1/(1+(((1/Base_Curves!C11-1)/(0.25-0))+Curve_Shocks_bps!C73/10000)*(0.25-0)) -> 0.98855581 | D74: =C74/(1+(((Base_Curves!C11/Base_Curves!D11-1)/(0.5-0.25))+Curve_Shocks_bps!D73/10000)*(0.5-0.25)) -> 0.97734667 | E74: =D74/(1+(((Base_Curves!D11/Base_Curves!E11-1)/(1-0.5))+Curve_Shocks_bps!E73/10000)*(1-0.5)) -> 0.95559115 | F74: =E74/(1+(((Base_Curves!E11/Base_Curves!F11-1)/(2-1))+Curve_Shocks_bps!F73/10000)*(2-1)) -> 0.91467895 | G74: =F74/(1+(((Base_Curves!F11/Base_Curves!G11-1)/(3-2))+Curve_Shocks_bps!G73/10000)*(3-2)) -> 0.8761444 | H74: =G74/(1+(((Base_Curves!G11/Base_Curves!H11-1)/(5-3))+Curve_Shocks_bps!H73/10000)*(5-3)) -> 0.8048725 | I74: =H74/(1+(((Base_Curves!H11/Base_Curves!I11-1)/(10-5))+Curve_Shocks_bps!I73/10000)*(10-5)) -> 0.64968212 | J74: =I74/(1+(((Base_Curves!I11/Base_Curves!J11-1)/(20-10))+Curve_Shocks_bps!J73/10000)*(20-10)) -> 0.42771197 | K74: =J74/(1+(((Base_Curves!J11/Base_Curves!K11-1)/(30-20))+Curve_Shocks_bps!K73/10000)*(30-20)) -> 0.28299634
A76: Scenario 10 | C76: 3M | D76: 6M | E76: 1Y | F76: 2Y | G76: 3Y | H76: 5Y | I76: 10Y | J76: 20Y | K76: 30Y
A77: SOFR | B77: IR | C77: =1/(1+(((1/Base_Curves!C6-1)/(0.25-0))+Curve_Shocks_bps!C76/10000)*(0.25-0)) -> 0.98680613 | D77: =C77/(1+(((Base_Curves!C6/Base_Curves!D6-1)/(0.5-0.25))+Curve_Shocks_bps!D76/10000)*(0.5-0.25)) -> 0.97408374 | E77: =D77/(1+(((Base_Curves!D6/Base_Curves!E6-1)/(1-0.5))+Curve_Shocks_bps!E76/10000)*(1-0.5)) -> 0.94992462 | F77: =E77/(1+(((Base_Curves!E6/Base_Curves!F6-1)/(2-1))+Curve_Shocks_bps!F76/10000)*(2-1)) -> 0.90532134 | G77: =F77/(1+(((Base_Curves!F6/Base_Curves!G6-1)/(3-2))+Curve_Shocks_bps!G76/10000)*(3-2)) -> 0.86394568 | H77: =G77/(1+(((Base_Curves!G6/Base_Curves!H6-1)/(5-3))+Curve_Shocks_bps!H76/10000)*(5-3)) -> 0.78855635 | I77: =H77/(1+(((Base_Curves!H6/Base_Curves!I6-1)/(10-5))+Curve_Shocks_bps!I76/10000)*(10-5)) -> 0.62678836 | J77: =I77/(1+(((Base_Curves!I6/Base_Curves!J6-1)/(20-10))+Curve_Shocks_bps!J76/10000)*(20-10)) -> 0.4003276 | K77: =J77/(1+(((Base_Curves!J6/Base_Curves!K6-1)/(30-20))+Curve_Shocks_bps!K76/10000)*(30-20)) -> 0.25598159
A78: ESTRN | B78: IR | C78: =1/(1+(((1/Base_Curves!C7-1)/(0.25-0))+Curve_Shocks_bps!C77/10000)*(0.25-0)) -> 0.9942886 | D78: =C78/(1+(((Base_Curves!C7/Base_Curves!D7-1)/(0.5-0.25))+Curve_Shocks_bps!D77/10000)*(0.5-0.25)) -> 0.98477237 | E78: =D78/(1+(((Base_Curves!D7/Base_Curves!E7-1)/(1-0.5))+Curve_Shocks_bps!E77/10000)*(1-0.5)) -> 0.97264772 | F78: =E78/(1+(((Base_Curves!E7/Base_Curves!F7-1)/(2-1))+Curve_Shocks_bps!F77/10000)*(2-1)) -> 0.93883126 | G78: =F78/(1+(((Base_Curves!F7/Base_Curves!G7-1)/(3-2))+Curve_Shocks_bps!G77/10000)*(3-2)) -> 0.90722402 | H78: =G78/(1+(((Base_Curves!G7/Base_Curves!H7-1)/(5-3))+Curve_Shocks_bps!H77/10000)*(5-3)) -> 0.84861985 | I78: =H78/(1+(((Base_Curves!H7/Base_Curves!I7-1)/(10-5))+Curve_Shocks_bps!I77/10000)*(10-5)) -> 0.71663723 | J78: =I78/(1+(((Base_Curves!I7/Base_Curves!J7-1)/(20-10))+Curve_Shocks_bps!J77/10000)*(20-10)) -> 0.51655882 | K78: =J78/(1+(((Base_Curves!J7/Base_Curves!K7-1)/(30-20))+Curve_Shocks_bps!K77/10000)*(30-20)) -> 0.37365933
A79: Treasury | B79: Credit | C79: =1/(1+(((1/Base_Curves!C8-1)/(0.25-0))+Curve_Shocks_bps!C78/10000)*(0.25-0)) -> 0.98663169 | D79: =C79/(1+(((Base_Curves!C8/Base_Curves!D8-1)/(0.5-0.25))+Curve_Shocks_bps!D78/10000)*(0.5-0.25)) -> 0.97367515 | E79: =D79/(1+(((Base_Curves!D8/Base_Curves!E8-1)/(1-0.5))+Curve_Shocks_bps!E78/10000)*(1-0.5)) -> 0.9572378 | F79: =E79/(1+(((Base_Curves!E8/Base_Curves!F8-1)/(2-1))+Curve_Shocks_bps!F78/10000)*(2-1)) -> 0.91226004 | G79: =F79/(1+(((Base_Curves!F8/Base_Curves!G8-1)/(3-2))+Curve_Shocks_bps!G78/10000)*(3-2)) -> 0.87116062 | H79: =G79/(1+(((Base_Curves!G8/Base_Curves!H8-1)/(5-3))+Curve_Shocks_bps!H78/10000)*(5-3)) -> 0.79627706 | I79: =H79/(1+(((Base_Curves!H8/Base_Curves!I8-1)/(10-5))+Curve_Shocks_bps!I78/10000)*(10-5)) -> 0.63578351 | J79: =I79/(1+(((Base_Curves!I8/Base_Curves!J8-1)/(20-10))+Curve_Shocks_bps!J78/10000)*(20-10)) -> 0.41016645 | K79: =J79/(1+(((Base_Curves!J8/Base_Curves!K8-1)/(30-20))+Curve_Shocks_bps!K78/10000)*(30-20)) -> 0.26493767
A80: Agency_FNMA | B80: Credit | C80: =1/(1+(((1/Base_Curves!C9-1)/(0.25-0))+Curve_Shocks_bps!C79/10000)*(0.25-0)) -> 0.98435568 | D80: =C80/(1+(((Base_Curves!C9/Base_Curves!D9-1)/(0.5-0.25))+Curve_Shocks_bps!D79/10000)*(0.5-0.25)) -> 0.97691882 | E80: =D80/(1+(((Base_Curves!D9/Base_Curves!E9-1)/(1-0.5))+Curve_Shocks_bps!E79/10000)*(1-0.5)) -> 0.94825632 | F80: =E80/(1+(((Base_Curves!E9/Base_Curves!F9-1)/(2-1))+Curve_Shocks_bps!F79/10000)*(2-1)) -> 0.91398546 | G80: =F80/(1+(((Base_Curves!F9/Base_Curves!G9-1)/(3-2))+Curve_Shocks_bps!G79/10000)*(3-2)) -> 0.86703602 | H80: =G80/(1+(((Base_Curves!G9/Base_Curves!H9-1)/(5-3))+Curve_Shocks_bps!H79/10000)*(5-3)) -> 0.78388223 | I80: =H80/(1+(((Base_Curves!H9/Base_Curves!I9-1)/(10-5))+Curve_Shocks_bps!I79/10000)*(10-5)) -> 0.61974821 | J80: =I80/(1+(((Base_Curves!I9/Base_Curves!J9-1)/(20-10))+Curve_Shocks_bps!J79/10000)*(20-10)) -> 0.38300649 | K80: =J80/(1+(((Base_Curves!J9/Base_Curves!K9-1)/(30-20))+Curve_Shocks_bps!K79/10000)*(30-20)) -> 0.23718257
A81: Eur_Govt | B81: Credit | C81: =1/(1+(((1/Base_Curves!C10-1)/(0.25-0))+Curve_Shocks_bps!C80/10000)*(0.25-0)) -> 0.98803908 | D81: =C81/(1+(((Base_Curves!C10/Base_Curves!D10-1)/(0.5-0.25))+Curve_Shocks_bps!D80/10000)*(0.5-0.25)) -> 0.97681706 | E81: =D81/(1+(((Base_Curves!D10/Base_Curves!E10-1)/(1-0.5))+Curve_Shocks_bps!E80/10000)*(1-0.5)) -> 0.96603972 | F81: =E81/(1+(((Base_Curves!E10/Base_Curves!F10-1)/(2-1))+Curve_Shocks_bps!F80/10000)*(2-1)) -> 0.92741683 | G81: =F81/(1+(((Base_Curves!F10/Base_Curves!G10-1)/(3-2))+Curve_Shocks_bps!G80/10000)*(3-2)) -> 0.89264359 | H81: =G81/(1+(((Base_Curves!G10/Base_Curves!H10-1)/(5-3))+Curve_Shocks_bps!H80/10000)*(5-3)) -> 0.83768015 | I81: =H81/(1+(((Base_Curves!H10/Base_Curves!I10-1)/(10-5))+Curve_Shocks_bps!I80/10000)*(10-5)) -> 0.69845285 | J81: =I81/(1+(((Base_Curves!I10/Base_Curves!J10-1)/(20-10))+Curve_Shocks_bps!J80/10000)*(20-10)) -> 0.49232259 | K81: =J81/(1+(((Base_Curves!J10/Base_Curves!K10-1)/(30-20))+Curve_Shocks_bps!K80/10000)*(30-20)) -> 0.3499365
A82: EURUSD | B82: FX | C82: =1/(1+(((1/Base_Curves!C11-1)/(0.25-0))+Curve_Shocks_bps!C81/10000)*(0.25-0)) -> 0.98849229 | D82: =C82/(1+(((Base_Curves!C11/Base_Curves!D11-1)/(0.5-0.25))+Curve_Shocks_bps!D81/10000)*(0.5-0.25)) -> 0.97717519 | E82: =D82/(1+(((Base_Curves!D11/Base_Curves!E11-1)/(1-0.5))+Curve_Shocks_bps!E81/10000)*(1-0.5)) -> 0.95521334 | F82: =E82/(1+(((Base_Curves!E11/Base_Curves!F11-1)/(2-1))+Curve_Shocks_bps!F81/10000)*(2-1)) -> 0.91421231 | G82: =F82/(1+(((Base_Curves!F11/Base_Curves!G11-1)/(3-2))+Curve_Shocks_bps!G81/10000)*(3-2)) -> 0.87562193 | H82: =G82/(1+(((Base_Curves!G11/Base_Curves!H11-1)/(5-3))+Curve_Shocks_bps!H81/10000)*(5-3)) -> 0.80859689 | I82: =H82/(1+(((Base_Curves!H11/Base_Curves!I11-1)/(10-5))+Curve_Shocks_bps!I81/10000)*(10-5)) -> 0.65239877 | J82: =I82/(1+(((Base_Curves!I11/Base_Curves!J11-1)/(20-10))+Curve_Shocks_bps!J81/10000)*(20-10)) -> 0.42938738 | K82: =J82/(1+(((Base_Curves!J11/Base_Curves!K11-1)/(30-20))+Curve_Shocks_bps!K81/10000)*(30-20)) -> 0.28290689

Sheet SABR_Base
B1: SABR Base Vol Surfaces — Swabr_Swaption (10x10 grids: Expiry x Tenor)
B3: Param: ATM
B4: Expiry \ Tenor | C4: 1M | D4: 3M | E4: 6M | F4: 1Y | G4: 2Y | H4: 3Y | I4: 5Y | J4: 10Y | K4: 20Y | L4: 30Y
B5: 1M | C5: 0.5465 | D5: 0.5264 | E5: 0.5197 | F5: 0.4914 | G5: 0.4841 | H5: 0.464 | I5: 0.4412 | J5: 0.4335 | K5: 0.4074 | L5: 0.3987
B6: 3M | C6: 0.5247 | D6: 0.5085 | E6: 0.4985 | F6: 0.4899 | G6: 0.4591 | H6: 0.4445 | I6: 0.4359 | J6: 0.4256 | K6: 0.4015 | L6: 0.3813
B7: 6M | C7: 0.5262 | D7: 0.4909 | E7: 0.4905 | F7: 0.4625 | G7: 0.4429 | H7: 0.4257 | I7: 0.4128 | J7: 0.4063 | K7: 0.3769 | L7: 0.3683
B8: 1Y | C8: 0.5028 | D8: 0.4808 | E8: 0.4676 | F8: 0.4413 | G8: 0.4245 | H8: 0.4108 | I8: 0.4036 | J8: 0.3819 | K8: 0.3629 | L8: 0.3517
B9: 2Y | C9: 0.4824 | D9: 0.4627 | E9: 0.4559 | F9: 0.4373 | G9: 0.4115 | H9: 0.4015 | I9: 0.3838 | J9: 0.3742 | K9: 0.3546 | L9: 0.3291
B10: 3Y | C10: 0.4763 | D10: 0.4424 | E10: 0.4317 | F10: 0.4218 | G10: 0.393 | H10: 0.3831 | I10: 0.3575 | J10: 0.3534 | K10: 0.3386 | L10: 0.3181
B11: 5Y | C11: 0.4575 | D11: 0.4296 | E11: 0.4206 | F11: 0.4019 | G11: 0.3849 | H11: 0.3658 | I11: 0.3568 | J11: 0.3422 | K11: 0.3161 | L11: 0.3033
B12: 10Y | C12: 0.4245 | D12: 0.4207 | E12: 0.4029 | F12: 0.3932 | G12: 0.3731 | H12: 0.3457 | I12: 0.331 | J12: 0.32 | K12: 0.2905 | L12: 0.2826
B13: 20Y | C13: 0.41 | D13: 0.3923 | E13: 0.3745 | F13: 0.372 | G13: 0.3426 | H13: 0.3283 | I13: 0.3145 | J13: 0.3074 | K13: 0.2749 | L13: 0.2657
B14: 30Y | C14: 0.401 | D14: 0.391 | E14: 0.3731 | F14: 0.3573 | G14: 0.3289 | H14: 0.315 | I14: 0.2972 | J14: 0.291 | K14: 0.2758 | L14: 0.243
B17: Param: RHO
B18: Expiry \ Tenor | C18: 1M | D18: 3M | E18: 6M | F18: 1Y | G18: 2Y | H18: 3Y | I18: 5Y | J18: 10Y | K18: 20Y | L18: 30Y
B19: 1M | C19: -0.3565 | D19: -0.3359 | E19: -0.3164 | F19: -0.292 | G19: -0.2704 | H19: -0.2575 | I19: -0.2433 | J19: -0.2155 | K19: -0.1971 | L19: -0.1737
B20: 3M | C20: -0.3215 | D20: -0.3073 | E20: -0.2914 | F20: -0.2699 | G20: -0.2493 | H20: -0.2423 | I20: -0.2059 | J20: -0.1888 | K20: -0.1675 | L20: -0.1496
B21: 6M | C21: -0.3133 | D21: -0.2937 | E21: -0.2802 | F21: -0.2501 | G21: -0.2421 | H21: -0.2225 | I21: -0.2003 | J21: -0.1818 | K21: -0.1588 | L21: -0.1451
B22: 1Y | C22: -0.3017 | D22: -0.2792 | E22: -0.2607 | F22: -0.2361 | G22: -0.2234 | H22: -0.187 | I22: -0.1727 | J22: -0.1626 | K22: -0.1411 | L22: -0.1197
B23: 2Y | C23: -0.2749 | D23: -0.2603 | E23: -0.2264 | F23: -0.204 | G23: -0.1951 | H23: -0.1753 | I23: -0.1638 | J23: -0.1441 | K23: -0.1198 | L23: -0.1019
B24: 3Y | C24: -0.2462 | D24: -0.2401 | E24: -0.2234 | F24: -0.1854 | G24: -0.1744 | H24: -0.1626 | I24: -0.1352 | J24: -0.1261 | K24: -0.0967 | L24: -0.0682
B25: 5Y | C25: -0.2261 | D25: -0.21 | E25: -0.1992 | F25: -0.1777 | G25: -0.1622 | H25: -0.1307 | I25: -0.116 | J25: -0.0916 | K25: -0.0812 | L25: -0.0639
B26: 10Y | C26: -0.2077 | D26: -0.1847 | E26: -0.1679 | F26: -0.1494 | G26: -0.1297 | H26: -0.1119 | I26: -0.1027 | J26: -0.0774 | K26: -0.0612 | L26: -0.0483
B27: 20Y | C27: -0.2039 | D27: -0.1794 | E27: -0.1604 | F27: -0.1323 | G27: -0.1075 | H27: -0.0983 | I27: -0.069 | J27: -0.0486 | K27: -0.0298 | L27: -0.0222
B28: 30Y | C28: -0.1806 | D28: -0.161 | E28: -0.1422 | F28: -0.1226 | G28: -0.0947 | H28: -0.0698 | I28: -0.0515 | J28: -0.0393 | K28: -0.0164 | L28: 0.006
B31: Param: NU
B32: Expiry \ Tenor | C32: 1M | D32: 3M | E32: 6M | F32: 1Y | G32: 2Y | H32: 3Y | I32: 5Y | J32: 10Y | K32: 20Y | L32: 30Y
B33: 1M | C33: 0.8417 | D33: 0.831 | E33: 0.8138 | F33: 0.789 | G33: 0.7661 | H33: 0.7384 | I33: 0.7102 | J33: 0.7002 | K33: 0.6689 | L33: 0.656
B34: 3M | C34: 0.8372 | D34: 0.8035 | E34: 0.7814 | F34: 0.77 | G34: 0.7434 | H34: 0.7101 | I34: 0.687 | J34: 0.6652 | K34: 0.6581 | L34: 0.6339
B35: 6M | C35: 0.7985 | D35: 0.7899 | E35: 0.7707 | F35: 0.742 | G35: 0.7137 | H35: 0.6954 | I35: 0.6648 | J35: 0.6403 | K35: 0.6372 | L35: 0.6085
B36: 1Y | C36: 0.7839 | D36: 0.7698 | E36: 0.7376 | F36: 0.7241 | G36: 0.701 | H36: 0.6664 | I36: 0.645 | J36: 0.6236 | K36: 0.6004 | L36: 0.5851
B37: 2Y | C37: 0.7563 | D37: 0.7373 | E37: 0.7093 | F37: 0.7026 | G37: 0.6693 | H37: 0.6492 | I37: 0.6294 | J37: 0.6136 | K37: 0.5817 | L37: 0.5695
B38: 3Y | C38: 0.7389 | D38: 0.7173 | E38: 0.6949 | F38: 0.6626 | G38: 0.6488 | H38: 0.6214 | I38: 0.5956 | J38: 0.5893 | K38: 0.5546 | L38: 0.5384
B39: 5Y | C39: 0.7212 | D39: 0.6956 | E39: 0.6687 | F39: 0.6504 | G39: 0.6289 | H39: 0.6112 | I39: 0.5755 | J39: 0.5623 | K39: 0.5339 | L39: 0.5122
B40: 10Y | C40: 0.6999 | D40: 0.6724 | E40: 0.6512 | F40: 0.633 | G40: 0.6138 | H40: 0.5822 | I40: 0.5634 | J40: 0.539 | K40: 0.5169 | L40: 0.4983
B41: 20Y | C41: 0.6713 | D41: 0.6507 | E41: 0.6273 | F41: 0.6144 | G41: 0.5873 | H41: 0.5686 | I41: 0.5477 | J41: 0.5119 | K41: 0.4956 | L41: 0.4811
B42: 30Y | C42: 0.6568 | D42: 0.6205 | E42: 0.598 | F42: 0.5822 | G42: 0.5526 | H42: 0.5337 | I42: 0.5081 | J42: 0.4978 | K42: 0.4779 | L42: 0.4579

Sheet SABR_Shocks
B1: SABR Scenario Shocks — Parameter-level shock size per scenario + per-cell Sensitivity Factor grid
B2: Shocked(i,j) = Base(i,j) + ScenarioShockSize(param,scenario) x SensitivityFactor(i,j). ScenarioShockSize is the parallel move applied to the whole surface for that scenario; SensitivityFactor reshapes it across the grid (illustrative: larger moves at short expiry/short tenor, typical of a stress period).
B4: Scenario Shock Size (per param, parallel move applied before sensitivity scaling)
B5: Scenario | C5: ATM | D5: RHO | E5: NU
B6: Scenario 1 | C6: 0.0099 | D6: 0.0057 | E6: 0.0224
B7: Scenario 2 | C7: 0.0125 | D7: 0.0065 | E7: 0.0206
B8: Scenario 3 | C8: 0.012 | D8: 0.0077 | E8: 0.0249
B9: Scenario 4 | C9: 0.0205 | D9: 0.0056 | E9: 0.0233
B10: Scenario 5 | C10: 0.0159 | D10: 0.0125 | E10: 0.0331
B11: Scenario 6 | C11: 0.0178 | D11: 0.0151 | E11: 0.041
B12: Scenario 7 | C12: 0.0263 | D12: 0.0133 | E12: 0.0317
B13: Scenario 8 | C13: 0.0224 | D13: 0.0138 | E13: 0.0338
B14: Scenario 9 | C14: 0.0265 | D14: 0.0127 | E14: 0.0369
B15: Scenario 10 | C15: 0.0316 | D15: 0.0155 | E15: 0.0535
B18: Sensitivity Factor Grid (shared shape across ATM/RHO/NU; applied to all scenarios)
B19: Expiry \ Tenor | C19: 1M | D19: 3M | E19: 6M | F19: 1Y | G19: 2Y | H19: 3Y | I19: 5Y | J19: 10Y | K19: 20Y | L19: 30Y
B20: 1M | C20: 1.601 | D20: 1.518 | E20: 1.42 | F20: 1.34 | G20: 1.237 | H20: 1.137 | I20: 1.09 | J20: 1 | K20: 0.9 | L20: 0.802
B21: 3M | C21: 1.499 | D21: 1.404 | E21: 1.317 | F21: 1.214 | G21: 1.166 | H21: 1.054 | I21: 0.991 | J21: 0.873 | K21: 0.817 | L21: 0.721
B22: 6M | C22: 1.39 | D22: 1.313 | E22: 1.265 | F22: 1.148 | G22: 1.089 | H22: 0.964 | I22: 0.854 | J22: 0.798 | K22: 0.717 | L22: 0.596
B23: 1Y | C23: 1.305 | D23: 1.23 | E23: 1.178 | F23: 1.075 | G23: 0.947 | H23: 0.865 | I23: 0.766 | J23: 0.674 | K23: 0.628 | L23: 0.501
B24: 2Y | C24: 1.244 | D24: 1.147 | E24: 1.041 | F24: 0.984 | G24: 0.858 | H24: 0.799 | I24: 0.677 | J24: 0.605 | K24: 0.503 | L24: 0.416
B25: 3Y | C25: 1.178 | D25: 1.078 | E25: 0.958 | F25: 0.903 | G25: 0.773 | H25: 0.694 | I25: 0.631 | J25: 0.529 | K25: 0.406 | L25: 0.369
B26: 5Y | C26: 1.043 | D26: 0.955 | E26: 0.896 | F26: 0.78 | G26: 0.688 | H26: 0.584 | I26: 0.495 | J26: 0.435 | K26: 0.325 | L26: 0.256
B27: 10Y | C27: 0.962 | D27: 0.877 | E27: 0.818 | F27: 0.699 | G27: 0.614 | H27: 0.542 | I27: 0.411 | J27: 0.319 | K27: 0.275 | L27: 0.179
B28: 20Y | C28: 0.865 | D28: 0.771 | E28: 0.714 | F28: 0.636 | G28: 0.502 | H28: 0.457 | I28: 0.363 | J28: 0.256 | K28: 0.155 | L28: 0.15
B29: 30Y | C29: 0.762 | D29: 0.728 | E29: 0.594 | F29: 0.532 | G29: 0.415 | H29: 0.359 | I29: 0.256 | J29: 0.15 | K29: 0.15 | L29: 0.15

Sheet SABR_Shocked
B1: SABR Shocked Vol Surfaces — 10x10 grids x 3 params x 10 scenarios
B2: Shocked(i,j) = SABR_Base!(param,i,j) + SABR_Shocks!ScenarioShockSize(param,scenario) x SABR_Shocks!SensitivityFactor(i,j)
B4: SCENARIO 1
B5: Param: ATM
B6: Expiry \ Tenor | C6: 1M | D6: 3M | E6: 6M | F6: 1Y | G6: 2Y | H6: 3Y | I6: 5Y | J6: 10Y | K6: 20Y | L6: 30Y
B7: 1M | C7: =SABR_Base!C5+SABR_Shocks!$C$6*SABR_Shocks!C20 -> 0.5623499 | D7: =SABR_Base!D5+SABR_Shocks!$C$6*SABR_Shocks!D20 -> 0.5414282 | E7: =SABR_Base!E5+SABR_Shocks!$C$6*SABR_Shocks!E20 -> 0.533758 | F7: =SABR_Base!F5+SABR_Shocks!$C$6*SABR_Shocks!F20 -> 0.504666 | G7: =SABR_Base!G5+SABR_Shocks!$C$6*SABR_Shocks!G20 -> 0.4963463 | H7: =SABR_Base!H5+SABR_Shocks!$C$6*SABR_Shocks!H20 -> 0.4752563 | I7: =SABR_Base!I5+SABR_Shocks!$C$6*SABR_Shocks!I20 -> 0.451991 | J7: =SABR_Base!J5+SABR_Shocks!$C$6*SABR_Shocks!J20 -> 0.4434 | ... L7: =SABR_Base!L5+SABR_Shocks!$C$6*SABR_Shocks!L20 -> 0.4066398
B8: 3M | C8: =SABR_Base!C6+SABR_Shocks!$C$6*SABR_Shocks!C21 -> 0.5395401 | D8: =SABR_Base!D6+SABR_Shocks!$C$6*SABR_Shocks!D21 -> 0.5223996 | E8: =SABR_Base!E6+SABR_Shocks!$C$6*SABR_Shocks!E21 -> 0.5115383 | F8: =SABR_Base!F6+SABR_Shocks!$C$6*SABR_Shocks!F21 -> 0.5019186 | G8: =SABR_Base!G6+SABR_Shocks!$C$6*SABR_Shocks!G21 -> 0.4706434 | H8: =SABR_Base!H6+SABR_Shocks!$C$6*SABR_Shocks!H21 -> 0.4549346 | I8: =SABR_Base!I6+SABR_Shocks!$C$6*SABR_Shocks!I21 -> 0.4457109 | J8: =SABR_Base!J6+SABR_Shocks!$C$6*SABR_Shocks!J21 -> 0.4342427 | ... L8: =SABR_Base!L6+SABR_Shocks!$C$6*SABR_Shocks!L21 -> 0.3884379
B9: 6M | C9: =SABR_Base!C7+SABR_Shocks!$C$6*SABR_Shocks!C22 -> 0.539961 | D9: =SABR_Base!D7+SABR_Shocks!$C$6*SABR_Shocks!D22 -> 0.5038987 | E9: =SABR_Base!E7+SABR_Shocks!$C$6*SABR_Shocks!E22 -> 0.5030235 | F9: =SABR_Base!F7+SABR_Shocks!$C$6*SABR_Shocks!F22 -> 0.4738652 | G9: =SABR_Base!G7+SABR_Shocks!$C$6*SABR_Shocks!G22 -> 0.4536811 | H9: =SABR_Base!H7+SABR_Shocks!$C$6*SABR_Shocks!H22 -> 0.4352436 | I9: =SABR_Base!I7+SABR_Shocks!$C$6*SABR_Shocks!I22 -> 0.4212546 | J9: =SABR_Base!J7+SABR_Shocks!$C$6*SABR_Shocks!J22 -> 0.4142002 | ... L9: =SABR_Base!L7+SABR_Shocks!$C$6*SABR_Shocks!L22 -> 0.3742004
B10: 1Y | C10: =SABR_Base!C8+SABR_Shocks!$C$6*SABR_Shocks!C23 -> 0.5157195 | D10: =SABR_Base!D8+SABR_Shocks!$C$6*SABR_Shocks!D23 -> 0.492977 | E10: =SABR_Base!E8+SABR_Shocks!$C$6*SABR_Shocks!E23 -> 0.4792622 | F10: =SABR_Base!F8+SABR_Shocks!$C$6*SABR_Shocks!F23 -> 0.4519425 | G10: =SABR_Base!G8+SABR_Shocks!$C$6*SABR_Shocks!G23 -> 0.4338753 | H10: =SABR_Base!H8+SABR_Shocks!$C$6*SABR_Shocks!H23 -> 0.4193635 | I10: =SABR_Base!I8+SABR_Shocks!$C$6*SABR_Shocks!I23 -> 0.4111834 | J10: =SABR_Base!J8+SABR_Shocks!$C$6*SABR_Shocks!J23 -> 0.3885726 | ... L10: =SABR_Base!L8+SABR_Shocks!$C$6*SABR_Shocks!L23 -> 0.3566599
B11: 2Y | C11: =SABR_Base!C9+SABR_Shocks!$C$6*SABR_Shocks!C24 -> 0.4947156 | D11: =SABR_Base!D9+SABR_Shocks!$C$6*SABR_Shocks!D24 -> 0.4740553 | E11: =SABR_Base!E9+SABR_Shocks!$C$6*SABR_Shocks!E24 -> 0.4662059 | F11: =SABR_Base!F9+SABR_Shocks!$C$6*SABR_Shocks!F24 -> 0.4470416 | G11: =SABR_Base!G9+SABR_Shocks!$C$6*SABR_Shocks!G24 -> 0.4199942 | H11: =SABR_Base!H9+SABR_Shocks!$C$6*SABR_Shocks!H24 -> 0.4094101 | I11: =SABR_Base!I9+SABR_Shocks!$C$6*SABR_Shocks!I24 -> 0.3905023 | J11: =SABR_Base!J9+SABR_Shocks!$C$6*SABR_Shocks!J24 -> 0.3801895 | ... L11: =SABR_Base!L9+SABR_Shocks!$C$6*SABR_Shocks!L24 -> 0.3332184
B12: 3Y | C12: =SABR_Base!C10+SABR_Shocks!$C$6*SABR_Shocks!C25 -> 0.4879622 | D12: =SABR_Base!D10+SABR_Shocks!$C$6*SABR_Shocks!D25 -> 0.4530722 | E12: =SABR_Base!E10+SABR_Shocks!$C$6*SABR_Shocks!E25 -> 0.4411842 | F12: =SABR_Base!F10+SABR_Shocks!$C$6*SABR_Shocks!F25 -> 0.4307397 | G12: =SABR_Base!G10+SABR_Shocks!$C$6*SABR_Shocks!G25 -> 0.4006527 | H12: =SABR_Base!H10+SABR_Shocks!$C$6*SABR_Shocks!H25 -> 0.3899706 | I12: =SABR_Base!I10+SABR_Shocks!$C$6*SABR_Shocks!I25 -> 0.3637469 | J12: =SABR_Base!J10+SABR_Shocks!$C$6*SABR_Shocks!J25 -> 0.3586371 | ... L12: =SABR_Base!L10+SABR_Shocks!$C$6*SABR_Shocks!L25 -> 0.3217531
B13: 5Y | C13: =SABR_Base!C11+SABR_Shocks!$C$6*SABR_Shocks!C26 -> 0.4678257 | D13: =SABR_Base!D11+SABR_Shocks!$C$6*SABR_Shocks!D26 -> 0.4390545 | E13: =SABR_Base!E11+SABR_Shocks!$C$6*SABR_Shocks!E26 -> 0.4294704 | F13: =SABR_Base!F11+SABR_Shocks!$C$6*SABR_Shocks!F26 -> 0.409622 | G13: =SABR_Base!G11+SABR_Shocks!$C$6*SABR_Shocks!G26 -> 0.3917112 | H13: =SABR_Base!H11+SABR_Shocks!$C$6*SABR_Shocks!H26 -> 0.3715816 | I13: =SABR_Base!I11+SABR_Shocks!$C$6*SABR_Shocks!I26 -> 0.3617005 | J13: =SABR_Base!J11+SABR_Shocks!$C$6*SABR_Shocks!J26 -> 0.3465065 | ... L13: =SABR_Base!L11+SABR_Shocks!$C$6*SABR_Shocks!L26 -> 0.3058344
B14: 10Y | C14: =SABR_Base!C12+SABR_Shocks!$C$6*SABR_Shocks!C27 -> 0.4340238 | D14: =SABR_Base!D12+SABR_Shocks!$C$6*SABR_Shocks!D27 -> 0.4293823 | E14: =SABR_Base!E12+SABR_Shocks!$C$6*SABR_Shocks!E27 -> 0.4109982 | F14: =SABR_Base!F12+SABR_Shocks!$C$6*SABR_Shocks!F27 -> 0.4001201 | G14: =SABR_Base!G12+SABR_Shocks!$C$6*SABR_Shocks!G27 -> 0.3791786 | H14: =SABR_Base!H12+SABR_Shocks!$C$6*SABR_Shocks!H27 -> 0.3510658 | I14: =SABR_Base!I12+SABR_Shocks!$C$6*SABR_Shocks!I27 -> 0.3350689 | J14: =SABR_Base!J12+SABR_Shocks!$C$6*SABR_Shocks!J27 -> 0.3231581 | ... L14: =SABR_Base!L12+SABR_Shocks!$C$6*SABR_Shocks!L27 -> 0.2843721
B15: 20Y | C15: =SABR_Base!C13+SABR_Shocks!$C$6*SABR_Shocks!C28 -> 0.4185635 | D15: =SABR_Base!D13+SABR_Shocks!$C$6*SABR_Shocks!D28 -> 0.3999329 | E15: =SABR_Base!E13+SABR_Shocks!$C$6*SABR_Shocks!E28 -> 0.3815686 | F15: =SABR_Base!F13+SABR_Shocks!$C$6*SABR_Shocks!F28 -> 0.3782964 | G15: =SABR_Base!G13+SABR_Shocks!$C$6*SABR_Shocks!G28 -> 0.3475698 | H15: =SABR_Base!H13+SABR_Shocks!$C$6*SABR_Shocks!H28 -> 0.3328243 | I15: =SABR_Base!I13+SABR_Shocks!$C$6*SABR_Shocks!I28 -> 0.3180937 | J15: =SABR_Base!J13+SABR_Shocks!$C$6*SABR_Shocks!J28 -> 0.3099344 | ... L15: =SABR_Base!L13+SABR_Shocks!$C$6*SABR_Shocks!L28 -> 0.267185
B16: 30Y | C16: =SABR_Base!C14+SABR_Shocks!$C$6*SABR_Shocks!C29 -> 0.4085438 | D16: =SABR_Base!D14+SABR_Shocks!$C$6*SABR_Shocks!D29 -> 0.3982072 | E16: =SABR_Base!E14+SABR_Shocks!$C$6*SABR_Shocks!E29 -> 0.3789806 | F16: =SABR_Base!F14+SABR_Shocks!$C$6*SABR_Shocks!F29 -> 0.3625668 | G16: =SABR_Base!G14+SABR_Shocks!$C$6*SABR_Shocks!G29 -> 0.3330085 | H16: =SABR_Base!H14+SABR_Shocks!$C$6*SABR_Shocks!H29 -> 0.3185541 | I16: =SABR_Base!I14+SABR_Shocks!$C$6*SABR_Shocks!I29 -> 0.2997344 | J16: =SABR_Base!J14+SABR_Shocks!$C$6*SABR_Shocks!J29 -> 0.292485 | ... L16: =SABR_Base!L14+SABR_Shocks!$C$6*SABR_Shocks!L29 -> 0.244485
B18: Param: RHO
B19: Expiry \ Tenor | C19: 1M | D19: 3M | E19: 6M | F19: 1Y | G19: 2Y | H19: 3Y | I19: 5Y | J19: 10Y | K19: 20Y | L19: 30Y
B20: 1M | C20: =SABR_Base!C19+SABR_Shocks!$D$6*SABR_Shocks!C20 -> -0.3473743 | D20: =SABR_Base!D19+SABR_Shocks!$D$6*SABR_Shocks!D20 -> -0.3272474 | E20: =SABR_Base!E19+SABR_Shocks!$D$6*SABR_Shocks!E20 -> -0.308306 | F20: =SABR_Base!F19+SABR_Shocks!$D$6*SABR_Shocks!F20 -> -0.284362 | G20: =SABR_Base!G19+SABR_Shocks!$D$6*SABR_Shocks!G20 -> -0.2633491 | H20: =SABR_Base!H19+SABR_Shocks!$D$6*SABR_Shocks!H20 -> -0.2510191 | I20: =SABR_Base!I19+SABR_Shocks!$D$6*SABR_Shocks!I20 -> -0.237087 | J20: =SABR_Base!J19+SABR_Shocks!$D$6*SABR_Shocks!J20 -> -0.2098 | ... L20: =SABR_Base!L19+SABR_Shocks!$D$6*SABR_Shocks!L20 -> -0.1691286
B21: 3M | C21: =SABR_Base!C20+SABR_Shocks!$D$6*SABR_Shocks!C21 -> -0.3129557 | D21: =SABR_Base!D20+SABR_Shocks!$D$6*SABR_Shocks!D21 -> -0.2992972 | E21: =SABR_Base!E20+SABR_Shocks!$D$6*SABR_Shocks!E21 -> -0.2838931 | F21: =SABR_Base!F20+SABR_Shocks!$D$6*SABR_Shocks!F21 -> -0.2629802 | G21: =SABR_Base!G20+SABR_Shocks!$D$6*SABR_Shocks!G21 -> -0.2426538 | H21: =SABR_Base!H20+SABR_Shocks!$D$6*SABR_Shocks!H21 -> -0.2362922 | I21: =SABR_Base!I20+SABR_Shocks!$D$6*SABR_Shocks!I21 -> -0.2002513 | J21: =SABR_Base!J20+SABR_Shocks!$D$6*SABR_Shocks!J21 -> -0.1838239 | ... L21: =SABR_Base!L20+SABR_Shocks!$D$6*SABR_Shocks!L21 -> -0.1454903
B22: 6M | C22: =SABR_Base!C21+SABR_Shocks!$D$6*SABR_Shocks!C22 -> -0.305377 | D22: =SABR_Base!D21+SABR_Shocks!$D$6*SABR_Shocks!D22 -> -0.2862159 | E22: =SABR_Base!E21+SABR_Shocks!$D$6*SABR_Shocks!E22 -> -0.2729895 | F22: =SABR_Base!F21+SABR_Shocks!$D$6*SABR_Shocks!F22 -> -0.2435564 | G22: =SABR_Base!G21+SABR_Shocks!$D$6*SABR_Shocks!G22 -> -0.2358927 | H22: =SABR_Base!H21+SABR_Shocks!$D$6*SABR_Shocks!H22 -> -0.2170052 | I22: =SABR_Base!I21+SABR_Shocks!$D$6*SABR_Shocks!I22 -> -0.1954322 | J22: =SABR_Base!J21+SABR_Shocks!$D$6*SABR_Shocks!J22 -> -0.1772514 | ... L22: =SABR_Base!L21+SABR_Shocks!$D$6*SABR_Shocks!L22 -> -0.1417028
B23: 1Y | C23: =SABR_Base!C22+SABR_Shocks!$D$6*SABR_Shocks!C23 -> -0.2942615 | D23: =SABR_Base!D22+SABR_Shocks!$D$6*SABR_Shocks!D23 -> -0.272189 | E23: =SABR_Base!E22+SABR_Shocks!$D$6*SABR_Shocks!E23 -> -0.2539854 | F23: =SABR_Base!F22+SABR_Shocks!$D$6*SABR_Shocks!F23 -> -0.2299725 | G23: =SABR_Base!G22+SABR_Shocks!$D$6*SABR_Shocks!G23 -> -0.2180021 | H23: =SABR_Base!H22+SABR_Shocks!$D$6*SABR_Shocks!H23 -> -0.1820695 | I23: =SABR_Base!I22+SABR_Shocks!$D$6*SABR_Shocks!I23 -> -0.1683338 | J23: =SABR_Base!J22+SABR_Shocks!$D$6*SABR_Shocks!J23 -> -0.1587582 | ... L23: =SABR_Base!L22+SABR_Shocks!$D$6*SABR_Shocks!L23 -> -0.1168443
B24: 2Y | C24: =SABR_Base!C23+SABR_Shocks!$D$6*SABR_Shocks!C24 -> -0.2678092 | D24: =SABR_Base!D23+SABR_Shocks!$D$6*SABR_Shocks!D24 -> -0.2537621 | E24: =SABR_Base!E23+SABR_Shocks!$D$6*SABR_Shocks!E24 -> -0.2204663 | F24: =SABR_Base!F23+SABR_Shocks!$D$6*SABR_Shocks!F24 -> -0.1983912 | G24: =SABR_Base!G23+SABR_Shocks!$D$6*SABR_Shocks!G24 -> -0.1902094 | H24: =SABR_Base!H23+SABR_Shocks!$D$6*SABR_Shocks!H24 -> -0.1707457 | I24: =SABR_Base!I23+SABR_Shocks!$D$6*SABR_Shocks!I24 -> -0.1599411 | J24: =SABR_Base!J23+SABR_Shocks!$D$6*SABR_Shocks!J24 -> -0.1406515 | ... L24: =SABR_Base!L23+SABR_Shocks!$D$6*SABR_Shocks!L24 -> -0.0995288
B25: 3Y | C25: =SABR_Base!C24+SABR_Shocks!$D$6*SABR_Shocks!C25 -> -0.2394854 | D25: =SABR_Base!D24+SABR_Shocks!$D$6*SABR_Shocks!D25 -> -0.2339554 | E25: =SABR_Base!E24+SABR_Shocks!$D$6*SABR_Shocks!E25 -> -0.2179394 | F25: =SABR_Base!F24+SABR_Shocks!$D$6*SABR_Shocks!F25 -> -0.1802529 | G25: =SABR_Base!G24+SABR_Shocks!$D$6*SABR_Shocks!G25 -> -0.1699939 | H25: =SABR_Base!H24+SABR_Shocks!$D$6*SABR_Shocks!H25 -> -0.1586442 | I25: =SABR_Base!I24+SABR_Shocks!$D$6*SABR_Shocks!I25 -> -0.1316033 | J25: =SABR_Base!J24+SABR_Shocks!$D$6*SABR_Shocks!J25 -> -0.1230847 | ... L25: =SABR_Base!L24+SABR_Shocks!$D$6*SABR_Shocks!L25 -> -0.0660967
B26: 5Y | C26: =SABR_Base!C25+SABR_Shocks!$D$6*SABR_Shocks!C26 -> -0.2201549 | D26: =SABR_Base!D25+SABR_Shocks!$D$6*SABR_Shocks!D26 -> -0.2045565 | E26: =SABR_Base!E25+SABR_Shocks!$D$6*SABR_Shocks!E26 -> -0.1940928 | F26: =SABR_Base!F25+SABR_Shocks!$D$6*SABR_Shocks!F26 -> -0.173254 | G26: =SABR_Base!G25+SABR_Shocks!$D$6*SABR_Shocks!G26 -> -0.1582784 | H26: =SABR_Base!H25+SABR_Shocks!$D$6*SABR_Shocks!H26 -> -0.1273712 | I26: =SABR_Base!I25+SABR_Shocks!$D$6*SABR_Shocks!I26 -> -0.1131785 | J26: =SABR_Base!J25+SABR_Shocks!$D$6*SABR_Shocks!J26 -> -0.0891205 | ... L26: =SABR_Base!L25+SABR_Shocks!$D$6*SABR_Shocks!L26 -> -0.0624408
B27: 10Y | C27: =SABR_Base!C26+SABR_Shocks!$D$6*SABR_Shocks!C27 -> -0.2022166 | D27: =SABR_Base!D26+SABR_Shocks!$D$6*SABR_Shocks!D27 -> -0.1797011 | E27: =SABR_Base!E26+SABR_Shocks!$D$6*SABR_Shocks!E27 -> -0.1632374 | F27: =SABR_Base!F26+SABR_Shocks!$D$6*SABR_Shocks!F27 -> -0.1454157 | G27: =SABR_Base!G26+SABR_Shocks!$D$6*SABR_Shocks!G27 -> -0.1262002 | H27: =SABR_Base!H26+SABR_Shocks!$D$6*SABR_Shocks!H27 -> -0.1088106 | I27: =SABR_Base!I26+SABR_Shocks!$D$6*SABR_Shocks!I27 -> -0.1003573 | J27: =SABR_Base!J26+SABR_Shocks!$D$6*SABR_Shocks!J27 -> -0.0755817 | ... L27: =SABR_Base!L26+SABR_Shocks!$D$6*SABR_Shocks!L27 -> -0.0472797
B28: 20Y | C28: =SABR_Base!C27+SABR_Shocks!$D$6*SABR_Shocks!C28 -> -0.1989695 | D28: =SABR_Base!D27+SABR_Shocks!$D$6*SABR_Shocks!D28 -> -0.1750053 | E28: =SABR_Base!E27+SABR_Shocks!$D$6*SABR_Shocks!E28 -> -0.1563302 | F28: =SABR_Base!F27+SABR_Shocks!$D$6*SABR_Shocks!F28 -> -0.1286748 | G28: =SABR_Base!G27+SABR_Shocks!$D$6*SABR_Shocks!G28 -> -0.1046386 | H28: =SABR_Base!H27+SABR_Shocks!$D$6*SABR_Shocks!H28 -> -0.0956951 | I28: =SABR_Base!I27+SABR_Shocks!$D$6*SABR_Shocks!I28 -> -0.0669309 | J28: =SABR_Base!J27+SABR_Shocks!$D$6*SABR_Shocks!J28 -> -0.0471408 | ... L28: =SABR_Base!L27+SABR_Shocks!$D$6*SABR_Shocks!L28 -> -0.021345
B29: 30Y | C29: =SABR_Base!C28+SABR_Shocks!$D$6*SABR_Shocks!C29 -> -0.1762566 | D29: =SABR_Base!D28+SABR_Shocks!$D$6*SABR_Shocks!D29 -> -0.1568504 | E29: =SABR_Base!E28+SABR_Shocks!$D$6*SABR_Shocks!E29 -> -0.1388142 | F29: =SABR_Base!F28+SABR_Shocks!$D$6*SABR_Shocks!F29 -> -0.1195676 | G29: =SABR_Base!G28+SABR_Shocks!$D$6*SABR_Shocks!G29 -> -0.0923345 | H29: =SABR_Base!H28+SABR_Shocks!$D$6*SABR_Shocks!H29 -> -0.0677537 | I29: =SABR_Base!I28+SABR_Shocks!$D$6*SABR_Shocks!I29 -> -0.0500408 | J29: =SABR_Base!J28+SABR_Shocks!$D$6*SABR_Shocks!J29 -> -0.038445 | ... L29: =SABR_Base!L28+SABR_Shocks!$D$6*SABR_Shocks!L29 -> 0.006855
B31: Param: NU
B32: Expiry \ Tenor | C32: 1M | D32: 3M | E32: 6M | F32: 1Y | G32: 2Y | H32: 3Y | I32: 5Y | J32: 10Y | K32: 20Y | L32: 30Y
B33: 1M | C33: =SABR_Base!C33+SABR_Shocks!$E$6*SABR_Shocks!C20 -> 0.8775624 | D33: =SABR_Base!D33+SABR_Shocks!$E$6*SABR_Shocks!D20 -> 0.8650032 | E33: =SABR_Base!E33+SABR_Shocks!$E$6*SABR_Shocks!E20 -> 0.845608 | F33: =SABR_Base!F33+SABR_Shocks!$E$6*SABR_Shocks!F20 -> 0.819016 | G33: =SABR_Base!G33+SABR_Shocks!$E$6*SABR_Shocks!G20 -> 0.7938088 | H33: =SABR_Base!H33+SABR_Shocks!$E$6*SABR_Shocks!H20 -> 0.7638688 | I33: =SABR_Base!I33+SABR_Shocks!$E$6*SABR_Shocks!I20 -> 0.734616 | J33: =SABR_Base!J33+SABR_Shocks!$E$6*SABR_Shocks!J20 -> 0.7226 | ... L33: =SABR_Base!L33+SABR_Shocks!$E$6*SABR_Shocks!L20 -> 0.6739648
B34: 3M | C34: =SABR_Base!C34+SABR_Shocks!$E$6*SABR_Shocks!C21 -> 0.8707776 | D34: =SABR_Base!D34+SABR_Shocks!$E$6*SABR_Shocks!D21 -> 0.8349496 | E34: =SABR_Base!E34+SABR_Shocks!$E$6*SABR_Shocks!E21 -> 0.8109008 | F34: =SABR_Base!F34+SABR_Shocks!$E$6*SABR_Shocks!F21 -> 0.7971936 | G34: =SABR_Base!G34+SABR_Shocks!$E$6*SABR_Shocks!G21 -> 0.7695184 | H34: =SABR_Base!H34+SABR_Shocks!$E$6*SABR_Shocks!H21 -> 0.7337096 | I34: =SABR_Base!I34+SABR_Shocks!$E$6*SABR_Shocks!I21 -> 0.7091984 | J34: =SABR_Base!J34+SABR_Shocks!$E$6*SABR_Shocks!J21 -> 0.6847552 | ... L34: =SABR_Base!L34+SABR_Shocks!$E$6*SABR_Shocks!L21 -> 0.6500504
B35: 6M | C35: =SABR_Base!C35+SABR_Shocks!$E$6*SABR_Shocks!C22 -> 0.829636 | D35: =SABR_Base!D35+SABR_Shocks!$E$6*SABR_Shocks!D22 -> 0.8193112 | E35: =SABR_Base!E35+SABR_Shocks!$E$6*SABR_Shocks!E22 -> 0.799036 | F35: =SABR_Base!F35+SABR_Shocks!$E$6*SABR_Shocks!F22 -> 0.7677152 | G35: =SABR_Base!G35+SABR_Shocks!$E$6*SABR_Shocks!G22 -> 0.7380936 | H35: =SABR_Base!H35+SABR_Shocks!$E$6*SABR_Shocks!H22 -> 0.7169936 | I35: =SABR_Base!I35+SABR_Shocks!$E$6*SABR_Shocks!I22 -> 0.6839296 | J35: =SABR_Base!J35+SABR_Shocks!$E$6*SABR_Shocks!J22 -> 0.6581752 | ... L35: =SABR_Base!L35+SABR_Shocks!$E$6*SABR_Shocks!L22 -> 0.6218504
B36: 1Y | C36: =SABR_Base!C36+SABR_Shocks!$E$6*SABR_Shocks!C23 -> 0.813132 | D36: =SABR_Base!D36+SABR_Shocks!$E$6*SABR_Shocks!D23 -> 0.797352 | E36: =SABR_Base!E36+SABR_Shocks!$E$6*SABR_Shocks!E23 -> 0.7639872 | F36: =SABR_Base!F36+SABR_Shocks!$E$6*SABR_Shocks!F23 -> 0.74818 | G36: =SABR_Base!G36+SABR_Shocks!$E$6*SABR_Shocks!G23 -> 0.7222128 | H36: =SABR_Base!H36+SABR_Shocks!$E$6*SABR_Shocks!H23 -> 0.685776 | I36: =SABR_Base!I36+SABR_Shocks!$E$6*SABR_Shocks!I23 -> 0.6621584 | J36: =SABR_Base!J36+SABR_Shocks!$E$6*SABR_Shocks!J23 -> 0.6386976 | ... L36: =SABR_Base!L36+SABR_Shocks!$E$6*SABR_Shocks!L23 -> 0.5963224
B37: 2Y | C37: =SABR_Base!C37+SABR_Shocks!$E$6*SABR_Shocks!C24 -> 0.7841656 | D37: =SABR_Base!D37+SABR_Shocks!$E$6*SABR_Shocks!D24 -> 0.7629928 | E37: =SABR_Base!E37+SABR_Shocks!$E$6*SABR_Shocks!E24 -> 0.7326184 | F37: =SABR_Base!F37+SABR_Shocks!$E$6*SABR_Shocks!F24 -> 0.7246416 | G37: =SABR_Base!G37+SABR_Shocks!$E$6*SABR_Shocks!G24 -> 0.6885192 | H37: =SABR_Base!H37+SABR_Shocks!$E$6*SABR_Shocks!H24 -> 0.6670976 | I37: =SABR_Base!I37+SABR_Shocks!$E$6*SABR_Shocks!I24 -> 0.6445648 | J37: =SABR_Base!J37+SABR_Shocks!$E$6*SABR_Shocks!J24 -> 0.627152 | ... L37: =SABR_Base!L37+SABR_Shocks!$E$6*SABR_Shocks!L24 -> 0.5788184
B38: 3Y | C38: =SABR_Base!C38+SABR_Shocks!$E$6*SABR_Shocks!C25 -> 0.7652872 | D38: =SABR_Base!D38+SABR_Shocks!$E$6*SABR_Shocks!D25 -> 0.7414472 | E38: =SABR_Base!E38+SABR_Shocks!$E$6*SABR_Shocks!E25 -> 0.7163592 | F38: =SABR_Base!F38+SABR_Shocks!$E$6*SABR_Shocks!F25 -> 0.6828272 | G38: =SABR_Base!G38+SABR_Shocks!$E$6*SABR_Shocks!G25 -> 0.6661152 | H38: =SABR_Base!H38+SABR_Shocks!$E$6*SABR_Shocks!H25 -> 0.6369456 | I38: =SABR_Base!I38+SABR_Shocks!$E$6*SABR_Shocks!I25 -> 0.6097344 | J38: =SABR_Base!J38+SABR_Shocks!$E$6*SABR_Shocks!J25 -> 0.6011496 | ... L38: =SABR_Base!L38+SABR_Shocks!$E$6*SABR_Shocks!L25 -> 0.5466656
B39: 5Y | C39: =SABR_Base!C39+SABR_Shocks!$E$6*SABR_Shocks!C26 -> 0.7445632 | D39: =SABR_Base!D39+SABR_Shocks!$E$6*SABR_Shocks!D26 -> 0.716992 | E39: =SABR_Base!E39+SABR_Shocks!$E$6*SABR_Shocks!E26 -> 0.6887704 | F39: =SABR_Base!F39+SABR_Shocks!$E$6*SABR_Shocks!F26 -> 0.667872 | G39: =SABR_Base!G39+SABR_Shocks!$E$6*SABR_Shocks!G26 -> 0.6443112 | H39: =SABR_Base!H39+SABR_Shocks!$E$6*SABR_Shocks!H26 -> 0.6242816 | I39: =SABR_Base!I39+SABR_Shocks!$E$6*SABR_Shocks!I26 -> 0.586588 | J39: =SABR_Base!J39+SABR_Shocks!$E$6*SABR_Shocks!J26 -> 0.572044 | ... L39: =SABR_Base!L39+SABR_Shocks!$E$6*SABR_Shocks!L26 -> 0.5179344
B40: 10Y | C40: =SABR_Base!C40+SABR_Shocks!$E$6*SABR_Shocks!C27 -> 0.7214488 | D40: =SABR_Base!D40+SABR_Shocks!$E$6*SABR_Shocks!D27 -> 0.6920448 | E40: =SABR_Base!E40+SABR_Shocks!$E$6*SABR_Shocks!E27 -> 0.6695232 | F40: =SABR_Base!F40+SABR_Shocks!$E$6*SABR_Shocks!F27 -> 0.6486576 | G40: =SABR_Base!G40+SABR_Shocks!$E$6*SABR_Shocks!G27 -> 0.6275536 | H40: =SABR_Base!H40+SABR_Shocks!$E$6*SABR_Shocks!H27 -> 0.5943408 | I40: =SABR_Base!I40+SABR_Shocks!$E$6*SABR_Shocks!I27 -> 0.5726064 | J40: =SABR_Base!J40+SABR_Shocks!$E$6*SABR_Shocks!J27 -> 0.5461456 | ... L40: =SABR_Base!L40+SABR_Shocks!$E$6*SABR_Shocks!L27 -> 0.5023096
B41: 20Y | C41: =SABR_Base!C41+SABR_Shocks!$E$6*SABR_Shocks!C28 -> 0.690676 | D41: =SABR_Base!D41+SABR_Shocks!$E$6*SABR_Shocks!D28 -> 0.6679704 | E41: =SABR_Base!E41+SABR_Shocks!$E$6*SABR_Shocks!E28 -> 0.6432936 | F41: =SABR_Base!F41+SABR_Shocks!$E$6*SABR_Shocks!F28 -> 0.6286464 | G41: =SABR_Base!G41+SABR_Shocks!$E$6*SABR_Shocks!G28 -> 0.5985448 | H41: =SABR_Base!H41+SABR_Shocks!$E$6*SABR_Shocks!H28 -> 0.5788368 | I41: =SABR_Base!I41+SABR_Shocks!$E$6*SABR_Shocks!I28 -> 0.5558312 | J41: =SABR_Base!J41+SABR_Shocks!$E$6*SABR_Shocks!J28 -> 0.5176344 | ... L41: =SABR_Base!L41+SABR_Shocks!$E$6*SABR_Shocks!L28 -> 0.48446
B42: 30Y | C42: =SABR_Base!C42+SABR_Shocks!$E$6*SABR_Shocks!C29 -> 0.6738688 | D42: =SABR_Base!D42+SABR_Shocks!$E$6*SABR_Shocks!D29 -> 0.6368072 | E42: =SABR_Base!E42+SABR_Shocks!$E$6*SABR_Shocks!E29 -> 0.6113056 | F42: =SABR_Base!F42+SABR_Shocks!$E$6*SABR_Shocks!F29 -> 0.5941168 | G42: =SABR_Base!G42+SABR_Shocks!$E$6*SABR_Shocks!G29 -> 0.561896 | H42: =SABR_Base!H42+SABR_Shocks!$E$6*SABR_Shocks!H29 -> 0.5417416 | I42: =SABR_Base!I42+SABR_Shocks!$E$6*SABR_Shocks!I29 -> 0.5138344 | J42: =SABR_Base!J42+SABR_Shocks!$E$6*SABR_Shocks!J29 -> 0.50116 | ... L42: =SABR_Base!L42+SABR_Shocks!$E$6*SABR_Shocks!L29 -> 0.46126
B45: SCENARIO 2
B46: Param: ATM
B47: Expiry \ Tenor | C47: 1M | D47: 3M | E47: 6M | F47: 1Y | G47: 2Y | H47: 3Y | I47: 5Y | J47: 10Y | K47: 20Y | L47: 30Y
B48: 1M | C48: =SABR_Base!C5+SABR_Shocks!$C$7*SABR_Shocks!C20 -> 0.5665125 | D48: =SABR_Base!D5+SABR_Shocks!$C$7*SABR_Shocks!D20 -> 0.545375 | E48: =SABR_Base!E5+SABR_Shocks!$C$7*SABR_Shocks!E20 -> 0.53745 | F48: =SABR_Base!F5+SABR_Shocks!$C$7*SABR_Shocks!F20 -> 0.50815 | G48: =SABR_Base!G5+SABR_Shocks!$C$7*SABR_Shocks!G20 -> 0.4995625 | H48: =SABR_Base!H5+SABR_Shocks!$C$7*SABR_Shocks!H20 -> 0.4782125 | I48: =SABR_Base!I5+SABR_Shocks!$C$7*SABR_Shocks!I20 -> 0.454825 | J48: =SABR_Base!J5+SABR_Shocks!$C$7*SABR_Shocks!J20 -> 0.446 | ... L48: =SABR_Base!L5+SABR_Shocks!$C$7*SABR_Shocks!L20 -> 0.408725
B49: 3M | C49: =SABR_Base!C6+SABR_Shocks!$C$7*SABR_Shocks!C21 -> 0.5434375 | D49: =SABR_Base!D6+SABR_Shocks!$C$7*SABR_Shocks!D21 -> 0.52605 | E49: =SABR_Base!E6+SABR_Shocks!$C$7*SABR_Shocks!E21 -> 0.5149625 | F49: =SABR_Base!F6+SABR_Shocks!$C$7*SABR_Shocks!F21 -> 0.505075 | G49: =SABR_Base!G6+SABR_Shocks!$C$7*SABR_Shocks!G21 -> 0.473675 | H49: =SABR_Base!H6+SABR_Shocks!$C$7*SABR_Shocks!H21 -> 0.457675 | I49: =SABR_Base!I6+SABR_Shocks!$C$7*SABR_Shocks!I21 -> 0.4482875 | J49: =SABR_Base!J6+SABR_Shocks!$C$7*SABR_Shocks!J21 -> 0.4365125 | ... L49: =SABR_Base!L6+SABR_Shocks!$C$7*SABR_Shocks!L21 -> 0.3903125
B50: 6M | C50: =SABR_Base!C7+SABR_Shocks!$C$7*SABR_Shocks!C22 -> 0.543575 | D50: =SABR_Base!D7+SABR_Shocks!$C$7*SABR_Shocks!D22 -> 0.5073125 | E50: =SABR_Base!E7+SABR_Shocks!$C$7*SABR_Shocks!E22 -> 0.5063125 | F50: =SABR_Base!F7+SABR_Shocks!$C$7*SABR_Shocks!F22 -> 0.47685 | G50: =SABR_Base!G7+SABR_Shocks!$C$7*SABR_Shocks!G22 -> 0.4565125 | H50: =SABR_Base!H7+SABR_Shocks!$C$7*SABR_Shocks!H22 -> 0.43775 | I50: =SABR_Base!I7+SABR_Shocks!$C$7*SABR_Shocks!I22 -> 0.423475 | J50: =SABR_Base!J7+SABR_Shocks!$C$7*SABR_Shocks!J22 -> 0.416275 | ... L50: =SABR_Base!L7+SABR_Shocks!$C$7*SABR_Shocks!L22 -> 0.37575
B51: 1Y | C51: =SABR_Base!C8+SABR_Shocks!$C$7*SABR_Shocks!C23 -> 0.5191125 | D51: =SABR_Base!D8+SABR_Shocks!$C$7*SABR_Shocks!D23 -> 0.496175 | E51: =SABR_Base!E8+SABR_Shocks!$C$7*SABR_Shocks!E23 -> 0.482325 | F51: =SABR_Base!F8+SABR_Shocks!$C$7*SABR_Shocks!F23 -> 0.4547375 | G51: =SABR_Base!G8+SABR_Shocks!$C$7*SABR_Shocks!G23 -> 0.4363375 | H51: =SABR_Base!H8+SABR_Shocks!$C$7*SABR_Shocks!H23 -> 0.4216125 | I51: =SABR_Base!I8+SABR_Shocks!$C$7*SABR_Shocks!I23 -> 0.413175 | J51: =SABR_Base!J8+SABR_Shocks!$C$7*SABR_Shocks!J23 -> 0.390325 | ... L51: =SABR_Base!L8+SABR_Shocks!$C$7*SABR_Shocks!L23 -> 0.3579625
B52: 2Y | C52: =SABR_Base!C9+SABR_Shocks!$C$7*SABR_Shocks!C24 -> 0.49795 | D52: =SABR_Base!D9+SABR_Shocks!$C$7*SABR_Shocks!D24 -> 0.4770375 | E52: =SABR_Base!E9+SABR_Shocks!$C$7*SABR_Shocks!E24 -> 0.4689125 | F52: =SABR_Base!F9+SABR_Shocks!$C$7*SABR_Shocks!F24 -> 0.4496 | G52: =SABR_Base!G9+SABR_Shocks!$C$7*SABR_Shocks!G24 -> 0.422225 | H52: =SABR_Base!H9+SABR_Shocks!$C$7*SABR_Shocks!H24 -> 0.4114875 | I52: =SABR_Base!I9+SABR_Shocks!$C$7*SABR_Shocks!I24 -> 0.3922625 | J52: =SABR_Base!J9+SABR_Shocks!$C$7*SABR_Shocks!J24 -> 0.3817625 | ... L52: =SABR_Base!L9+SABR_Shocks!$C$7*SABR_Shocks!L24 -> 0.3343
B53: 3Y | C53: =SABR_Base!C10+SABR_Shocks!$C$7*SABR_Shocks!C25 -> 0.491025 | D53: =SABR_Base!D10+SABR_Shocks!$C$7*SABR_Shocks!D25 -> 0.455875 | E53: =SABR_Base!E10+SABR_Shocks!$C$7*SABR_Shocks!E25 -> 0.443675 | F53: =SABR_Base!F10+SABR_Shocks!$C$7*SABR_Shocks!F25 -> 0.4330875 | G53: =SABR_Base!G10+SABR_Shocks!$C$7*SABR_Shocks!G25 -> 0.4026625 | H53: =SABR_Base!H10+SABR_Shocks!$C$7*SABR_Shocks!H25 -> 0.391775 | I53: =SABR_Base!I10+SABR_Shocks!$C$7*SABR_Shocks!I25 -> 0.3653875 | J53: =SABR_Base!J10+SABR_Shocks!$C$7*SABR_Shocks!J25 -> 0.3600125 | ... L53: =SABR_Base!L10+SABR_Shocks!$C$7*SABR_Shocks!L25 -> 0.3227125
B54: 5Y | C54: =SABR_Base!C11+SABR_Shocks!$C$7*SABR_Shocks!C26 -> 0.4705375 | D54: =SABR_Base!D11+SABR_Shocks!$C$7*SABR_Shocks!D26 -> 0.4415375 | E54: =SABR_Base!E11+SABR_Shocks!$C$7*SABR_Shocks!E26 -> 0.4318 | F54: =SABR_Base!F11+SABR_Shocks!$C$7*SABR_Shocks!F26 -> 0.41165 | G54: =SABR_Base!G11+SABR_Shocks!$C$7*SABR_Shocks!G26 -> 0.3935 | H54: =SABR_Base!H11+SABR_Shocks!$C$7*SABR_Shocks!H26 -> 0.3731 | I54: =SABR_Base!I11+SABR_Shocks!$C$7*SABR_Shocks!I26 -> 0.3629875 | J54: =SABR_Base!J11+SABR_Shocks!$C$7*SABR_Shocks!J26 -> 0.3476375 | ... L54: =SABR_Base!L11+SABR_Shocks!$C$7*SABR_Shocks!L26 -> 0.3065
B55: 10Y | C55: =SABR_Base!C12+SABR_Shocks!$C$7*SABR_Shocks!C27 -> 0.436525 | D55: =SABR_Base!D12+SABR_Shocks!$C$7*SABR_Shocks!D27 -> 0.4316625 | E55: =SABR_Base!E12+SABR_Shocks!$C$7*SABR_Shocks!E27 -> 0.413125 | F55: =SABR_Base!F12+SABR_Shocks!$C$7*SABR_Shocks!F27 -> 0.4019375 | G55: =SABR_Base!G12+SABR_Shocks!$C$7*SABR_Shocks!G27 -> 0.380775 | H55: =SABR_Base!H12+SABR_Shocks!$C$7*SABR_Shocks!H27 -> 0.352475 | I55: =SABR_Base!I12+SABR_Shocks!$C$7*SABR_Shocks!I27 -> 0.3361375 | J55: =SABR_Base!J12+SABR_Shocks!$C$7*SABR_Shocks!J27 -> 0.3239875 | ... L55: =SABR_Base!L12+SABR_Shocks!$C$7*SABR_Shocks!L27 -> 0.2848375
B56: 20Y | C56: =SABR_Base!C13+SABR_Shocks!$C$7*SABR_Shocks!C28 -> 0.4208125 | D56: =SABR_Base!D13+SABR_Shocks!$C$7*SABR_Shocks!D28 -> 0.4019375 | E56: =SABR_Base!E13+SABR_Shocks!$C$7*SABR_Shocks!E28 -> 0.383425 | F56: =SABR_Base!F13+SABR_Shocks!$C$7*SABR_Shocks!F28 -> 0.37995 | G56: =SABR_Base!G13+SABR_Shocks!$C$7*SABR_Shocks!G28 -> 0.348875 | H56: =SABR_Base!H13+SABR_Shocks!$C$7*SABR_Shocks!H28 -> 0.3340125 | I56: =SABR_Base!I13+SABR_Shocks!$C$7*SABR_Shocks!I28 -> 0.3190375 | J56: =SABR_Base!J13+SABR_Shocks!$C$7*SABR_Shocks!J28 -> 0.3106 | ... L56: =SABR_Base!L13+SABR_Shocks!$C$7*SABR_Shocks!L28 -> 0.267575
B57: 30Y | C57: =SABR_Base!C14+SABR_Shocks!$C$7*SABR_Shocks!C29 -> 0.410525 | D57: =SABR_Base!D14+SABR_Shocks!$C$7*SABR_Shocks!D29 -> 0.4001 | E57: =SABR_Base!E14+SABR_Shocks!$C$7*SABR_Shocks!E29 -> 0.380525 | F57: =SABR_Base!F14+SABR_Shocks!$C$7*SABR_Shocks!F29 -> 0.36395 | G57: =SABR_Base!G14+SABR_Shocks!$C$7*SABR_Shocks!G29 -> 0.3340875 | H57: =SABR_Base!H14+SABR_Shocks!$C$7*SABR_Shocks!H29 -> 0.3194875 | I57: =SABR_Base!I14+SABR_Shocks!$C$7*SABR_Shocks!I29 -> 0.3004 | J57: =SABR_Base!J14+SABR_Shocks!$C$7*SABR_Shocks!J29 -> 0.292875 | ... L57: =SABR_Base!L14+SABR_Shocks!$C$7*SABR_Shocks!L29 -> 0.244875
B59: Param: RHO
B60: Expiry \ Tenor | C60: 1M | D60: 3M | E60: 6M | F60: 1Y | G60: 2Y | H60: 3Y | I60: 5Y | J60: 10Y | K60: 20Y | L60: 30Y
B61: 1M | C61: =SABR_Base!C19+SABR_Shocks!$D$7*SABR_Shocks!C20 -> -0.3460935 | D61: =SABR_Base!D19+SABR_Shocks!$D$7*SABR_Shocks!D20 -> -0.326033 | E61: =SABR_Base!E19+SABR_Shocks!$D$7*SABR_Shocks!E20 -> -0.30717 | F61: =SABR_Base!F19+SABR_Shocks!$D$7*SABR_Shocks!F20 -> -0.28329 | G61: =SABR_Base!G19+SABR_Shocks!$D$7*SABR_Shocks!G20 -> -0.2623595 | H61: =SABR_Base!H19+SABR_Shocks!$D$7*SABR_Shocks!H20 -> -0.2501095 | I61: =SABR_Base!I19+SABR_Shocks!$D$7*SABR_Shocks!I20 -> -0.236215 | J61: =SABR_Base!J19+SABR_Shocks!$D$7*SABR_Shocks!J20 -> -0.209 | ... L61: =SABR_Base!L19+SABR_Shocks!$D$7*SABR_Shocks!L20 -> -0.168487
B62: 3M | C62: =SABR_Base!C20+SABR_Shocks!$D$7*SABR_Shocks!C21 -> -0.3117565 | D62: =SABR_Base!D20+SABR_Shocks!$D$7*SABR_Shocks!D21 -> -0.298174 | E62: =SABR_Base!E20+SABR_Shocks!$D$7*SABR_Shocks!E21 -> -0.2828395 | F62: =SABR_Base!F20+SABR_Shocks!$D$7*SABR_Shocks!F21 -> -0.262009 | G62: =SABR_Base!G20+SABR_Shocks!$D$7*SABR_Shocks!G21 -> -0.241721 | H62: =SABR_Base!H20+SABR_Shocks!$D$7*SABR_Shocks!H21 -> -0.235449 | I62: =SABR_Base!I20+SABR_Shocks!$D$7*SABR_Shocks!I21 -> -0.1994585 | J62: =SABR_Base!J20+SABR_Shocks!$D$7*SABR_Shocks!J21 -> -0.1831255 | ... L62: =SABR_Base!L20+SABR_Shocks!$D$7*SABR_Shocks!L21 -> -0.1449135
B63: 6M | C63: =SABR_Base!C21+SABR_Shocks!$D$7*SABR_Shocks!C22 -> -0.304265 | D63: =SABR_Base!D21+SABR_Shocks!$D$7*SABR_Shocks!D22 -> -0.2851655 | E63: =SABR_Base!E21+SABR_Shocks!$D$7*SABR_Shocks!E22 -> -0.2719775 | F63: =SABR_Base!F21+SABR_Shocks!$D$7*SABR_Shocks!F22 -> -0.242638 | G63: =SABR_Base!G21+SABR_Shocks!$D$7*SABR_Shocks!G22 -> -0.2350215 | H63: =SABR_Base!H21+SABR_Shocks!$D$7*SABR_Shocks!H22 -> -0.216234 | I63: =SABR_Base!I21+SABR_Shocks!$D$7*SABR_Shocks!I22 -> -0.194749 | J63: =SABR_Base!J21+SABR_Shocks!$D$7*SABR_Shocks!J22 -> -0.176613 | ... L63: =SABR_Base!L21+SABR_Shocks!$D$7*SABR_Shocks!L22 -> -0.141226
B64: 1Y | C64: =SABR_Base!C22+SABR_Shocks!$D$7*SABR_Shocks!C23 -> -0.2932175 | D64: =SABR_Base!D22+SABR_Shocks!$D$7*SABR_Shocks!D23 -> -0.271205 | E64: =SABR_Base!E22+SABR_Shocks!$D$7*SABR_Shocks!E23 -> -0.253043 | F64: =SABR_Base!F22+SABR_Shocks!$D$7*SABR_Shocks!F23 -> -0.2291125 | G64: =SABR_Base!G22+SABR_Shocks!$D$7*SABR_Shocks!G23 -> -0.2172445 | H64: =SABR_Base!H22+SABR_Shocks!$D$7*SABR_Shocks!H23 -> -0.1813775 | I64: =SABR_Base!I22+SABR_Shocks!$D$7*SABR_Shocks!I23 -> -0.167721 | J64: =SABR_Base!J22+SABR_Shocks!$D$7*SABR_Shocks!J23 -> -0.158219 | ... L64: =SABR_Base!L22+SABR_Shocks!$D$7*SABR_Shocks!L23 -> -0.1164435
B65: 2Y | C65: =SABR_Base!C23+SABR_Shocks!$D$7*SABR_Shocks!C24 -> -0.266814 | D65: =SABR_Base!D23+SABR_Shocks!$D$7*SABR_Shocks!D24 -> -0.2528445 | E65: =SABR_Base!E23+SABR_Shocks!$D$7*SABR_Shocks!E24 -> -0.2196335 | F65: =SABR_Base!F23+SABR_Shocks!$D$7*SABR_Shocks!F24 -> -0.197604 | G65: =SABR_Base!G23+SABR_Shocks!$D$7*SABR_Shocks!G24 -> -0.189523 | H65: =SABR_Base!H23+SABR_Shocks!$D$7*SABR_Shocks!H24 -> -0.1701065 | I65: =SABR_Base!I23+SABR_Shocks!$D$7*SABR_Shocks!I24 -> -0.1593995 | J65: =SABR_Base!J23+SABR_Shocks!$D$7*SABR_Shocks!J24 -> -0.1401675 | ... L65: =SABR_Base!L23+SABR_Shocks!$D$7*SABR_Shocks!L24 -> -0.099196
B66: 3Y | C66: =SABR_Base!C24+SABR_Shocks!$D$7*SABR_Shocks!C25 -> -0.238543 | D66: =SABR_Base!D24+SABR_Shocks!$D$7*SABR_Shocks!D25 -> -0.233093 | E66: =SABR_Base!E24+SABR_Shocks!$D$7*SABR_Shocks!E25 -> -0.217173 | F66: =SABR_Base!F24+SABR_Shocks!$D$7*SABR_Shocks!F25 -> -0.1795305 | G66: =SABR_Base!G24+SABR_Shocks!$D$7*SABR_Shocks!G25 -> -0.1693755 | H66: =SABR_Base!H24+SABR_Shocks!$D$7*SABR_Shocks!H25 -> -0.158089 | I66: =SABR_Base!I24+SABR_Shocks!$D$7*SABR_Shocks!I25 -> -0.1310985 | J66: =SABR_Base!J24+SABR_Shocks!$D$7*SABR_Shocks!J25 -> -0.1226615 | ... L66: =SABR_Base!L24+SABR_Shocks!$D$7*SABR_Shocks!L25 -> -0.0658015
B67: 5Y | C67: =SABR_Base!C25+SABR_Shocks!$D$7*SABR_Shocks!C26 -> -0.2193205 | D67: =SABR_Base!D25+SABR_Shocks!$D$7*SABR_Shocks!D26 -> -0.2037925 | E67: =SABR_Base!E25+SABR_Shocks!$D$7*SABR_Shocks!E26 -> -0.193376 | F67: =SABR_Base!F25+SABR_Shocks!$D$7*SABR_Shocks!F26 -> -0.17263 | G67: =SABR_Base!G25+SABR_Shocks!$D$7*SABR_Shocks!G26 -> -0.157728 | H67: =SABR_Base!H25+SABR_Shocks!$D$7*SABR_Shocks!H26 -> -0.126904 | I67: =SABR_Base!I25+SABR_Shocks!$D$7*SABR_Shocks!I26 -> -0.1127825 | J67: =SABR_Base!J25+SABR_Shocks!$D$7*SABR_Shocks!J26 -> -0.0887725 | ... L67: =SABR_Base!L25+SABR_Shocks!$D$7*SABR_Shocks!L26 -> -0.062236
B68: 10Y | C68: =SABR_Base!C26+SABR_Shocks!$D$7*SABR_Shocks!C27 -> -0.201447 | D68: =SABR_Base!D26+SABR_Shocks!$D$7*SABR_Shocks!D27 -> -0.1789995 | E68: =SABR_Base!E26+SABR_Shocks!$D$7*SABR_Shocks!E27 -> -0.162583 | F68: =SABR_Base!F26+SABR_Shocks!$D$7*SABR_Shocks!F27 -> -0.1448565 | G68: =SABR_Base!G26+SABR_Shocks!$D$7*SABR_Shocks!G27 -> -0.125709 | H68: =SABR_Base!H26+SABR_Shocks!$D$7*SABR_Shocks!H27 -> -0.108377 | I68: =SABR_Base!I26+SABR_Shocks!$D$7*SABR_Shocks!I27 -> -0.1000285 | J68: =SABR_Base!J26+SABR_Shocks!$D$7*SABR_Shocks!J27 -> -0.0753265 | ... L68: =SABR_Base!L26+SABR_Shocks!$D$7*SABR_Shocks!L27 -> -0.0471365
B69: 20Y | C69: =SABR_Base!C27+SABR_Shocks!$D$7*SABR_Shocks!C28 -> -0.1982775 | D69: =SABR_Base!D27+SABR_Shocks!$D$7*SABR_Shocks!D28 -> -0.1743885 | E69: =SABR_Base!E27+SABR_Shocks!$D$7*SABR_Shocks!E28 -> -0.155759 | F69: =SABR_Base!F27+SABR_Shocks!$D$7*SABR_Shocks!F28 -> -0.128166 | G69: =SABR_Base!G27+SABR_Shocks!$D$7*SABR_Shocks!G28 -> -0.104237 | H69: =SABR_Base!H27+SABR_Shocks!$D$7*SABR_Shocks!H28 -> -0.0953295 | I69: =SABR_Base!I27+SABR_Shocks!$D$7*SABR_Shocks!I28 -> -0.0666405 | J69: =SABR_Base!J27+SABR_Shocks!$D$7*SABR_Shocks!J28 -> -0.046936 | ... L69: =SABR_Base!L27+SABR_Shocks!$D$7*SABR_Shocks!L28 -> -0.021225
B70: 30Y | C70: =SABR_Base!C28+SABR_Shocks!$D$7*SABR_Shocks!C29 -> -0.175647 | D70: =SABR_Base!D28+SABR_Shocks!$D$7*SABR_Shocks!D29 -> -0.156268 | E70: =SABR_Base!E28+SABR_Shocks!$D$7*SABR_Shocks!E29 -> -0.138339 | F70: =SABR_Base!F28+SABR_Shocks!$D$7*SABR_Shocks!F29 -> -0.119142 | G70: =SABR_Base!G28+SABR_Shocks!$D$7*SABR_Shocks!G29 -> -0.0920025 | H70: =SABR_Base!H28+SABR_Shocks!$D$7*SABR_Shocks!H29 -> -0.0674665 | I70: =SABR_Base!I28+SABR_Shocks!$D$7*SABR_Shocks!I29 -> -0.049836 | J70: =SABR_Base!J28+SABR_Shocks!$D$7*SABR_Shocks!J29 -> -0.038325 | ... L70: =SABR_Base!L28+SABR_Shocks!$D$7*SABR_Shocks!L29 -> 0.006975
B72: Param: NU
B73: Expiry \ Tenor | C73: 1M | D73: 3M | E73: 6M | F73: 1Y | G73: 2Y | H73: 3Y | I73: 5Y | J73: 10Y | K73: 20Y | L73: 30Y
B74: 1M | C74: =SABR_Base!C33+SABR_Shocks!$E$7*SABR_Shocks!C20 -> 0.8746806 | D74: =SABR_Base!D33+SABR_Shocks!$E$7*SABR_Shocks!D20 -> 0.8622708 | E74: =SABR_Base!E33+SABR_Shocks!$E$7*SABR_Shocks!E20 -> 0.843052 | F74: =SABR_Base!F33+SABR_Shocks!$E$7*SABR_Shocks!F20 -> 0.816604 | G74: =SABR_Base!G33+SABR_Shocks!$E$7*SABR_Shocks!G20 -> 0.7915822 | H74: =SABR_Base!H33+SABR_Shocks!$E$7*SABR_Shocks!H20 -> 0.7618222 | I74: =SABR_Base!I33+SABR_Shocks!$E$7*SABR_Shocks!I20 -> 0.732654 | J74: =SABR_Base!J33+SABR_Shocks!$E$7*SABR_Shocks!J20 -> 0.7208 | ... L74: =SABR_Base!L33+SABR_Shocks!$E$7*SABR_Shocks!L20 -> 0.6725212
B75: 3M | C75: =SABR_Base!C34+SABR_Shocks!$E$7*SABR_Shocks!C21 -> 0.8680794 | D75: =SABR_Base!D34+SABR_Shocks!$E$7*SABR_Shocks!D21 -> 0.8324224 | E75: =SABR_Base!E34+SABR_Shocks!$E$7*SABR_Shocks!E21 -> 0.8085302 | F75: =SABR_Base!F34+SABR_Shocks!$E$7*SABR_Shocks!F21 -> 0.7950084 | G75: =SABR_Base!G34+SABR_Shocks!$E$7*SABR_Shocks!G21 -> 0.7674196 | H75: =SABR_Base!H34+SABR_Shocks!$E$7*SABR_Shocks!H21 -> 0.7318124 | I75: =SABR_Base!I34+SABR_Shocks!$E$7*SABR_Shocks!I21 -> 0.7074146 | J75: =SABR_Base!J34+SABR_Shocks!$E$7*SABR_Shocks!J21 -> 0.6831838 | ... L75: =SABR_Base!L34+SABR_Shocks!$E$7*SABR_Shocks!L21 -> 0.6487526
B76: 6M | C76: =SABR_Base!C35+SABR_Shocks!$E$7*SABR_Shocks!C22 -> 0.827134 | D76: =SABR_Base!D35+SABR_Shocks!$E$7*SABR_Shocks!D22 -> 0.8169478 | E76: =SABR_Base!E35+SABR_Shocks!$E$7*SABR_Shocks!E22 -> 0.796759 | F76: =SABR_Base!F35+SABR_Shocks!$E$7*SABR_Shocks!F22 -> 0.7656488 | G76: =SABR_Base!G35+SABR_Shocks!$E$7*SABR_Shocks!G22 -> 0.7361334 | H76: =SABR_Base!H35+SABR_Shocks!$E$7*SABR_Shocks!H22 -> 0.7152584 | I76: =SABR_Base!I35+SABR_Shocks!$E$7*SABR_Shocks!I22 -> 0.6823924 | J76: =SABR_Base!J35+SABR_Shocks!$E$7*SABR_Shocks!J22 -> 0.6567388 | ... L76: =SABR_Base!L35+SABR_Shocks!$E$7*SABR_Shocks!L22 -> 0.6207776
B77: 1Y | C77: =SABR_Base!C36+SABR_Shocks!$E$7*SABR_Shocks!C23 -> 0.810783 | D77: =SABR_Base!D36+SABR_Shocks!$E$7*SABR_Shocks!D23 -> 0.795138 | E77: =SABR_Base!E36+SABR_Shocks!$E$7*SABR_Shocks!E23 -> 0.7618668 | F77: =SABR_Base!F36+SABR_Shocks!$E$7*SABR_Shocks!F23 -> 0.746245 | G77: =SABR_Base!G36+SABR_Shocks!$E$7*SABR_Shocks!G23 -> 0.7205082 | H77: =SABR_Base!H36+SABR_Shocks!$E$7*SABR_Shocks!H23 -> 0.684219 | I77: =SABR_Base!I36+SABR_Shocks!$E$7*SABR_Shocks!I23 -> 0.6607796 | J77: =SABR_Base!J36+SABR_Shocks!$E$7*SABR_Shocks!J23 -> 0.6374844 | ... L77: =SABR_Base!L36+SABR_Shocks!$E$7*SABR_Shocks!L23 -> 0.5954206
B78: 2Y | C78: =SABR_Base!C37+SABR_Shocks!$E$7*SABR_Shocks!C24 -> 0.7819264 | D78: =SABR_Base!D37+SABR_Shocks!$E$7*SABR_Shocks!D24 -> 0.7609282 | E78: =SABR_Base!E37+SABR_Shocks!$E$7*SABR_Shocks!E24 -> 0.7307446 | F78: =SABR_Base!F37+SABR_Shocks!$E$7*SABR_Shocks!F24 -> 0.7228704 | G78: =SABR_Base!G37+SABR_Shocks!$E$7*SABR_Shocks!G24 -> 0.6869748 | H78: =SABR_Base!H37+SABR_Shocks!$E$7*SABR_Shocks!H24 -> 0.6656594 | I78: =SABR_Base!I37+SABR_Shocks!$E$7*SABR_Shocks!I24 -> 0.6433462 | J78: =SABR_Base!J37+SABR_Shocks!$E$7*SABR_Shocks!J24 -> 0.626063 | ... L78: =SABR_Base!L37+SABR_Shocks!$E$7*SABR_Shocks!L24 -> 0.5780696
B79: 3Y | C79: =SABR_Base!C38+SABR_Shocks!$E$7*SABR_Shocks!C25 -> 0.7631668 | D79: =SABR_Base!D38+SABR_Shocks!$E$7*SABR_Shocks!D25 -> 0.7395068 | E79: =SABR_Base!E38+SABR_Shocks!$E$7*SABR_Shocks!E25 -> 0.7146348 | F79: =SABR_Base!F38+SABR_Shocks!$E$7*SABR_Shocks!F25 -> 0.6812018 | G79: =SABR_Base!G38+SABR_Shocks!$E$7*SABR_Shocks!G25 -> 0.6647238 | H79: =SABR_Base!H38+SABR_Shocks!$E$7*SABR_Shocks!H25 -> 0.6356964 | I79: =SABR_Base!I38+SABR_Shocks!$E$7*SABR_Shocks!I25 -> 0.6085986 | J79: =SABR_Base!J38+SABR_Shocks!$E$7*SABR_Shocks!J25 -> 0.6001974 | ... L79: =SABR_Base!L38+SABR_Shocks!$E$7*SABR_Shocks!L25 -> 0.5460014
B80: 5Y | C80: =SABR_Base!C39+SABR_Shocks!$E$7*SABR_Shocks!C26 -> 0.7426858 | D80: =SABR_Base!D39+SABR_Shocks!$E$7*SABR_Shocks!D26 -> 0.715273 | E80: =SABR_Base!E39+SABR_Shocks!$E$7*SABR_Shocks!E26 -> 0.6871576 | F80: =SABR_Base!F39+SABR_Shocks!$E$7*SABR_Shocks!F26 -> 0.666468 | G80: =SABR_Base!G39+SABR_Shocks!$E$7*SABR_Shocks!G26 -> 0.6430728 | H80: =SABR_Base!H39+SABR_Shocks!$E$7*SABR_Shocks!H26 -> 0.6232304 | I80: =SABR_Base!I39+SABR_Shocks!$E$7*SABR_Shocks!I26 -> 0.585697 | J80: =SABR_Base!J39+SABR_Shocks!$E$7*SABR_Shocks!J26 -> 0.571261 | ... L80: =SABR_Base!L39+SABR_Shocks!$E$7*SABR_Shocks!L26 -> 0.5174736
B81: 10Y | C81: =SABR_Base!C40+SABR_Shocks!$E$7*SABR_Shocks!C27 -> 0.7197172 | D81: =SABR_Base!D40+SABR_Shocks!$E$7*SABR_Shocks!D27 -> 0.6904662 | E81: =SABR_Base!E40+SABR_Shocks!$E$7*SABR_Shocks!E27 -> 0.6680508 | F81: =SABR_Base!F40+SABR_Shocks!$E$7*SABR_Shocks!F27 -> 0.6473994 | G81: =SABR_Base!G40+SABR_Shocks!$E$7*SABR_Shocks!G27 -> 0.6264484 | H81: =SABR_Base!H40+SABR_Shocks!$E$7*SABR_Shocks!H27 -> 0.5933652 | I81: =SABR_Base!I40+SABR_Shocks!$E$7*SABR_Shocks!I27 -> 0.5718666 | J81: =SABR_Base!J40+SABR_Shocks!$E$7*SABR_Shocks!J27 -> 0.5455714 | ... L81: =SABR_Base!L40+SABR_Shocks!$E$7*SABR_Shocks!L27 -> 0.5019874
B82: 20Y | C82: =SABR_Base!C41+SABR_Shocks!$E$7*SABR_Shocks!C28 -> 0.689119 | D82: =SABR_Base!D41+SABR_Shocks!$E$7*SABR_Shocks!D28 -> 0.6665826 | E82: =SABR_Base!E41+SABR_Shocks!$E$7*SABR_Shocks!E28 -> 0.6420084 | F82: =SABR_Base!F41+SABR_Shocks!$E$7*SABR_Shocks!F28 -> 0.6275016 | G82: =SABR_Base!G41+SABR_Shocks!$E$7*SABR_Shocks!G28 -> 0.5976412 | H82: =SABR_Base!H41+SABR_Shocks!$E$7*SABR_Shocks!H28 -> 0.5780142 | I82: =SABR_Base!I41+SABR_Shocks!$E$7*SABR_Shocks!I28 -> 0.5551778 | J82: =SABR_Base!J41+SABR_Shocks!$E$7*SABR_Shocks!J28 -> 0.5171736 | ... L82: =SABR_Base!L41+SABR_Shocks!$E$7*SABR_Shocks!L28 -> 0.48419
B83: 30Y | C83: =SABR_Base!C42+SABR_Shocks!$E$7*SABR_Shocks!C29 -> 0.6724972 | D83: =SABR_Base!D42+SABR_Shocks!$E$7*SABR_Shocks!D29 -> 0.6354968 | E83: =SABR_Base!E42+SABR_Shocks!$E$7*SABR_Shocks!E29 -> 0.6102364 | F83: =SABR_Base!F42+SABR_Shocks!$E$7*SABR_Shocks!F29 -> 0.5931592 | G83: =SABR_Base!G42+SABR_Shocks!$E$7*SABR_Shocks!G29 -> 0.561149 | H83: =SABR_Base!H42+SABR_Shocks!$E$7*SABR_Shocks!H29 -> 0.5410954 | I83: =SABR_Base!I42+SABR_Shocks!$E$7*SABR_Shocks!I29 -> 0.5133736 | J83: =SABR_Base!J42+SABR_Shocks!$E$7*SABR_Shocks!J29 -> 0.50089 | ... L83: =SABR_Base!L42+SABR_Shocks!$E$7*SABR_Shocks!L29 -> 0.46099
B86: SCENARIO 3
B87: Param: ATM
B88: Expiry \ Tenor | C88: 1M | D88: 3M | E88: 6M | F88: 1Y | G88: 2Y | H88: 3Y | I88: 5Y | J88: 10Y | K88: 20Y | L88: 30Y
B89: 1M | C89: =SABR_Base!C5+SABR_Shocks!$C$8*SABR_Shocks!C20 -> 0.565712 | D89: =SABR_Base!D5+SABR_Shocks!$C$8*SABR_Shocks!D20 -> 0.544616 | E89: =SABR_Base!E5+SABR_Shocks!$C$8*SABR_Shocks!E20 -> 0.53674 | F89: =SABR_Base!F5+SABR_Shocks!$C$8*SABR_Shocks!F20 -> 0.50748 | G89: =SABR_Base!G5+SABR_Shocks!$C$8*SABR_Shocks!G20 -> 0.498944 | H89: =SABR_Base!H5+SABR_Shocks!$C$8*SABR_Shocks!H20 -> 0.477644 | I89: =SABR_Base!I5+SABR_Shocks!$C$8*SABR_Shocks!I20 -> 0.45428 | J89: =SABR_Base!J5+SABR_Shocks!$C$8*SABR_Shocks!J20 -> 0.4455 | ... L89: =SABR_Base!L5+SABR_Shocks!$C$8*SABR_Shocks!L20 -> 0.408324
B90: 3M | C90: =SABR_Base!C6+SABR_Shocks!$C$8*SABR_Shocks!C21 -> 0.542688 | D90: =SABR_Base!D6+SABR_Shocks!$C$8*SABR_Shocks!D21 -> 0.525348 | E90: =SABR_Base!E6+SABR_Shocks!$C$8*SABR_Shocks!E21 -> 0.514304 | F90: =SABR_Base!F6+SABR_Shocks!$C$8*SABR_Shocks!F21 -> 0.504468 | G90: =SABR_Base!G6+SABR_Shocks!$C$8*SABR_Shocks!G21 -> 0.473092 | H90: =SABR_Base!H6+SABR_Shocks!$C$8*SABR_Shocks!H21 -> 0.457148 | I90: =SABR_Base!I6+SABR_Shocks!$C$8*SABR_Shocks!I21 -> 0.447792 | J90: =SABR_Base!J6+SABR_Shocks!$C$8*SABR_Shocks!J21 -> 0.436076 | ... L90: =SABR_Base!L6+SABR_Shocks!$C$8*SABR_Shocks!L21 -> 0.389952
B91: 6M | C91: =SABR_Base!C7+SABR_Shocks!$C$8*SABR_Shocks!C22 -> 0.54288 | D91: =SABR_Base!D7+SABR_Shocks!$C$8*SABR_Shocks!D22 -> 0.506656 | E91: =SABR_Base!E7+SABR_Shocks!$C$8*SABR_Shocks!E22 -> 0.50568 | F91: =SABR_Base!F7+SABR_Shocks!$C$8*SABR_Shocks!F22 -> 0.476276 | G91: =SABR_Base!G7+SABR_Shocks!$C$8*SABR_Shocks!G22 -> 0.455968 | H91: =SABR_Base!H7+SABR_Shocks!$C$8*SABR_Shocks!H22 -> 0.437268 | I91: =SABR_Base!I7+SABR_Shocks!$C$8*SABR_Shocks!I22 -> 0.423048 | J91: =SABR_Base!J7+SABR_Shocks!$C$8*SABR_Shocks!J22 -> 0.415876 | ... L91: =SABR_Base!L7+SABR_Shocks!$C$8*SABR_Shocks!L22 -> 0.375452
B92: 1Y | C92: =SABR_Base!C8+SABR_Shocks!$C$8*SABR_Shocks!C23 -> 0.51846 | D92: =SABR_Base!D8+SABR_Shocks!$C$8*SABR_Shocks!D23 -> 0.49556 | E92: =SABR_Base!E8+SABR_Shocks!$C$8*SABR_Shocks!E23 -> 0.481736 | F92: =SABR_Base!F8+SABR_Shocks!$C$8*SABR_Shocks!F23 -> 0.4542 | G92: =SABR_Base!G8+SABR_Shocks!$C$8*SABR_Shocks!G23 -> 0.435864 | H92: =SABR_Base!H8+SABR_Shocks!$C$8*SABR_Shocks!H23 -> 0.42118 | I92: =SABR_Base!I8+SABR_Shocks!$C$8*SABR_Shocks!I23 -> 0.412792 | J92: =SABR_Base!J8+SABR_Shocks!$C$8*SABR_Shocks!J23 -> 0.389988 | ... L92: =SABR_Base!L8+SABR_Shocks!$C$8*SABR_Shocks!L23 -> 0.357712
B93: 2Y | C93: =SABR_Base!C9+SABR_Shocks!$C$8*SABR_Shocks!C24 -> 0.497328 | D93: =SABR_Base!D9+SABR_Shocks!$C$8*SABR_Shocks!D24 -> 0.476464 | E93: =SABR_Base!E9+SABR_Shocks!$C$8*SABR_Shocks!E24 -> 0.468392 | F93: =SABR_Base!F9+SABR_Shocks!$C$8*SABR_Shocks!F24 -> 0.449108 | G93: =SABR_Base!G9+SABR_Shocks!$C$8*SABR_Shocks!G24 -> 0.421796 | H93: =SABR_Base!H9+SABR_Shocks!$C$8*SABR_Shocks!H24 -> 0.411088 | I93: =SABR_Base!I9+SABR_Shocks!$C$8*SABR_Shocks!I24 -> 0.391924 | J93: =SABR_Base!J9+SABR_Shocks!$C$8*SABR_Shocks!J24 -> 0.38146 | ... L93: =SABR_Base!L9+SABR_Shocks!$C$8*SABR_Shocks!L24 -> 0.334092
B94: 3Y | C94: =SABR_Base!C10+SABR_Shocks!$C$8*SABR_Shocks!C25 -> 0.490436 | D94: =SABR_Base!D10+SABR_Shocks!$C$8*SABR_Shocks!D25 -> 0.455336 | E94: =SABR_Base!E10+SABR_Shocks!$C$8*SABR_Shocks!E25 -> 0.443196 | F94: =SABR_Base!F10+SABR_Shocks!$C$8*SABR_Shocks!F25 -> 0.432636 | G94: =SABR_Base!G10+SABR_Shocks!$C$8*SABR_Shocks!G25 -> 0.402276 | H94: =SABR_Base!H10+SABR_Shocks!$C$8*SABR_Shocks!H25 -> 0.391428 | I94: =SABR_Base!I10+SABR_Shocks!$C$8*SABR_Shocks!I25 -> 0.365072 | J94: =SABR_Base!J10+SABR_Shocks!$C$8*SABR_Shocks!J25 -> 0.359748 | ... L94: =SABR_Base!L10+SABR_Shocks!$C$8*SABR_Shocks!L25 -> 0.322528
B95: 5Y | C95: =SABR_Base!C11+SABR_Shocks!$C$8*SABR_Shocks!C26 -> 0.470016 | D95: =SABR_Base!D11+SABR_Shocks!$C$8*SABR_Shocks!D26 -> 0.44106 | E95: =SABR_Base!E11+SABR_Shocks!$C$8*SABR_Shocks!E26 -> 0.431352 | F95: =SABR_Base!F11+SABR_Shocks!$C$8*SABR_Shocks!F26 -> 0.41126 | G95: =SABR_Base!G11+SABR_Shocks!$C$8*SABR_Shocks!G26 -> 0.393156 | H95: =SABR_Base!H11+SABR_Shocks!$C$8*SABR_Shocks!H26 -> 0.372808 | I95: =SABR_Base!I11+SABR_Shocks!$C$8*SABR_Shocks!I26 -> 0.36274 | J95: =SABR_Base!J11+SABR_Shocks!$C$8*SABR_Shocks!J26 -> 0.34742 | ... L95: =SABR_Base!L11+SABR_Shocks!$C$8*SABR_Shocks!L26 -> 0.306372
B96: 10Y | C96: =SABR_Base!C12+SABR_Shocks!$C$8*SABR_Shocks!C27 -> 0.436044 | D96: =SABR_Base!D12+SABR_Shocks!$C$8*SABR_Shocks!D27 -> 0.431224 | E96: =SABR_Base!E12+SABR_Shocks!$C$8*SABR_Shocks!E27 -> 0.412716 | F96: =SABR_Base!F12+SABR_Shocks!$C$8*SABR_Shocks!F27 -> 0.401588 | G96: =SABR_Base!G12+SABR_Shocks!$C$8*SABR_Shocks!G27 -> 0.380468 | H96: =SABR_Base!H12+SABR_Shocks!$C$8*SABR_Shocks!H27 -> 0.352204 | I96: =SABR_Base!I12+SABR_Shocks!$C$8*SABR_Shocks!I27 -> 0.335932 | J96: =SABR_Base!J12+SABR_Shocks!$C$8*SABR_Shocks!J27 -> 0.323828 | ... L96: =SABR_Base!L12+SABR_Shocks!$C$8*SABR_Shocks!L27 -> 0.284748
B97: 20Y | C97: =SABR_Base!C13+SABR_Shocks!$C$8*SABR_Shocks!C28 -> 0.42038 | D97: =SABR_Base!D13+SABR_Shocks!$C$8*SABR_Shocks!D28 -> 0.401552 | E97: =SABR_Base!E13+SABR_Shocks!$C$8*SABR_Shocks!E28 -> 0.383068 | F97: =SABR_Base!F13+SABR_Shocks!$C$8*SABR_Shocks!F28 -> 0.379632 | G97: =SABR_Base!G13+SABR_Shocks!$C$8*SABR_Shocks!G28 -> 0.348624 | H97: =SABR_Base!H13+SABR_Shocks!$C$8*SABR_Shocks!H28 -> 0.333784 | I97: =SABR_Base!I13+SABR_Shocks!$C$8*SABR_Shocks!I28 -> 0.318856 | J97: =SABR_Base!J13+SABR_Shocks!$C$8*SABR_Shocks!J28 -> 0.310472 | ... L97: =SABR_Base!L13+SABR_Shocks!$C$8*SABR_Shocks!L28 -> 0.2675
B98: 30Y | C98: =SABR_Base!C14+SABR_Shocks!$C$8*SABR_Shocks!C29 -> 0.410144 | D98: =SABR_Base!D14+SABR_Shocks!$C$8*SABR_Shocks!D29 -> 0.399736 | E98: =SABR_Base!E14+SABR_Shocks!$C$8*SABR_Shocks!E29 -> 0.380228 | F98: =SABR_Base!F14+SABR_Shocks!$C$8*SABR_Shocks!F29 -> 0.363684 | G98: =SABR_Base!G14+SABR_Shocks!$C$8*SABR_Shocks!G29 -> 0.33388 | H98: =SABR_Base!H14+SABR_Shocks!$C$8*SABR_Shocks!H29 -> 0.319308 | I98: =SABR_Base!I14+SABR_Shocks!$C$8*SABR_Shocks!I29 -> 0.300272 | J98: =SABR_Base!J14+SABR_Shocks!$C$8*SABR_Shocks!J29 -> 0.2928 | ... L98: =SABR_Base!L14+SABR_Shocks!$C$8*SABR_Shocks!L29 -> 0.2448
B100: Param: RHO
B101: Expiry \ Tenor | C101: 1M | D101: 3M | E101: 6M | F101: 1Y | G101: 2Y | H101: 3Y | I101: 5Y | J101: 10Y | K101: 20Y | L101: 30Y
B102: 1M | C102: =SABR_Base!C19+SABR_Shocks!$D$8*SABR_Shocks!C20 -> -0.3441723 | D102: =SABR_Base!D19+SABR_Shocks!$D$8*SABR_Shocks!D20 -> -0.3242114 | E102: =SABR_Base!E19+SABR_Shocks!$D$8*SABR_Shocks!E20 -> -0.305466 | F102: =SABR_Base!F19+SABR_Shocks!$D$8*SABR_Shocks!F20 -> -0.281682 | G102: =SABR_Base!G19+SABR_Shocks!$D$8*SABR_Shocks!G20 -> -0.2608751 | H102: =SABR_Base!H19+SABR_Shocks!$D$8*SABR_Shocks!H20 -> -0.2487451 | I102: =SABR_Base!I19+SABR_Shocks!$D$8*SABR_Shocks!I20 -> -0.234907 | J102: =SABR_Base!J19+SABR_Shocks!$D$8*SABR_Shocks!J20 -> -0.2078 | ... L102: =SABR_Base!L19+SABR_Shocks!$D$8*SABR_Shocks!L20 -> -0.1675246
B103: 3M | C103: =SABR_Base!C20+SABR_Shocks!$D$8*SABR_Shocks!C21 -> -0.3099577 | D103: =SABR_Base!D20+SABR_Shocks!$D$8*SABR_Shocks!D21 -> -0.2964892 | E103: =SABR_Base!E20+SABR_Shocks!$D$8*SABR_Shocks!E21 -> -0.2812591 | F103: =SABR_Base!F20+SABR_Shocks!$D$8*SABR_Shocks!F21 -> -0.2605522 | G103: =SABR_Base!G20+SABR_Shocks!$D$8*SABR_Shocks!G21 -> -0.2403218 | H103: =SABR_Base!H20+SABR_Shocks!$D$8*SABR_Shocks!H21 -> -0.2341842 | I103: =SABR_Base!I20+SABR_Shocks!$D$8*SABR_Shocks!I21 -> -0.1982693 | J103: =SABR_Base!J20+SABR_Shocks!$D$8*SABR_Shocks!J21 -> -0.1820779 | ... L103: =SABR_Base!L20+SABR_Shocks!$D$8*SABR_Shocks!L21 -> -0.1440483
B104: 6M | C104: =SABR_Base!C21+SABR_Shocks!$D$8*SABR_Shocks!C22 -> -0.302597 | D104: =SABR_Base!D21+SABR_Shocks!$D$8*SABR_Shocks!D22 -> -0.2835899 | E104: =SABR_Base!E21+SABR_Shocks!$D$8*SABR_Shocks!E22 -> -0.2704595 | F104: =SABR_Base!F21+SABR_Shocks!$D$8*SABR_Shocks!F22 -> -0.2412604 | G104: =SABR_Base!G21+SABR_Shocks!$D$8*SABR_Shocks!G22 -> -0.2337147 | H104: =SABR_Base!H21+SABR_Shocks!$D$8*SABR_Shocks!H22 -> -0.2150772 | I104: =SABR_Base!I21+SABR_Shocks!$D$8*SABR_Shocks!I22 -> -0.1937242 | J104: =SABR_Base!J21+SABR_Shocks!$D$8*SABR_Shocks!J22 -> -0.1756554 | ... L104: =SABR_Base!L21+SABR_Shocks!$D$8*SABR_Shocks!L22 -> -0.1405108
B105: 1Y | C105: =SABR_Base!C22+SABR_Shocks!$D$8*SABR_Shocks!C23 -> -0.2916515 | D105: =SABR_Base!D22+SABR_Shocks!$D$8*SABR_Shocks!D23 -> -0.269729 | E105: =SABR_Base!E22+SABR_Shocks!$D$8*SABR_Shocks!E23 -> -0.2516294 | F105: =SABR_Base!F22+SABR_Shocks!$D$8*SABR_Shocks!F23 -> -0.2278225 | G105: =SABR_Base!G22+SABR_Shocks!$D$8*SABR_Shocks!G23 -> -0.2161081 | H105: =SABR_Base!H22+SABR_Shocks!$D$8*SABR_Shocks!H23 -> -0.1803395 | I105: =SABR_Base!I22+SABR_Shocks!$D$8*SABR_Shocks!I23 -> -0.1668018 | J105: =SABR_Base!J22+SABR_Shocks!$D$8*SABR_Shocks!J23 -> -0.1574102 | ... L105: =SABR_Base!L22+SABR_Shocks!$D$8*SABR_Shocks!L23 -> -0.1158423
B106: 2Y | C106: =SABR_Base!C23+SABR_Shocks!$D$8*SABR_Shocks!C24 -> -0.2653212 | D106: =SABR_Base!D23+SABR_Shocks!$D$8*SABR_Shocks!D24 -> -0.2514681 | E106: =SABR_Base!E23+SABR_Shocks!$D$8*SABR_Shocks!E24 -> -0.2183843 | F106: =SABR_Base!F23+SABR_Shocks!$D$8*SABR_Shocks!F24 -> -0.1964232 | G106: =SABR_Base!G23+SABR_Shocks!$D$8*SABR_Shocks!G24 -> -0.1884934 | H106: =SABR_Base!H23+SABR_Shocks!$D$8*SABR_Shocks!H24 -> -0.1691477 | I106: =SABR_Base!I23+SABR_Shocks!$D$8*SABR_Shocks!I24 -> -0.1585871 | J106: =SABR_Base!J23+SABR_Shocks!$D$8*SABR_Shocks!J24 -> -0.1394415 | ... L106: =SABR_Base!L23+SABR_Shocks!$D$8*SABR_Shocks!L24 -> -0.0986968
B107: 3Y | C107: =SABR_Base!C24+SABR_Shocks!$D$8*SABR_Shocks!C25 -> -0.2371294 | D107: =SABR_Base!D24+SABR_Shocks!$D$8*SABR_Shocks!D25 -> -0.2317994 | E107: =SABR_Base!E24+SABR_Shocks!$D$8*SABR_Shocks!E25 -> -0.2160234 | F107: =SABR_Base!F24+SABR_Shocks!$D$8*SABR_Shocks!F25 -> -0.1784469 | G107: =SABR_Base!G24+SABR_Shocks!$D$8*SABR_Shocks!G25 -> -0.1684479 | H107: =SABR_Base!H24+SABR_Shocks!$D$8*SABR_Shocks!H25 -> -0.1572562 | I107: =SABR_Base!I24+SABR_Shocks!$D$8*SABR_Shocks!I25 -> -0.1303413 | J107: =SABR_Base!J24+SABR_Shocks!$D$8*SABR_Shocks!J25 -> -0.1220267 | ... L107: =SABR_Base!L24+SABR_Shocks!$D$8*SABR_Shocks!L25 -> -0.0653587
B108: 5Y | C108: =SABR_Base!C25+SABR_Shocks!$D$8*SABR_Shocks!C26 -> -0.2180689 | D108: =SABR_Base!D25+SABR_Shocks!$D$8*SABR_Shocks!D26 -> -0.2026465 | E108: =SABR_Base!E25+SABR_Shocks!$D$8*SABR_Shocks!E26 -> -0.1923008 | F108: =SABR_Base!F25+SABR_Shocks!$D$8*SABR_Shocks!F26 -> -0.171694 | G108: =SABR_Base!G25+SABR_Shocks!$D$8*SABR_Shocks!G26 -> -0.1569024 | H108: =SABR_Base!H25+SABR_Shocks!$D$8*SABR_Shocks!H26 -> -0.1262032 | I108: =SABR_Base!I25+SABR_Shocks!$D$8*SABR_Shocks!I26 -> -0.1121885 | J108: =SABR_Base!J25+SABR_Shocks!$D$8*SABR_Shocks!J26 -> -0.0882505 | ... L108: =SABR_Base!L25+SABR_Shocks!$D$8*SABR_Shocks!L26 -> -0.0619288
B109: 10Y | C109: =SABR_Base!C26+SABR_Shocks!$D$8*SABR_Shocks!C27 -> -0.2002926 | D109: =SABR_Base!D26+SABR_Shocks!$D$8*SABR_Shocks!D27 -> -0.1779471 | E109: =SABR_Base!E26+SABR_Shocks!$D$8*SABR_Shocks!E27 -> -0.1616014 | F109: =SABR_Base!F26+SABR_Shocks!$D$8*SABR_Shocks!F27 -> -0.1440177 | G109: =SABR_Base!G26+SABR_Shocks!$D$8*SABR_Shocks!G27 -> -0.1249722 | H109: =SABR_Base!H26+SABR_Shocks!$D$8*SABR_Shocks!H27 -> -0.1077266 | I109: =SABR_Base!I26+SABR_Shocks!$D$8*SABR_Shocks!I27 -> -0.0995353 | J109: =SABR_Base!J26+SABR_Shocks!$D$8*SABR_Shocks!J27 -> -0.0749437 | ... L109: =SABR_Base!L26+SABR_Shocks!$D$8*SABR_Shocks!L27 -> -0.0469217
B110: 20Y | C110: =SABR_Base!C27+SABR_Shocks!$D$8*SABR_Shocks!C28 -> -0.1972395 | D110: =SABR_Base!D27+SABR_Shocks!$D$8*SABR_Shocks!D28 -> -0.1734633 | E110: =SABR_Base!E27+SABR_Shocks!$D$8*SABR_Shocks!E28 -> -0.1549022 | F110: =SABR_Base!F27+SABR_Shocks!$D$8*SABR_Shocks!F28 -> -0.1274028 | G110: =SABR_Base!G27+SABR_Shocks!$D$8*SABR_Shocks!G28 -> -0.1036346 | H110: =SABR_Base!H27+SABR_Shocks!$D$8*SABR_Shocks!H28 -> -0.0947811 | I110: =SABR_Base!I27+SABR_Shocks!$D$8*SABR_Shocks!I28 -> -0.0662049 | J110: =SABR_Base!J27+SABR_Shocks!$D$8*SABR_Shocks!J28 -> -0.0466288 | ... L110: =SABR_Base!L27+SABR_Shocks!$D$8*SABR_Shocks!L28 -> -0.021045
...

Sheet NPV_Engine
A1: Full-Reval NPV Engine — Cross / IR / Credit / FX (Base vs Stressed, Trade 123456)
A2: Illustrative simplified full-reval pricer (NOT a production model): NPV = Notional x DF_SOFR(1Y) x [DF_ESTRN(1Y)/DF_ESTRN_base(1Y)] x [1+0.5x(ATM(1Yx10Y)-ATM_base)] x [AVERAGE(DF_Treasury,DF_Agency_FNMA,DF_Eur_Govt)(1Y)/DF_SOFR(1Y)] x [DF_EURUSD(1Y)/DF_EURUSD_base(1Y)]. Each risk-class table below feeds this same pricer with only that risk class's curves shocked; the rest held at BASE.
A4: Notional (USD) | B4: =Trade_Info!B7 -> 10000000
A6: Reference base constants
A7: DF_SOFR_base(1Y) | B7: =Base_Curves!E6 -> 0.957768
A8: DF_ESTRN_base(1Y) | B8: =Base_Curves!E7 -> 0.96933
A9: DF_Treasury_base(1Y) | B9: =Base_Curves!E8 -> 0.958726
A10: DF_Agency_FNMA_base(1Y) | B10: =Base_Curves!E9 -> 0.954899
A11: DF_Eur_Govt_base(1Y) | B11: =Base_Curves!E10 -> 0.967393
A12: DF_EURUSD_base(1Y) | B12: =Base_Curves!E11 -> 0.960645
A13: ATM_base(1Yx10Y) | B13: =SABR_Base!J8 -> 0.3819
A16: Cross — Full-Reval NPV
A17: Case | B17: DF_SOFR(1Y) | C17: DF_ESTRN(1Y) | D17: ATM(1Yx10Y) | E17: DF_Treasury(1Y) | F17: DF_Agency_FNMA(1Y) | G17: DF_Eur_Govt(1Y) | H17: DF_EURUSD(1Y) | I17: NPV (USD)
A18: Base | B18: =$B$7 -> 0.957768 | C18: =$B$8 -> 0.96933 | D18: =$B$13 -> 0.3819 | E18: =$B$9 -> 0.958726 | F18: =$B$10 -> 0.954899 | G18: =$B$11 -> 0.967393 | H18: =$B$12 -> 0.960645 | I18: =$B$4*B18*(C18/$B$8)*(1+0.5*(D18-$B$13))*(AVERAGE(E18,F18,G18)/B18)*(H18/$B$12) -> 9603393.3
A19: Scenario 1 | B19: =Shocked_Curves_DF!E5 -> 0.95645567 | C19: =Shocked_Curves_DF!E6 -> 0.96826858 | D19: =SABR_Shocked!J10 -> 0.3885726 | E19: =Shocked_Curves_DF!E7 -> 0.95806183 | F19: =Shocked_Curves_DF!E8 -> 0.94931135 | G19: =Shocked_Curves_DF!E9 -> 0.96229709 | H19: =Shocked_Curves_DF!E10 -> 0.95855049 | I19: =$B$4*B19*(C19/$B$8)*(1+0.5*(D19-$B$13))*(AVERAGE(E19,F19,G19)/B19)*(H19/$B$12) -> 9566069.2
A20: Scenario 2 | B20: =Shocked_Curves_DF!E13 -> 0.95398447 | C20: =Shocked_Curves_DF!E14 -> 0.9689389 | D20: =SABR_Shocked!J51 -> 0.390325 | E20: =Shocked_Curves_DF!E15 -> 0.95458892 | F20: =Shocked_Curves_DF!E16 -> 0.95209186 | G20: =Shocked_Curves_DF!E17 -> 0.96495558 | H20: =Shocked_Curves_DF!E18 -> 0.95783612 | I20: =$B$4*B20*(C20/$B$8)*(1+0.5*(D20-$B$13))*(AVERAGE(E20,F20,G20)/B20)*(H20/$B$12) -> 9580470.4
A21: Scenario 3 | B21: =Shocked_Curves_DF!E21 -> 0.95342826 | C21: =Shocked_Curves_DF!E22 -> 0.96769945 | D21: =SABR_Shocked!J92 -> 0.389988 | E21: =Shocked_Curves_DF!E23 -> 0.95400896 | F21: =Shocked_Curves_DF!E24 -> 0.95361271 | G21: =Shocked_Curves_DF!E25 -> 0.96122366 | H21: =Shocked_Curves_DF!E26 -> 0.9575846 | I21: =$B$4*B21*(C21/$B$8)*(1+0.5*(D21-$B$13))*(AVERAGE(E21,F21,G21)/B21)*(H21/$B$12) -> 9554802
A22: Scenario 4 | B22: =Shocked_Curves_DF!E29 -> 0.95304179 | C22: =Shocked_Curves_DF!E30 -> 0.96526908 | D22: =SABR_Shocked!J133 -> 0.395717 | E22: =Shocked_Curves_DF!E31 -> 0.95320762 | F22: =Shocked_Curves_DF!E32 -> 0.94623448 | G22: =Shocked_Curves_DF!E33 -> 0.9603367 | H22: =Shocked_Curves_DF!E34 -> 0.96226356 | I22: =$B$4*B22*(C22/$B$8)*(1+0.5*(D22-$B$13))*(AVERAGE(E22,F22,G22)/B22)*(H22/$B$12) -> 9574344.5
A23: Scenario 5 | B23: =Shocked_Curves_DF!E37 -> 0.95548798 | C23: =Shocked_Curves_DF!E38 -> 0.96483623 | D23: =SABR_Shocked!J174 -> 0.3926166 | E23: =Shocked_Curves_DF!E39 -> 0.95639571 | F23: =Shocked_Curves_DF!E40 -> 0.94534426 | G23: =Shocked_Curves_DF!E41 -> 0.96004351 | H23: =Shocked_Curves_DF!E42 -> 0.95680489 | I23: =$B$4*B23*(C23/$B$8)*(1+0.5*(D23-$B$13))*(AVERAGE(E23,F23,G23)/B23)*(H23/$B$12) -> 9507772.7
A24: Scenario 6 | B24: =Shocked_Curves_DF!E45 -> 0.9549911 | C24: =Shocked_Curves_DF!E46 -> 0.96434632 | D24: =SABR_Shocked!J215 -> 0.3938972 | E24: =Shocked_Curves_DF!E47 -> 0.9521379 | F24: =Shocked_Curves_DF!E48 -> 0.94448209 | G24: =Shocked_Curves_DF!E49 -> 0.95861205 | H24: =Shocked_Curves_DF!E50 -> 0.95873693 | I24: =$B$4*B24*(C24/$B$8)*(1+0.5*(D24-$B$13))*(AVERAGE(E24,F24,G24)/B24)*(H24/$B$12) -> 9506385.8
A25: Scenario 7 | B25: =Shocked_Curves_DF!E53 -> 0.95463157 | C25: =Shocked_Curves_DF!E54 -> 0.96389894 | D25: =SABR_Shocked!J256 -> 0.3996262 | E25: =Shocked_Curves_DF!E55 -> 0.9516449 | F25: =Shocked_Curves_DF!E56 -> 0.95011547 | G25: =Shocked_Curves_DF!E57 -> 0.95780838 | H25: =Shocked_Curves_DF!E58 -> 0.95626063 | I25: =$B$4*B25*(C25/$B$8)*(1+0.5*(D25-$B$13))*(AVERAGE(E25,F25,G25)/B25)*(H25/$B$12) -> 9518855.2
A26: Scenario 8 | B26: =Shocked_Curves_DF!E61 -> 0.95085969 | C26: =Shocked_Curves_DF!E62 -> 0.97201771 | D26: =SABR_Shocked!J297 -> 0.3969976 | E26: =Shocked_Curves_DF!E63 -> 0.95082457 | F26: =Shocked_Curves_DF!E64 -> 0.94234687 | G26: =Shocked_Curves_DF!E65 -> 0.95705696 | H26: =Shocked_Curves_DF!E66 -> 0.96022971 | I26: =$B$4*B26*(C26/$B$8)*(1+0.5*(D26-$B$13))*(AVERAGE(E26,F26,G26)/B26)*(H26/$B$12) -> 9594873.2
A27: Scenario 9 | B27: =Shocked_Curves_DF!E69 -> 0.95063 | C27: =Shocked_Curves_DF!E70 -> 0.96317151 | D27: =SABR_Shocked!J338 -> 0.399761 | E27: =Shocked_Curves_DF!E71 -> 0.95006942 | F27: =Shocked_Curves_DF!E72 -> 0.94108519 | G27: =Shocked_Curves_DF!E73 -> 0.9561681 | H27: =Shocked_Curves_DF!E74 -> 0.95559115 | I27: =$B$4*B27*(C27/$B$8)*(1+0.5*(D27-$B$13))*(AVERAGE(E27,F27,G27)/B27)*(H27/$B$12) -> 9464939.8
A28: Scenario 10 | B28: =Shocked_Curves_DF!E77 -> 0.94992462 | C28: =Shocked_Curves_DF!E78 -> 0.97264772 | D28: =SABR_Shocked!J379 -> 0.4031984 | E28: =Shocked_Curves_DF!E79 -> 0.9572378 | F28: =Shocked_Curves_DF!E80 -> 0.94825632 | G28: =Shocked_Curves_DF!E81 -> 0.96603972 | H28: =Shocked_Curves_DF!E82 -> 0.95521334 | I28: =$B$4*B28*(C28/$B$8)*(1+0.5*(D28-$B$13))*(AVERAGE(E28,F28,G28)/B28)*(H28/$B$12) -> 9651937.4
A31: IR — Full-Reval NPV
A32: Case | B32: DF_SOFR(1Y) | C32: DF_ESTRN(1Y) | D32: ATM(1Yx10Y) | E32: DF_Treasury(1Y) | F32: DF_Agency_FNMA(1Y) | G32: DF_Eur_Govt(1Y) | H32: DF_EURUSD(1Y) | I32: NPV (USD)
A33: Base | B33: =$B$7 -> 0.957768 | C33: =$B$8 -> 0.96933 | D33: =$B$13 -> 0.3819 | E33: =$B$9 -> 0.958726 | F33: =$B$10 -> 0.954899 | G33: =$B$11 -> 0.967393 | H33: =$B$12 -> 0.960645 | I33: =$B$4*B33*(C33/$B$8)*(1+0.5*(D33-$B$13))*(AVERAGE(E33,F33,G33)/B33)*(H33/$B$12) -> 9603393.3
A34: Scenario 1 | B34: =Shocked_Curves_DF!E5 -> 0.95645567 | C34: =Shocked_Curves_DF!E6 -> 0.96826858 | D34: =SABR_Shocked!J10 -> 0.3885726 | E34: =$B$9 -> 0.958726 | F34: =$B$10 -> 0.954899 | G34: =$B$11 -> 0.967393 | H34: =$B$12 -> 0.960645 | I34: =$B$4*B34*(C34/$B$8)*(1+0.5*(D34-$B$13))*(AVERAGE(E34,F34,G34)/B34)*(H34/$B$12) -> 9624882.2
A35: Scenario 2 | B35: =Shocked_Curves_DF!E13 -> 0.95398447 | C35: =Shocked_Curves_DF!E14 -> 0.9689389 | D35: =SABR_Shocked!J51 -> 0.390325 | E35: =$B$9 -> 0.958726 | F35: =$B$10 -> 0.954899 | G35: =$B$11 -> 0.967393 | H35: =$B$12 -> 0.960645 | I35: =$B$4*B35*(C35/$B$8)*(1+0.5*(D35-$B$13))*(AVERAGE(E35,F35,G35)/B35)*(H35/$B$12) -> 9639956.6
A36: Scenario 3 | B36: =Shocked_Curves_DF!E21 -> 0.95342826 | C36: =Shocked_Curves_DF!E22 -> 0.96769945 | D36: =SABR_Shocked!J92 -> 0.389988 | E36: =$B$9 -> 0.958726 | F36: =$B$10 -> 0.954899 | G36: =$B$11 -> 0.967393 | H36: =$B$12 -> 0.960645 | I36: =$B$4*B36*(C36/$B$8)*(1+0.5*(D36-$B$13))*(AVERAGE(E36,F36,G36)/B36)*(H36/$B$12) -> 9626009.9
A37: Scenario 4 | B37: =Shocked_Curves_DF!E29 -> 0.95304179 | C37: =Shocked_Curves_DF!E30 -> 0.96526908 | D37: =SABR_Shocked!J133 -> 0.395717 | E37: =$B$9 -> 0.958726 | F37: =$B$10 -> 0.954899 | G37: =$B$11 -> 0.967393 | H37: =$B$12 -> 0.960645 | I37: =$B$4*B37*(C37/$B$8)*(1+0.5*(D37-$B$13))*(AVERAGE(E37,F37,G37)/B37)*(H37/$B$12) -> 9629227.9
A38: Scenario 5 | B38: =Shocked_Curves_DF!E37 -> 0.95548798 | C38: =Shocked_Curves_DF!E38 -> 0.96483623 | D38: =SABR_Shocked!J174 -> 0.3926166 | E38: =$B$9 -> 0.958726 | F38: =$B$10 -> 0.954899 | G38: =$B$11 -> 0.967393 | H38: =$B$12 -> 0.960645 | I38: =$B$4*B38*(C38/$B$8)*(1+0.5*(D38-$B$13))*(AVERAGE(E38,F38,G38)/B38)*(H38/$B$12) -> 9610091.7
A39: Scenario 6 | B39: =Shocked_Curves_DF!E45 -> 0.9549911 | C39: =Shocked_Curves_DF!E46 -> 0.96434632 | D39: =SABR_Shocked!J215 -> 0.3938972 | E39: =$B$9 -> 0.958726 | F39: =$B$10 -> 0.954899 | G39: =$B$11 -> 0.967393 | H39: =$B$12 -> 0.960645 | I39: =$B$4*B39*(C39/$B$8)*(1+0.5*(D39-$B$13))*(AVERAGE(E39,F39,G39)/B39)*(H39/$B$12) -> 9611329.5
A40: Scenario 7 | B40: =Shocked_Curves_DF!E53 -> 0.95463157 | C40: =Shocked_Curves_DF!E54 -> 0.96389894 | D40: =SABR_Shocked!J256 -> 0.3996262 | E40: =$B$9 -> 0.958726 | F40: =$B$10 -> 0.954899 | G40: =$B$11 -> 0.967393 | H40: =$B$12 -> 0.960645 | I40: =$B$4*B40*(C40/$B$8)*(1+0.5*(D40-$B$13))*(AVERAGE(E40,F40,G40)/B40)*(H40/$B$12) -> 9634225.4
A41: Scenario 8 | B41: =Shocked_Curves_DF!E61 -> 0.95085969 | C41: =Shocked_Curves_DF!E62 -> 0.97201771 | D41: =SABR_Shocked!J297 -> 0.3969976 | E41: =$B$9 -> 0.958726 | F41: =$B$10 -> 0.954899 | G41: =$B$11 -> 0.967393 | H41: =$B$12 -> 0.960645 | I41: =$B$4*B41*(C41/$B$8)*(1+0.5*(D41-$B$13))*(AVERAGE(E41,F41,G41)/B41)*(H41/$B$12) -> 9702716.3
A42: Scenario 9 | B42: =Shocked_Curves_DF!E69 -> 0.95063 | C42: =Shocked_Curves_DF!E70 -> 0.96317151 | D42: =SABR_Shocked!J338 -> 0.399761 | E42: =$B$9 -> 0.958726 | F42: =$B$10 -> 0.954899 | G42: =$B$11 -> 0.967393 | H42: =$B$12 -> 0.960645 | I42: =$B$4*B42*(C42/$B$8)*(1+0.5*(D42-$B$13))*(AVERAGE(E42,F42,G42)/B42)*(H42/$B$12) -> 9627597.9
A43: Scenario 10 | B43: =Shocked_Curves_DF!E77 -> 0.94992462 | C43: =Shocked_Curves_DF!E78 -> 0.97264772 | D43: =SABR_Shocked!J379 -> 0.4031984 | E43: =$B$9 -> 0.958726 | F43: =$B$10 -> 0.954899 | G43: =$B$11 -> 0.967393 | H43: =$B$12 -> 0.960645 | I43: =$B$4*B43*(C43/$B$8)*(1+0.5*(D43-$B$13))*(AVERAGE(E43,F43,G43)/B43)*(H43/$B$12) -> 9738881.3
A46: Credit — Full-Reval NPV
A47: Case | B47: DF_SOFR(1Y) | C47: DF_ESTRN(1Y) | D47: ATM(1Yx10Y) | E47: DF_Treasury(1Y) | F47: DF_Agency_FNMA(1Y) | G47: DF_Eur_Govt(1Y) | H47: DF_EURUSD(1Y) | I47: NPV (USD)
A48: Base | B48: =$B$7 -> 0.957768 | C48: =$B$8 -> 0.96933 | D48: =$B$13 -> 0.3819 | E48: =$B$9 -> 0.958726 | F48: =$B$10 -> 0.954899 | G48: =$B$11 -> 0.967393 | H48: =$B$12 -> 0.960645 | I48: =$B$4*B48*(C48/$B$8)*(1+0.5*(D48-$B$13))*(AVERAGE(E48,F48,G48)/B48)*(H48/$B$12) -> 9603393.3
A49: Scenario 1 | B49: =$B$7 -> 0.957768 | C49: =$B$8 -> 0.96933 | D49: =$B$13 -> 0.3819 | E49: =Shocked_Curves_DF!E7 -> 0.95806183 | F49: =Shocked_Curves_DF!E8 -> 0.94931135 | G49: =Shocked_Curves_DF!E9 -> 0.96229709 | H49: =$B$12 -> 0.960645 | I49: =$B$4*B49*(C49/$B$8)*(1+0.5*(D49-$B$13))*(AVERAGE(E49,F49,G49)/B49)*(H49/$B$12) -> 9565567.5
A50: Scenario 2 | B50: =$B$7 -> 0.957768 | C50: =$B$8 -> 0.96933 | D50: =$B$13 -> 0.3819 | E50: =Shocked_Curves_DF!E15 -> 0.95458892 | F50: =Shocked_Curves_DF!E16 -> 0.95209186 | G50: =Shocked_Curves_DF!E17 -> 0.96495558 | H50: =$B$12 -> 0.960645 | I50: =$B$4*B50*(C50/$B$8)*(1+0.5*(D50-$B$13))*(AVERAGE(E50,F50,G50)/B50)*(H50/$B$12) -> 9572121.2
A51: Scenario 3 | B51: =$B$7 -> 0.957768 | C51: =$B$8 -> 0.96933 | D51: =$B$13 -> 0.3819 | E51: =Shocked_Curves_DF!E23 -> 0.95400896 | F51: =Shocked_Curves_DF!E24 -> 0.95361271 | G51: =Shocked_Curves_DF!E25 -> 0.96122366 | H51: =$B$12 -> 0.960645 | I51: =$B$4*B51*(C51/$B$8)*(1+0.5*(D51-$B$13))*(AVERAGE(E51,F51,G51)/B51)*(H51/$B$12) -> 9562817.8
A52: Scenario 4 | B52: =$B$7 -> 0.957768 | C52: =$B$8 -> 0.96933 | D52: =$B$13 -> 0.3819 | E52: =Shocked_Curves_DF!E31 -> 0.95320762 | F52: =Shocked_Curves_DF!E32 -> 0.94623448 | G52: =Shocked_Curves_DF!E33 -> 0.9603367 | H52: =$B$12 -> 0.960645 | I52: =$B$4*B52*(C52/$B$8)*(1+0.5*(D52-$B$13))*(AVERAGE(E52,F52,G52)/B52)*(H52/$B$12) -> 9532596
A53: Scenario 5 | B53: =$B$7 -> 0.957768 | C53: =$B$8 -> 0.96933 | D53: =$B$13 -> 0.3819 | E53: =Shocked_Curves_DF!E39 -> 0.95639571 | F53: =Shocked_Curves_DF!E40 -> 0.94534426 | G53: =Shocked_Curves_DF!E41 -> 0.96004351 | H53: =$B$12 -> 0.960645 | I53: =$B$4*B53*(C53/$B$8)*(1+0.5*(D53-$B$13))*(AVERAGE(E53,F53,G53)/B53)*(H53/$B$12) -> 9539278.2
A54: Scenario 6 | B54: =$B$7 -> 0.957768 | C54: =$B$8 -> 0.96933 | D54: =$B$13 -> 0.3819 | E54: =Shocked_Curves_DF!E47 -> 0.9521379 | F54: =Shocked_Curves_DF!E48 -> 0.94448209 | G54: =Shocked_Curves_DF!E49 -> 0.95861205 | H54: =$B$12 -> 0.960645 | I54: =$B$4*B54*(C54/$B$8)*(1+0.5*(D54-$B$13))*(AVERAGE(E54,F54,G54)/B54)*(H54/$B$12) -> 9517440.1
A55: Scenario 7 | B55: =$B$7 -> 0.957768 | C55: =$B$8 -> 0.96933 | D55: =$B$13 -> 0.3819 | E55: =Shocked_Curves_DF!E55 -> 0.9516449 | F55: =Shocked_Curves_DF!E56 -> 0.95011547 | G55: =Shocked_Curves_DF!E57 -> 0.95780838 | H55: =$B$12 -> 0.960645 | I55: =$B$4*B55*(C55/$B$8)*(1+0.5*(D55-$B$13))*(AVERAGE(E55,F55,G55)/B55)*(H55/$B$12) -> 9531895.8
A56: Scenario 8 | B56: =$B$7 -> 0.957768 | C56: =$B$8 -> 0.96933 | D56: =$B$13 -> 0.3819 | E56: =Shocked_Curves_DF!E63 -> 0.95082457 | F56: =Shocked_Curves_DF!E64 -> 0.94234687 | G56: =Shocked_Curves_DF!E65 -> 0.95705696 | H56: =$B$12 -> 0.960645 | I56: =$B$4*B56*(C56/$B$8)*(1+0.5*(D56-$B$13))*(AVERAGE(E56,F56,G56)/B56)*(H56/$B$12) -> 9500761.4
A57: Scenario 9 | B57: =$B$7 -> 0.957768 | C57: =$B$8 -> 0.96933 | D57: =$B$13 -> 0.3819 | E57: =Shocked_Curves_DF!E71 -> 0.95006942 | F57: =Shocked_Curves_DF!E72 -> 0.94108519 | G57: =Shocked_Curves_DF!E73 -> 0.9561681 | H57: =$B$12 -> 0.960645 | I57: =$B$4*B57*(C57/$B$8)*(1+0.5*(D57-$B$13))*(AVERAGE(E57,F57,G57)/B57)*(H57/$B$12) -> 9491075.7
A58: Scenario 10 | B58: =$B$7 -> 0.957768 | C58: =$B$8 -> 0.96933 | D58: =$B$13 -> 0.3819 | E58: =Shocked_Curves_DF!E79 -> 0.9572378 | F58: =Shocked_Curves_DF!E80 -> 0.94825632 | G58: =Shocked_Curves_DF!E81 -> 0.96603972 | H58: =$B$12 -> 0.960645 | I58: =$B$4*B58*(C58/$B$8)*(1+0.5*(D58-$B$13))*(AVERAGE(E58,F58,G58)/B58)*(H58/$B$12) -> 9571779.5
A61: FX — Full-Reval NPV
A62: Case | B62: DF_SOFR(1Y) | C62: DF_ESTRN(1Y) | D62: ATM(1Yx10Y) | E62: DF_Treasury(1Y) | F62: DF_Agency_FNMA(1Y) | G62: DF_Eur_Govt(1Y) | H62: DF_EURUSD(1Y) | I62: NPV (USD)
A63: Base | B63: =$B$7 -> 0.957768 | C63: =$B$8 -> 0.96933 | D63: =$B$13 -> 0.3819 | E63: =$B$9 -> 0.958726 | F63: =$B$10 -> 0.954899 | G63: =$B$11 -> 0.967393 | H63: =$B$12 -> 0.960645 | I63: =$B$4*B63*(C63/$B$8)*(1+0.5*(D63-$B$13))*(AVERAGE(E63,F63,G63)/B63)*(H63/$B$12) -> 9603393.3
A64: Scenario 1 | B64: =$B$7 -> 0.957768 | C64: =$B$8 -> 0.96933 | D64: =$B$13 -> 0.3819 | E64: =$B$9 -> 0.958726 | F64: =$B$10 -> 0.954899 | G64: =$B$11 -> 0.967393 | H64: =Shocked_Curves_DF!E10 -> 0.95855049 | I64: =$B$4*B64*(C64/$B$8)*(1+0.5*(D64-$B$13))*(AVERAGE(E64,F64,G64)/B64)*(H64/$B$12) -> 9582454.9
A65: Scenario 2 | B65: =$B$7 -> 0.957768 | C65: =$B$8 -> 0.96933 | D65: =$B$13 -> 0.3819 | E65: =$B$9 -> 0.958726 | F65: =$B$10 -> 0.954899 | G65: =$B$11 -> 0.967393 | H65: =Shocked_Curves_DF!E18 -> 0.95783612 | I65: =$B$4*B65*(C65/$B$8)*(1+0.5*(D65-$B$13))*(AVERAGE(E65,F65,G65)/B65)*(H65/$B$12) -> 9575313.4
A66: Scenario 3 | B66: =$B$7 -> 0.957768 | C66: =$B$8 -> 0.96933 | D66: =$B$13 -> 0.3819 | E66: =$B$9 -> 0.958726 | F66: =$B$10 -> 0.954899 | G66: =$B$11 -> 0.967393 | H66: =Shocked_Curves_DF!E26 -> 0.9575846 | I66: =$B$4*B66*(C66/$B$8)*(1+0.5*(D66-$B$13))*(AVERAGE(E66,F66,G66)/B66)*(H66/$B$12) -> 9572799.1
A67: Scenario 4 | B67: =$B$7 -> 0.957768 | C67: =$B$8 -> 0.96933 | D67: =$B$13 -> 0.3819 | E67: =$B$9 -> 0.958726 | F67: =$B$10 -> 0.954899 | G67: =$B$11 -> 0.967393 | H67: =Shocked_Curves_DF!E34 -> 0.96226356 | I67: =$B$4*B67*(C67/$B$8)*(1+0.5*(D67-$B$13))*(AVERAGE(E67,F67,G67)/B67)*(H67/$B$12) -> 9619573.8
A68: Scenario 5 | B68: =$B$7 -> 0.957768 | C68: =$B$8 -> 0.96933 | D68: =$B$13 -> 0.3819 | E68: =$B$9 -> 0.958726 | F68: =$B$10 -> 0.954899 | G68: =$B$11 -> 0.967393 | H68: =Shocked_Curves_DF!E42 -> 0.95680489 | I68: =$B$4*B68*(C68/$B$8)*(1+0.5*(D68-$B$13))*(AVERAGE(E68,F68,G68)/B68)*(H68/$B$12) -> 9565004.4
A69: Scenario 6 | B69: =$B$7 -> 0.957768 | C69: =$B$8 -> 0.96933 | D69: =$B$13 -> 0.3819 | E69: =$B$9 -> 0.958726 | F69: =$B$10 -> 0.954899 | G69: =$B$11 -> 0.967393 | H69: =Shocked_Curves_DF!E50 -> 0.95873693 | I69: =$B$4*B69*(C69/$B$8)*(1+0.5*(D69-$B$13))*(AVERAGE(E69,F69,G69)/B69)*(H69/$B$12) -> 9584318.8
A70: Scenario 7 | B70: =$B$7 -> 0.957768 | C70: =$B$8 -> 0.96933 | D70: =$B$13 -> 0.3819 | E70: =$B$9 -> 0.958726 | F70: =$B$10 -> 0.954899 | G70: =$B$11 -> 0.967393 | H70: =Shocked_Curves_DF!E58 -> 0.95626063 | I70: =$B$4*B70*(C70/$B$8)*(1+0.5*(D70-$B$13))*(AVERAGE(E70,F70,G70)/B70)*(H70/$B$12) -> 9559563.6
A71: Scenario 8 | B71: =$B$7 -> 0.957768 | C71: =$B$8 -> 0.96933 | D71: =$B$13 -> 0.3819 | E71: =$B$9 -> 0.958726 | F71: =$B$10 -> 0.954899 | G71: =$B$11 -> 0.967393 | H71: =Shocked_Curves_DF!E66 -> 0.96022971 | I71: =$B$4*B71*(C71/$B$8)*(1+0.5*(D71-$B$13))*(AVERAGE(E71,F71,G71)/B71)*(H71/$B$12) -> 9599241.8
A72: Scenario 9 | B72: =$B$7 -> 0.957768 | C72: =$B$8 -> 0.96933 | D72: =$B$13 -> 0.3819 | E72: =$B$9 -> 0.958726 | F72: =$B$10 -> 0.954899 | G72: =$B$11 -> 0.967393 | H72: =Shocked_Curves_DF!E74 -> 0.95559115 | I72: =$B$4*B72*(C72/$B$8)*(1+0.5*(D72-$B$13))*(AVERAGE(E72,F72,G72)/B72)*(H72/$B$12) -> 9552870.9
A73: Scenario 10 | B73: =$B$7 -> 0.957768 | C73: =$B$8 -> 0.96933 | D73: =$B$13 -> 0.3819 | E73: =$B$9 -> 0.958726 | F73: =$B$10 -> 0.954899 | G73: =$B$11 -> 0.967393 | H73: =Shocked_Curves_DF!E82 -> 0.95521334 | I73: =$B$4*B73*(C73/$B$8)*(1+0.5*(D73-$B$13))*(AVERAGE(E73,F73,G73)/B73)*(H73/$B$12) -> 9549094.1

Sheet PnL_Summary
A1: Full-Reval ES PnL Vectors — PnL = StressedNPV − BaseNPV (Trade 123456, Val Date 7/23/2026)
A2: Stress anchor date: 20-Nov-2008. Cross = all curves shocked. IR = SOFR/ESTRN/SABR shocked only. Credit = Treasury/Agency_FNMA/Eur_Govt shocked only. FX = EURUSD shocked only (others held at Base each time).
A4: Scenario | B4: Cross PnL (USD) | C4: IR PnL (USD) | D4: Credit PnL (USD) | E4: FX PnL (USD)
A5: Scenario 1 | B5: =NPV_Engine!I19-NPV_Engine!I18 -> -37324.156 | C5: =NPV_Engine!I34-NPV_Engine!I33 -> 21488.916 | D5: =NPV_Engine!I49-NPV_Engine!I48 -> -37825.797 | E5: =NPV_Engine!I64-NPV_Engine!I63 -> -20938.439
A6: Scenario 2 | B6: =NPV_Engine!I20-NPV_Engine!I18 -> -22922.95 | C6: =NPV_Engine!I35-NPV_Engine!I33 -> 36563.219 | D6: =NPV_Engine!I50-NPV_Engine!I48 -> -31272.096 | E6: =NPV_Engine!I65-NPV_Engine!I63 -> -28079.888
A7: Scenario 3 | B7: =NPV_Engine!I21-NPV_Engine!I18 -> -48591.296 | C7: =NPV_Engine!I36-NPV_Engine!I33 -> 22616.557 | D7: =NPV_Engine!I51-NPV_Engine!I48 -> -40575.571 | E7: =NPV_Engine!I66-NPV_Engine!I63 -> -30594.242
A8: Scenario 4 | B8: =NPV_Engine!I22-NPV_Engine!I18 -> -29048.841 | C8: =NPV_Engine!I37-NPV_Engine!I33 -> 25834.562 | D8: =NPV_Engine!I52-NPV_Engine!I48 -> -70797.319 | E8: =NPV_Engine!I67-NPV_Engine!I63 -> 16180.448
A9: Scenario 5 | B9: =NPV_Engine!I23-NPV_Engine!I18 -> -95620.661 | C9: =NPV_Engine!I38-NPV_Engine!I33 -> 6698.3961 | D9: =NPV_Engine!I53-NPV_Engine!I48 -> -64115.106 | E9: =NPV_Engine!I68-NPV_Engine!I63 -> -38388.929
A10: Scenario 6 | B10: =NPV_Engine!I24-NPV_Engine!I18 -> -97007.552 | C10: =NPV_Engine!I39-NPV_Engine!I33 -> 7936.1716 | D10: =NPV_Engine!I54-NPV_Engine!I48 -> -85953.213 | E10: =NPV_Engine!I69-NPV_Engine!I63 -> -19074.58
A11: Scenario 7 | B11: =NPV_Engine!I25-NPV_Engine!I18 -> -84538.111 | C11: =NPV_Engine!I40-NPV_Engine!I33 -> 30832.057 | D11: =NPV_Engine!I55-NPV_Engine!I48 -> -71497.499 | E11: =NPV_Engine!I70-NPV_Engine!I63 -> -43829.767
A12: Scenario 8 | B12: =NPV_Engine!I26-NPV_Engine!I18 -> -8520.1785 | C12: =NPV_Engine!I41-NPV_Engine!I33 -> 99322.937 | D12: =NPV_Engine!I56-NPV_Engine!I48 -> -102631.98 | E12: =NPV_Engine!I71-NPV_Engine!I63 -> -4151.5519
A13: Scenario 9 | B13: =NPV_Engine!I27-NPV_Engine!I18 -> -138453.55 | C13: =NPV_Engine!I42-NPV_Engine!I33 -> 24204.56 | D13: =NPV_Engine!I57-NPV_Engine!I48 -> -112317.63 | E13: =NPV_Engine!I72-NPV_Engine!I63 -> -50522.433
A14: Scenario 10 | B14: =NPV_Engine!I28-NPV_Engine!I18 -> 48544.057 | C14: =NPV_Engine!I43-NPV_Engine!I33 -> 135488.02 | D14: =NPV_Engine!I58-NPV_Engine!I48 -> -31613.869 | E14: =NPV_Engine!I73-NPV_Engine!I63 -> -54299.27
A16: Worst (min) PnL | B16: =MIN(B5:B14) -> -138453.55 | C16: =MIN(C5:C14) -> 6698.3961 | D16: =MIN(D5:D14) -> -112317.63 | E16: =MIN(E5:E14) -> -54299.27
A17: Best (max) PnL | B17: =MAX(B5:B14) -> 48544.057 | C17: =MAX(C5:C14) -> 135488.02 | D17: =MAX(D5:D14) -> -31272.096 | E17: =MAX(E5:E14) -> 16180.448
A18: Average PnL | B18: =AVERAGE(B5:B14) -> -51348.324 | C18: =AVERAGE(C5:C14) -> 41098.539 | D18: =AVERAGE(D5:D14) -> -64860.009 | E18: =AVERAGE(E5:E14) -> -27369.865
A20: ES illustration note: rank the Cross PnL vector and average the worst-tail observations per the chosen ES confidence level to derive the (illustrative) Expected Shortfall capital number.
