Workbook

Sheet ReadMe
B2: FRTB IMA — Full Revaluation PnL Vectors for Expected Shortfall (ES)
B3: Illustrative workbook — trade 123456, valuation date 7/23/2026. Demonstrates the mechanics of a full-revaluation Stressed PnL vector: PnL = StressedNPV − BaseNPV, built curve-by-curve and then combined cross-risk-class.
B5: Purpose
B6: Illustrate, end to end, how a full-reval ES PnL vector is constructed: base curve objects → shocked curve objects (10 scenarios, stress date 20-Nov-2008) → base/stressed NPV via full reval → PnL vector, both cross-risk-class and isolated by risk class (IR / Credit / FX).
B8: Tabs
B9: ReadMe | Trade_Info | Curves (Base, Shift Illustration, Shocks+Shocked aligned side-by-side) | SABR (Base, Shocks, Shocked - ATM/RHO/NU/Combined aligned horizontally per scenario) | NPV_Engine | PnL_Summary
B11: Curve shift mechanic
B12: gxlCurveDiscShift is simulated with a sequential (cascading) bootstrap: the simple forward rate implied by the BASE curve between consecutive tenors is bumped by the scenario shock (bps), and the SHOCKED discount factor for tenor i is solved from the SHOCKED discount factor at tenor i-1 (not the base one). 3M is bumped first; 6M relies on the bumped 3M; and so on to 30Y — exactly mirroring the described gxlCurveDiscShift behaviour.
B14: SABR surface mechanic
B15: Each of ATM / RHO / NU is a 10x10 grid (expiry x tenor). Each scenario applies a parameter-level shock size to every grid point, scaled by a per-cell Sensitivity Factor grid (captures the typical stress-period pattern of larger moves at short expiries/tenors). The result is a full shocked vol surface per parameter per scenario, exactly as gxlCurveDiscShift-style functions return a shocked object for curves.
B17: NPV engine
B18: NPV is an ILLUSTRATIVE simplified full-reval pricer (not a production pricer) that consumes: SOFR/ESTRN discount factors (IR discounting), the SABR ATM grid point matching the trade's expiry/tenor (IR_VOL / optionality), Treasury/Agency_FNMA/Eur_Govt discount factors (Credit spread proxy), and the EURUSD curve (FX discount/forward proxy). Base NPV = pricer with ALL curves at BASE. Stressed NPV = pricer with the relevant curve set SHOCKED for scenario s.
... B27: All curve levels, shock sizes and SABR parameters are illustrative placeholder assumptions chosen for demonstration purposes only — they are not calibrated to actual 20-Nov-2008 market data and this is not a production pricing/risk engine.

Sheet Trade_Info
A1: Trade & Valuation Info
A3: Trade ID | B3: 123456
A4: Valuation Date | B4: 7/23/2026
A5: Stress / Shock anchor date | B5: 11/20/2008
A6: Number of scenarios | B6: 10
A7: Notional (USD) | B7: 10000000
A8: Product | B8: EUR-underlying payer swaption vs USD-collateral discounting
A9: Representative discounting tenor | B9: 1Y
A10: Representative SABR grid point (Expiry x Tenor) | B10: 1Y x 10Y
A12: Curve list, MDO used, and risk-class mapping
A13: Curve (MDO) | B13: Risk Class | C13: Notes
A14: Agency_FNMA | B14: Credit | C14: Credit — GSE/agency spread curve
A15: Eur_Govt | B15: Credit | C15: Credit — EUR sovereign curve
A16: SOFR | B16: IR | C16: IR_RATE — USD OIS/SOFR discounting curve
A17: Treasury | B17: Credit | C17: Credit — US Treasury (sovereign benchmark) curve
A18: Sabr_Swaption | B18: IR | C18: IR_VOL — SABR surface (ATM, RHO, NU); handled on SABR_* tabs
A19: EURUSD | B19: FX | C19: FX_RATE — EUR/USD FX curve
A20: ESTRN | B20: IR | C20: IR — EUR €STR discounting curve
A22: Liquidity-Horizon Curve Inclusion by Risk Class
A24: Class | B24: LH10 | C24: LH20 | D24: LH40 | E24: LH60
A25: Credit | B25: Agency_FNMA + Eur_Govt + Treasury | C25: Agency_FNMA + Eur_Govt + Treasury | D25: Agency_FNMA only | E25: —
A26: IR | B26: SOFR + ESTRN + Swaption | C26: Swaption only | D26: Swaption only | E26: Swaption only
A27: FX | B27: EURUSD | C27: — | D27: — | E27: —
A28: Cross | B28: all six | C28: Agency_FNMA + Eur_Govt + Treasury + Swaption | D28: Agency_FNMA + Swaption | E28: Swaption only
A30: Rule: at horizon bucket T, a curve is shocked only if its own assigned Liquidity Horizon >= T. Credit now includes Treasury (LH20) alongside Eur_Govt (LH20) and Agency_FNMA (LH40).

Sheet Curves
A1: Curve Objects — Base -> Shift Mechanics -> Shocks -> Shocked Curves (Combined)
A2: Trade 123456 | Val date 7/23/2026 | Stress anchor 20-Nov-2008
A3: SECTION 1 - BASE CURVE OBJECTS: Discount Factors (as of 7/23/2026)
A5: Curve | B5: Risk Class | C5: 3M | D5: 6M | E5: 1Y | F5: 2Y | G5: 3Y | H5: 5Y | I5: 10Y | J5: 20Y | K5: 30Y
A6: Tenor Date | C6: 10/23/2026 | D6: 1/23/2027 | E6: 7/23/2027 | F6: 7/23/2028 | G6: 7/23/2029 | H6: 7/23/2031 | I6: 7/23/2036 | J6: 7/23/2046 | K6: 7/23/2056
A7: Year Frac (t) | C7: 0.25 | D7: 0.5 | E7: 1 | F7: 2 | G7: 3 | H7: 5 | I7: 10 | J7: 20 | K7: 30
A8: SOFR | B8: IR | C8: 0.989298 | D8: 0.978693 | E8: 0.957768 | F8: 0.917044 | G8: 0.877788 | H8: 0.803523 | I8: 0.640824 | J8: 0.410656 | K8: 0.263158
A9: ESTRN | B9: IR | C9: 0.992271 | D9: 0.984583 | E9: 0.96933 | F9: 0.939319 | G9: 0.909964 | H9: 0.85321 | I9: 0.722527 | J9: 0.522046 | K9: 0.377192
A10: Treasury | B10: Credit | C10: 0.989546 | D10: 0.979182 | E10: 0.958726 | F10: 0.91888 | G10: 0.880425 | H10: 0.80755 | I10: 0.647265 | J10: 0.418952 | K10: 0.271173
A11: Agency_FNMA | B11: Credit | C11: 0.988557 | D11: 0.977226 | E11: 0.954899 | F11: 0.911558 | G11: 0.869924 | H11: 0.79156 | I11: 0.621885 | J11: 0.386741 | K11: 0.240508
A12: Eur_Govt | B12: Credit | C12: 0.991775 | D12: 0.983598 | E12: 0.967393 | F12: 0.935569 | G12: 0.904521 | H12: 0.84472 | I12: 0.70822 | J12: 0.501576 | K12: 0.355226
A13: EURUSD | B13: FX | C13: 0.990041 | D13: 0.980162 | E13: 0.960645 | F13: 0.922563 | G13: 0.885724 | H13: 0.815666 | I13: 0.66034 | J13: 0.436049 | K13: 0.287941
A15: Base DF values are illustrative placeholder inputs (blue), not calibrated to a real curve build.
A17: SECTION 2 - gxlCurveDiscShift STEP-BY-STEP ILLUSTRATION (Curve = SOFR, Scenario 1)
A18: Sequential / cascading bootstrap: base forward rate (Section 1) + scenario shock (bps, Section 3) = shocked forward rate; the SHOCKED discount factor at tenor i is solved off the SHOCKED discount factor at tenor i-1 (not the base one). 3M is shocked first and feeds into 6M, which feeds into 1Y, and so on to 30Y.
A21: Tenor | B21: t | C21: Base DF (prior) | D21: Base DF (current) | E21: Base Fwd Rate (simple, ann.) | F21: Shock (bps) | G21: Shocked Fwd Rate | H21: Shocked DF (current) | I21: Formula logic
A22: 3M | B22: 0.25 | C22: 1 | D22: =C8 -> 0.989298 | E22: =(C22/D22-1)/(0.25-0) -> 0.043271087 | F22: =C37 -> -40.9 | G22: =E22+F22/10000 -> 0.039181087 | H22: =1/(1+G22*(0.25-0)) -> 0.99029974 | I22: Anchors at DF=1, t=0
A23: 6M | B23: 0.5 | C23: =C8 -> 0.989298 | D23: =D8 -> 0.978693 | E23: =(C23/D23-1)/(0.5-0.25) -> 0.04334352 | F23: =D37 -> 34.3 | G23: =E23+F23/10000 -> 0.04677352 | H23: =H22/(1+G23*(0.5-0.25)) -> 0.97885364 | I23: Uses SHOCKED DF from 3M (row above), not base
A24: 1Y | B24: 1 | C24: =D8 -> 0.978693 | D24: =E8 -> 0.957768 | E24: =(C24/D24-1)/(1-0.5) -> 0.043695342 | F24: =E37 -> 31.4 | G24: =E24+F24/10000 -> 0.046835342 | H24: =H23/(1+G24*(1-0.5)) -> 0.95645567 | I24: Uses SHOCKED DF from 6M (row above), not base
A25: 2Y | B25: 2 | C25: =E8 -> 0.957768 | D25: =F8 -> 0.917044 | E25: =(C25/D25-1)/(2-1) -> 0.044407902 | F25: =F37 -> -21.7 | G25: =E25+F25/10000 -> 0.042237902 | H25: =H24/(1+G25*(2-1)) -> 0.9176942 | I25: Uses SHOCKED DF from 1Y (row above), not base
A26: 3Y | B26: 3 | C26: =F8 -> 0.917044 | D26: =G8 -> 0.877788 | E26: =(C26/D26-1)/(3-2) -> 0.044721505 | F26: =G37 -> -13 | G26: =E26+F26/10000 -> 0.043421505 | H26: =H25/(1+G26*(3-2)) -> 0.87950478 | I26: Uses SHOCKED DF from 2Y (row above), not base
A27: 5Y | B27: 5 | C27: =G8 -> 0.877788 | D27: =H8 -> 0.803523 | E27: =(C27/D27-1)/(5-3) -> 0.046212118 | F27: =H37 -> 6.1 | G27: =E27+F27/10000 -> 0.046822118 | H27: =H26/(1+G27*(5-3)) -> 0.80419642 | I27: Uses SHOCKED DF from 3Y (row above), not base
A28: 10Y | B28: 10 | C28: =H8 -> 0.803523 | D28: =I8 -> 0.640824 | E28: =(C28/D28-1)/(10-5) -> 0.050778061 | F28: =I37 -> 2.9 | G28: =E28+F28/10000 -> 0.051068061 | H28: =H27/(1+G28*(10-5)) -> 0.64062025 | I28: Uses SHOCKED DF from 5Y (row above), not base
A29: 20Y | B29: 20 | C29: =I8 -> 0.640824 | D29: =J8 -> 0.410656 | E29: =(C29/D29-1)/(20-10) -> 0.056048858 | F29: =J37 -> 2.1 | G29: =E29+F29/10000 -> 0.056258858 | H29: =H28/(1+G29*(20-10)) -> 0.40997372 | I29: Uses SHOCKED DF from 10Y (row above), not base
A30: 30Y | B30: 30 | C30: =J8 -> 0.410656 | D30: =K8 -> 0.263158 | E30: =(C30/D30-1)/(30-20) -> 0.056049218 | F30: =K37 -> 1.2 | G30: =E30+F30/10000 -> 0.056169218 | H30: =H29/(1+G30*(30-20)) -> 0.2625189 | I30: Uses SHOCKED DF from 20Y (row above), not base
A32: This exact column-H formula pattern is replicated for all 6 curves x 10 scenarios in Sections 3/4 below.
A34: SECTION 3 - SHOCK VECTORS: Forward-Rate Shock (bps), 10 Scenarios (anchor 20-Nov-2008) | M34: SECTION 4 - SHOCKED CURVE OBJECTS (gxlCurveDiscShift output): Discount Factors
A36: Scenario 1 | C36: 3M | D36: 6M | E36: 1Y | F36: 2Y | G36: 3Y | H36: 5Y | I36: 10Y | J36: 20Y | K36: 30Y | M36: Scenario 1 | O36: 3M | P36: 6M | Q36: 1Y | R36: 2Y | S36: 3Y | T36: 5Y | U36: 10Y | V36: 20Y | W36: 30Y
A37: SOFR | B37: IR | C37: -40.9 | D37: 34.3 | E37: 31.4 | F37: -21.7 | G37: -13 | H37: 6.1 | I37: 2.9 | J37: 2.1 | K37: 1.2 | M37: SOFR | N37: IR | O37: =1/(1+(((1/C8-1)/(0.25-0))+C37/10000)*(0.25-0)) -> 0.99029974 | P37: =O37/(1+(((C8/D8-1)/(0.5-0.25))+D37/10000)*(0.5-0.25)) -> 0.97885364 | Q37: =P37/(1+(((D8/E8-1)/(1-0.5))+E37/10000)*(1-0.5)) -> 0.95645567 | R37: =Q37/(1+(((E8/F8-1)/(2-1))+F37/10000)*(2-1)) -> 0.9176942 | S37: =R37/(1+(((F8/G8-1)/(3-2))+G37/10000)*(3-2)) -> 0.87950478 | T37: =S37/(1+(((G8/H8-1)/(5-3))+H37/10000)*(5-3)) -> 0.80419642 | U37: =T37/(1+(((H8/I8-1)/(10-5))+I37/10000)*(10-5)) -> 0.64062025 | V37: =U37/(1+(((I8/J8-1)/(20-10))+J37/10000)*(20-10)) -> 0.40997372 | W37: =V37/(1+(((J8/K8-1)/(30-20))+K37/10000)*(30-20)) -> 0.2625189
A38: ESTRN | B38: IR | C38: -35.5 | D38: 31.9 | E38: 24.1 | F38: 18.3 | G38: -8.9 | H38: 5.7 | I38: 2.8 | J38: 1.3 | K38: 0.6 | M38: ESTRN | N38: IR | O38: =1/(1+(((1/C9-1)/(0.25-0))+C38/10000)*(0.25-0)) -> 0.9931456 | P38: =O38/(1+(((C9/D9-1)/(0.5-0.25))+D38/10000)*(0.5-0.25)) -> 0.98467164 | Q38: =P38/(1+(((D9/E9-1)/(1-0.5))+E38/10000)*(1-0.5)) -> 0.96826858 | R38: =Q38/(1+(((E9/F9-1)/(2-1))+F38/10000)*(2-1)) -> 0.93662947 | S38: =R38/(1+(((F9/G9-1)/(3-2))+G38/10000)*(3-2)) -> 0.90814151 | T38: =S38/(1+(((G9/H9-1)/(5-3))+H38/10000)*(5-3)) -> 0.85059198 | U38: =T38/(1+(((H9/I9-1)/(10-5))+I38/10000)*(10-5)) -> 0.71945701 | V38: =U38/(1+(((I9/J9-1)/(20-10))+J38/10000)*(20-10)) -> 0.51934004 | W38: =V38/(1+(((J9/K9-1)/(30-20))+K38/10000)*(30-20)) -> 0.37507427
A39: Treasury | B39: Credit | C39: 49.9 | D39: 46.7 | E39: -34.6 | F39: 21.6 | G39: 13 | H39: 7.2 | I39: 4.1 | J39: 1.9 | K39: 1.2 | M39: Treasury | N39: Credit | O39: =1/(1+(((1/C10-1)/(0.25-0))+C39/10000)*(0.25-0)) -> 0.98832595 | P39: =O39/(1+(((C10/D10-1)/(0.5-0.25))+D39/10000)*(0.5-0.25)) -> 0.97684621 | Q39: =P39/(1+(((D10/E10-1)/(1-0.5))+E39/10000)*(1-0.5)) -> 0.95806183 | R39: =Q39/(1+(((E10/F10-1)/(2-1))+F39/10000)*(2-1)) -> 0.91634638 | S39: =R39/(1+(((F10/G10-1)/(3-2))+G39/10000)*(3-2)) -> 0.87690515 | T39: =S39/(1+(((G10/H10-1)/(5-3))+H39/10000)*(5-3)) -> 0.80326054 | U39: =T39/(1+(((H10/I10-1)/(10-5))+I39/10000)*(10-5)) -> 0.64277078 | V39: =U39/(1+(((I10/J10-1)/(20-10))+J39/10000)*(20-10)) -> 0.41553203 | W39: =V39/(1+(((J10/K10-1)/(30-20))+K39/10000)*(30-20)) -> 0.26875063
A40: Agency_FNMA | B40: Credit | C40: 75.2 | D40: 60.7 | E40: 51.5 | F40: 44.3 | G40: 26.8 | H40: 15.7 | I40: -6.2 | J40: 3.8 | K40: 2.5 | M40: Agency_FNMA | N40: Credit | O40: =1/(1+(((1/C11-1)/(0.25-0))+C40/10000)*(0.25-0)) -> 0.98672319 | P40: =O40/(1+(((C11/D11-1)/(0.5-0.25))+D40/10000)*(0.5-0.25)) -> 0.97395218 | Q40: =P40/(1+(((D11/E11-1)/(1-0.5))+E40/10000)*(1-0.5)) -> 0.94931135 | R40: =Q40/(1+(((E11/F11-1)/(2-1))+F40/10000)*(2-1)) -> 0.90240774 | S40: =R40/(1+(((F11/G11-1)/(3-2))+G40/10000)*(3-2)) -> 0.8589947 | T40: =S40/(1+(((G11/H11-1)/(5-3))+H40/10000)*(5-3)) -> 0.7793884 | U40: =T40/(1+(((H11/I11-1)/(10-5))+I40/10000)*(10-5)) -> 0.6138174 | V40: =U40/(1+(((I11/J11-1)/(20-10))+J40/10000)*(20-10)) -> 0.38082393 | W40: =V40/(1+(((J11/K11-1)/(30-20))+K40/10000)*(30-20)) -> 0.23646064
A41: Eur_Govt | B41: Credit | C41: 64.8 | D41: 54.8 | E41: 47.2 | F41: 28 | G41: 18.8 | H41: 10.1 | I41: 5.2 | J41: 3 | K41: -1.8 | M41: Eur_Govt | N41: Credit | O41: =1/(1+(((1/C12-1)/(0.25-0))+C41/10000)*(0.25-0)) -> 0.9901841 | P41: =O41/(1+(((C12/D12-1)/(0.5-0.25))+D41/10000)*(0.5-0.25)) -> 0.98068775 | Q41: =P41/(1+(((D12/E12-1)/(1-0.5))+E41/10000)*(1-0.5)) -> 0.96229709 | R41: =Q41/(1+(((E12/F12-1)/(2-1))+F41/10000)*(2-1)) -> 0.92812746 | S41: =R41/(1+(((F12/G12-1)/(3-2))+G41/10000)*(3-2)) -> 0.89569839 | T41: =S41/(1+(((G12/H12-1)/(5-3))+H41/10000)*(5-3)) -> 0.83490567 | U41: =T41/(1+(((H12/I12-1)/(10-5))+I41/10000)*(10-5)) -> 0.69846902 | V41: =U41/(1+(((I12/J12-1)/(20-10))+J41/10000)*(20-10)) -> 0.49362138 | W41: =V41/(1+(((J12/K12-1)/(30-20))+K41/10000)*(30-20)) -> 0.35003861
A42: EURUSD | B42: FX | C42: 23.9 | D42: 26.9 | E42: 18.9 | F42: 16.3 | G42: 11 | H42: 5.2 | I42: 3.4 | J42: 1.9 | K42: 1.2 | M42: EURUSD | N42: FX | O42: =1/(1+(((1/C13-1)/(0.25-0))+C42/10000)*(0.25-0)) -> 0.98945569 | P42: =O42/(1+(((C13/D13-1)/(0.5-0.25))+D42/10000)*(0.5-0.25)) -> 0.97893077 | Q42: =P42/(1+(((D13/E13-1)/(1-0.5))+E42/10000)*(1-0.5)) -> 0.95855049 | R42: =Q42/(1+(((E13/F13-1)/(2-1))+F42/10000)*(2-1)) -> 0.91911276 | S42: =R42/(1+(((F13/G13-1)/(3-2))+G42/10000)*(3-2)) -> 0.88148062 | T42: =S42/(1+(((G13/H13-1)/(5-3))+H42/10000)*(5-3)) -> 0.81098155 | U42: =T42/(1+(((H13/I13-1)/(10-5))+I42/10000)*(10-5)) -> 0.65564525 | V42: =U42/(1+(((I13/J13-1)/(20-10))+J42/10000)*(20-10)) -> 0.43240635 | W42: =V42/(1+(((J13/K13-1)/(30-20))+K42/10000)*(30-20)) -> 0.28530953
A44: Scenario 2 | C44: 3M | D44: 6M | E44: 1Y | F44: 2Y | G44: 3Y | H44: 5Y | I44: 10Y | J44: 20Y | K44: 30Y | M44: Scenario 2 | O44: 3M | P44: 6M | Q44: 1Y | R44: 2Y | S44: 3Y | T44: 5Y | U44: 10Y | V44: 20Y | W44: 30Y
A45: SOFR | B45: IR | C45: 45.8 | D45: 45.7 | E45: 34.7 | F45: 25.1 | G45: 14.8 | H45: 7.9 | I45: 4.1 | J45: 2.4 | K45: 1.4 | M45: SOFR | N45: IR | O45: =1/(1+(((1/C8-1)/(0.25-0))+C45/10000)*(0.25-0)) -> 0.98817864 | P45: =O45/(1+(((C8/D8-1)/(0.5-0.25))+D45/10000)*(0.5-0.25)) -> 0.97648197 | Q45: =P45/(1+(((D8/E8-1)/(1-0.5))+E45/10000)*(1-0.5)) -> 0.95398447 | R45: =Q45/(1+(((E8/F8-1)/(2-1))+F45/10000)*(2-1)) -> 0.9112314 | S45: =R45/(1+(((F8/G8-1)/(3-2))+G45/10000)*(3-2)) -> 0.87099034 | T45: =S45/(1+(((G8/H8-1)/(5-3))+H45/10000)*(5-3)) -> 0.79614896 | U45: =T45/(1+(((H8/I8-1)/(10-5))+I45/10000)*(10-5)) -> 0.63390669 | V45: =U45/(1+(((I8/J8-1)/(20-10))+J45/10000)*(20-10)) -> 0.40559941 | W45: =V45/(1+(((J8/K8-1)/(30-20))+K45/10000)*(30-20)) -> 0.25968464
A46: ESTRN | B46: IR | C46: 34.7 | D46: 37.4 | E46: -28.1 | F46: 20.8 | G46: 10.6 | H46: 5.6 | I46: -3.3 | J46: 1.5 | K46: 0.7 | M46: ESTRN | N46: IR | O46: =1/(1+(((1/C9-1)/(0.25-0))+C46/10000)*(0.25-0)) -> 0.99141759 | P46: =O46/(1+(((C9/D9-1)/(0.5-0.25))+D46/10000)*(0.5-0.25)) -> 0.98282438 | Q46: =P46/(1+(((D9/E9-1)/(1-0.5))+E46/10000)*(1-0.5)) -> 0.9689389 | R46: =Q46/(1+(((E9/F9-1)/(2-1))+F46/10000)*(2-1)) -> 0.93705128 | S46: =R46/(1+(((F9/G9-1)/(3-2))+G46/10000)*(3-2)) -> 0.90683595 | T46: =S46/(1+(((G9/H9-1)/(5-3))+H46/10000)*(5-3)) -> 0.84938506 | U46: =T46/(1+(((H9/I9-1)/(10-5))+I46/10000)*(10-5)) -> 0.72029436 | V46: =U46/(1+(((I9/J9-1)/(20-10))+J46/10000)*(20-10)) -> 0.51986943 | W46: =V46/(1+(((J9/K9-1)/(30-20))+K46/10000)*(30-20)) -> 0.37542949
A47: Treasury | B47: Credit | C47: 53 | D47: 50.5 | E47: 36.1 | F47: 29.7 | G47: 16.7 | H47: 8.5 | I47: 4.5 | J47: 2.2 | K47: 1.4 | M47: Treasury | N47: Credit | O47: =1/(1+(((1/C10-1)/(0.25-0))+C47/10000)*(0.25-0)) -> 0.98825026 | P47: =O47/(1+(((C10/D10-1)/(0.5-0.25))+D47/10000)*(0.5-0.25)) -> 0.97667968 | Q47: =P47/(1+(((D10/E10-1)/(1-0.5))+E47/10000)*(1-0.5)) -> 0.95458892 | R47: =Q47/(1+(((E10/F10-1)/(2-1))+F47/10000)*(2-1)) -> 0.9123179 | S47: =R47/(1+(((F10/G10-1)/(3-2))+G47/10000)*(3-2)) -> 0.87274104 | T47: =S47/(1+(((G10/H10-1)/(5-3))+H47/10000)*(5-3)) -> 0.79925579 | U47: =T47/(1+(((H10/I10-1)/(10-5))+I47/10000)*(10-5)) -> 0.63946383 | V47: =U47/(1+(((I10/J10-1)/(20-10))+J47/10000)*(20-10)) -> 0.41331402 | W47: =V47/(1+(((J10/K10-1)/(30-20))+K47/10000)*(30-20)) -> 0.26728153
A48: Agency_FNMA | B48: Credit | C48: 79.9 | D48: -82.8 | E48: 61.9 | F48: -43.5 | G48: 33.6 | H48: 16.8 | I48: 8.2 | J48: 4.2 | K48: 3 | M48: Agency_FNMA | N48: Credit | O48: =1/(1+(((1/C11-1)/(0.25-0))+C48/10000)*(0.25-0)) -> 0.9866088 | P48: =O48/(1+(((C11/D11-1)/(0.5-0.25))+D48/10000)*(0.5-0.25)) -> 0.97729995 | Q48: =P48/(1+(((D11/E11-1)/(1-0.5))+E48/10000)*(1-0.5)) -> 0.95209186 | R48: =Q48/(1+(((E11/F11-1)/(2-1))+F48/10000)*(2-1)) -> 0.91266819 | S48: =R48/(1+(((F11/G11-1)/(3-2))+G48/10000)*(3-2)) -> 0.86819957 | T48: =S48/(1+(((G11/H11-1)/(5-3))+H48/10000)*(5-3)) -> 0.78758301 | U48: =T48/(1+(((H11/I11-1)/(10-5))+I48/10000)*(10-5)) -> 0.61677378 | V48: =U48/(1+(((I11/J11-1)/(20-10))+J48/10000)*(20-10)) -> 0.38256318 | W48: =V48/(1+(((J11/K11-1)/(30-20))+K48/10000)*(30-20)) -> 0.23746685
A49: Eur_Govt | B49: Credit | C49: 72.6 | D49: -67.8 | E49: 49 | F49: 37.3 | G49: 20.2 | H49: 11.4 | I49: 5.8 | J49: 3 | K49: -2.3 | M49: Eur_Govt | N49: Credit | O49: =1/(1+(((1/C12-1)/(0.25-0))+C49/10000)*(0.25-0)) -> 0.98999294 | P49: =O49/(1+(((C12/D12-1)/(0.5-0.25))+D49/10000)*(0.5-0.25)) -> 0.9834839 | Q49: =P49/(1+(((D12/E12-1)/(1-0.5))+E49/10000)*(1-0.5)) -> 0.96495558 | R49: =Q49/(1+(((E12/F12-1)/(2-1))+F49/10000)*(2-1)) -> 0.9298575 | S49: =R49/(1+(((F12/G12-1)/(3-2))+G49/10000)*(3-2)) -> 0.89724675 | T49: =S49/(1+(((G12/H12-1)/(5-3))+H49/10000)*(5-3)) -> 0.8361463 | U49: =T49/(1+(((H12/I12-1)/(10-5))+I49/10000)*(10-5)) -> 0.6993314 | V49: =U49/(1+(((I12/J12-1)/(20-10))+J49/10000)*(20-10)) -> 0.49423084 | W49: =V49/(1+(((J12/K12-1)/(30-20))+K49/10000)*(30-20)) -> 0.3505951
A50: EURUSD | B50: FX | C50: 34 | D50: 32.1 | E50: 26.4 | F50: 16.9 | G50: -11.3 | H50: 6.8 | I50: 3.7 | J50: 2.3 | K50: 1.7 | M50: EURUSD | N50: FX | O50: =1/(1+(((1/C13-1)/(0.25-0))+C50/10000)*(0.25-0)) -> 0.98920855 | P50: =O50/(1+(((C13/D13-1)/(0.5-0.25))+D50/10000)*(0.5-0.25)) -> 0.97856039 | Q50: =P50/(1+(((D13/E13-1)/(1-0.5))+E50/10000)*(1-0.5)) -> 0.95783612 | R50: =Q50/(1+(((E13/F13-1)/(2-1))+F50/10000)*(2-1)) -> 0.91837494 | S50: =R50/(1+(((F13/G13-1)/(3-2))+G50/10000)*(3-2)) -> 0.88266075 | T50: =S50/(1+(((G13/H13-1)/(5-3))+H50/10000)*(5-3)) -> 0.81182829 | U50: =T50/(1+(((H13/I13-1)/(10-5))+I50/10000)*(10-5)) -> 0.65625023 | V50: =U50/(1+(((I13/J13-1)/(20-10))+J50/10000)*(20-10)) -> 0.4326912 | W50: =V50/(1+(((J13/K13-1)/(30-20))+K50/10000)*(30-20)) -> 0.28540332
A52: Scenario 3 | C52: 3M | D52: 6M | E52: 1Y | F52: 2Y | G52: 3Y | H52: 5Y | I52: 10Y | J52: 20Y | K52: 30Y | M52: Scenario 3 | O52: 3M | P52: 6M | Q52: 1Y | R52: 2Y | S52: 3Y | T52: 5Y | U52: 10Y | V52: 20Y | W52: 30Y
A53: SOFR | B53: IR | C53: 53.3 | D53: 45.4 | E53: 43 | F53: 26.6 | G53: 16.2 | H53: 8.8 | I53: 4.1 | J53: 2.4 | K53: 1.8 | M53: SOFR | N53: IR | O53: =1/(1+(((1/C8-1)/(0.25-0))+C53/10000)*(0.25-0)) -> 0.98799559 | P53: =O53/(1+(((C8/D8-1)/(0.5-0.25))+D53/10000)*(0.5-0.25)) -> 0.97630832 | Q53: =P53/(1+(((D8/E8-1)/(1-0.5))+E53/10000)*(1-0.5)) -> 0.95342826 | R53: =Q53/(1+(((E8/F8-1)/(2-1))+F53/10000)*(2-1)) -> 0.91056965 | S53: =R53/(1+(((F8/G8-1)/(3-2))+G53/10000)*(3-2)) -> 0.87024136 | T53: =S53/(1+(((G8/H8-1)/(5-3))+H53/10000)*(5-3)) -> 0.79533348 | U53: =T53/(1+(((H8/I8-1)/(10-5))+I53/10000)*(10-5)) -> 0.63325739 | V53: =U53/(1+(((I8/J8-1)/(20-10))+J53/10000)*(20-10)) -> 0.40518397 | W53: =V53/(1+(((J8/K8-1)/(30-20))+K53/10000)*(30-20)) -> 0.25935223
A54: ESTRN | B54: IR | C54: -41.9 | D54: 42.4 | E54: 34 | F54: 21.7 | G54: 13.3 | H54: 6.7 | I54: 3.4 | J54: 1.8 | K54: 0.9 | M54: ESTRN | N54: IR | O54: =1/(1+(((1/C9-1)/(0.25-0))+C54/10000)*(0.25-0)) -> 0.99330344 | P54: =O54/(1+(((C9/D9-1)/(0.5-0.25))+D54/10000)*(0.5-0.25)) -> 0.98457188 | Q54: =P54/(1+(((D9/E9-1)/(1-0.5))+E54/10000)*(1-0.5)) -> 0.96769945 | R54: =Q54/(1+(((E9/F9-1)/(2-1))+F54/10000)*(2-1)) -> 0.93577118 | S54: =R54/(1+(((F9/G9-1)/(3-2))+G54/10000)*(3-2)) -> 0.90536056 | T54: =S54/(1+(((G9/H9-1)/(5-3))+H54/10000)*(5-3)) -> 0.84782844 | U54: =T54/(1+(((H9/I9-1)/(10-5))+I54/10000)*(10-5)) -> 0.7169376 | V54: =U54/(1+(((I9/J9-1)/(20-10))+J54/10000)*(20-10)) -> 0.51733468 | W54: =V54/(1+(((J9/K9-1)/(30-20))+K54/10000)*(30-20)) -> 0.37354504
A55: Treasury | B55: Credit | C55: 56.8 | D55: 62.4 | E55: 40.6 | F55: 29.5 | G55: 20.7 | H55: 10.3 | I55: 5.6 | J55: 2.7 | K55: -1.8 | M55: Treasury | N55: Credit | O55: =1/(1+(((1/C10-1)/(0.25-0))+C55/10000)*(0.25-0)) -> 0.98815749 | P55: =O55/(1+(((C10/D10-1)/(0.5-0.25))+D55/10000)*(0.5-0.25)) -> 0.97630095 | Q55: =P55/(1+(((D10/E10-1)/(1-0.5))+E55/10000)*(1-0.5)) -> 0.95400896 | R55: =Q55/(1+(((E10/F10-1)/(2-1))+F55/10000)*(2-1)) -> 0.91178104 | S55: =R55/(1+(((F10/G10-1)/(3-2))+G55/10000)*(3-2)) -> 0.87189384 | T55: =S55/(1+(((G10/H10-1)/(5-3))+H55/10000)*(5-3)) -> 0.79821677 | U55: =T55/(1+(((H10/I10-1)/(10-5))+I55/10000)*(10-5)) -> 0.63835164 | V55: =U55/(1+(((I10/J10-1)/(20-10))+J55/10000)*(20-10)) -> 0.41246187 | W55: =V55/(1+(((J10/K10-1)/(30-20))+K55/10000)*(30-20)) -> 0.26728357
A56: Agency_FNMA | B56: Credit | C56: 102.4 | D56: 90.6 | E56: -69.8 | F56: 49 | G56: 33.7 | H56: 20.1 | I56: 9 | J56: 5.3 | K56: -3.7 | M56: Agency_FNMA | N56: Credit | O56: =1/(1+(((1/C11-1)/(0.25-0))+C56/10000)*(0.25-0)) -> 0.98606157 | P56: =O56/(1+(((C11/D11-1)/(0.5-0.25))+D56/10000)*(0.5-0.25)) -> 0.97258152 | Q56: =P56/(1+(((D11/E11-1)/(1-0.5))+E56/10000)*(1-0.5)) -> 0.95361271 | R56: =Q56/(1+(((E11/F11-1)/(2-1))+F56/10000)*(2-1)) -> 0.90609176 | S56: =R56/(1+(((F11/G11-1)/(3-2))+G56/10000)*(3-2)) -> 0.86193537 | T56: =S56/(1+(((G11/H11-1)/(5-3))+H56/10000)*(5-3)) -> 0.78143261 | U56: =T56/(1+(((H11/I11-1)/(10-5))+I56/10000)*(10-5)) -> 0.61176563 | V56: =U56/(1+(((I11/J11-1)/(20-10))+J56/10000)*(20-10)) -> 0.37919808 | W56: =V56/(1+(((J11/K11-1)/(30-20))+K56/10000)*(30-20)) -> 0.23636104
A57: Eur_Govt | B57: Credit | C57: 78.1 | D57: 64 | E57: 58.6 | F57: 41.3 | G57: -24.3 | H57: 12.2 | I57: 7.6 | J57: 3.7 | K57: -2.5 | M57: Eur_Govt | N57: Credit | O57: =1/(1+(((1/C12-1)/(0.25-0))+C57/10000)*(0.25-0)) -> 0.9898582 | P57: =O57/(1+(((C12/D12-1)/(0.5-0.25))+D57/10000)*(0.5-0.25)) -> 0.9801417 | Q57: =P57/(1+(((D12/E12-1)/(1-0.5))+E57/10000)*(1-0.5)) -> 0.96122366 | R57: =Q57/(1+(((E12/F12-1)/(2-1))+F57/10000)*(2-1)) -> 0.92590443 | S57: =R57/(1+(((F12/G12-1)/(3-2))+G57/10000)*(3-2)) -> 0.8972852 | T57: =S57/(1+(((G12/H12-1)/(5-3))+H57/10000)*(5-3)) -> 0.83605747 | U57: =T57/(1+(((H12/I12-1)/(10-5))+I57/10000)*(10-5)) -> 0.69873115 | V57: =U57/(1+(((I12/J12-1)/(20-10))+J57/10000)*(20-10)) -> 0.49356246 | W57: =V57/(1+(((J12/K12-1)/(30-20))+K57/10000)*(30-20)) -> 0.35017065
A58: EURUSD | B58: FX | C58: 34 | D58: 35.2 | E58: 30.2 | F58: -18.5 | G58: 13.9 | H58: 7.8 | I58: 4.1 | J58: 2.8 | K58: 1.9 | M58: EURUSD | N58: FX | O58: =1/(1+(((1/C13-1)/(0.25-0))+C58/10000)*(0.25-0)) -> 0.98920855 | P58: =O58/(1+(((C13/D13-1)/(0.5-0.25))+D58/10000)*(0.5-0.25)) -> 0.97848538 | Q58: =P58/(1+(((D13/E13-1)/(1-0.5))+E58/10000)*(1-0.5)) -> 0.9575846 | R58: =Q58/(1+(((E13/F13-1)/(2-1))+F58/10000)*(2-1)) -> 0.92126069 | S58: =R58/(1+(((F13/G13-1)/(3-2))+G58/10000)*(3-2)) -> 0.88329494 | T58: =S58/(1+(((G13/H13-1)/(5-3))+H58/10000)*(5-3)) -> 0.81226217 | U58: =T58/(1+(((H13/I13-1)/(10-5))+I58/10000)*(10-5)) -> 0.65649482 | V58: =U58/(1+(((I13/J13-1)/(20-10))+J58/10000)*(20-10)) -> 0.43270981 | W58: =V58/(1+(((J13/K13-1)/(30-20))+K58/10000)*(30-20)) -> 0.28537795
A60: Scenario 4 | C60: 3M | D60: 6M | E60: 1Y | F60: 2Y | G60: 3Y | H60: 5Y | I60: 10Y | J60: 20Y | K60: 30Y | M60: Scenario 4 | O60: 3M | P60: 6M | Q60: 1Y | R60: 2Y | S60: 3Y | T60: 5Y | U60: 10Y | V60: 20Y | W60: 30Y
A61: SOFR | B61: IR | C61: 54.8 | D61: 53 | E61: 46.7 | F61: 31.2 | G61: -20.7 | H61: 10.5 | I61: 4.7 | J61: 3 | K61: 2.1 | M61: SOFR | N61: IR | O61: =1/(1+(((1/C8-1)/(0.25-0))+C61/10000)*(0.25-0)) -> 0.98795898 | P61: =O61/(1+(((C8/D8-1)/(0.5-0.25))+D61/10000)*(0.5-0.25)) -> 0.97608888 | Q61: =P61/(1+(((D8/E8-1)/(1-0.5))+E61/10000)*(1-0.5)) -> 0.95304179 | R61: =Q61/(1+(((E8/F8-1)/(2-1))+F61/10000)*(2-1)) -> 0.90980086 | S61: =R61/(1+(((F8/G8-1)/(3-2))+G61/10000)*(3-2)) -> 0.87258385 | T61: =S61/(1+(((G8/H8-1)/(5-3))+H61/10000)*(5-3)) -> 0.79722661 | U61: =T61/(1+(((H8/I8-1)/(10-5))+I61/10000)*(10-5)) -> 0.63461314 | V61: =U61/(1+(((I8/J8-1)/(20-10))+J61/10000)*(20-10)) -> 0.4058956 | W61: =V61/(1+(((J8/K8-1)/(30-20))+K61/10000)*(30-20)) -> 0.25975786
A62: ESTRN | B62: IR | C62: 45.7 | D62: 43.3 | E62: 40.5 | F62: 25.3 | G62: 16 | H62: -8.5 | I62: 4.3 | J62: 2.1 | K62: 0.9 | M62: ESTRN | N62: IR | O62: =1/(1+(((1/C9-1)/(0.25-0))+C62/10000)*(0.25-0)) -> 0.99114737 | P62: =O62/(1+(((C9/D9-1)/(0.5-0.25))+D62/10000)*(0.5-0.25)) -> 0.98241285 | Q62: =P62/(1+(((D9/E9-1)/(1-0.5))+E62/10000)*(1-0.5)) -> 0.96526908 | R62: =Q62/(1+(((E9/F9-1)/(2-1))+F62/10000)*(2-1)) -> 0.93309617 | S62: =R62/(1+(((F9/G9-1)/(3-2))+G62/10000)*(3-2)) -> 0.90253671 | T62: =S62/(1+(((G9/H9-1)/(5-3))+H62/10000)*(5-3)) -> 0.84759699 | U62: =T62/(1+(((H9/I9-1)/(10-5))+I62/10000)*(10-5)) -> 0.71646924 | V62: =U62/(1+(((I9/J9-1)/(20-10))+J62/10000)*(20-10)) -> 0.51688483 | W62: =V62/(1+(((J9/K9-1)/(30-20))+K62/10000)*(30-20)) -> 0.37322022
A63: Treasury | B63: Credit | C63: 71.9 | D63: 65.5 | E63: 48.6 | F63: 33.3 | G63: 20 | H63: 12 | I63: 6.2 | J63: -2.9 | K63: 2 | M63: Treasury | N63: Credit | O63: =1/(1+(((1/C10-1)/(0.25-0))+C63/10000)*(0.25-0)) -> 0.98778901 | P63: =O63/(1+(((C10/D10-1)/(0.5-0.25))+D63/10000)*(0.5-0.25)) -> 0.97586217 | Q63: =P63/(1+(((D10/E10-1)/(1-0.5))+E63/10000)*(1-0.5)) -> 0.95320762 | R63: =Q63/(1+(((E10/F10-1)/(2-1))+F63/10000)*(2-1)) -> 0.91068443 | S63: =R63/(1+(((F10/G10-1)/(3-2))+G63/10000)*(3-2)) -> 0.87090351 | T63: =S63/(1+(((G10/H10-1)/(5-3))+H63/10000)*(5-3)) -> 0.79706201 | U63: =T63/(1+(((H10/I10-1)/(10-5))+I63/10000)*(10-5)) -> 0.63727526 | V63: =U63/(1+(((I10/J10-1)/(20-10))+J63/10000)*(20-10)) -> 0.41326171 | W63: =V63/(1+(((J10/K10-1)/(30-20))+K63/10000)*(30-20)) -> 0.26714405
A64: Agency_FNMA | B64: Credit | C64: 105.6 | D64: 102.5 | E64: 81.6 | F64: 58.5 | G64: 37.2 | H64: 23.3 | I64: 10.5 | J64: 5.7 | K64: 3.6 | M64: Agency_FNMA | N64: Credit | O64: =1/(1+(((1/C11-1)/(0.25-0))+C64/10000)*(0.25-0)) -> 0.98598379 | P64: =O64/(1+(((C11/D11-1)/(0.5-0.25))+D64/10000)*(0.5-0.25)) -> 0.97221953 | Q64: =P64/(1+(((D11/E11-1)/(1-0.5))+E64/10000)*(1-0.5)) -> 0.94623448 | R64: =Q64/(1+(((E11/F11-1)/(2-1))+F64/10000)*(2-1)) -> 0.89827037 | S64: =R64/(1+(((F11/G11-1)/(3-2))+G64/10000)*(3-2)) -> 0.85421074 | T64: =S64/(1+(((G11/H11-1)/(5-3))+H64/10000)*(5-3)) -> 0.77398036 | U64: =T64/(1+(((H11/I11-1)/(10-5))+I64/10000)*(10-5)) -> 0.60557587 | V64: =U64/(1+(((I11/J11-1)/(20-10))+J64/10000)*(20-10)) -> 0.37526836 | W64: =V64/(1+(((J11/K11-1)/(30-20))+K64/10000)*(30-20)) -> 0.23285205
A65: Eur_Govt | B65: Credit | C65: 88.1 | D65: 81.2 | E65: 63.7 | F65: 44.4 | G65: 29 | H65: 13.9 | I65: 8.1 | J65: 4.2 | K65: 3.1 | M65: Eur_Govt | N65: Credit | O65: =1/(1+(((1/C12-1)/(0.25-0))+C65/10000)*(0.25-0)) -> 0.9896133 | P65: =O65/(1+(((C12/D12-1)/(0.5-0.25))+D65/10000)*(0.5-0.25)) -> 0.97948217 | Q65: =P65/(1+(((D12/E12-1)/(1-0.5))+E65/10000)*(1-0.5)) -> 0.9603367 | R65: =Q65/(1+(((E12/F12-1)/(2-1))+F65/10000)*(2-1)) -> 0.92477391 | S65: =R65/(1+(((F12/G12-1)/(3-2))+G65/10000)*(3-2)) -> 0.89158437 | T65: =S65/(1+(((G12/H12-1)/(5-3))+H65/10000)*(5-3)) -> 0.83048255 | U65: =T65/(1+(((H12/I12-1)/(10-5))+I65/10000)*(10-5)) -> 0.69392694 | V65: =U65/(1+(((I12/J12-1)/(20-10))+J65/10000)*(20-10)) -> 0.48999586 | W65: =V65/(1+(((J12/K12-1)/(30-20))+K65/10000)*(30-20)) -> 0.3462645
A66: EURUSD | B66: FX | C66: -37.7 | D66: 36.1 | E66: -33.5 | F66: 21.5 | G66: 14.1 | H66: 8.9 | I66: -5.1 | J66: 3.1 | K66: 1.9 | M66: EURUSD | N66: FX | O66: =1/(1+(((1/C13-1)/(0.25-0))+C66/10000)*(0.25-0)) -> 0.99096568 | P66: =O66/(1+(((C13/D13-1)/(0.5-0.25))+D66/10000)*(0.5-0.25)) -> 0.98020165 | Q66: =P66/(1+(((D13/E13-1)/(1-0.5))+E66/10000)*(1-0.5)) -> 0.96226356 | R66: =Q66/(1+(((E13/F13-1)/(2-1))+F66/10000)*(2-1)) -> 0.92221324 | S66: =R66/(1+(((F13/G13-1)/(3-2))+G66/10000)*(3-2)) -> 0.88419128 | T66: =S66/(1+(((G13/H13-1)/(5-3))+H66/10000)*(5-3)) -> 0.81292196 | U66: =T66/(1+(((H13/I13-1)/(10-5))+I66/10000)*(10-5)) -> 0.65947994 | V66: =U66/(1+(((I13/J13-1)/(20-10))+J66/10000)*(20-10)) -> 0.43459144 | W66: =V66/(1+(((J13/K13-1)/(30-20))+K66/10000)*(30-20)) -> 0.28661891
A68: Scenario 5 | C68: 3M | D68: 6M | E68: 1Y | F68: 2Y | G68: 3Y | H68: 5Y | I68: 10Y | J68: 20Y | K68: 30Y | M68: Scenario 5 | O68: 3M | P68: 6M | Q68: 1Y | R68: 2Y | S68: 3Y | T68: 5Y | U68: 10Y | V68: 20Y | W68: 30Y
A69: SOFR | B69: IR | C69: 62.9 | D69: -60.7 | E69: 47.7 | F69: 32.8 | G69: 22.5 | H69: 11.2 | I69: 5.8 | J69: 3.4 | K69: 2.3 | M69: SOFR | N69: IR | O69: =1/(1+(((1/C8-1)/(0.25-0))+C69/10000)*(0.25-0)) -> 0.98776137 | P69: =O69/(1+(((C8/D8-1)/(0.5-0.25))+D69/10000)*(0.5-0.25)) -> 0.97864201 | Q69: =P69/(1+(((D8/E8-1)/(1-0.5))+E69/10000)*(1-0.5)) -> 0.95548798 | R69: =Q69/(1+(((E8/F8-1)/(2-1))+F69/10000)*(2-1)) -> 0.91199677 | S69: =R69/(1+(((F8/G8-1)/(3-2))+G69/10000)*(3-2)) -> 0.8710808 | T69: =S69/(1+(((G8/H8-1)/(5-3))+H69/10000)*(5-3)) -> 0.79575158 | U69: =T69/(1+(((H8/I8-1)/(10-5))+I69/10000)*(10-5)) -> 0.63316178 | V69: =U69/(1+(((I8/J8-1)/(20-10))+J69/10000)*(20-10)) -> 0.40486374 | W69: =V69/(1+(((J8/K8-1)/(30-20))+K69/10000)*(30-20)) -> 0.25906435
A70: ESTRN | B70: IR | C70: 58.2 | D70: 49.3 | E70: 40.3 | F70: 28.6 | G70: 16.8 | H70: 8.3 | I70: 4.3 | J70: -2.2 | K70: 1.1 | M70: ESTRN | N70: IR | O70: =1/(1+(((1/C9-1)/(0.25-0))+C70/10000)*(0.25-0)) -> 0.99084047 | P70: =O70/(1+(((C9/D9-1)/(0.5-0.25))+D70/10000)*(0.5-0.25)) -> 0.98196266 | Q70: =P70/(1+(((D9/E9-1)/(1-0.5))+E70/10000)*(1-0.5)) -> 0.96483623 | R70: =Q70/(1+(((E9/F9-1)/(2-1))+F70/10000)*(2-1)) -> 0.93238031 | S70: =R70/(1+(((F9/G9-1)/(3-2))+G70/10000)*(3-2)) -> 0.90177452 | T70: =S70/(1+(((G9/H9-1)/(5-3))+H70/10000)*(5-3)) -> 0.8442173 | U70: =T70/(1+(((H9/I9-1)/(10-5))+I70/10000)*(10-5)) -> 0.71361241 | V70: =U70/(1+(((I9/J9-1)/(20-10))+J70/10000)*(20-10)) -> 0.51642585 | W70: =V70/(1+(((J9/K9-1)/(30-20))+K70/10000)*(30-20)) -> 0.37283497
A71: Treasury | B71: Credit | C71: -79.3 | D71: 70.5 | E71: 54.3 | F71: 38.1 | G71: 24.5 | H71: 13.9 | I71: -6.5 | J71: 3.2 | K71: 2.3 | M71: Treasury | N71: Credit | O71: =1/(1+(((1/C10-1)/(0.25-0))+C71/10000)*(0.25-0)) -> 0.99149108 | P71: =O71/(1+(((C10/D10-1)/(0.5-0.25))+D71/10000)*(0.5-0.25)) -> 0.9793986 | Q71: =P71/(1+(((D10/E10-1)/(1-0.5))+E71/10000)*(1-0.5)) -> 0.95639571 | R71: =Q71/(1+(((E10/F10-1)/(2-1))+F71/10000)*(2-1)) -> 0.91331146 | S71: =R71/(1+(((F10/G10-1)/(3-2))+G71/10000)*(3-2)) -> 0.87304007 | T71: =S71/(1+(((G10/H10-1)/(5-3))+H71/10000)*(5-3)) -> 0.79873964 | U71: =T71/(1+(((H10/I10-1)/(10-5))+I71/10000)*(10-5)) -> 0.64187539 | V71: =U71/(1+(((I10/J10-1)/(20-10))+J71/10000)*(20-10)) -> 0.41460474 | W71: =V71/(1+(((J10/K10-1)/(30-20))+K71/10000)*(30-20)) -> 0.26796026
A72: Agency_FNMA | B72: Credit | C72: 119.6 | D72: 110.7 | E72: 89.7 | F72: -65.4 | G72: 43 | H72: 23.9 | I72: -10.9 | J72: -6.7 | K72: 4.3 | M72: Agency_FNMA | N72: Credit | O72: =1/(1+(((1/C11-1)/(0.25-0))+C72/10000)*(0.25-0)) -> 0.98564365 | P72: =O72/(1+(((C11/D11-1)/(0.5-0.25))+D72/10000)*(0.5-0.25)) -> 0.97168772 | Q72: =P72/(1+(((D11/E11-1)/(1-0.5))+E72/10000)*(1-0.5)) -> 0.94534426 | R72: =Q72/(1+(((E11/F11-1)/(2-1))+F72/10000)*(2-1)) -> 0.90810638 | S72: =R72/(1+(((F11/G11-1)/(3-2))+G72/10000)*(3-2)) -> 0.86308826 | T72: =S72/(1+(((G11/H11-1)/(5-3))+H72/10000)*(5-3)) -> 0.78193906 | U72: =T72/(1+(((H11/I11-1)/(10-5))+I72/10000)*(10-5)) -> 0.61696807 | V72: =U72/(1+(((I11/J11-1)/(20-10))+J72/10000)*(20-10)) -> 0.38528859 | W72: =V72/(1+(((J11/K11-1)/(30-20))+K72/10000)*(30-20)) -> 0.23896575
A73: Eur_Govt | B73: Credit | C73: 92.2 | D73: 83.3 | E73: 66.8 | F73: 47.4 | G73: 32 | H73: 17.1 | I73: -8.5 | J73: 4.1 | K73: 3.5 | M73: Eur_Govt | N73: Credit | O73: =1/(1+(((1/C12-1)/(0.25-0))+C73/10000)*(0.25-0)) -> 0.98951293 | P73: =O73/(1+(((C12/D12-1)/(0.5-0.25))+D73/10000)*(0.5-0.25)) -> 0.97933194 | Q73: =P73/(1+(((D12/E12-1)/(1-0.5))+E73/10000)*(1-0.5)) -> 0.96004351 | R73: =Q73/(1+(((E12/F12-1)/(2-1))+F73/10000)*(2-1)) -> 0.92422457 | S73: =R73/(1+(((F12/G12-1)/(3-2))+G73/10000)*(3-2)) -> 0.8907971 | T73: =S73/(1+(((G12/H12-1)/(5-3))+H73/10000)*(5-3)) -> 0.82925488 | U73: =T73/(1+(((H12/I12-1)/(10-5))+I73/10000)*(10-5)) -> 0.69774013 | V73: =U73/(1+(((I12/J12-1)/(20-10))+J73/10000)*(20-10)) -> 0.49272322 | W73: =V73/(1+(((J12/K12-1)/(30-20))+K73/10000)*(30-20)) -> 0.34809344
A74: EURUSD | B74: FX | C74: 45 | D74: 42.7 | E74: 37.5 | F74: 22.5 | G74: 15.6 | H74: 10 | I74: 5.7 | J74: 3.1 | K74: -2.3 | M74: EURUSD | N74: FX | O74: =1/(1+(((1/C13-1)/(0.25-0))+C74/10000)*(0.25-0)) -> 0.98893952 | P74: =O74/(1+(((C13/D13-1)/(0.5-0.25))+D74/10000)*(0.5-0.25)) -> 0.97803788 | Q74: =P74/(1+(((D13/E13-1)/(1-0.5))+E74/10000)*(1-0.5)) -> 0.95680489 | R74: =Q74/(1+(((E13/F13-1)/(2-1))+F74/10000)*(2-1)) -> 0.91689389 | S74: =R74/(1+(((F13/G13-1)/(3-2))+G74/10000)*(3-2)) -> 0.87896483 | T74: =S74/(1+(((G13/H13-1)/(5-3))+H74/10000)*(5-3)) -> 0.80795336 | U74: =T74/(1+(((H13/I13-1)/(10-5))+I74/10000)*(10-5)) -> 0.65259036 | V74: =U74/(1+(((I13/J13-1)/(20-10))+J74/10000)*(20-10)) -> 0.43005126 | W74: =V74/(1+(((J13/K13-1)/(30-20))+K74/10000)*(30-20)) -> 0.28441241
A76: Scenario 6 | C76: 3M | D76: 6M | E76: 1Y | F76: 2Y | G76: 3Y | H76: 5Y | I76: 10Y | J76: 20Y | K76: 30Y | M76: Scenario 6 | O76: 3M | P76: 6M | Q76: 1Y | R76: 2Y | S76: 3Y | T76: 5Y | U76: 10Y | V76: 20Y | W76: 30Y
A77: SOFR | B77: IR | C77: 75.7 | D77: -63.1 | E77: 53.1 | F77: 38.5 | G77: -24.9 | H77: 12.4 | I77: 5.7 | J77: 3.8 | K77: 2.3 | M77: SOFR | N77: IR | O77: =1/(1+(((1/C8-1)/(0.25-0))+C77/10000)*(0.25-0)) -> 0.98744925 | P77: =O77/(1+(((C8/D8-1)/(0.5-0.25))+D77/10000)*(0.5-0.25)) -> 0.97839094 | Q77: =P77/(1+(((D8/E8-1)/(1-0.5))+E77/10000)*(1-0.5)) -> 0.9549911 | R77: =Q77/(1+(((E8/F8-1)/(2-1))+F77/10000)*(2-1)) -> 0.91102686 | S77: =R77/(1+(((F8/G8-1)/(3-2))+G77/10000)*(3-2)) -> 0.8741118 | T77: =S77/(1+(((G8/H8-1)/(5-3))+H77/10000)*(5-3)) -> 0.79834544 | U77: =T77/(1+(((H8/I8-1)/(10-5))+I77/10000)*(10-5)) -> 0.63525092 | V77: =U77/(1+(((I8/J8-1)/(20-10))+J77/10000)*(20-10)) -> 0.40609574 | W77: =V77/(1+(((J8/K8-1)/(30-20))+K77/10000)*(30-20)) -> 0.25985268
A78: ESTRN | B78: IR | C78: 62.8 | D78: 53.9 | E78: 46 | F78: 31.6 | G78: 17.2 | H78: 9.9 | I78: 5 | J78: 2.5 | K78: 1.2 | M78: ESTRN | N78: IR | O78: =1/(1+(((1/C9-1)/(0.25-0))+C78/10000)*(0.25-0)) -> 0.99072758 | P78: =O78/(1+(((C9/D9-1)/(0.5-0.25))+D78/10000)*(0.5-0.25)) -> 0.98173889 | Q78: =P78/(1+(((D9/E9-1)/(1-0.5))+E78/10000)*(1-0.5)) -> 0.96434632 | R78: =Q78/(1+(((E9/F9-1)/(2-1))+F78/10000)*(2-1)) -> 0.93163679 | S78: =R78/(1+(((F9/G9-1)/(3-2))+G78/10000)*(3-2)) -> 0.90102055 | T78: =S78/(1+(((G9/H9-1)/(5-3))+H78/10000)*(5-3)) -> 0.84325883 | U78: =T78/(1+(((H9/I9-1)/(10-5))+I78/10000)*(10-5)) -> 0.7125914 | V78: =U78/(1+(((I9/J9-1)/(20-10))+J78/10000)*(20-10)) -> 0.51393891 | W78: =V78/(1+(((J9/K9-1)/(30-20))+K78/10000)*(30-20)) -> 0.37101273
A79: Treasury | B79: Credit | C79: 85.1 | D79: 78 | E79: 58.6 | F79: -44.2 | G79: 28 | H79: 14.5 | I79: -7.1 | J79: 3.8 | K79: 2.3 | M79: Treasury | N79: Credit | O79: =1/(1+(((1/C10-1)/(0.25-0))+C79/10000)*(0.25-0)) -> 0.98746713 | P79: =O79/(1+(((C10/D10-1)/(0.5-0.25))+D79/10000)*(0.5-0.25)) -> 0.97524309 | Q79: =P79/(1+(((D10/E10-1)/(1-0.5))+E79/10000)*(1-0.5)) -> 0.9521379 | R79: =Q79/(1+(((E10/F10-1)/(2-1))+F79/10000)*(2-1)) -> 0.91644806 | S79: =R79/(1+(((F10/G10-1)/(3-2))+G79/10000)*(3-2)) -> 0.87574536 | T79: =S79/(1+(((G10/H10-1)/(5-3))+H79/10000)*(5-3)) -> 0.80112674 | U79: =T79/(1+(((H10/I10-1)/(10-5))+I79/10000)*(10-5)) -> 0.64394893 | V79: =U79/(1+(((I10/J10-1)/(20-10))+J79/10000)*(20-10)) -> 0.41578296 | W79: =V79/(1+(((J10/K10-1)/(30-20))+K79/10000)*(30-20)) -> 0.26872175
A80: Agency_FNMA | B80: Credit | C80: 130.3 | D80: 124.2 | E80: 96.2 | F80: 68.6 | G80: 48.3 | H80: 27.3 | I80: 12.1 | J80: 6.9 | K80: 5 | M80: Agency_FNMA | N80: Credit | O80: =1/(1+(((1/C11-1)/(0.25-0))+C80/10000)*(0.25-0)) -> 0.98538384 | P80: =O80/(1+(((C11/D11-1)/(0.5-0.25))+D80/10000)*(0.5-0.25)) -> 0.97110848 | Q80: =P80/(1+(((D11/E11-1)/(1-0.5))+E80/10000)*(1-0.5)) -> 0.94448209 | R80: =Q80/(1+(((E11/F11-1)/(2-1))+F80/10000)*(2-1)) -> 0.89574796 | S80: =R80/(1+(((F11/G11-1)/(3-2))+G80/10000)*(3-2)) -> 0.85091386 | T80: =S80/(1+(((G11/H11-1)/(5-3))+H80/10000)*(5-3)) -> 0.77043468 | U80: =T80/(1+(((H11/I11-1)/(10-5))+I80/10000)*(10-5)) -> 0.60242459 | V80: =U80/(1+(((I11/J11-1)/(20-10))+J80/10000)*(20-10)) -> 0.37303815 | W80: =V80/(1+(((J11/K11-1)/(30-20))+K80/10000)*(30-20)) -> 0.23126731
A81: Eur_Govt | B81: Credit | C81: 110.1 | D81: 97.2 | E81: 81.2 | F81: 55.9 | G81: -32.8 | H81: -17.4 | I81: 9.7 | J81: 4.6 | K81: 3.6 | M81: Eur_Govt | N81: Credit | O81: =1/(1+(((1/C12-1)/(0.25-0))+C81/10000)*(0.25-0)) -> 0.98907496 | P81: =O81/(1+(((C12/D12-1)/(0.5-0.25))+D81/10000)*(0.5-0.25)) -> 0.97856192 | Q81: =P81/(1+(((D12/E12-1)/(1-0.5))+E81/10000)*(1-0.5)) -> 0.95861205 | R81: =Q81/(1+(((E12/F12-1)/(2-1))+F81/10000)*(2-1)) -> 0.92209199 | S81: =R81/(1+(((F12/G12-1)/(3-2))+G81/10000)*(3-2)) -> 0.89432728 | T81: =S81/(1+(((G12/H12-1)/(5-3))+H81/10000)*(5-3)) -> 0.83792341 | U81: =T81/(1+(((H12/I12-1)/(10-5))+I81/10000)*(10-5)) -> 0.69967661 | V81: =U81/(1+(((I12/J12-1)/(20-10))+J81/10000)*(20-10)) -> 0.49391631 | W81: =V81/(1+(((J12/K12-1)/(30-20))+K81/10000)*(30-20)) -> 0.34891167
A82: EURUSD | B82: FX | C82: 51.5 | D82: -44.7 | E82: 37.2 | F82: -25.5 | G82: 18.2 | H82: 11.6 | I82: -6.2 | J82: 3.8 | K82: 2.5 | M82: EURUSD | N82: FX | O82: =1/(1+(((1/C13-1)/(0.25-0))+C82/10000)*(0.25-0)) -> 0.98878062 | P82: =O82/(1+(((C13/D13-1)/(0.5-0.25))+D82/10000)*(0.5-0.25)) -> 0.97999842 | Q82: =P82/(1+(((D13/E13-1)/(1-0.5))+E82/10000)*(1-0.5)) -> 0.95873693 | R82: =Q82/(1+(((E13/F13-1)/(2-1))+F82/10000)*(2-1)) -> 0.9229909 | S82: =R82/(1+(((F13/G13-1)/(3-2))+G82/10000)*(3-2)) -> 0.88458915 | T82: =S82/(1+(((G13/H13-1)/(5-3))+H82/10000)*(5-3)) -> 0.81288419 | U82: =T82/(1+(((H13/I13-1)/(10-5))+I82/10000)*(10-5)) -> 0.65974366 | V82: =U82/(1+(((I13/J13-1)/(20-10))+J82/10000)*(20-10)) -> 0.43456477 | W82: =V82/(1+(((J13/K13-1)/(30-20))+K82/10000)*(30-20)) -> 0.28648795
A84: Scenario 7 | C84: 3M | D84: 6M | E84: 1Y | F84: 2Y | G84: 3Y | H84: 5Y | I84: 10Y | J84: 20Y | K84: 30Y | M84: Scenario 7 | O84: 3M | P84: 6M | Q84: 1Y | R84: 2Y | S84: 3Y | T84: 5Y | U84: 10Y | V84: 20Y | W84: 30Y
A85: SOFR | B85: IR | C85: 78.9 | D85: -69.8 | E85: 62.6 | F85: 41.1 | G85: 25 | H85: -12.5 | I85: 6.7 | J85: -4.2 | K85: 2.7 | M85: SOFR | N85: IR | O85: =1/(1+(((1/C8-1)/(0.25-0))+C85/10000)*(0.25-0)) -> 0.98737125 | P85: =O85/(1+(((C8/D8-1)/(0.5-0.25))+D85/10000)*(0.5-0.25)) -> 0.97847604 | Q85: =P85/(1+(((D8/E8-1)/(1-0.5))+E85/10000)*(1-0.5)) -> 0.95463157 | R85: =Q85/(1+(((E8/F8-1)/(2-1))+F85/10000)*(2-1)) -> 0.91045806 | S85: =R85/(1+(((F8/G8-1)/(3-2))+G85/10000)*(3-2)) -> 0.86940352 | T85: =S85/(1+(((G8/H8-1)/(5-3))+H85/10000)*(5-3)) -> 0.79767335 | U85: =T85/(1+(((H8/I8-1)/(10-5))+I85/10000)*(10-5)) -> 0.63446371 | V85: =U85/(1+(((I8/J8-1)/(20-10))+J85/10000)*(20-10)) -> 0.40767742 | W85: =V85/(1+(((J8/K8-1)/(30-20))+K85/10000)*(30-20)) -> 0.26079802
A86: ESTRN | B86: IR | C86: 68.3 | D86: 59.6 | E86: 49.8 | F86: 35 | G86: 20.1 | H86: 10.9 | I86: 5.1 | J86: 2.7 | K86: -1.3 | M86: ESTRN | N86: IR | O86: =1/(1+(((1/C9-1)/(0.25-0))+C86/10000)*(0.25-0)) -> 0.99059264 | P86: =O86/(1+(((C9/D9-1)/(0.5-0.25))+D86/10000)*(0.5-0.25)) -> 0.98146659 | Q86: =P86/(1+(((D9/E9-1)/(1-0.5))+E86/10000)*(1-0.5)) -> 0.96389894 | R86: =Q86/(1+(((E9/F9-1)/(2-1))+F86/10000)*(2-1)) -> 0.93089881 | S86: =R86/(1+(((F9/G9-1)/(3-2))+G86/10000)*(3-2)) -> 0.90005438 | T86: =S86/(1+(((G9/H9-1)/(5-3))+H86/10000)*(5-3)) -> 0.84219696 | U86: =T86/(1+(((H9/I9-1)/(10-5))+I86/10000)*(10-5)) -> 0.711664 | V86: =U86/(1+(((I9/J9-1)/(20-10))+J86/10000)*(20-10)) -> 0.51319602 | W86: =V86/(1+(((J9/K9-1)/(30-20))+K86/10000)*(30-20)) -> 0.37114627
A87: Treasury | B87: Credit | C87: 86.8 | D87: 86.8 | E87: 63.9 | F87: 47.3 | G87: 29.7 | H87: 16.4 | I87: 8.1 | J87: 3.9 | K87: 2.7 | M87: Treasury | N87: Credit | O87: =1/(1+(((1/C10-1)/(0.25-0))+C87/10000)*(0.25-0)) -> 0.98742569 | P87: =O87/(1+(((C10/D10-1)/(0.5-0.25))+D87/10000)*(0.5-0.25)) -> 0.97499032 | Q87: =P87/(1+(((D10/E10-1)/(1-0.5))+E87/10000)*(1-0.5)) -> 0.9516449 | R87: =Q87/(1+(((E10/F10-1)/(2-1))+F87/10000)*(2-1)) -> 0.90797697 | S87: =R87/(1+(((F10/G10-1)/(3-2))+G87/10000)*(3-2)) -> 0.86750958 | T87: =S87/(1+(((G10/H10-1)/(5-3))+H87/10000)*(5-3)) -> 0.79331693 | U87: =T87/(1+(((H10/I10-1)/(10-5))+I87/10000)*(10-5)) -> 0.63379955 | V87: =U87/(1+(((I10/J10-1)/(20-10))+J87/10000)*(20-10)) -> 0.40920332 | W87: =V87/(1+(((J10/K10-1)/(30-20))+K87/10000)*(30-20)) -> 0.26440095
A88: Agency_FNMA | B88: Credit | C88: -150.9 | D88: 126.7 | E88: 115.6 | F88: -77.2 | G88: 54 | H88: 30.6 | I88: -13.2 | J88: 7.5 | K88: 5.2 | M88: Agency_FNMA | N88: Credit | O88: =1/(1+(((1/C11-1)/(0.25-0))+C88/10000)*(0.25-0)) -> 0.99225746 | P88: =O88/(1+(((C11/D11-1)/(0.5-0.25))+D88/10000)*(0.5-0.25)) -> 0.97782229 | Q88: =P88/(1+(((D11/E11-1)/(1-0.5))+E88/10000)*(1-0.5)) -> 0.95011547 | R88: =Q88/(1+(((E11/F11-1)/(2-1))+F88/10000)*(2-1)) -> 0.91372538 | S88: =R88/(1+(((F11/G11-1)/(3-2))+G88/10000)*(3-2)) -> 0.86752173 | T88: =S88/(1+(((G11/H11-1)/(5-3))+H88/10000)*(5-3)) -> 0.78500269 | U88: =T88/(1+(((H11/I11-1)/(10-5))+I88/10000)*(10-5)) -> 0.61994787 | V88: =U88/(1+(((I11/J11-1)/(20-10))+J88/10000)*(20-10)) -> 0.38374648 | W88: =V88/(1+(((J11/K11-1)/(30-20))+K88/10000)*(30-20)) -> 0.23787651
A89: Eur_Govt | B89: Credit | C89: 112.9 | D89: 109.9 | E89: 90.5 | F89: 60.6 | G89: 34.9 | H89: 19.7 | I89: 11.1 | J89: 5.3 | K89: -4 | M89: Eur_Govt | N89: Credit | O89: =1/(1+(((1/C12-1)/(0.25-0))+C89/10000)*(0.25-0)) -> 0.98900649 | P89: =O89/(1+(((C12/D12-1)/(0.5-0.25))+D89/10000)*(0.5-0.25)) -> 0.9781869 | Q89: =P89/(1+(((D12/E12-1)/(1-0.5))+E89/10000)*(1-0.5)) -> 0.95780838 | R89: =Q89/(1+(((E12/F12-1)/(2-1))+F89/10000)*(2-1)) -> 0.92090259 | S89: =R89/(1+(((F12/G12-1)/(3-2))+G89/10000)*(3-2)) -> 0.88734725 | T89: =S89/(1+(((G12/H12-1)/(5-3))+H89/10000)*(5-3)) -> 0.8256437 | U89: =T89/(1+(((H12/I12-1)/(10-5))+I89/10000)*(10-5)) -> 0.68902015 | V89: =U89/(1+(((I12/J12-1)/(20-10))+J89/10000)*(20-10)) -> 0.48615346 | W89: =V89/(1+(((J12/K12-1)/(30-20))+K89/10000)*(30-20)) -> 0.34528159
A90: EURUSD | B90: FX | C90: 51.8 | D90: 51.2 | E90: 41.4 | F90: 28.3 | G90: 20.6 | H90: 11.8 | I90: 6.5 | J90: 3.9 | K90: 2.8 | M90: EURUSD | N90: FX | O90: =1/(1+(((1/C13-1)/(0.25-0))+C90/10000)*(0.25-0)) -> 0.98877329 | P90: =O90/(1+(((C13/D13-1)/(0.5-0.25))+D90/10000)*(0.5-0.25)) -> 0.97766801 | Q90: =P90/(1+(((D13/E13-1)/(1-0.5))+E90/10000)*(1-0.5)) -> 0.95626063 | R90: =Q90/(1+(((E13/F13-1)/(2-1))+F90/10000)*(2-1)) -> 0.91586329 | S90: =R90/(1+(((F13/G13-1)/(3-2))+G90/10000)*(3-2)) -> 0.87755624 | T90: =S90/(1+(((G13/H13-1)/(5-3))+H90/10000)*(5-3)) -> 0.80639172 | U90: =T90/(1+(((H13/I13-1)/(10-5))+I90/10000)*(10-5)) -> 0.65111865 | V90: =U90/(1+(((I13/J13-1)/(20-10))+J90/10000)*(20-10)) -> 0.42885533 | W90: =V90/(1+(((J13/K13-1)/(30-20))+K90/10000)*(30-20)) -> 0.28266808
A92: Scenario 8 | C92: 3M | D92: 6M | E92: 1Y | F92: 2Y | G92: 3Y | H92: 5Y | I92: 10Y | J92: 20Y | K92: 30Y | M92: Scenario 8 | O92: 3M | P92: 6M | Q92: 1Y | R92: 2Y | S92: 3Y | T92: 5Y | U92: 10Y | V92: 20Y | W92: 30Y
A93: SOFR | B93: IR | C93: 86.2 | D93: 75.9 | E93: 66.2 | F93: 44.1 | G93: 28.8 | H93: 14.2 | I93: 6.8 | J93: 4.3 | K93: 2.8 | M93: SOFR | N93: IR | O93: =1/(1+(((1/C8-1)/(0.25-0))+C93/10000)*(0.25-0)) -> 0.98719337 | P93: =O93/(1+(((C8/D8-1)/(0.5-0.25))+D93/10000)*(0.5-0.25)) -> 0.97478111 | Q93: =P93/(1+(((D8/E8-1)/(1-0.5))+E93/10000)*(1-0.5)) -> 0.95085969 | R93: =Q93/(1+(((E8/F8-1)/(2-1))+F93/10000)*(2-1)) -> 0.90660132 | S93: =R93/(1+(((F8/G8-1)/(3-2))+G93/10000)*(3-2)) -> 0.86540666 | T93: =S93/(1+(((G8/H8-1)/(5-3))+H93/10000)*(5-3)) -> 0.79013505 | U93: =T93/(1+(((H8/I8-1)/(10-5))+I93/10000)*(10-5)) -> 0.62844281 | V93: =U93/(1+(((I8/J8-1)/(20-10))+J93/10000)*(20-10)) -> 0.40161515 | W93: =V93/(1+(((J8/K8-1)/(30-20))+K93/10000)*(30-20)) -> 0.25690345
A94: ESTRN | B94: IR | C94: -71.9 | D94: 67.9 | E94: -54.1 | F94: 37.1 | G94: 22 | H94: 11.1 | I94: 6 | J94: 2.9 | K94: 1.5 | M94: ESTRN | N94: IR | O94: =1/(1+(((1/C9-1)/(0.25-0))+C94/10000)*(0.25-0)) -> 0.99404398 | P94: =O94/(1+(((C9/D9-1)/(0.5-0.25))+D94/10000)*(0.5-0.25)) -> 0.9846837 | Q94: =P94/(1+(((D9/E9-1)/(1-0.5))+E94/10000)*(1-0.5)) -> 0.97201771 | R94: =Q94/(1+(((E9/F9-1)/(2-1))+F94/10000)*(2-1)) -> 0.93854929 | S94: =R94/(1+(((F9/G9-1)/(3-2))+G94/10000)*(3-2)) -> 0.90728469 | T94: =S94/(1+(((G9/H9-1)/(5-3))+H94/10000)*(5-3)) -> 0.84893072 | U94: =T94/(1+(((H9/I9-1)/(10-5))+I94/10000)*(10-5)) -> 0.71708141 | V94: =U94/(1+(((I9/J9-1)/(20-10))+J94/10000)*(20-10)) -> 0.51702807 | W94: =V94/(1+(((J9/K9-1)/(30-20))+K94/10000)*(30-20)) -> 0.37316198
A95: Treasury | B95: Credit | C95: 104.3 | D95: 90.6 | E95: 70.8 | F95: 50.1 | G95: 30.7 | H95: 17.3 | I95: -8.6 | J95: 4.3 | K95: 2.9 | M95: Treasury | N95: Credit | O95: =1/(1+(((1/C10-1)/(0.25-0))+C95/10000)*(0.25-0)) -> 0.9869993 | P95: =O95/(1+(((C10/D10-1)/(0.5-0.25))+D95/10000)*(0.5-0.25)) -> 0.9744779 | Q95: =P95/(1+(((D10/E10-1)/(1-0.5))+E95/10000)*(1-0.5)) -> 0.95082457 | R95: =Q95/(1+(((E10/F10-1)/(2-1))+F95/10000)*(2-1)) -> 0.90695199 | S95: =R95/(1+(((F10/G10-1)/(3-2))+G95/10000)*(3-2)) -> 0.8664475 | T95: =S95/(1+(((G10/H10-1)/(5-3))+H95/10000)*(5-3)) -> 0.79221527 | U95: =T95/(1+(((H10/I10-1)/(10-5))+I95/10000)*(10-5)) -> 0.63716998 | V95: =U95/(1+(((I10/J10-1)/(20-10))+J95/10000)*(20-10)) -> 0.41127317 | W95: =V95/(1+(((J10/K10-1)/(30-20))+K95/10000)*(30-20)) -> 0.26570402
A96: Agency_FNMA | B96: Credit | C96: 156.5 | D96: 138 | E96: 122.5 | F96: -88.4 | G96: 58.8 | H96: 32.6 | I96: 14.6 | J96: 9 | K96: 5.4 | M96: Agency_FNMA | N96: Credit | O96: =1/(1+(((1/C11-1)/(0.25-0))+C96/10000)*(0.25-0)) -> 0.98474826 | P96: =O96/(1+(((C11/D11-1)/(0.5-0.25))+D96/10000)*(0.5-0.25)) -> 0.97015226 | Q96: =P96/(1+(((D11/E11-1)/(1-0.5))+E96/10000)*(1-0.5)) -> 0.94234687 | R96: =Q96/(1+(((E11/F11-1)/(2-1))+F96/10000)*(2-1)) -> 0.9072315 | S96: =R96/(1+(((F11/G11-1)/(3-2))+G96/10000)*(3-2)) -> 0.86096386 | T96: =S96/(1+(((G11/H11-1)/(5-3))+H96/10000)*(5-3)) -> 0.77878672 | U96: =T96/(1+(((H11/I11-1)/(10-5))+I96/10000)*(10-5)) -> 0.60836066 | V96: =U96/(1+(((I11/J11-1)/(20-10))+J96/10000)*(20-10)) -> 0.3762247 | W96: =V96/(1+(((J11/K11-1)/(30-20))+K96/10000)*(30-20)) -> 0.23318501
A97: Eur_Govt | B97: Credit | C97: 130 | D97: 119.2 | E97: 93.2 | F97: 66 | G97: 40.7 | H97: 21.4 | I97: 11.2 | J97: 5.8 | K97: 4.5 | M97: Eur_Govt | N97: Credit | O97: =1/(1+(((1/C12-1)/(0.25-0))+C97/10000)*(0.25-0)) -> 0.98858851 | P97: =O97/(1+(((C12/D12-1)/(0.5-0.25))+D97/10000)*(0.5-0.25)) -> 0.97754871 | Q97: =P97/(1+(((D12/E12-1)/(1-0.5))+E97/10000)*(1-0.5)) -> 0.95705696 | R97: =Q97/(1+(((E12/F12-1)/(2-1))+F97/10000)*(2-1)) -> 0.91970263 | S97: =R97/(1+(((F12/G12-1)/(3-2))+G97/10000)*(3-2)) -> 0.88569602 | T97: =S97/(1+(((G12/H12-1)/(5-3))+H97/10000)*(5-3)) -> 0.82384666 | U97: =T97/(1+(((H12/I12-1)/(10-5))+I97/10000)*(10-5)) -> 0.6874918 | V97: =U97/(1+(((I12/J12-1)/(20-10))+J97/10000)*(20-10)) -> 0.48490403 | W97: =V97/(1+(((J12/K12-1)/(30-20))+K97/10000)*(30-20)) -> 0.34232759
A98: EURUSD | B98: FX | C98: 56.4 | D98: 55.7 | E98: -47.7 | F98: 29.9 | G98: 22.5 | H98: 13.2 | I98: 6.8 | J98: 4.5 | K98: 2.9 | M98: EURUSD | N98: FX | O98: =1/(1+(((1/C13-1)/(0.25-0))+C98/10000)*(0.25-0)) -> 0.98866087 | P98: =O98/(1+(((C13/D13-1)/(0.5-0.25))+D98/10000)*(0.5-0.25)) -> 0.97744813 | Q98: =P98/(1+(((D13/E13-1)/(1-0.5))+E98/10000)*(1-0.5)) -> 0.96022971 | R98: =Q98/(1+(((E13/F13-1)/(2-1))+F98/10000)*(2-1)) -> 0.91952379 | S98: =R98/(1+(((F13/G13-1)/(3-2))+G98/10000)*(3-2)) -> 0.88090326 | T98: =S98/(1+(((G13/H13-1)/(5-3))+H98/10000)*(5-3)) -> 0.80925911 | U98: =T98/(1+(((H13/I13-1)/(10-5))+I98/10000)*(10-5)) -> 0.65335478 | V98: =U98/(1+(((I13/J13-1)/(20-10))+J98/10000)*(20-10)) -> 0.43015815 | W98: =V98/(1+(((J13/K13-1)/(30-20))+K98/10000)*(30-20)) -> 0.28350811
A100: Scenario 9 | C100: 3M | D100: 6M | E100: 1Y | F100: 2Y | G100: 3Y | H100: 5Y | I100: 10Y | J100: 20Y | K100: 30Y | M100: Scenario 9 | O100: 3M | P100: 6M | Q100: 1Y | R100: 2Y | S100: 3Y | T100: 5Y | U100: 10Y | V100: 20Y | W100: 30Y
A101: SOFR | B101: IR | C101: 88 | D101: 82.9 | E101: 66.7 | F101: 46.5 | G101: -29.7 | H101: 16 | I101: 7.5 | J101: 4.4 | K101: 3 | M101: SOFR | N101: IR | O101: =1/(1+(((1/C8-1)/(0.25-0))+C101/10000)*(0.25-0)) -> 0.98714951 | P101: =O101/(1+(((C8/D8-1)/(0.5-0.25))+D101/10000)*(0.5-0.25)) -> 0.9745694 | Q101: =P101/(1+(((D8/E8-1)/(1-0.5))+E101/10000)*(1-0.5)) -> 0.95063 | R101: =Q101/(1+(((E8/F8-1)/(2-1))+F101/10000)*(2-1)) -> 0.90617496 | S101: =R101/(1+(((F8/G8-1)/(3-2))+G101/10000)*(3-2)) -> 0.86985711 | T101: =S101/(1+(((G8/H8-1)/(5-3))+H101/10000)*(5-3)) -> 0.79393745 | U101: =T101/(1+(((H8/I8-1)/(10-5))+I101/10000)*(10-5)) -> 0.63129135 | V101: =U101/(1+(((I8/J8-1)/(20-10))+J101/10000)*(20-10)) -> 0.40340978 | W101: =V101/(1+(((J8/K8-1)/(30-20))+K101/10000)*(30-20)) -> 0.25801842
A102: ESTRN | B102: IR | C102: 73.1 | D102: 72.2 | E102: 56.4 | F102: 37.9 | G102: 23.4 | H102: 12 | I102: 6 | J102: 3.1 | K102: 1.6 | M102: ESTRN | N102: IR | O102: =1/(1+(((1/C9-1)/(0.25-0))+C102/10000)*(0.25-0)) -> 0.9904749 | P102: =O102/(1+(((C9/D9-1)/(0.5-0.25))+D102/10000)*(0.5-0.25)) -> 0.98104375 | Q102: =P102/(1+(((D9/E9-1)/(1-0.5))+E102/10000)*(1-0.5)) -> 0.96317151 | R102: =Q102/(1+(((E9/F9-1)/(2-1))+F102/10000)*(2-1)) -> 0.92993585 | S102: =R102/(1+(((F9/G9-1)/(3-2))+G102/10000)*(3-2)) -> 0.89883653 | T102: =S102/(1+(((G9/H9-1)/(5-3))+H102/10000)*(5-3)) -> 0.8408843 | U102: =T102/(1+(((H9/I9-1)/(10-5))+I102/10000)*(10-5)) -> 0.7102847 | V102: =U102/(1+(((I9/J9-1)/(20-10))+J102/10000)*(20-10)) -> 0.51205368 | W102: =V102/(1+(((J9/K9-1)/(30-20))+K102/10000)*(30-20)) -> 0.36954507
A103: Treasury | B103: Credit | C103: 113.3 | D103: 105.1 | E103: 75.2 | F103: 54.9 | G103: 32.3 | H103: 18.5 | I103: 9 | J103: 4.7 | K103: 3.1 | M103: Treasury | N103: Credit | O103: =1/(1+(((1/C10-1)/(0.25-0))+C103/10000)*(0.25-0)) -> 0.98678016 | P103: =O103/(1+(((C10/D10-1)/(0.5-0.25))+D103/10000)*(0.5-0.25)) -> 0.97391298 | Q103: =P103/(1+(((D10/E10-1)/(1-0.5))+E103/10000)*(1-0.5)) -> 0.95006942 | R103: =Q103/(1+(((E10/F10-1)/(2-1))+F103/10000)*(2-1)) -> 0.90581695 | S103: =R103/(1+(((F10/G10-1)/(3-2))+G103/10000)*(3-2)) -> 0.86523089 | T103: =S103/(1+(((G10/H10-1)/(5-3))+H103/10000)*(5-3)) -> 0.79092934 | U103: =T103/(1+(((H10/I10-1)/(10-5))+I103/10000)*(10-5)) -> 0.63166495 | V103: =U103/(1+(((I10/J10-1)/(20-10))+J103/10000)*(20-10)) -> 0.40761461 | W103: =V103/(1+(((J10/K10-1)/(30-20))+K103/10000)*(30-20)) -> 0.26330637
A104: Agency_FNMA | B104: Credit | C104: 172.5 | D104: 156.5 | E104: 132.6 | F104: 93.8 | G104: 61.2 | H104: -34.7 | I104: 15.1 | J104: -8.9 | K104: 6.2 | M104: Agency_FNMA | N104: Credit | O104: =1/(1+(((1/C11-1)/(0.25-0))+C104/10000)*(0.25-0)) -> 0.98436052 | P104: =O104/(1+(((C11/D11-1)/(0.5-0.25))+D104/10000)*(0.5-0.25)) -> 0.96932859 | Q104: =P104/(1+(((D11/E11-1)/(1-0.5))+E104/10000)*(1-0.5)) -> 0.94108519 | R104: =Q104/(1+(((E11/F11-1)/(2-1))+F104/10000)*(2-1)) -> 0.89039831 | S104: =R104/(1+(((F11/G11-1)/(3-2))+G104/10000)*(3-2)) -> 0.84479673 | T104: =S104/(1+(((G11/H11-1)/(5-3))+H104/10000)*(5-3)) -> 0.77358127 | U104: =T104/(1+(((H11/I11-1)/(10-5))+I104/10000)*(10-5)) -> 0.60417636 | V104: =U104/(1+(((I11/J11-1)/(20-10))+J104/10000)*(20-10)) -> 0.37781941 | W104: =V104/(1+(((J11/K11-1)/(30-20))+K104/10000)*(30-20)) -> 0.23405735
A105: Eur_Govt | B105: Credit | C105: 139 | D105: 127.4 | E105: 103.5 | F105: 71.5 | G105: -42.4 | H105: -24.2 | I105: 12.9 | J105: 6.3 | K105: 4.8 | M105: Eur_Govt | N105: Credit | O105: =1/(1+(((1/C12-1)/(0.25-0))+C105/10000)*(0.25-0)) -> 0.98836867 | P105: =O105/(1+(((C12/D12-1)/(0.5-0.25))+D105/10000)*(0.5-0.25)) -> 0.97713324 | Q105: =P105/(1+(((D12/E12-1)/(1-0.5))+E105/10000)*(1-0.5)) -> 0.9561681 | R105: =Q105/(1+(((E12/F12-1)/(2-1))+F105/10000)*(2-1)) -> 0.91836308 | S105: =R105/(1+(((F12/G12-1)/(3-2))+G105/10000)*(3-2)) -> 0.89154076 | T105: =S105/(1+(((G12/H12-1)/(5-3))+H105/10000)*(5-3)) -> 0.83637837 | U105: =T105/(1+(((H12/I12-1)/(10-5))+I105/10000)*(10-5)) -> 0.69745466 | V105: =U105/(1+(((I12/J12-1)/(20-10))+J105/10000)*(20-10)) -> 0.49175765 | W105: =V105/(1+(((J12/K12-1)/(30-20))+K105/10000)*(30-20)) -> 0.34709252
A106: EURUSD | B106: FX | C106: 60.7 | D106: 55.6 | E106: 49 | F106: 34.5 | G106: 23.9 | H106: 13.3 | I106: 7.3 | J106: 4.6 | K106: -3 | M106: EURUSD | N106: FX | O106: =1/(1+(((1/C13-1)/(0.25-0))+C106/10000)*(0.25-0)) -> 0.98855581 | P106: =O106/(1+(((C13/D13-1)/(0.5-0.25))+D106/10000)*(0.5-0.25)) -> 0.97734667 | Q106: =P106/(1+(((D13/E13-1)/(1-0.5))+E106/10000)*(1-0.5)) -> 0.95559115 | R106: =Q106/(1+(((E13/F13-1)/(2-1))+F106/10000)*(2-1)) -> 0.91467895 | S106: =R106/(1+(((F13/G13-1)/(3-2))+G106/10000)*(3-2)) -> 0.8761444 | T106: =S106/(1+(((G13/H13-1)/(5-3))+H106/10000)*(5-3)) -> 0.8048725 | U106: =T106/(1+(((H13/I13-1)/(10-5))+I106/10000)*(10-5)) -> 0.64968212 | V106: =U106/(1+(((I13/J13-1)/(20-10))+J106/10000)*(20-10)) -> 0.42771197 | W106: =V106/(1+(((J13/K13-1)/(30-20))+K106/10000)*(30-20)) -> 0.28299634
A108: Scenario 10 | C108: 3M | D108: 6M | E108: 1Y | F108: 2Y | G108: 3Y | H108: 5Y | I108: 10Y | J108: 20Y | K108: 30Y | M108: Scenario 10 | O108: 3M | P108: 6M | Q108: 1Y | R108: 2Y | S108: 3Y | T108: 5Y | U108: 10Y | V108: 20Y | W108: 30Y
A109: SOFR | B109: IR | C109: 102.1 | D109: 89 | E109: 71.7 | F109: 48.6 | G109: 31.7 | H109: 15.9 | I109: 8.4 | J109: 5.2 | K109: 3.4 | M109: SOFR | N109: IR | O109: =1/(1+(((1/C8-1)/(0.25-0))+C109/10000)*(0.25-0)) -> 0.98680613 | P109: =O109/(1+(((C8/D8-1)/(0.5-0.25))+D109/10000)*(0.5-0.25)) -> 0.97408374 | Q109: =P109/(1+(((D8/E8-1)/(1-0.5))+E109/10000)*(1-0.5)) -> 0.94992462 | R109: =Q109/(1+(((E8/F8-1)/(2-1))+F109/10000)*(2-1)) -> 0.90532134 | S109: =R109/(1+(((F8/G8-1)/(3-2))+G109/10000)*(3-2)) -> 0.86394568 | T109: =S109/(1+(((G8/H8-1)/(5-3))+H109/10000)*(5-3)) -> 0.78855635 | U109: =T109/(1+(((H8/I8-1)/(10-5))+I109/10000)*(10-5)) -> 0.62678836 | V109: =U109/(1+(((I8/J8-1)/(20-10))+J109/10000)*(20-10)) -> 0.4003276 | W109: =V109/(1+(((J8/K8-1)/(30-20))+K109/10000)*(30-20)) -> 0.25598159
A110: ESTRN | B110: IR | C110: -81.8 | D110: 74.2 | E110: -65.4 | F110: 40.7 | G110: 25.8 | H110: 12.7 | I110: 6.6 | J110: 3.3 | K110: -1.6 | M110: ESTRN | N110: IR | O110: =1/(1+(((1/C9-1)/(0.25-0))+C110/10000)*(0.25-0)) -> 0.9942886 | P110: =O110/(1+(((C9/D9-1)/(0.5-0.25))+D110/10000)*(0.5-0.25)) -> 0.98477237 | Q110: =P110/(1+(((D9/E9-1)/(1-0.5))+E110/10000)*(1-0.5)) -> 0.97264772 | R110: =Q110/(1+(((E9/F9-1)/(2-1))+F110/10000)*(2-1)) -> 0.93883126 | S110: =R110/(1+(((F9/G9-1)/(3-2))+G110/10000)*(3-2)) -> 0.90722402 | T110: =S110/(1+(((G9/H9-1)/(5-3))+H110/10000)*(5-3)) -> 0.84861985 | U110: =T110/(1+(((H9/I9-1)/(10-5))+I110/10000)*(10-5)) -> 0.71663723 | V110: =U110/(1+(((I9/J9-1)/(20-10))+J110/10000)*(20-10)) -> 0.51655882 | W110: =V110/(1+(((J9/K9-1)/(30-20))+K110/10000)*(30-20)) -> 0.37365933
A111: Treasury | B111: Credit | C111: 119.4 | D111: 108.9 | E111: -83.3 | F111: 59.4 | G111: 35 | H111: 19 | I111: 9.6 | J111: 5.1 | K111: 3.2 | M111: Treasury | N111: Credit | O111: =1/(1+(((1/C10-1)/(0.25-0))+C111/10000)*(0.25-0)) -> 0.98663169 | P111: =O111/(1+(((C10/D10-1)/(0.5-0.25))+D111/10000)*(0.5-0.25)) -> 0.97367515 | Q111: =P111/(1+(((D10/E10-1)/(1-0.5))+E111/10000)*(1-0.5)) -> 0.9572378 | R111: =Q111/(1+(((E10/F10-1)/(2-1))+F111/10000)*(2-1)) -> 0.91226004 | S111: =R111/(1+(((F10/G10-1)/(3-2))+G111/10000)*(3-2)) -> 0.87116062 | T111: =S111/(1+(((G10/H10-1)/(5-3))+H111/10000)*(5-3)) -> 0.79627706 | U111: =T111/(1+(((H10/I10-1)/(10-5))+I111/10000)*(10-5)) -> 0.63578351 | V111: =U111/(1+(((I10/J10-1)/(20-10))+J111/10000)*(20-10)) -> 0.41016645 | W111: =V111/(1+(((J10/K10-1)/(30-20))+K111/10000)*(30-20)) -> 0.26493767
A112: Agency_FNMA | B112: Credit | C112: 172.7 | D112: -159.3 | E112: 136.9 | F112: -100.5 | G112: 62.9 | H112: 35.4 | I112: -16 | J112: 10.1 | K112: 6.8 | M112: Agency_FNMA | N112: Credit | O112: =1/(1+(((1/C11-1)/(0.25-0))+C112/10000)*(0.25-0)) -> 0.98435568 | P112: =O112/(1+(((C11/D11-1)/(0.5-0.25))+D112/10000)*(0.5-0.25)) -> 0.97691882 | Q112: =P112/(1+(((D11/E11-1)/(1-0.5))+E112/10000)*(1-0.5)) -> 0.94825632 | R112: =Q112/(1+(((E11/F11-1)/(2-1))+F112/10000)*(2-1)) -> 0.91398546 | S112: =R112/(1+(((F11/G11-1)/(3-2))+G112/10000)*(3-2)) -> 0.86703602 | T112: =S112/(1+(((G11/H11-1)/(5-3))+H112/10000)*(5-3)) -> 0.78388223 | U112: =T112/(1+(((H11/I11-1)/(10-5))+I112/10000)*(10-5)) -> 0.61974821 | V112: =U112/(1+(((I11/J11-1)/(20-10))+J112/10000)*(20-10)) -> 0.38300649 | W112: =V112/(1+(((J11/K11-1)/(30-20))+K112/10000)*(30-20)) -> 0.23718257
A113: Eur_Govt | B113: Credit | C113: 152.5 | D113: 127 | E113: -111.9 | F113: 76.3 | G113: 46.3 | H113: -25.9 | I113: 13.2 | J113: 6.7 | K113: -5.1 | M113: Eur_Govt | N113: Credit | O113: =1/(1+(((1/C12-1)/(0.25-0))+C113/10000)*(0.25-0)) -> 0.98803908 | P113: =O113/(1+(((C12/D12-1)/(0.5-0.25))+D113/10000)*(0.5-0.25)) -> 0.97681706 | Q113: =P113/(1+(((D12/E12-1)/(1-0.5))+E113/10000)*(1-0.5)) -> 0.96603972 | R113: =Q113/(1+(((E12/F12-1)/(2-1))+F113/10000)*(2-1)) -> 0.92741683 | S113: =R113/(1+(((F12/G12-1)/(3-2))+G113/10000)*(3-2)) -> 0.89264359 | T113: =S113/(1+(((G12/H12-1)/(5-3))+H113/10000)*(5-3)) -> 0.83768015 | U113: =T113/(1+(((H12/I12-1)/(10-5))+I113/10000)*(10-5)) -> 0.69845285 | V113: =U113/(1+(((I12/J12-1)/(20-10))+J113/10000)*(20-10)) -> 0.49232259 | W113: =V113/(1+(((J12/K12-1)/(30-20))+K113/10000)*(30-20)) -> 0.3499365
A114: EURUSD | B114: FX | C114: 63.3 | D114: 60.1 | E114: 53.5 | F114: 35.7 | G114: 24.8 | H114: -15 | I114: 8.4 | J114: 5 | K114: 3.4 | M114: EURUSD | N114: FX | O114: =1/(1+(((1/C13-1)/(0.25-0))+C114/10000)*(0.25-0)) -> 0.98849229 | P114: =O114/(1+(((C13/D13-1)/(0.5-0.25))+D114/10000)*(0.5-0.25)) -> 0.97717519 | Q114: =P114/(1+(((D13/E13-1)/(1-0.5))+E114/10000)*(1-0.5)) -> 0.95521334 | R114: =Q114/(1+(((E13/F13-1)/(2-1))+F114/10000)*(2-1)) -> 0.91421231 | S114: =R114/(1+(((F13/G13-1)/(3-2))+G114/10000)*(3-2)) -> 0.87562193 | T114: =S114/(1+(((G13/H13-1)/(5-3))+H114/10000)*(5-3)) -> 0.80859689 | U114: =T114/(1+(((H13/I13-1)/(10-5))+I114/10000)*(10-5)) -> 0.65239877 | V114: =U114/(1+(((I13/J13-1)/(20-10))+J114/10000)*(20-10)) -> 0.42938738 | W114: =V114/(1+(((J13/K13-1)/(30-20))+K114/10000)*(30-20)) -> 0.28290689
A116: Section 3 (left, blue) = raw hardcoded shock inputs for the stress period. Section 4 (right, black) = shocked discount factors, computed with the same cascading bootstrap formula illustrated in Section 2, sitting directly across from the shocks that drive them.

Sheet Curves_Current
A1: Curve Objects — CURRENT PERIOD Shocks + Shocked Curves (normal/recent market conditions)
A2: Same base curves as the Curves tab (Section 1) — only the shock magnitude differs. Current-period shocks are ~30% the size of the 2008 stress-period shocks on the Curves tab, representing normal/recent market conditions rather than a crisis. Used for the 'Full Set - Current Period' and 'Reduced Set - Current Period' cases on FullReduced_NPV_Engine.
A4: SECTION A - CURRENT PERIOD SHOCK VECTORS (bps), 10 Scenarios | M4: SECTION B - CURRENT PERIOD SHOCKED CURVES (Discount Factors)
A6: Scenario 1 | C6: 3M | D6: 6M | E6: 1Y | F6: 2Y | G6: 3Y | H6: 5Y | I6: 10Y | J6: 20Y | K6: 30Y | M6: Scenario 1 | O6: 3M | P6: 6M | Q6: 1Y | R6: 2Y | S6: 3Y | T6: 5Y | U6: 10Y | V6: 20Y | W6: 30Y
A7: SOFR | B7: IR | C7: 12.12 | D7: 10.86 | E7: 8.58 | F7: -5.6 | G7: 3.64 | H7: 2.16 | I7: 0.88 | J7: 0.54 | K7: 0.38 | M7: SOFR | N7: IR | O7: =1/(1+(((1/Curves!C8-1)/(0.25-0))+C7/10000)*(0.25-0)) -> 0.98900154 | P7: =O7/(1+(((Curves!C8/Curves!D8-1)/(0.5-0.25))+D7/10000)*(0.5-0.25)) -> 0.978137 | Q7: =P7/(1+(((Curves!D8/Curves!E8-1)/(1-0.5))+E7/10000)*(1-0.5)) -> 0.95682219 | R7: =Q7/(1+(((Curves!E8/Curves!F8-1)/(2-1))+F7/10000)*(2-1)) -> 0.91662989 | S7: =R7/(1+(((Curves!F8/Curves!G8-1)/(3-2))+G7/10000)*(3-2)) -> 0.87708602 | T7: =S7/(1+(((Curves!G8/Curves!H8-1)/(5-3))+H7/10000)*(5-3)) -> 0.80256304 | U7: =T7/(1+(((Curves!H8/Curves!I8-1)/(10-5))+I7/10000)*(10-5)) -> 0.63983389 | V7: =U7/(1+(((Curves!I8/Curves!J8-1)/(20-10))+J7/10000)*(20-10)) -> 0.40987968 | W7: =V7/(1+(((Curves!J8/Curves!K8-1)/(30-20))+K7/10000)*(30-20)) -> 0.26259657
A8: ESTRN | B8: IR | C8: 9.86 | D8: -9.57 | E8: 6.86 | F8: 4.36 | G8: 3.18 | H8: 1.68 | I8: 0.86 | J8: 0.37 | K8: -0.18 | M8: ESTRN | N8: IR | O8: =1/(1+(((1/Curves!C9-1)/(0.25-0))+C8/10000)*(0.25-0)) -> 0.99202836 | P8: =O8/(1+(((Curves!C9/Curves!D9-1)/(0.5-0.25))+D8/10000)*(0.5-0.25)) -> 0.98457597 | Q8: =P8/(1+(((Curves!D9/Curves!E9-1)/(1-0.5))+E8/10000)*(1-0.5)) -> 0.96899586 | R8: =Q8/(1+(((Curves!E9/Curves!F9-1)/(2-1))+F8/10000)*(2-1)) -> 0.93859865 | S8: =R8/(1+(((Curves!F9/Curves!G9-1)/(3-2))+G8/10000)*(3-2)) -> 0.90898614 | T8: =S8/(1+(((Curves!G9/Curves!H9-1)/(5-3))+H8/10000)*(5-3)) -> 0.8520247 | U8: =T8/(1+(((Curves!H9/Curves!I9-1)/(10-5))+I8/10000)*(10-5)) -> 0.72126061 | V8: =U8/(1+(((Curves!I9/Curves!J9-1)/(20-10))+J8/10000)*(20-10)) -> 0.52099172 | W8: =V8/(1+(((Curves!J9/Curves!K9-1)/(30-20))+K8/10000)*(30-20)) -> 0.37647922
A9: Treasury | B9: Credit | C9: 12.97 | D9: 13.61 | E9: 8.83 | F9: -6.3 | G9: 4.46 | H9: 2.24 | I9: 1.22 | J9: 0.66 | K9: 0.37 | M9: Treasury | N9: Credit | O9: =1/(1+(((1/Curves!C10-1)/(0.25-0))+C9/10000)*(0.25-0)) -> 0.9892286 | P9: =O9/(1+(((Curves!C10/Curves!D10-1)/(0.5-0.25))+D9/10000)*(0.5-0.25)) -> 0.97853846 | Q9: =P9/(1+(((Curves!D10/Curves!E10-1)/(1-0.5))+E9/10000)*(1-0.5)) -> 0.95768192 | R9: =Q9/(1+(((Curves!E10/Curves!F10-1)/(2-1))+F9/10000)*(2-1)) -> 0.91843388 | S9: =R9/(1+(((Curves!F10/Curves!G10-1)/(3-2))+G9/10000)*(3-2)) -> 0.87962166 | T9: =S9/(1+(((Curves!G10/Curves!H10-1)/(5-3))+H9/10000)*(5-3)) -> 0.80648175 | U9: =T9/(1+(((Curves!H10/Curves!I10-1)/(10-5))+I9/10000)*(10-5)) -> 0.64609289 | V9: =U9/(1+(((Curves!I10/Curves!J10-1)/(20-10))+J9/10000)*(20-10)) -> 0.41801476 | W9: =V9/(1+(((Curves!J10/Curves!K10-1)/(30-20))+K9/10000)*(30-20)) -> 0.27050158
A10: Agency_FNMA | B10: Credit | C10: -20.65 | D10: 19.75 | E10: 16.2 | F10: -12.65 | G10: 6.97 | H10: 4.75 | I10: 2.12 | J10: 1.25 | K10: 0.85 | M10: Agency_FNMA | N10: Credit | O10: =1/(1+(((1/Curves!C11-1)/(0.25-0))+C10/10000)*(0.25-0)) -> 0.98906176 | P10: =O10/(1+(((Curves!C11/Curves!D11-1)/(0.5-0.25))+D10/10000)*(0.5-0.25)) -> 0.97724799 | Q10: =P10/(1+(((Curves!D11/Curves!E11-1)/(1-0.5))+E10/10000)*(1-0.5)) -> 0.95416527 | R10: =Q10/(1+(((Curves!E11/Curves!F11-1)/(2-1))+F10/10000)*(2-1)) -> 0.91195884 | S10: =R10/(1+(((Curves!F11/Curves!G11-1)/(3-2))+G10/10000)*(3-2)) -> 0.86972802 | T10: =S10/(1+(((Curves!G11/Curves!H11-1)/(5-3))+H10/10000)*(5-3)) -> 0.79069818 | U10: =T10/(1+(((Curves!H11/Curves!I11-1)/(10-5))+I10/10000)*(10-5)) -> 0.62069101 | V10: =U10/(1+(((Curves!I11/Curves!J11-1)/(20-10))+J10/10000)*(20-10)) -> 0.38569865 | W10: =V10/(1+(((Curves!J11/Curves!K11-1)/(30-20))+K10/10000)*(30-20)) -> 0.23973306
A11: Eur_Govt | B11: Credit | C11: -19.24 | D11: -15.73 | E11: -13.57 | F11: 9.42 | G11: -4.93 | H11: 2.98 | I11: 1.77 | J11: 0.85 | K11: 0.63 | M11: Eur_Govt | N11: Credit | O11: =1/(1+(((1/Curves!C12-1)/(0.25-0))+C11/10000)*(0.25-0)) -> 0.99224835 | P11: =O11/(1+(((Curves!C12/Curves!D12-1)/(0.5-0.25))+D11/10000)*(0.5-0.25)) -> 0.98445139 | Q11: =P11/(1+(((Curves!D12/Curves!E12-1)/(1-0.5))+E11/10000)*(1-0.5)) -> 0.96887888 | R11: =Q11/(1+(((Curves!E12/Curves!F12-1)/(2-1))+F11/10000)*(2-1)) -> 0.93615315 | S11: =R11/(1+(((Curves!F12/Curves!G12-1)/(3-2))+G11/10000)*(3-2)) -> 0.90551737 | T11: =S11/(1+(((Curves!G12/Curves!H12-1)/(5-3))+H11/10000)*(5-3)) -> 0.84518008 | U11: =T11/(1+(((Curves!H12/Curves!I12-1)/(10-5))+I11/10000)*(10-5)) -> 0.70808034 | V11: =U11/(1+(((Curves!I12/Curves!J12-1)/(20-10))+J11/10000)*(20-10)) -> 0.50117539 | W11: =V11/(1+(((Curves!J12/Curves!K12-1)/(30-20))+K11/10000)*(30-20)) -> 0.35478398
A12: EURUSD | B12: FX | C12: 7.83 | D12: 6.65 | E12: 6.3 | F12: 4.58 | G12: 2.79 | H12: 1.86 | I12: 0.96 | J12: 0.56 | K12: 0.35 | M12: EURUSD | N12: FX | O12: =1/(1+(((1/Curves!C13-1)/(0.25-0))+C12/10000)*(0.25-0)) -> 0.98984917 | P12: =O12/(1+(((Curves!C13/Curves!D13-1)/(0.5-0.25))+D12/10000)*(0.5-0.25)) -> 0.97981081 | Q12: =P12/(1+(((Curves!D13/Curves!E13-1)/(1-0.5))+E12/10000)*(1-0.5)) -> 0.96000443 | R12: =Q12/(1+(((Curves!E13/Curves!F13-1)/(2-1))+F12/10000)*(2-1)) -> 0.92154248 | S12: =R12/(1+(((Curves!F13/Curves!G13-1)/(3-2))+G12/10000)*(3-2)) -> 0.88450731 | T12: =S12/(1+(((Curves!G13/Curves!H13-1)/(5-3))+H12/10000)*(5-3)) -> 0.8142666 | U12: =T12/(1+(((Curves!H13/Curves!I13-1)/(10-5))+I12/10000)*(10-5)) -> 0.65895102 | V12: =U12/(1+(((Curves!I13/Curves!J13-1)/(20-10))+J12/10000)*(20-10)) -> 0.43497095 | W12: =V12/(1+(((Curves!J13/Curves!K13-1)/(30-20))+K12/10000)*(30-20)) -> 0.28716275
A14: Scenario 2 | C14: 3M | D14: 6M | E14: 1Y | F14: 2Y | G14: 3Y | H14: 5Y | I14: 10Y | J14: 20Y | K14: 30Y | M14: Scenario 2 | O14: 3M | P14: 6M | Q14: 1Y | R14: 2Y | S14: 3Y | T14: 5Y | U14: 10Y | V14: 20Y | W14: 30Y
A15: SOFR | B15: IR | C15: 13.1 | D15: 12.55 | E15: 10.02 | F15: -7.49 | G15: 5.08 | H15: 2.25 | I15: 1.11 | J15: 0.65 | K15: 0.44 | M15: SOFR | N15: IR | O15: =1/(1+(((1/Curves!C8-1)/(0.25-0))+C15/10000)*(0.25-0)) -> 0.98897758 | P15: =O15/(1+(((Curves!C8/Curves!D8-1)/(0.5-0.25))+D15/10000)*(0.5-0.25)) -> 0.97807243 | Q15: =P15/(1+(((Curves!D8/Curves!E8-1)/(1-0.5))+E15/10000)*(1-0.5)) -> 0.95669164 | R15: =Q15/(1+(((Curves!E8/Curves!F8-1)/(2-1))+F15/10000)*(2-1)) -> 0.9166708 | S15: =R15/(1+(((Curves!F8/Curves!G8-1)/(3-2))+G15/10000)*(3-2)) -> 0.87700433 | T15: =S15/(1+(((Curves!G8/Curves!H8-1)/(5-3))+H15/10000)*(5-3)) -> 0.80247507 | U15: =T15/(1+(((Curves!H8/Curves!I8-1)/(10-5))+I15/10000)*(10-5)) -> 0.63970511 | V15: =U15/(1+(((Curves!I8/Curves!J8-1)/(20-10))+J15/10000)*(20-10)) -> 0.4097683 | W15: =V15/(1+(((Curves!J8/Curves!K8-1)/(30-20))+K15/10000)*(30-20)) -> 0.26251512
A16: ESTRN | B16: IR | C16: 11.68 | D16: 11.38 | E16: 8.82 | F16: -5.37 | G16: 3.66 | H16: -1.82 | I16: 0.94 | J16: 0.47 | K16: 0.25 | M16: ESTRN | N16: IR | O16: =1/(1+(((1/Curves!C9-1)/(0.25-0))+C16/10000)*(0.25-0)) -> 0.99198358 | P16: =O16/(1+(((Curves!C9/Curves!D9-1)/(0.5-0.25))+D16/10000)*(0.5-0.25)) -> 0.98402002 | Q16: =P16/(1+(((Curves!D9/Curves!E9-1)/(1-0.5))+E16/10000)*(1-0.5)) -> 0.96835531 | R16: =Q16/(1+(((Curves!E9/Curves!F9-1)/(2-1))+F16/10000)*(2-1)) -> 0.93886305 | S16: =R16/(1+(((Curves!F9/Curves!G9-1)/(3-2))+G16/10000)*(3-2)) -> 0.90919993 | T16: =S16/(1+(((Curves!G9/Curves!H9-1)/(5-3))+H16/10000)*(5-3)) -> 0.85278464 | U16: =T16/(1+(((Curves!H9/Curves!I9-1)/(10-5))+I16/10000)*(10-5)) -> 0.72187947 | V16: =U16/(1+(((Curves!I9/Curves!J9-1)/(20-10))+J16/10000)*(20-10)) -> 0.52140108 | W16: =V16/(1+(((Curves!J9/Curves!K9-1)/(30-20))+K16/10000)*(30-20)) -> 0.37665799
A17: Treasury | B17: Credit | C17: -16.81 | D17: 14.57 | E17: 11.02 | F17: 8.02 | G17: 4.9 | H17: 2.51 | I17: 1.29 | J17: 0.66 | K17: 0.46 | M17: Treasury | N17: Credit | O17: =1/(1+(((1/Curves!C10-1)/(0.25-0))+C17/10000)*(0.25-0)) -> 0.98995768 | P17: =O17/(1+(((Curves!C10/Curves!D10-1)/(0.5-0.25))+D17/10000)*(0.5-0.25)) -> 0.97923642 | Q17: =P17/(1+(((Curves!D10/Curves!E10-1)/(1-0.5))+E17/10000)*(1-0.5)) -> 0.95826231 | R17: =Q17/(1+(((Curves!E10/Curves!F10-1)/(2-1))+F17/10000)*(2-1)) -> 0.91773015 | S17: =R17/(1+(((Curves!F10/Curves!G10-1)/(3-2))+G17/10000)*(3-2)) -> 0.87891063 | T17: =S17/(1+(((Curves!G10/Curves!H10-1)/(5-3))+H17/10000)*(5-3)) -> 0.80578995 | U17: =T17/(1+(((Curves!H10/Curves!I10-1)/(10-5))+I17/10000)*(10-5)) -> 0.64552057 | V17: =U17/(1+(((Curves!I10/Curves!J10-1)/(20-10))+J17/10000)*(20-10)) -> 0.41764448 | W17: =V17/(1+(((Curves!J10/Curves!K10-1)/(30-20))+K17/10000)*(30-20)) -> 0.27024622
A18: Agency_FNMA | B18: Credit | C18: 27.49 | D18: 21.95 | E18: 18.27 | F18: 14.01 | G18: 9.77 | H18: 5.46 | I18: 2.33 | J18: 1.41 | K18: 1.01 | M18: Agency_FNMA | N18: Credit | O18: =1/(1+(((1/Curves!C11-1)/(0.25-0))+C18/10000)*(0.25-0)) -> 0.98788584 | P18: =O18/(1+(((Curves!C11/Curves!D11-1)/(0.5-0.25))+D18/10000)*(0.5-0.25)) -> 0.97603308 | Q18: =P18/(1+(((Curves!D11/Curves!E11-1)/(1-0.5))+E18/10000)*(1-0.5)) -> 0.95288276 | R18: =Q18/(1+(((Curves!E11/Curves!F11-1)/(2-1))+F18/10000)*(2-1)) -> 0.90841835 | S18: =R18/(1+(((Curves!F11/Curves!G11-1)/(3-2))+G18/10000)*(3-2)) -> 0.86612019 | T18: =S18/(1+(((Curves!G11/Curves!H11-1)/(5-3))+H18/10000)*(5-3)) -> 0.78731654 | U18: =T18/(1+(((Curves!H11/Curves!I11-1)/(10-5))+I18/10000)*(10-5)) -> 0.61798552 | V18: =U18/(1+(((Curves!I11/Curves!J11-1)/(20-10))+J18/10000)*(20-10)) -> 0.38397928 | W18: =V18/(1+(((Curves!J11/Curves!K11-1)/(30-20))+K18/10000)*(30-20)) -> 0.23864064
A19: Eur_Govt | B19: Credit | C19: 19.01 | D19: 17.11 | E19: 15.88 | F19: 10.29 | G19: 6.32 | H19: 3.68 | I19: 1.94 | J19: 0.9 | K19: 0.69 | M19: Eur_Govt | N19: Credit | O19: =1/(1+(((1/Curves!C12-1)/(0.25-0))+C19/10000)*(0.25-0)) -> 0.99130776 | P19: =O19/(1+(((Curves!C12/Curves!D12-1)/(0.5-0.25))+D19/10000)*(0.5-0.25)) -> 0.98271772 | Q19: =P19/(1+(((Curves!D12/Curves!E12-1)/(1-0.5))+E19/10000)*(1-0.5)) -> 0.96577303 | R19: =Q19/(1+(((Curves!E12/Curves!F12-1)/(2-1))+F19/10000)*(2-1)) -> 0.93307377 | S19: =R19/(1+(((Curves!F12/Curves!G12-1)/(3-2))+G19/10000)*(3-2)) -> 0.9015577 | T19: =S19/(1+(((Curves!G12/Curves!H12-1)/(5-3))+H19/10000)*(5-3)) -> 0.84137431 | U19: =T19/(1+(((Curves!H12/Curves!I12-1)/(10-5))+I19/10000)*(10-5)) -> 0.70484173 | V19: =U19/(1+(((Curves!I12/Curves!J12-1)/(20-10))+J19/10000)*(20-10)) -> 0.49886546 | W19: =V19/(1+(((Curves!J12/Curves!K12-1)/(30-20))+K19/10000)*(30-20)) -> 0.35313378
A20: EURUSD | B20: FX | C20: 8.38 | D20: 8.31 | E20: 7.3 | F20: 4.77 | G20: 3.29 | H20: 1.88 | I20: -1.15 | J20: 0.63 | K20: 0.43 | M20: EURUSD | N20: FX | O20: =1/(1+(((1/Curves!C13-1)/(0.25-0))+C20/10000)*(0.25-0)) -> 0.98983569 | P20: =O20/(1+(((Curves!C13/Curves!D13-1)/(0.5-0.25))+D20/10000)*(0.5-0.25)) -> 0.97975723 | Q20: =P20/(1+(((Curves!D13/Curves!E13-1)/(1-0.5))+E20/10000)*(1-0.5)) -> 0.9599049 | R20: =Q20/(1+(((Curves!E13/Curves!F13-1)/(2-1))+F20/10000)*(2-1)) -> 0.92143014 | S20: =R20/(1+(((Curves!F13/Curves!G13-1)/(3-2))+G20/10000)*(3-2)) -> 0.88435704 | T20: =S20/(1+(((Curves!G13/Curves!H13-1)/(5-3))+H20/10000)*(5-3)) -> 0.81412527 | U20: =T20/(1+(((Curves!H13/Curves!I13-1)/(10-5))+I20/10000)*(10-5)) -> 0.65939962 | V20: =U20/(1+(((Curves!I13/Curves!J13-1)/(20-10))+J20/10000)*(20-10)) -> 0.43524696 | W20: =V20/(1+(((Curves!J13/Curves!K13-1)/(30-20))+K20/10000)*(30-20)) -> 0.28732979
A22: Scenario 3 | C22: 3M | D22: 6M | E22: 1Y | F22: 2Y | G22: 3Y | H22: 5Y | I22: 10Y | J22: 20Y | K22: 30Y | M22: Scenario 3 | O22: 3M | P22: 6M | Q22: 1Y | R22: 2Y | S22: 3Y | T22: 5Y | U22: 10Y | V22: 20Y | W22: 30Y
A23: SOFR | B23: IR | C23: 14.57 | D23: -14.93 | E23: 11 | F23: 8.22 | G23: -5.24 | H23: 2.7 | I23: -1.3 | J23: -0.83 | K23: 0.48 | M23: SOFR | N23: IR | O23: =1/(1+(((1/Curves!C8-1)/(0.25-0))+C23/10000)*(0.25-0)) -> 0.98894163 | P23: =O23/(1+(((Curves!C8/Curves!D8-1)/(0.5-0.25))+D23/10000)*(0.5-0.25)) -> 0.97870184 | Q23: =P23/(1+(((Curves!D8/Curves!E8-1)/(1-0.5))+E23/10000)*(1-0.5)) -> 0.95726141 | R23: =Q23/(1+(((Curves!E8/Curves!F8-1)/(2-1))+F23/10000)*(2-1)) -> 0.91583814 | S23: =R23/(1+(((Curves!F8/Curves!G8-1)/(3-2))+G23/10000)*(3-2)) -> 0.87707367 | T23: =S23/(1+(((Curves!G8/Curves!H8-1)/(5-3))+H23/10000)*(5-3)) -> 0.80247244 | U23: =T23/(1+(((Curves!H8/Curves!I8-1)/(10-5))+I23/10000)*(10-5)) -> 0.64031809 | V23: =U23/(1+(((Curves!I8/Curves!J8-1)/(20-10))+J23/10000)*(20-10)) -> 0.41055017 | W23: =V23/(1+(((Curves!J8/Curves!K8-1)/(30-20))+K23/10000)*(30-20)) -> 0.26300928
A24: ESTRN | B24: IR | C24: 12.53 | D24: 11.15 | E24: 9.15 | F24: 6.46 | G24: 4.04 | H24: -2.11 | I24: -0.99 | J24: -0.56 | K24: -0.24 | M24: ESTRN | N24: IR | O24: =1/(1+(((1/Curves!C9-1)/(0.25-0))+C24/10000)*(0.25-0)) -> 0.99196267 | P24: =O24/(1+(((Curves!C9/Curves!D9-1)/(0.5-0.25))+D24/10000)*(0.5-0.25)) -> 0.98400489 | Q24: =P24/(1+(((Curves!D9/Curves!E9-1)/(1-0.5))+E24/10000)*(1-0.5)) -> 0.9683247 | R24: =Q24/(1+(((Curves!E9/Curves!F9-1)/(2-1))+F24/10000)*(2-1)) -> 0.93775779 | S24: =R24/(1+(((Curves!F9/Curves!G9-1)/(3-2))+G24/10000)*(3-2)) -> 0.90809618 | T24: =S24/(1+(((Curves!G9/Curves!H9-1)/(5-3))+H24/10000)*(5-3)) -> 0.85179571 | U24: =T24/(1+(((Curves!H9/Curves!I9-1)/(10-5))+I24/10000)*(10-5)) -> 0.72163183 | V24: =U24/(1+(((Curves!I9/Curves!J9-1)/(20-10))+J24/10000)*(20-10)) -> 0.52161026 | W24: =V24/(1+(((Curves!J9/Curves!K9-1)/(30-20))+K24/10000)*(30-20)) -> 0.37694253
A25: Treasury | B25: Credit | C25: 17.96 | D25: 18.23 | E25: 14.38 | F25: 9.02 | G25: 6.28 | H25: 3.35 | I25: 1.44 | J25: -0.76 | K25: 0.49 | M25: Treasury | N25: Credit | O25: =1/(1+(((1/Curves!C10-1)/(0.25-0))+C25/10000)*(0.25-0)) -> 0.98910653 | P25: =O25/(1+(((Curves!C10/Curves!D10-1)/(0.5-0.25))+D25/10000)*(0.5-0.25)) -> 0.97830594 | Q25: =P25/(1+(((Curves!D10/Curves!E10-1)/(1-0.5))+E25/10000)*(1-0.5)) -> 0.9571944 | R25: =Q25/(1+(((Curves!E10/Curves!F10-1)/(2-1))+F25/10000)*(2-1)) -> 0.91661963 | S25: =R25/(1+(((Curves!F10/Curves!G10-1)/(3-2))+G25/10000)*(3-2)) -> 0.87773108 | T25: =S25/(1+(((Curves!G10/Curves!H10-1)/(5-3))+H25/10000)*(5-3)) -> 0.80458461 | U25: =T25/(1+(((Curves!H10/Curves!I10-1)/(10-5))+I25/10000)*(10-5)) -> 0.64451624 | V25: =U25/(1+(((Curves!I10/Curves!J10-1)/(20-10))+J25/10000)*(20-10)) -> 0.41737814 | W25: =V25/(1+(((Curves!J10/Curves!K10-1)/(30-20))+K25/10000)*(30-20)) -> 0.27006864
A26: Agency_FNMA | B26: Credit | C26: 30.38 | D26: -26.47 | E26: -21.02 | F26: -17.01 | G26: 11.17 | H26: 6.11 | I26: 2.8 | J26: 1.48 | K26: 1.06 | M26: Agency_FNMA | N26: Credit | O26: =1/(1+(((1/Curves!C11-1)/(0.25-0))+C26/10000)*(0.25-0)) -> 0.98781534 | P26: =O26/(1+(((Curves!C11/Curves!D11-1)/(0.5-0.25))+D26/10000)*(0.5-0.25)) -> 0.97713205 | Q26: =P26/(1+(((Curves!D11/Curves!E11-1)/(1-0.5))+E26/10000)*(1-0.5)) -> 0.95578878 | R26: =Q26/(1+(((Curves!E11/Curves!F11-1)/(2-1))+F26/10000)*(2-1)) -> 0.91389136 | S26: =R26/(1+(((Curves!F11/Curves!G11-1)/(3-2))+G26/10000)*(3-2)) -> 0.87122208 | T26: =S26/(1+(((Curves!G11/Curves!H11-1)/(5-3))+H26/10000)*(5-3)) -> 0.79186066 | U26: =T26/(1+(((Curves!H11/Curves!I11-1)/(10-5))+I26/10000)*(10-5)) -> 0.62143769 | V26: =U26/(1+(((Curves!I11/Curves!J11-1)/(20-10))+J26/10000)*(20-10)) -> 0.38610746 | W26: =V26/(1+(((Curves!J11/Curves!K11-1)/(30-20))+K26/10000)*(30-20)) -> 0.23995583
A27: Eur_Govt | B27: Credit | C27: 24.9 | D27: -20.85 | E27: 17.83 | F27: -11.02 | G27: 6.89 | H27: 4.14 | I27: -1.98 | J27: 1.03 | K27: 0.78 | M27: Eur_Govt | N27: Credit | O27: =1/(1+(((1/Curves!C12-1)/(0.25-0))+C27/10000)*(0.25-0)) -> 0.99116308 | P27: =O27/(1+(((Curves!C12/Curves!D12-1)/(0.5-0.25))+D27/10000)*(0.5-0.25)) -> 0.98349954 | Q27: =P27/(1+(((Curves!D12/Curves!E12-1)/(1-0.5))+E27/10000)*(1-0.5)) -> 0.96644877 | R27: =Q27/(1+(((Curves!E12/Curves!F12-1)/(2-1))+F27/10000)*(2-1)) -> 0.935653 | S27: =R27/(1+(((Curves!F12/Curves!G12-1)/(3-2))+G27/10000)*(3-2)) -> 0.90400003 | T27: =S27/(1+(((Curves!G12/Curves!H12-1)/(5-3))+H27/10000)*(5-3)) -> 0.84358117 | U27: =T27/(1+(((Curves!H12/Curves!I12-1)/(10-5))+I27/10000)*(10-5)) -> 0.70785273 | V27: =U27/(1+(((Curves!I12/Curves!J12-1)/(20-10))+J27/10000)*(20-10)) -> 0.50095046 | W27: =V27/(1+(((Curves!J12/Curves!K12-1)/(30-20))+K27/10000)*(30-20)) -> 0.3545871
A28: EURUSD | B28: FX | C28: 11.35 | D28: 10.56 | E28: 8.56 | F28: 5.41 | G28: 3.64 | H28: 2.25 | I28: 1.21 | J28: 0.79 | K28: 0.57 | M28: EURUSD | N28: FX | O28: =1/(1+(((1/Curves!C13-1)/(0.25-0))+C28/10000)*(0.25-0)) -> 0.98976295 | P28: =O28/(1+(((Curves!C13/Curves!D13-1)/(0.5-0.25))+D28/10000)*(0.5-0.25)) -> 0.97963068 | Q28: =P28/(1+(((Curves!D13/Curves!E13-1)/(1-0.5))+E28/10000)*(1-0.5)) -> 0.95972168 | R28: =Q28/(1+(((Curves!E13/Curves!F13-1)/(2-1))+F28/10000)*(2-1)) -> 0.92119767 | S28: =R28/(1+(((Curves!F13/Curves!G13-1)/(3-2))+G28/10000)*(3-2)) -> 0.88410423 | T28: =S28/(1+(((Curves!G13/Curves!H13-1)/(5-3))+H28/10000)*(5-3)) -> 0.81383709 | U28: =T28/(1+(((Curves!H13/Curves!I13-1)/(10-5))+I28/10000)*(10-5)) -> 0.65853682 | V28: =U28/(1+(((Curves!I13/Curves!J13-1)/(20-10))+J28/10000)*(20-10)) -> 0.43463155 | W28: =V28/(1+(((Curves!J13/Curves!K13-1)/(30-20))+K28/10000)*(30-20)) -> 0.28689702
A30: Scenario 4 | C30: 3M | D30: 6M | E30: 1Y | F30: 2Y | G30: 3Y | H30: 5Y | I30: 10Y | J30: 20Y | K30: 30Y | M30: Scenario 4 | O30: 3M | P30: 6M | Q30: 1Y | R30: 2Y | S30: 3Y | T30: 5Y | U30: 10Y | V30: 20Y | W30: 30Y
A31: SOFR | B31: IR | C31: -19.01 | D31: -17.29 | E31: 14.24 | F31: -8.2 | G31: 6.25 | H31: 2.94 | I31: 1.38 | J31: 0.88 | K31: 0.61 | M31: SOFR | N31: IR | O31: =1/(1+(((1/Curves!C8-1)/(0.25-0))+C31/10000)*(0.25-0)) -> 0.98976335 | P31: =O31/(1+(((Curves!C8/Curves!D8-1)/(0.5-0.25))+D31/10000)*(0.5-0.25)) -> 0.97957224 | Q31: =P31/(1+(((Curves!D8/Curves!E8-1)/(1-0.5))+E31/10000)*(1-0.5)) -> 0.95796096 | R31: =Q31/(1+(((Curves!E8/Curves!F8-1)/(2-1))+F31/10000)*(2-1)) -> 0.91794947 | S31: =R31/(1+(((Curves!F8/Curves!G8-1)/(3-2))+G31/10000)*(3-2)) -> 0.87812937 | T31: =S31/(1+(((Curves!G8/Curves!H8-1)/(5-3))+H31/10000)*(5-3)) -> 0.80340306 | U31: =T31/(1+(((Curves!H8/Curves!I8-1)/(10-5))+I31/10000)*(10-5)) -> 0.64037595 | V31: =U31/(1+(((Curves!I8/Curves!J8-1)/(20-10))+J31/10000)*(20-10)) -> 0.41013759 | W31: =V31/(1+(((Curves!J8/Curves!K8-1)/(30-20))+K31/10000)*(30-20)) -> 0.26272309
A32: ESTRN | B32: IR | C32: 15.96 | D32: -12.95 | E32: 10.93 | F32: 6.93 | G32: 4.41 | H32: 2.31 | I32: 1.14 | J32: 0.57 | K32: 0.28 | M32: ESTRN | N32: IR | O32: =1/(1+(((1/Curves!C9-1)/(0.25-0))+C32/10000)*(0.25-0)) -> 0.9918783 | P32: =O32/(1+(((Curves!C9/Curves!D9-1)/(0.5-0.25))+D32/10000)*(0.5-0.25)) -> 0.98450961 | Q32: =P32/(1+(((Curves!D9/Curves!E9-1)/(1-0.5))+E32/10000)*(1-0.5)) -> 0.96873653 | R32: =Q32/(1+(((Curves!E9/Curves!F9-1)/(2-1))+F32/10000)*(2-1)) -> 0.93811392 | S32: =R32/(1+(((Curves!F9/Curves!G9-1)/(3-2))+G32/10000)*(3-2)) -> 0.90840849 | T32: =S32/(1+(((Curves!G9/Curves!H9-1)/(5-3))+H32/10000)*(5-3)) -> 0.8513827 | U32: =T32/(1+(((Curves!H9/Curves!I9-1)/(10-5))+I32/10000)*(10-5)) -> 0.72063174 | V32: =U32/(1+(((Curves!I9/Curves!J9-1)/(20-10))+J32/10000)*(20-10)) -> 0.52046227 | W32: =V32/(1+(((Curves!J9/Curves!K9-1)/(30-20))+K32/10000)*(30-20)) -> 0.37597165
A33: Treasury | B33: Credit | C33: 22.27 | D33: 19.36 | E33: 14.63 | F33: 11.18 | G33: 6.16 | H33: 3.78 | I33: -1.81 | J33: 0.94 | K33: 0.57 | M33: Treasury | N33: Credit | O33: =1/(1+(((1/Curves!C10-1)/(0.25-0))+C33/10000)*(0.25-0)) -> 0.98900113 | P33: =O33/(1+(((Curves!C10/Curves!D10-1)/(0.5-0.25))+D33/10000)*(0.5-0.25)) -> 0.97817436 | Q33: =P33/(1+(((Curves!D10/Curves!E10-1)/(1-0.5))+E33/10000)*(1-0.5)) -> 0.95705395 | R33: =Q33/(1+(((Curves!E10/Curves!F10-1)/(2-1))+F33/10000)*(2-1)) -> 0.9162956 | S33: =R33/(1+(((Curves!F10/Curves!G10-1)/(3-2))+G33/10000)*(3-2)) -> 0.87743088 | T33: =S33/(1+(((Curves!G10/Curves!H10-1)/(5-3))+H33/10000)*(5-3)) -> 0.80424603 | U33: =T33/(1+(((Curves!H10/Curves!I10-1)/(10-5))+I33/10000)*(10-5)) -> 0.64508474 | V33: =U33/(1+(((Curves!I10/Curves!J10-1)/(20-10))+J33/10000)*(20-10)) -> 0.4172869 | W33: =V33/(1+(((Curves!J10/Curves!K10-1)/(30-20))+K33/10000)*(30-20)) -> 0.26999563
A34: Agency_FNMA | B34: Credit | C34: 32.63 | D34: 31.59 | E34: 27.09 | F34: 16.43 | G34: 11.1 | H34: 6.25 | I34: -3.01 | J34: 1.76 | K34: 1.17 | M34: Agency_FNMA | N34: Credit | O34: =1/(1+(((1/Curves!C11-1)/(0.25-0))+C34/10000)*(0.25-0)) -> 0.98776045 | P34: =O34/(1+(((Curves!C11/Curves!D11-1)/(0.5-0.25))+D34/10000)*(0.5-0.25)) -> 0.97567688 | Q34: =P34/(1+(((Curves!D11/Curves!E11-1)/(1-0.5))+E34/10000)*(1-0.5)) -> 0.95212508 | R34: =Q34/(1+(((Curves!E11/Curves!F11-1)/(2-1))+F34/10000)*(2-1)) -> 0.90748666 | S34: =R34/(1+(((Curves!F11/Curves!G11-1)/(3-2))+G34/10000)*(3-2)) -> 0.86512218 | T34: =S34/(1+(((Curves!G11/Curves!H11-1)/(5-3))+H34/10000)*(5-3)) -> 0.78629641 | U34: =T34/(1+(((Curves!H11/Curves!I11-1)/(10-5))+I34/10000)*(10-5)) -> 0.61848097 | V34: =U34/(1+(((Curves!I11/Curves!J11-1)/(20-10))+J34/10000)*(20-10)) -> 0.38420357 | W34: =V34/(1+(((Curves!J11/Curves!K11-1)/(30-20))+K34/10000)*(30-20)) -> 0.23875629
A35: Eur_Govt | B35: Credit | C35: 27.61 | D35: 23.34 | E35: 19.38 | F35: -13.99 | G35: 8.3 | H35: 4.12 | I35: 2.53 | J35: 1.27 | K35: 0.92 | M35: Eur_Govt | N35: Credit | O35: =1/(1+(((1/Curves!C12-1)/(0.25-0))+C35/10000)*(0.25-0)) -> 0.99109652 | P35: =O35/(1+(((Curves!C12/Curves!D12-1)/(0.5-0.25))+D35/10000)*(0.5-0.25)) -> 0.98235664 | Q35: =P35/(1+(((Curves!D12/Curves!E12-1)/(1-0.5))+E35/10000)*(1-0.5)) -> 0.96525217 | R35: =Q35/(1+(((Curves!E12/Curves!F12-1)/(2-1))+F35/10000)*(2-1)) -> 0.93476331 | S35: =R35/(1+(((Curves!F12/Curves!G12-1)/(3-2))+G35/10000)*(3-2)) -> 0.90301742 | T35: =S35/(1+(((Curves!G12/Curves!H12-1)/(5-3))+H35/10000)*(5-3)) -> 0.84266737 | U35: =T35/(1+(((Curves!H12/Curves!I12-1)/(10-5))+I35/10000)*(10-5)) -> 0.70575055 | V35: =U35/(1+(((Curves!I12/Curves!J12-1)/(20-10))+J35/10000)*(20-10)) -> 0.49937792 | W35: =V35/(1+(((Curves!J12/Curves!K12-1)/(30-20))+K35/10000)*(30-20)) -> 0.35343899
A36: EURUSD | B36: FX | C36: 11.12 | D36: 10.6 | E36: 10.14 | F36: 6.2 | G36: 4.74 | H36: 2.53 | I36: 1.43 | J36: 0.86 | K36: 0.6 | M36: EURUSD | N36: FX | O36: =1/(1+(((1/Curves!C13-1)/(0.25-0))+C36/10000)*(0.25-0)) -> 0.98976858 | P36: =O36/(1+(((Curves!C13/Curves!D13-1)/(0.5-0.25))+D36/10000)*(0.5-0.25)) -> 0.97963529 | Q36: =P36/(1+(((Curves!D13/Curves!E13-1)/(1-0.5))+E36/10000)*(1-0.5)) -> 0.95965192 | R36: =Q36/(1+(((Curves!E13/Curves!F13-1)/(2-1))+F36/10000)*(2-1)) -> 0.92106087 | S36: =R36/(1+(((Curves!F13/Curves!G13-1)/(3-2))+G36/10000)*(3-2)) -> 0.88387962 | T36: =S36/(1+(((Curves!G13/Curves!H13-1)/(5-3))+H36/10000)*(5-3)) -> 0.81358839 | U36: =T36/(1+(((Curves!H13/Curves!I13-1)/(10-5))+I36/10000)*(10-5)) -> 0.65827699 | V36: =U36/(1+(((Curves!I13/Curves!J13-1)/(20-10))+J36/10000)*(20-10)) -> 0.43444 | W36: =V36/(1+(((Curves!J13/Curves!K13-1)/(30-20))+K36/10000)*(30-20)) -> 0.28676489
A38: Scenario 5 | C38: 3M | D38: 6M | E38: 1Y | F38: 2Y | G38: 3Y | H38: 5Y | I38: 10Y | J38: 20Y | K38: 30Y | M38: Scenario 5 | O38: 3M | P38: 6M | Q38: 1Y | R38: 2Y | S38: 3Y | T38: 5Y | U38: 10Y | V38: 20Y | W38: 30Y
A39: SOFR | B39: IR | C39: 20.8 | D39: 18.09 | E39: 14.02 | F39: 10.51 | G39: 7.07 | H39: 3.13 | I39: 1.64 | J39: 1.05 | K39: 0.66 | M39: SOFR | N39: IR | O39: =1/(1+(((1/Curves!C8-1)/(0.25-0))+C39/10000)*(0.25-0)) -> 0.98878933 | P39: =O39/(1+(((Curves!C8/Curves!D8-1)/(0.5-0.25))+D39/10000)*(0.5-0.25)) -> 0.97775234 | Q39: =P39/(1+(((Curves!D8/Curves!E8-1)/(1-0.5))+E39/10000)*(1-0.5)) -> 0.95619149 | R39: =Q39/(1+(((Curves!E8/Curves!F8-1)/(2-1))+F39/10000)*(2-1)) -> 0.91461414 | S39: =R39/(1+(((Curves!F8/Curves!G8-1)/(3-2))+G39/10000)*(3-2)) -> 0.8748701 | T39: =S39/(1+(((Curves!G8/Curves!H8-1)/(5-3))+H39/10000)*(5-3)) -> 0.80039331 | U39: =T39/(1+(((Curves!H8/Curves!I8-1)/(10-5))+I39/10000)*(10-5)) -> 0.63791084 | V39: =U39/(1+(((Curves!I8/Curves!J8-1)/(20-10))+J39/10000)*(20-10)) -> 0.4085143 | W39: =V39/(1+(((Curves!J8/Curves!K8-1)/(30-20))+K39/10000)*(30-20)) -> 0.26167488
A40: ESTRN | B40: IR | C40: 16.07 | D40: 15.03 | E40: 12.95 | F40: 8.58 | G40: 4.65 | H40: 2.65 | I40: 1.41 | J40: 0.7 | K40: 0.35 | M40: ESTRN | N40: IR | O40: =1/(1+(((1/Curves!C9-1)/(0.25-0))+C40/10000)*(0.25-0)) -> 0.99187559 | P40: =O40/(1+(((Curves!C9/Curves!D9-1)/(0.5-0.25))+D40/10000)*(0.5-0.25)) -> 0.98382385 | Q40: =P40/(1+(((Curves!D9/Curves!E9-1)/(1-0.5))+E40/10000)*(1-0.5)) -> 0.96796556 | R40: =Q40/(1+(((Curves!E9/Curves!F9-1)/(2-1))+F40/10000)*(2-1)) -> 0.93721757 | S40: =R40/(1+(((Curves!F9/Curves!G9-1)/(3-2))+G40/10000)*(3-2)) -> 0.90751943 | T40: =S40/(1+(((Curves!G9/Curves!H9-1)/(5-3))+H40/10000)*(5-3)) -> 0.85049525 | U40: =T40/(1+(((Curves!H9/Curves!I9-1)/(10-5))+I40/10000)*(10-5)) -> 0.71979833 | V40: =U40/(1+(((Curves!I9/Curves!J9-1)/(20-10))+J40/10000)*(20-10)) -> 0.51981155 | W40: =V40/(1+(((Curves!J9/Curves!K9-1)/(30-20))+K40/10000)*(30-20)) -> 0.3754826
A41: Treasury | B41: Credit | C41: 22.73 | D41: -21.78 | E41: 17.02 | F41: 11.96 | G41: 7.2 | H41: 3.97 | I41: 2.1 | J41: 1.03 | K41: 0.68 | M41: Treasury | N41: Credit | O41: =1/(1+(((1/Curves!C10-1)/(0.25-0))+C41/10000)*(0.25-0)) -> 0.98898988 | P41: =O41/(1+(((Curves!C10/Curves!D10-1)/(0.5-0.25))+D41/10000)*(0.5-0.25)) -> 0.97915927 | Q41: =P41/(1+(((Curves!D10/Curves!E10-1)/(1-0.5))+E41/10000)*(1-0.5)) -> 0.9579056 | R41: =Q41/(1+(((Curves!E10/Curves!F10-1)/(2-1))+F41/10000)*(2-1)) -> 0.9170425 | S41: =R41/(1+(((Curves!F10/Curves!G10-1)/(3-2))+G41/10000)*(3-2)) -> 0.87805865 | T41: =S41/(1+(((Curves!G10/Curves!H10-1)/(5-3))+H41/10000)*(5-3)) -> 0.80479341 | U41: =T41/(1+(((Curves!H10/Curves!I10-1)/(10-5))+I41/10000)*(10-5)) -> 0.64451313 | V41: =U41/(1+(((Curves!I10/Curves!J10-1)/(20-10))+J41/10000)*(20-10)) -> 0.41689287 | W41: =V41/(1+(((Curves!J10/Curves!K10-1)/(30-20))+K41/10000)*(30-20)) -> 0.26972148
A42: Agency_FNMA | B42: Credit | C42: 36.17 | D42: 31.56 | E42: 26.02 | F42: 20.58 | G42: 12.85 | H42: 7.78 | I42: -3.17 | J42: 2.03 | K42: 1.36 | M42: Agency_FNMA | N42: Credit | O42: =1/(1+(((1/Curves!C11-1)/(0.25-0))+C42/10000)*(0.25-0)) -> 0.98767412 | P42: =O42/(1+(((Curves!C11/Curves!D11-1)/(0.5-0.25))+D42/10000)*(0.5-0.25)) -> 0.97559232 | Q42: =P42/(1+(((Curves!D11/Curves!E11-1)/(1-0.5))+E42/10000)*(1-0.5)) -> 0.95209227 | R42: =Q42/(1+(((Curves!E11/Curves!F11-1)/(2-1))+F42/10000)*(2-1)) -> 0.90709659 | S42: =R42/(1+(((Curves!F11/Curves!G11-1)/(3-2))+G42/10000)*(3-2)) -> 0.86460608 | T42: =S42/(1+(((Curves!G11/Curves!H11-1)/(5-3))+H42/10000)*(5-3)) -> 0.78560884 | U42: =T42/(1+(((Curves!H11/Curves!I11-1)/(10-5))+I42/10000)*(10-5)) -> 0.61797903 | V42: =U42/(1+(((Curves!I11/Curves!J11-1)/(20-10))+J42/10000)*(20-10)) -> 0.38382738 | W42: =V42/(1+(((Curves!J11/Curves!K11-1)/(30-20))+K42/10000)*(30-20)) -> 0.23849436
A43: Eur_Govt | B43: Credit | C43: 28.02 | D43: 27.14 | E43: 21.19 | F43: 13.78 | G43: -9.13 | H43: -4.65 | I43: 2.56 | J43: 1.41 | K43: 1.02 | M43: Eur_Govt | N43: Credit | O43: =1/(1+(((1/Curves!C12-1)/(0.25-0))+C43/10000)*(0.25-0)) -> 0.99108645 | P43: =O43/(1+(((Curves!C12/Curves!D12-1)/(0.5-0.25))+D43/10000)*(0.5-0.25)) -> 0.98225417 | Q43: =P43/(1+(((Curves!D12/Curves!E12-1)/(1-0.5))+E43/10000)*(1-0.5)) -> 0.96506567 | R43: =Q43/(1+(((Curves!E12/Curves!F12-1)/(2-1))+F43/10000)*(2-1)) -> 0.93207608 | S43: =R43/(1+(((Curves!F12/Curves!G12-1)/(3-2))+G43/10000)*(3-2)) -> 0.90194014 | T43: =S43/(1+(((Curves!G12/Curves!H12-1)/(5-3))+H43/10000)*(5-3)) -> 0.84304196 | U43: =T43/(1+(((Curves!H12/Curves!I12-1)/(10-5))+I43/10000)*(10-5)) -> 0.70605541 | V43: =U43/(1+(((Curves!I12/Curves!J12-1)/(20-10))+J43/10000)*(20-10)) -> 0.49954415 | W43: =V43/(1+(((Curves!J12/Curves!K12-1)/(30-20))+K43/10000)*(30-20)) -> 0.35353162
A44: EURUSD | B44: FX | C44: -12.66 | D44: 12.1 | E44: 10.69 | F44: 7.43 | G44: -4.91 | H44: 2.77 | I44: 1.65 | J44: 1.01 | K44: 0.67 | M44: EURUSD | N44: FX | O44: =1/(1+(((1/Curves!C13-1)/(0.25-0))+C44/10000)*(0.25-0)) -> 0.99035132 | P44: =O44/(1+(((Curves!C13/Curves!D13-1)/(0.5-0.25))+D44/10000)*(0.5-0.25)) -> 0.98017568 | Q44: =P44/(1+(((Curves!D13/Curves!E13-1)/(1-0.5))+E44/10000)*(1-0.5)) -> 0.96015543 | R44: =Q44/(1+(((Curves!E13/Curves!F13-1)/(2-1))+F44/10000)*(2-1)) -> 0.92143535 | S44: =R44/(1+(((Curves!F13/Curves!G13-1)/(3-2))+G44/10000)*(3-2)) -> 0.88505859 | T44: =S44/(1+(((Curves!G13/Curves!H13-1)/(5-3))+H44/10000)*(5-3)) -> 0.81463761 | U44: =T44/(1+(((Curves!H13/Curves!I13-1)/(10-5))+I44/10000)*(10-5)) -> 0.65906725 | V44: =U44/(1+(((Curves!I13/Curves!J13-1)/(20-10))+J44/10000)*(20-10)) -> 0.43491849 | W44: =V44/(1+(((Curves!J13/Curves!K13-1)/(30-20))+K44/10000)*(30-20)) -> 0.28706747
A46: Scenario 6 | C46: 3M | D46: 6M | E46: 1Y | F46: 2Y | G46: 3Y | H46: 5Y | I46: 10Y | J46: 20Y | K46: 30Y | M46: Scenario 6 | O46: 3M | P46: 6M | Q46: 1Y | R46: 2Y | S46: 3Y | T46: 5Y | U46: 10Y | V46: 20Y | W46: 30Y
A47: SOFR | B47: IR | C47: 21.12 | D47: 19.21 | E47: 15.49 | F47: 11.04 | G47: 7.31 | H47: -3.52 | I47: 1.73 | J47: 1.11 | K47: 0.75 | M47: SOFR | N47: IR | O47: =1/(1+(((1/Curves!C8-1)/(0.25-0))+C47/10000)*(0.25-0)) -> 0.98878151 | P47: =O47/(1+(((Curves!C8/Curves!D8-1)/(0.5-0.25))+D47/10000)*(0.5-0.25)) -> 0.97771753 | Q47: =P47/(1+(((Curves!D8/Curves!E8-1)/(1-0.5))+E47/10000)*(1-0.5)) -> 0.95608873 | R47: =Q47/(1+(((Curves!E8/Curves!F8-1)/(2-1))+F47/10000)*(2-1)) -> 0.91446948 | S47: =R47/(1+(((Curves!F8/Curves!G8-1)/(3-2))+G47/10000)*(3-2)) -> 0.87471165 | T47: =S47/(1+(((Curves!G8/Curves!H8-1)/(5-3))+H47/10000)*(5-3)) -> 0.80122326 | U47: =T47/(1+(((Curves!H8/Curves!I8-1)/(10-5))+I47/10000)*(10-5)) -> 0.63854941 | V47: =U47/(1+(((Curves!I8/Curves!J8-1)/(20-10))+J47/10000)*(20-10)) -> 0.40890752 | W47: =V47/(1+(((Curves!J8/Curves!K8-1)/(30-20))+K47/10000)*(30-20)) -> 0.26191166
A48: ESTRN | B48: IR | C48: 18.98 | D48: 16.37 | E48: -14.4 | F48: 8.84 | G48: 5.72 | H48: 2.86 | I48: 1.42 | J48: 0.76 | K48: 0.38 | M48: ESTRN | N48: IR | O48: =1/(1+(((1/Curves!C9-1)/(0.25-0))+C48/10000)*(0.25-0)) -> 0.99180403 | P48: =O48/(1+(((Curves!C9/Curves!D9-1)/(0.5-0.25))+D48/10000)*(0.5-0.25)) -> 0.98372018 | Q48: =P48/(1+(((Curves!D9/Curves!E9-1)/(1-0.5))+E48/10000)*(1-0.5)) -> 0.96916753 | R48: =Q48/(1+(((Curves!E9/Curves!F9-1)/(2-1))+F48/10000)*(2-1)) -> 0.93835774 | S48: =R48/(1+(((Curves!F9/Curves!G9-1)/(3-2))+G48/10000)*(3-2)) -> 0.90852934 | T48: =S48/(1+(((Curves!G9/Curves!H9-1)/(5-3))+H48/10000)*(5-3)) -> 0.85140819 | U48: =T48/(1+(((Curves!H9/Curves!I9-1)/(10-5))+I48/10000)*(10-5)) -> 0.72056792 | V48: =U48/(1+(((Curves!I9/Curves!J9-1)/(20-10))+J48/10000)*(20-10)) -> 0.52034478 | W48: =V48/(1+(((Curves!J9/Curves!K9-1)/(30-20))+K48/10000)*(30-20)) -> 0.37585963
A49: Treasury | B49: Credit | C49: 25.73 | D49: 23.39 | E49: -17.37 | F49: 12.72 | G49: 8.16 | H49: 4.5 | I49: 2.06 | J49: 1.04 | K49: 0.76 | M49: Treasury | N49: Credit | O49: =1/(1+(((1/Curves!C10-1)/(0.25-0))+C49/10000)*(0.25-0)) -> 0.98891653 | P49: =O49/(1+(((Curves!C10/Curves!D10-1)/(0.5-0.25))+D49/10000)*(0.5-0.25)) -> 0.97799323 | Q49: =P49/(1+(((Curves!D10/Curves!E10-1)/(1-0.5))+E49/10000)*(1-0.5)) -> 0.95837703 | R49: =Q49/(1+(((Curves!E10/Curves!F10-1)/(2-1))+F49/10000)*(2-1)) -> 0.91742706 | S49: =R49/(1+(((Curves!F10/Curves!G10-1)/(3-2))+G49/10000)*(3-2)) -> 0.87834613 | T49: =S49/(1+(((Curves!G10/Curves!H10-1)/(5-3))+H49/10000)*(5-3)) -> 0.80497869 | U49: =T49/(1+(((Curves!H10/Curves!I10-1)/(10-5))+I49/10000)*(10-5)) -> 0.64467184 | V49: =U49/(1+(((Curves!I10/Curves!J10-1)/(20-10))+J49/10000)*(20-10)) -> 0.41699284 | W49: =V49/(1+(((Curves!J10/Curves!K10-1)/(30-20))+K49/10000)*(30-20)) -> 0.26977219
A50: Agency_FNMA | B50: Credit | C50: 38.02 | D50: 36.31 | E50: 32.04 | F50: 20.84 | G50: 15 | H50: 7.79 | I50: 3.87 | J50: 2.13 | K50: 1.48 | M50: Agency_FNMA | N50: Credit | O50: =1/(1+(((1/Curves!C11-1)/(0.25-0))+C50/10000)*(0.25-0)) -> 0.987629 | P50: =O50/(1+(((Curves!C11/Curves!D11-1)/(0.5-0.25))+D50/10000)*(0.5-0.25)) -> 0.97543334 | Q50: =P50/(1+(((Curves!D11/Curves!E11-1)/(1-0.5))+E50/10000)*(1-0.5)) -> 0.95165757 | R50: =Q50/(1+(((Curves!E11/Curves!F11-1)/(2-1))+F50/10000)*(2-1)) -> 0.90665997 | S50: =R50/(1+(((Curves!F11/Curves!G11-1)/(3-2))+G50/10000)*(3-2)) -> 0.86401286 | T50: =S50/(1+(((Curves!G11/Curves!H11-1)/(5-3))+H50/10000)*(5-3)) -> 0.78506839 | U50: =T50/(1+(((Curves!H11/Curves!I11-1)/(10-5))+I50/10000)*(10-5)) -> 0.61584867 | V50: =U50/(1+(((Curves!I11/Curves!J11-1)/(20-10))+J50/10000)*(20-10)) -> 0.38248046 | W50: =V50/(1+(((Curves!J11/Curves!K11-1)/(30-20))+K50/10000)*(30-20)) -> 0.23763972
A51: Eur_Govt | B51: Credit | C51: 33.13 | D51: 29.25 | E51: -24.3 | F51: 15.91 | G51: 9.67 | H51: 5.37 | I51: -2.83 | J51: 1.5 | K51: 1.06 | M51: Eur_Govt | N51: Credit | O51: =1/(1+(((1/Curves!C12-1)/(0.25-0))+C51/10000)*(0.25-0)) -> 0.99096099 | P51: =O51/(1+(((Curves!C12/Curves!D12-1)/(0.5-0.25))+D51/10000)*(0.5-0.25)) -> 0.98207847 | Q51: =P51/(1+(((Curves!D12/Curves!E12-1)/(1-0.5))+E51/10000)*(1-0.5)) -> 0.96705412 | R51: =Q51/(1+(((Curves!E12/Curves!F12-1)/(2-1))+F51/10000)*(2-1)) -> 0.93380446 | S51: =R51/(1+(((Curves!F12/Curves!G12-1)/(3-2))+G51/10000)*(3-2)) -> 0.90197176 | T51: =S51/(1+(((Curves!G12/Curves!H12-1)/(5-3))+H51/10000)*(5-3)) -> 0.84149528 | U51: =T51/(1+(((Curves!H12/Curves!I12-1)/(10-5))+I51/10000)*(10-5)) -> 0.70635435 | V51: =U51/(1+(((Curves!I12/Curves!J12-1)/(20-10))+J51/10000)*(20-10)) -> 0.49972384 | W51: =V51/(1+(((Curves!J12/Curves!K12-1)/(30-20))+K51/10000)*(30-20)) -> 0.35364877
A52: EURUSD | B52: FX | C52: 14.82 | D52: -13.53 | E52: 11.16 | F52: 8.21 | G52: 5.41 | H52: 3.42 | I52: 1.71 | J52: 1.06 | K52: 0.75 | M52: EURUSD | N52: FX | O52: =1/(1+(((1/Curves!C13-1)/(0.25-0))+C52/10000)*(0.25-0)) -> 0.98967798 | P52: =O52/(1+(((Curves!C13/Curves!D13-1)/(0.5-0.25))+D52/10000)*(0.5-0.25)) -> 0.98013082 | Q52: =P52/(1+(((Curves!D13/Curves!E13-1)/(1-0.5))+E52/10000)*(1-0.5)) -> 0.96008938 | R52: =Q52/(1+(((Curves!E13/Curves!F13-1)/(2-1))+F52/10000)*(2-1)) -> 0.921303 | S52: =R52/(1+(((Curves!F13/Curves!G13-1)/(3-2))+G52/10000)*(3-2)) -> 0.88405514 | T52: =S52/(1+(((Curves!G13/Curves!H13-1)/(5-3))+H52/10000)*(5-3)) -> 0.81361664 | U52: =T52/(1+(((Curves!H13/Curves!I13-1)/(10-5))+I52/10000)*(10-5)) -> 0.65822529 | V52: =U52/(1+(((Curves!I13/Curves!J13-1)/(20-10))+J52/10000)*(20-10)) -> 0.43434854 | W52: =V52/(1+(((Curves!J13/Curves!K13-1)/(30-20))+K52/10000)*(30-20)) -> 0.28667614
A54: Scenario 7 | C54: 3M | D54: 6M | E54: 1Y | F54: 2Y | G54: 3Y | H54: 5Y | I54: 10Y | J54: 20Y | K54: 30Y | M54: Scenario 7 | O54: 3M | P54: 6M | Q54: 1Y | R54: 2Y | S54: 3Y | T54: 5Y | U54: 10Y | V54: 20Y | W54: 30Y
A55: SOFR | B55: IR | C55: 25 | D55: 22.69 | E55: 17.84 | F55: 12.13 | G55: 8.37 | H55: 4.06 | I55: 2.07 | J55: 1.13 | K55: 0.75 | M55: SOFR | N55: IR | O55: =1/(1+(((1/Curves!C8-1)/(0.25-0))+C55/10000)*(0.25-0)) -> 0.98868668 | P55: =O55/(1+(((Curves!C8/Curves!D8-1)/(0.5-0.25))+D55/10000)*(0.5-0.25)) -> 0.97753967 | Q55: =P55/(1+(((Curves!D8/Curves!E8-1)/(1-0.5))+E55/10000)*(1-0.5)) -> 0.95580498 | R55: =Q55/(1+(((Curves!E8/Curves!F8-1)/(2-1))+F55/10000)*(2-1)) -> 0.91410279 | S55: =R55/(1+(((Curves!F8/Curves!G8-1)/(3-2))+G55/10000)*(3-2)) -> 0.87427225 | T55: =S55/(1+(((Curves!G8/Curves!H8-1)/(5-3))+H55/10000)*(5-3)) -> 0.79971027 | U55: =T55/(1+(((Curves!H8/Curves!I8-1)/(10-5))+I55/10000)*(10-5)) -> 0.63725727 | V55: =U55/(1+(((Curves!I8/Curves!J8-1)/(20-10))+J55/10000)*(20-10)) -> 0.40807485 | W55: =V55/(1+(((Curves!J8/Curves!K8-1)/(30-20))+K55/10000)*(30-20)) -> 0.26137832
A56: ESTRN | B56: IR | C56: 19.22 | D56: 17.99 | E56: 15.95 | F56: 9.91 | G56: 5.73 | H56: 3.24 | I56: 1.58 | J56: 0.76 | K56: 0.41 | M56: ESTRN | N56: IR | O56: =1/(1+(((1/Curves!C9-1)/(0.25-0))+C56/10000)*(0.25-0)) -> 0.99179812 | P56: =O56/(1+(((Curves!C9/Curves!D9-1)/(0.5-0.25))+D56/10000)*(0.5-0.25)) -> 0.98367481 | Q56: =P56/(1+(((Curves!D9/Curves!E9-1)/(1-0.5))+E56/10000)*(1-0.5)) -> 0.96767611 | R56: =Q56/(1+(((Curves!E9/Curves!F9-1)/(2-1))+F56/10000)*(2-1)) -> 0.93681667 | S56: =R56/(1+(((Curves!F9/Curves!G9-1)/(3-2))+G56/10000)*(3-2)) -> 0.90703639 | T56: =S56/(1+(((Curves!G9/Curves!H9-1)/(5-3))+H56/10000)*(5-3)) -> 0.84994856 | U56: =T56/(1+(((Curves!H9/Curves!I9-1)/(10-5))+I56/10000)*(10-5)) -> 0.71928391 | V56: =U56/(1+(((Curves!I9/Curves!J9-1)/(20-10))+J56/10000)*(20-10)) -> 0.51941755 | W56: =V56/(1+(((Curves!J9/Curves!K9-1)/(30-20))+K56/10000)*(30-20)) -> 0.37518173
A57: Treasury | B57: Credit | C57: 27.38 | D57: 25.98 | E57: 20.21 | F57: -13.3 | G57: 8.63 | H57: 4.81 | I57: 2.49 | J57: 1.22 | K57: 0.81 | M57: Treasury | N57: Credit | O57: =1/(1+(((1/Curves!C10-1)/(0.25-0))+C57/10000)*(0.25-0)) -> 0.98887619 | P57: =O57/(1+(((Curves!C10/Curves!D10-1)/(0.5-0.25))+D57/10000)*(0.5-0.25)) -> 0.97789072 | Q57: =P57/(1+(((Curves!D10/Curves!E10-1)/(1-0.5))+E57/10000)*(1-0.5)) -> 0.95651533 | R57: =Q57/(1+(((Curves!E10/Curves!F10-1)/(2-1))+F57/10000)*(2-1)) -> 0.91793131 | S57: =R57/(1+(((Curves!F10/Curves!G10-1)/(3-2))+G57/10000)*(3-2)) -> 0.87878936 | T57: =S57/(1+(((Curves!G10/Curves!H10-1)/(5-3))+H57/10000)*(5-3)) -> 0.80533914 | U57: =T57/(1+(((Curves!H10/Curves!I10-1)/(10-5))+I57/10000)*(10-5)) -> 0.64484947 | V57: =U57/(1+(((Curves!I10/Curves!J10-1)/(20-10))+J57/10000)*(20-10)) -> 0.41705917 | W57: =V57/(1+(((Curves!J10/Curves!K10-1)/(30-20))+K57/10000)*(30-20)) -> 0.26980638
A58: Agency_FNMA | B58: Credit | C58: 43.12 | D58: 37.62 | E58: 32.89 | F58: -23.01 | G58: 15.48 | H58: 9.12 | I58: 4.12 | J58: -2.46 | K58: 1.6 | M58: Agency_FNMA | N58: Credit | O58: =1/(1+(((1/Curves!C11-1)/(0.25-0))+C58/10000)*(0.25-0)) -> 0.98750465 | P58: =O58/(1+(((Curves!C11/Curves!D11-1)/(0.5-0.25))+D58/10000)*(0.5-0.25)) -> 0.97527898 | Q58: =P58/(1+(((Curves!D11/Curves!E11-1)/(1-0.5))+E58/10000)*(1-0.5)) -> 0.95146752 | R58: =Q58/(1+(((Curves!E11/Curves!F11-1)/(2-1))+F58/10000)*(2-1)) -> 0.91028176 | S58: =R58/(1+(((Curves!F11/Curves!G11-1)/(3-2))+G58/10000)*(3-2)) -> 0.86742461 | T58: =S58/(1+(((Curves!G11/Curves!H11-1)/(5-3))+H58/10000)*(5-3)) -> 0.78797796 | U58: =T58/(1+(((Curves!H11/Curves!I11-1)/(10-5))+I58/10000)*(10-5)) -> 0.61807048 | V58: =U58/(1+(((Curves!I11/Curves!J11-1)/(20-10))+J58/10000)*(20-10)) -> 0.38495773 | W58: =V58/(1+(((Curves!J11/Curves!K11-1)/(30-20))+K58/10000)*(30-20)) -> 0.23916105
A59: Eur_Govt | B59: Credit | C59: 37.51 | D59: 30.55 | E59: 24.81 | F59: -18.84 | G59: 11.03 | H59: 5.75 | I59: 3.09 | J59: 1.5 | K59: 1.16 | M59: Eur_Govt | N59: Credit | O59: =1/(1+(((1/Curves!C12-1)/(0.25-0))+C59/10000)*(0.25-0)) -> 0.99085347 | P59: =O59/(1+(((Curves!C12/Curves!D12-1)/(0.5-0.25))+D59/10000)*(0.5-0.25)) -> 0.98194029 | Q59: =P59/(1+(((Curves!D12/Curves!E12-1)/(1-0.5))+E59/10000)*(1-0.5)) -> 0.96458575 | R59: =Q59/(1+(((Curves!E12/Curves!F12-1)/(2-1))+F59/10000)*(2-1)) -> 0.93455688 | S59: =R59/(1+(((Curves!F12/Curves!G12-1)/(3-2))+G59/10000)*(3-2)) -> 0.90257996 | T59: =S59/(1+(((Curves!G12/Curves!H12-1)/(5-3))+H59/10000)*(5-3)) -> 0.84200301 | U59: =T59/(1+(((Curves!H12/Curves!I12-1)/(10-5))+I59/10000)*(10-5)) -> 0.7050288 | V59: =U59/(1+(((Curves!I12/Curves!J12-1)/(20-10))+J59/10000)*(20-10)) -> 0.49878605 | W59: =V59/(1+(((Curves!J12/Curves!K12-1)/(30-20))+K59/10000)*(30-20)) -> 0.35296013
A60: EURUSD | B60: FX | C60: 15.81 | D60: 15.52 | E60: 13.38 | F60: 9.08 | G60: -6.16 | H60: -3.78 | I60: 2.01 | J60: -1.12 | K60: 0.81 | M60: EURUSD | N60: FX | O60: =1/(1+(((1/Curves!C13-1)/(0.25-0))+C60/10000)*(0.25-0)) -> 0.98965373 | P60: =O60/(1+(((Curves!C13/Curves!D13-1)/(0.5-0.25))+D60/10000)*(0.5-0.25)) -> 0.97940238 | Q60: =P60/(1+(((Curves!D13/Curves!E13-1)/(1-0.5))+E60/10000)*(1-0.5)) -> 0.95927153 | R60: =Q60/(1+(((Curves!E13/Curves!F13-1)/(2-1))+F60/10000)*(2-1)) -> 0.92044135 | S60: =R60/(1+(((Curves!F13/Curves!G13-1)/(3-2))+G60/10000)*(3-2)) -> 0.88421 | T60: =S60/(1+(((Curves!G13/Curves!H13-1)/(5-3))+H60/10000)*(5-3)) -> 0.81483904 | U60: =T60/(1+(((Curves!H13/Curves!I13-1)/(10-5))+I60/10000)*(10-5)) -> 0.65913423 | V60: =U60/(1+(((Curves!I13/Curves!J13-1)/(20-10))+J60/10000)*(20-10)) -> 0.43557493 | W60: =V60/(1+(((Curves!J13/Curves!K13-1)/(30-20))+K60/10000)*(30-20)) -> 0.28747419
A62: Scenario 8 | C62: 3M | D62: 6M | E62: 1Y | F62: 2Y | G62: 3Y | H62: 5Y | I62: 10Y | J62: 20Y | K62: 30Y | M62: Scenario 8 | O62: 3M | P62: 6M | Q62: 1Y | R62: 2Y | S62: 3Y | T62: 5Y | U62: 10Y | V62: 20Y | W62: 30Y
A63: SOFR | B63: IR | C63: 26.16 | D63: 23.72 | E63: 18.24 | F63: 12.98 | G63: 8.47 | H63: -4.14 | I63: 2.09 | J63: 1.25 | K63: 0.81 | M63: SOFR | N63: IR | O63: =1/(1+(((1/Curves!C8-1)/(0.25-0))+C63/10000)*(0.25-0)) -> 0.98865834 | P63: =O63/(1+(((Curves!C8/Curves!D8-1)/(0.5-0.25))+D63/10000)*(0.5-0.25)) -> 0.97748676 | Q63: =P63/(1+(((Curves!D8/Curves!E8-1)/(1-0.5))+E63/10000)*(1-0.5)) -> 0.95573455 | R63: =Q63/(1+(((Curves!E8/Curves!F8-1)/(2-1))+F63/10000)*(2-1)) -> 0.91396114 | S63: =R63/(1+(((Curves!F8/Curves!G8-1)/(3-2))+G63/10000)*(3-2)) -> 0.87412841 | T63: =S63/(1+(((Curves!G8/Curves!H8-1)/(5-3))+H63/10000)*(5-3)) -> 0.80077998 | U63: =T63/(1+(((Curves!H8/Curves!I8-1)/(10-5))+I63/10000)*(10-5)) -> 0.63810459 | V63: =U63/(1+(((Curves!I8/Curves!J8-1)/(20-10))+J63/10000)*(20-10)) -> 0.40858605 | W63: =V63/(1+(((Curves!J8/Curves!K8-1)/(30-20))+K63/10000)*(30-20)) -> 0.26169569
A64: ESTRN | B64: IR | C64: -21.01 | D64: 19.42 | E64: 15.9 | F64: 10.49 | G64: -6.26 | H64: 3.43 | I64: 1.74 | J64: 0.81 | K64: 0.44 | M64: ESTRN | N64: IR | O64: =1/(1+(((1/Curves!C9-1)/(0.25-0))+C64/10000)*(0.25-0)) -> 0.99278843 | P64: =O64/(1+(((Curves!C9/Curves!D9-1)/(0.5-0.25))+D64/10000)*(0.5-0.25)) -> 0.98462209 | Q64: =P64/(1+(((Curves!D9/Curves!E9-1)/(1-0.5))+E64/10000)*(1-0.5)) -> 0.96861037 | R64: =Q64/(1+(((Curves!E9/Curves!F9-1)/(2-1))+F64/10000)*(2-1)) -> 0.93766849 | S64: =R64/(1+(((Curves!F9/Curves!G9-1)/(3-2))+G64/10000)*(3-2)) -> 0.90891627 | T64: =S64/(1+(((Curves!G9/Curves!H9-1)/(5-3))+H64/10000)*(5-3)) -> 0.8516798 | U64: =T64/(1+(((Curves!H9/Curves!I9-1)/(10-5))+I64/10000)*(10-5)) -> 0.72070021 | V64: =U64/(1+(((Curves!I9/Curves!J9-1)/(20-10))+J64/10000)*(20-10)) -> 0.52042151 | W64: =V64/(1+(((Curves!J9/Curves!K9-1)/(30-20))+K64/10000)*(30-20)) -> 0.37589876
A65: Treasury | B65: Credit | C65: 29.83 | D65: 28.49 | E65: 22.41 | F65: 14.27 | G65: 9.55 | H65: -5.04 | I65: 2.44 | J65: 1.22 | K65: -0.82 | M65: Treasury | N65: Credit | O65: =1/(1+(((1/Curves!C10-1)/(0.25-0))+C65/10000)*(0.25-0)) -> 0.9888163 | P65: =O65/(1+(((Curves!C10/Curves!D10-1)/(0.5-0.25))+D65/10000)*(0.5-0.25)) -> 0.97777082 | Q65: =P65/(1+(((Curves!D10/Curves!E10-1)/(1-0.5))+E65/10000)*(1-0.5)) -> 0.95629516 | R65: =Q65/(1+(((Curves!E10/Curves!F10-1)/(2-1))+F65/10000)*(2-1)) -> 0.91529834 | S65: =R65/(1+(((Curves!F10/Curves!G10-1)/(3-2))+G65/10000)*(3-2)) -> 0.87619149 | T65: =S65/(1+(((Curves!G10/Curves!H10-1)/(5-3))+H65/10000)*(5-3)) -> 0.80441064 | U65: =T65/(1+(((Curves!H10/Curves!I10-1)/(10-5))+I65/10000)*(10-5)) -> 0.64411889 | V65: =U65/(1+(((Curves!I10/Curves!J10-1)/(20-10))+J65/10000)*(20-10)) -> 0.41658667 | W65: =V65/(1+(((Curves!J10/Curves!K10-1)/(30-20))+K65/10000)*(30-20)) -> 0.2697852
A66: Agency_FNMA | B66: Credit | C66: 47.53 | D66: 44.18 | E66: 35.46 | F66: 25.04 | G66: 16.46 | H66: 9.62 | I66: -4.38 | J66: 2.59 | K66: 1.77 | M66: Agency_FNMA | N66: Credit | O66: =1/(1+(((1/Curves!C11-1)/(0.25-0))+C66/10000)*(0.25-0)) -> 0.98739715 | P66: =O66/(1+(((Curves!C11/Curves!D11-1)/(0.5-0.25))+D66/10000)*(0.5-0.25)) -> 0.97501489 | Q66: =P66/(1+(((Curves!D11/Curves!E11-1)/(1-0.5))+E66/10000)*(1-0.5)) -> 0.95109065 | R66: =Q66/(1+(((Curves!E11/Curves!F11-1)/(2-1))+F66/10000)*(2-1)) -> 0.90575742 | S66: =R66/(1+(((Curves!F11/Curves!G11-1)/(3-2))+G66/10000)*(3-2)) -> 0.86303269 | T66: =S66/(1+(((Curves!G11/Curves!H11-1)/(5-3))+H66/10000)*(5-3)) -> 0.78391708 | U66: =T66/(1+(((Curves!H11/Curves!I11-1)/(10-5))+I66/10000)*(10-5)) -> 0.61694186 | V66: =U66/(1+(((Curves!I11/Curves!J11-1)/(20-10))+J66/10000)*(20-10)) -> 0.38304996 | W66: =V66/(1+(((Curves!J11/Curves!K11-1)/(30-20))+K66/10000)*(30-20)) -> 0.23795068
A67: Eur_Govt | B67: Credit | C67: 39.99 | D67: 36.17 | E67: 28.19 | F67: 18.72 | G67: 12.57 | H67: 6.3 | I67: 3.37 | J67: 1.71 | K67: 1.34 | M67: Eur_Govt | N67: Credit | O67: =1/(1+(((1/Curves!C12-1)/(0.25-0))+C67/10000)*(0.25-0)) -> 0.9907926 | P67: =O67/(1+(((Curves!C12/Curves!D12-1)/(0.5-0.25))+D67/10000)*(0.5-0.25)) -> 0.98174328 | Q67: =P67/(1+(((Curves!D12/Curves!E12-1)/(1-0.5))+E67/10000)*(1-0.5)) -> 0.96423214 | R67: =Q67/(1+(((Curves!E12/Curves!F12-1)/(2-1))+F67/10000)*(2-1)) -> 0.93082694 | S67: =R67/(1+(((Curves!F12/Curves!G12-1)/(3-2))+G67/10000)*(3-2)) -> 0.89884396 | T67: =S67/(1+(((Curves!G12/Curves!H12-1)/(5-3))+H67/10000)*(5-3)) -> 0.83843171 | U67: =T67/(1+(((Curves!H12/Curves!I12-1)/(10-5))+I67/10000)*(10-5)) -> 0.70195618 | V67: =U67/(1+(((Curves!I12/Curves!J12-1)/(20-10))+J67/10000)*(20-10)) -> 0.4965385 | W67: =V67/(1+(((Curves!J12/Curves!K12-1)/(30-20))+K67/10000)*(30-20)) -> 0.35132493
A68: EURUSD | B68: FX | C68: -17.19 | D68: 16.95 | E68: 13.46 | F68: 9.48 | G68: 6.29 | H68: 4.07 | I68: 2.13 | J68: -1.34 | K68: 0.82 | M68: EURUSD | N68: FX | O68: =1/(1+(((1/Curves!C13-1)/(0.25-0))+C68/10000)*(0.25-0)) -> 0.99046241 | P68: =O68/(1+(((Curves!C13/Curves!D13-1)/(0.5-0.25))+D68/10000)*(0.5-0.25)) -> 0.98016801 | Q68: =P68/(1+(((Curves!D13/Curves!E13-1)/(1-0.5))+E68/10000)*(1-0.5)) -> 0.96001766 | R68: =Q68/(1+(((Curves!E13/Curves!F13-1)/(2-1))+F68/10000)*(2-1)) -> 0.92112192 | S68: =R68/(1+(((Curves!F13/Curves!G13-1)/(3-2))+G68/10000)*(3-2)) -> 0.88380675 | T68: =S68/(1+(((Curves!G13/Curves!H13-1)/(5-3))+H68/10000)*(5-3)) -> 0.81329074 | U68: =T68/(1+(((Curves!H13/Curves!I13-1)/(10-5))+I68/10000)*(10-5)) -> 0.65784986 | V68: =U68/(1+(((Curves!I13/Curves!J13-1)/(20-10))+J68/10000)*(20-10)) -> 0.43478939 | W68: =V68/(1+(((Curves!J13/Curves!K13-1)/(30-20))+K68/10000)*(30-20)) -> 0.28695385
A70: Scenario 9 | C70: 3M | D70: 6M | E70: 1Y | F70: 2Y | G70: 3Y | H70: 5Y | I70: 10Y | J70: 20Y | K70: 30Y | M70: Scenario 9 | O70: 3M | P70: 6M | Q70: 1Y | R70: 2Y | S70: 3Y | T70: 5Y | U70: 10Y | V70: 20Y | W70: 30Y
A71: SOFR | B71: IR | C71: -28.47 | D71: 25.63 | E71: 20.46 | F71: 14.49 | G71: -8.92 | H71: 4.76 | I71: 2.25 | J71: 1.34 | K71: 0.9 | M71: SOFR | N71: IR | O71: =1/(1+(((1/Curves!C8-1)/(0.25-0))+C71/10000)*(0.25-0)) -> 0.98999509 | P71: =O71/(1+(((Curves!C8/Curves!D8-1)/(0.5-0.25))+D71/10000)*(0.5-0.25)) -> 0.9787622 | Q71: =P71/(1+(((Curves!D8/Curves!E8-1)/(1-0.5))+E71/10000)*(1-0.5)) -> 0.95687776 | R71: =Q71/(1+(((Curves!E8/Curves!F8-1)/(2-1))+F71/10000)*(2-1)) -> 0.91492226 | S71: =R71/(1+(((Curves!F8/Curves!G8-1)/(3-2))+G71/10000)*(3-2)) -> 0.87650546 | T71: =S71/(1+(((Curves!G8/Curves!H8-1)/(5-3))+H71/10000)*(5-3)) -> 0.80165037 | U71: =T71/(1+(((Curves!H8/Curves!I8-1)/(10-5))+I71/10000)*(10-5)) -> 0.63875744 | V71: =U71/(1+(((Curves!I8/Curves!J8-1)/(20-10))+J71/10000)*(20-10)) -> 0.4089805 | W71: =V71/(1+(((Curves!J8/Curves!K8-1)/(30-20))+K71/10000)*(30-20)) -> 0.26193324
A72: ESTRN | B72: IR | C72: 23.43 | D72: 21.55 | E72: 18.08 | F72: 10.96 | G72: 6.76 | H72: 3.75 | I72: 1.88 | J72: 0.96 | K72: -0.46 | M72: ESTRN | N72: IR | O72: =1/(1+(((1/Curves!C9-1)/(0.25-0))+C72/10000)*(0.25-0)) -> 0.9916946 | P72: =O72/(1+(((Curves!C9/Curves!D9-1)/(0.5-0.25))+D72/10000)*(0.5-0.25)) -> 0.98348532 | Q72: =P72/(1+(((Curves!D9/Curves!E9-1)/(1-0.5))+E72/10000)*(1-0.5)) -> 0.96738836 | R72: =Q72/(1+(((Curves!E9/Curves!F9-1)/(2-1))+F72/10000)*(2-1)) -> 0.93644291 | S72: =R72/(1+(((Curves!F9/Curves!G9-1)/(3-2))+G72/10000)*(3-2)) -> 0.90658409 | T72: =S72/(1+(((Curves!G9/Curves!H9-1)/(5-3))+H72/10000)*(5-3)) -> 0.84944354 | U72: =T72/(1+(((Curves!H9/Curves!I9-1)/(10-5))+I72/10000)*(10-5)) -> 0.71876528 | V72: =U72/(1+(((Curves!I9/Curves!J9-1)/(20-10))+J72/10000)*(20-10)) -> 0.51896808 | W72: =V72/(1+(((Curves!J9/Curves!K9-1)/(30-20))+K72/10000)*(30-20)) -> 0.37509279
A73: Treasury | B73: Credit | C73: 32.94 | D73: 30.77 | E73: 23.2 | F73: 16.87 | G73: -10.57 | H73: 5.43 | I73: 2.9 | J73: -1.35 | K73: 0.9 | M73: Treasury | N73: Credit | O73: =1/(1+(((1/Curves!C10-1)/(0.25-0))+C73/10000)*(0.25-0)) -> 0.98874028 | P73: =O73/(1+(((Curves!C10/Curves!D10-1)/(0.5-0.25))+D73/10000)*(0.5-0.25)) -> 0.97764055 | Q73: =P73/(1+(((Curves!D10/Curves!E10-1)/(1-0.5))+E73/10000)*(1-0.5)) -> 0.95613081 | R73: =Q73/(1+(((Curves!E10/Curves!F10-1)/(2-1))+F73/10000)*(2-1)) -> 0.91491336 | S73: =R73/(1+(((Curves!F10/Curves!G10-1)/(3-2))+G73/10000)*(3-2)) -> 0.87751308 | T73: =S73/(1+(((Curves!G10/Curves!H10-1)/(5-3))+H73/10000)*(5-3)) -> 0.80407815 | U73: =T73/(1+(((Curves!H10/Curves!I10-1)/(10-5))+I73/10000)*(10-5)) -> 0.64373411 | V73: =U73/(1+(((Curves!I10/Curves!J10-1)/(20-10))+J73/10000)*(20-10)) -> 0.41703098 | W73: =V73/(1+(((Curves!J10/Curves!K10-1)/(30-20))+K73/10000)*(30-20)) -> 0.26977244
A74: Agency_FNMA | B74: Credit | C74: 48.79 | D74: 44.35 | E74: 38.83 | F74: 28.13 | G74: 18.14 | H74: 10.47 | I74: 4.42 | J74: 2.71 | K74: 1.82 | M74: Agency_FNMA | N74: Credit | O74: =1/(1+(((1/Curves!C11-1)/(0.25-0))+C74/10000)*(0.25-0)) -> 0.98736644 | P74: =O74/(1+(((Curves!C11/Curves!D11-1)/(0.5-0.25))+D74/10000)*(0.5-0.25)) -> 0.97498047 | Q74: =P74/(1+(((Curves!D11/Curves!E11-1)/(1-0.5))+E74/10000)*(1-0.5)) -> 0.95090078 | R74: =Q74/(1+(((Curves!E11/Curves!F11-1)/(2-1))+F74/10000)*(2-1)) -> 0.9053102 | S74: =R74/(1+(((Curves!F11/Curves!G11-1)/(3-2))+G74/10000)*(3-2)) -> 0.8624685 | T74: =S74/(1+(((Curves!G11/Curves!H11-1)/(5-3))+H74/10000)*(5-3)) -> 0.78328366 | U74: =T74/(1+(((Curves!H11/Curves!I11-1)/(10-5))+I74/10000)*(10-5)) -> 0.61431611 | V74: =U74/(1+(((Curves!I11/Curves!J11-1)/(20-10))+J74/10000)*(20-10)) -> 0.38139126 | W74: =V74/(1+(((Curves!J11/Curves!K11-1)/(30-20))+K74/10000)*(30-20)) -> 0.23691294
A75: Eur_Govt | B75: Credit | C75: 43.44 | D75: 36.85 | E75: 30.45 | F75: 20.38 | G75: 12.4 | H75: 6.95 | I75: 3.79 | J75: 1.84 | K75: 1.45 | M75: Eur_Govt | N75: Credit | O75: =1/(1+(((1/Curves!C12-1)/(0.25-0))+C75/10000)*(0.25-0)) -> 0.99070794 | P75: =O75/(1+(((Curves!C12/Curves!D12-1)/(0.5-0.25))+D75/10000)*(0.5-0.25)) -> 0.98164286 | Q75: =P75/(1+(((Curves!D12/Curves!E12-1)/(1-0.5))+E75/10000)*(1-0.5)) -> 0.96402652 | R75: =Q75/(1+(((Curves!E12/Curves!F12-1)/(2-1))+F75/10000)*(2-1)) -> 0.93047933 | S75: =R75/(1+(((Curves!F12/Curves!G12-1)/(3-2))+G75/10000)*(3-2)) -> 0.89852304 | T75: =S75/(1+(((Curves!G12/Curves!H12-1)/(5-3))+H75/10000)*(5-3)) -> 0.83803074 | U75: =T75/(1+(((Curves!H12/Curves!I12-1)/(10-5))+I75/10000)*(10-5)) -> 0.70149714 | V75: =U75/(1+(((Curves!I12/Curves!J12-1)/(20-10))+J75/10000)*(20-10)) -> 0.49616816 | W75: =V75/(1+(((Curves!J12/Curves!K12-1)/(30-20))+K75/10000)*(30-20)) -> 0.35103558
A76: EURUSD | B76: FX | C76: -19.21 | D76: -17.84 | E76: 14.29 | F76: 10.61 | G76: 6.94 | H76: 4.26 | I76: 2.22 | J76: 1.36 | K76: 0.89 | M76: EURUSD | N76: FX | O76: =1/(1+(((1/Curves!C13-1)/(0.25-0))+C76/10000)*(0.25-0)) -> 0.99051196 | P76: =O76/(1+(((Curves!C13/Curves!D13-1)/(0.5-0.25))+D76/10000)*(0.5-0.25)) -> 0.98106144 | Q76: =P76/(1+(((Curves!D13/Curves!E13-1)/(1-0.5))+E76/10000)*(1-0.5)) -> 0.96085367 | R76: =Q76/(1+(((Curves!E13/Curves!F13-1)/(2-1))+F76/10000)*(2-1)) -> 0.92182412 | S76: =R76/(1+(((Curves!F13/Curves!G13-1)/(3-2))+G76/10000)*(3-2)) -> 0.88442534 | T76: =S76/(1+(((Curves!G13/Curves!H13-1)/(5-3))+H76/10000)*(5-3)) -> 0.81383152 | U76: =T76/(1+(((Curves!H13/Curves!I13-1)/(10-5))+I76/10000)*(10-5)) -> 0.65826333 | V76: =U76/(1+(((Curves!I13/Curves!J13-1)/(20-10))+J76/10000)*(20-10)) -> 0.43428767 | W76: =V76/(1+(((Curves!J13/Curves!K13-1)/(30-20))+K76/10000)*(30-20)) -> 0.28660948
A78: Scenario 10 | C78: 3M | D78: 6M | E78: 1Y | F78: 2Y | G78: 3Y | H78: 5Y | I78: 10Y | J78: 20Y | K78: 30Y | M78: Scenario 10 | O78: 3M | P78: 6M | Q78: 1Y | R78: 2Y | S78: 3Y | T78: 5Y | U78: 10Y | V78: 20Y | W78: 30Y
A79: SOFR | B79: IR | C79: 30.45 | D79: 27.71 | E79: 21.91 | F79: 15.48 | G79: 9.66 | H79: 5.18 | I79: 2.58 | J79: 1.55 | K79: 0.99 | M79: SOFR | N79: IR | O79: =1/(1+(((1/Curves!C8-1)/(0.25-0))+C79/10000)*(0.25-0)) -> 0.98855352 | P79: =O79/(1+(((Curves!C8/Curves!D8-1)/(0.5-0.25))+D79/10000)*(0.5-0.25)) -> 0.97728674 | Q79: =P79/(1+(((Curves!D8/Curves!E8-1)/(1-0.5))+E79/10000)*(1-0.5)) -> 0.95536758 | R79: =Q79/(1+(((Curves!E8/Curves!F8-1)/(2-1))+F79/10000)*(2-1)) -> 0.91339183 | S79: =R79/(1+(((Curves!F8/Curves!G8-1)/(3-2))+G79/10000)*(3-2)) -> 0.87348451 | T79: =S79/(1+(((Curves!G8/Curves!H8-1)/(5-3))+H79/10000)*(5-3)) -> 0.79882604 | U79: =T79/(1+(((Curves!H8/Curves!I8-1)/(10-5))+I79/10000)*(10-5)) -> 0.63642334 | V79: =U79/(1+(((Curves!I8/Curves!J8-1)/(20-10))+J79/10000)*(20-10)) -> 0.40743125 | W79: =V79/(1+(((Curves!J8/Curves!K8-1)/(30-20))+K79/10000)*(30-20)) -> 0.26092597
A80: ESTRN | B80: IR | C80: -25.53 | D80: 22.84 | E80: 19.01 | F80: 12.71 | G80: 7.7 | H80: 3.85 | I80: 1.94 | J80: 1.01 | K80: 0.48 | M80: ESTRN | N80: IR | O80: =1/(1+(((1/Curves!C9-1)/(0.25-0))+C80/10000)*(0.25-0)) -> 0.99289982 | P80: =O80/(1+(((Curves!C9/Curves!D9-1)/(0.5-0.25))+D80/10000)*(0.5-0.25)) -> 0.98464907 | Q80: =P80/(1+(((Curves!D9/Curves!E9-1)/(1-0.5))+E80/10000)*(1-0.5)) -> 0.96848876 | R80: =Q80/(1+(((Curves!E9/Curves!F9-1)/(2-1))+F80/10000)*(2-1)) -> 0.93734932 | S80: =R80/(1+(((Curves!F9/Curves!G9-1)/(3-2))+G80/10000)*(3-2)) -> 0.90737903 | T80: =S80/(1+(((Curves!G9/Curves!H9-1)/(5-3))+H80/10000)*(5-3)) -> 0.85017245 | U80: =T80/(1+(((Curves!H9/Curves!I9-1)/(10-5))+I80/10000)*(10-5)) -> 0.71936379 | V80: =U80/(1+(((Curves!I9/Curves!J9-1)/(20-10))+J80/10000)*(20-10)) -> 0.51938147 | W80: =V80/(1+(((Curves!J9/Curves!K9-1)/(30-20))+K80/10000)*(30-20)) -> 0.37513671
A81: Treasury | B81: Credit | C81: 33.89 | D81: 31.34 | E81: 24.28 | F81: 17.55 | G81: 10.77 | H81: 5.76 | I81: 2.93 | J81: 1.49 | K81: -0.99 | M81: Treasury | N81: Credit | O81: =1/(1+(((1/Curves!C10-1)/(0.25-0))+C81/10000)*(0.25-0)) -> 0.98871707 | P81: =O81/(1+(((Curves!C10/Curves!D10-1)/(0.5-0.25))+D81/10000)*(0.5-0.25)) -> 0.97760382 | Q81: =P81/(1+(((Curves!D10/Curves!E10-1)/(1-0.5))+E81/10000)*(1-0.5)) -> 0.9560444 | R81: =Q81/(1+(((Curves!E10/Curves!F10-1)/(2-1))+F81/10000)*(2-1)) -> 0.91477115 | S81: =R81/(1+(((Curves!F10/Curves!G10-1)/(3-2))+G81/10000)*(3-2)) -> 0.87558456 | T81: =S81/(1+(((Curves!G10/Curves!H10-1)/(5-3))+H81/10000)*(5-3)) -> 0.80226251 | U81: =T81/(1+(((Curves!H10/Curves!I10-1)/(10-5))+I81/10000)*(10-5)) -> 0.64227282 | V81: =U81/(1+(((Curves!I10/Curves!J10-1)/(20-10))+J81/10000)*(20-10)) -> 0.41532019 | W81: =V81/(1+(((Curves!J10/Curves!K10-1)/(30-20))+K81/10000)*(30-20)) -> 0.26899463
A82: Agency_FNMA | B82: Credit | C82: -55.63 | D82: 51.36 | E82: 43.03 | F82: 30.7 | G82: 20.58 | H82: -10.85 | I82: 5.06 | J82: -2.9 | K82: 1.96 | M82: Agency_FNMA | N82: Credit | O82: =1/(1+(((1/Curves!C11-1)/(0.25-0))+C82/10000)*(0.25-0)) -> 0.98991797 | P82: =O82/(1+(((Curves!C11/Curves!D11-1)/(0.5-0.25))+D82/10000)*(0.5-0.25)) -> 0.97733087 | Q82: =P82/(1+(((Curves!D11/Curves!E11-1)/(1-0.5))+E82/10000)*(1-0.5)) -> 0.95299794 | R82: =Q82/(1+(((Curves!E11/Curves!F11-1)/(2-1))+F82/10000)*(2-1)) -> 0.90708487 | S82: =R82/(1+(((Curves!F11/Curves!G11-1)/(3-2))+G82/10000)*(3-2)) -> 0.86395836 | T82: =S82/(1+(((Curves!G11/Curves!H11-1)/(5-3))+H82/10000)*(5-3)) -> 0.78768706 | U82: =T82/(1+(((Curves!H11/Curves!I11-1)/(10-5))+I82/10000)*(10-5)) -> 0.61761462 | V82: =U82/(1+(((Curves!I11/Curves!J11-1)/(20-10))+J82/10000)*(20-10)) -> 0.38477925 | W82: =V82/(1+(((Curves!J11/Curves!K11-1)/(30-20))+K82/10000)*(30-20)) -> 0.23899671
A83: Eur_Govt | B83: Credit | C83: 42.92 | D83: 38.38 | E83: 32.34 | F83: 23.18 | G83: 13.52 | H83: -7.14 | I83: 3.83 | J83: 2.07 | K83: 1.53 | M83: Eur_Govt | N83: Credit | O83: =1/(1+(((1/Curves!C12-1)/(0.25-0))+C83/10000)*(0.25-0)) -> 0.9907207 | P83: =O83/(1+(((Curves!C12/Curves!D12-1)/(0.5-0.25))+D83/10000)*(0.5-0.25)) -> 0.9816183 | Q83: =P83/(1+(((Curves!D12/Curves!E12-1)/(1-0.5))+E83/10000)*(1-0.5)) -> 0.96391294 | R83: =Q83/(1+(((Curves!E12/Curves!F12-1)/(2-1))+F83/10000)*(2-1)) -> 0.93011834 | S83: =R83/(1+(((Curves!F12/Curves!G12-1)/(3-2))+G83/10000)*(3-2)) -> 0.89807732 | T83: =S83/(1+(((Curves!G12/Curves!H12-1)/(5-3))+H83/10000)*(5-3)) -> 0.83982231 | U83: =T83/(1+(((Curves!H12/Curves!I12-1)/(10-5))+I83/10000)*(10-5)) -> 0.70298506 | V83: =U83/(1+(((Curves!I12/Curves!J12-1)/(20-10))+J83/10000)*(20-10)) -> 0.49713969 | W83: =V83/(1+(((Curves!J12/Curves!K12-1)/(30-20))+K83/10000)*(30-20)) -> 0.35170302
A84: EURUSD | B84: FX | C84: 19.37 | D84: 18.93 | E84: 15.85 | F84: 10.44 | G84: 7.09 | H84: 4.26 | I84: 2.45 | J84: 1.51 | K84: 1.01 | M84: EURUSD | N84: FX | O84: =1/(1+(((1/Curves!C13-1)/(0.25-0))+C84/10000)*(0.25-0)) -> 0.98956657 | P84: =O84/(1+(((Curves!C13/Curves!D13-1)/(0.5-0.25))+D84/10000)*(0.5-0.25)) -> 0.97923351 | Q84: =P84/(1+(((Curves!D13/Curves!E13-1)/(1-0.5))+E84/10000)*(1-0.5)) -> 0.95899013 | R84: =Q84/(1+(((Curves!E13/Curves!F13-1)/(2-1))+F84/10000)*(2-1)) -> 0.92005128 | S84: =R84/(1+(((Curves!F13/Curves!G13-1)/(3-2))+G84/10000)*(3-2)) -> 0.88271172 | T84: =S84/(1+(((Curves!G13/Curves!H13-1)/(5-3))+H84/10000)*(5-3)) -> 0.81225468 | U84: =T84/(1+(((Curves!H13/Curves!I13-1)/(10-5))+I84/10000)*(10-5)) -> 0.6569268 | V84: =U84/(1+(((Curves!I13/Curves!J13-1)/(20-10))+J84/10000)*(20-10)) -> 0.43336302 | W84: =V84/(1+(((Curves!J13/Curves!K13-1)/(30-20))+K84/10000)*(30-20)) -> 0.2859766
A86: Same cascading bootstrap as the Curves tab Section 2, applied to the smaller current-period shocks: shocked DF at tenor i is solved off the shocked DF at tenor i-1, off BASE forward rates pulled from Curves!Section 1.

Sheet SABR
A1: SABR Swaption Vol Surfaces — Base -> Scenario Shocks -> Shocked Surfaces, ATM/RHO/NU/Combined aligned
A2: Swabr_Swaption (IR_VOL) | Trade 123456 | Stress anchor 20-Nov-2008
A3: SECTION 1 - BASE SABR SURFACES (ATM, RHO, NU, Combined Effective Vol aligned horizontally)
B5: Param: ATM | N5: Param: RHO | Z5: Param: NU | AL5: Combined Effective ATM Vol (Hagan approx, beta=1)
B6: Expiry \ Tenor | C6: 1M | D6: 3M | E6: 6M | F6: 1Y | G6: 2Y | H6: 3Y | I6: 5Y | J6: 10Y | K6: 20Y | L6: 30Y | N6: Expiry \ Tenor | O6: 1M | P6: 3M | Q6: 6M | R6: 1Y | S6: 2Y | T6: 3Y | U6: 5Y | V6: 10Y | W6: 20Y | X6: 30Y | Z6: Expiry \ Tenor | AA6: 1M | AB6: 3M | AC6: 6M | AD6: 1Y | AE6: 2Y | AF6: 3Y | AG6: 5Y | AH6: 10Y | AI6: 20Y | AJ6: 30Y | AL6: Expiry \ Tenor | AM6: 1M | AN6: 3M | AO6: 6M | AP6: 1Y | AQ6: 2Y | AR6: 3Y | AS6: 5Y | AT6: 10Y | AU6: 20Y | AV6: 30Y
B7: 1M | C7: 0.5465 | D7: 0.5264 | E7: 0.5197 | F7: 0.4914 | G7: 0.4841 | H7: 0.464 | I7: 0.4412 | J7: 0.4335 | K7: 0.4074 | L7: 0.3987 | N7: 1M | O7: -0.3586 | P7: -0.3387 | Q7: -0.3126 | R7: -0.2851 | S7: -0.2797 | T7: -0.2583 | U7: -0.2308 | V7: -0.2049 | W7: -0.1929 | X7: -0.1771 | Z7: 1M | AA7: 0.8595 | AB7: 0.8187 | AC7: 0.8127 | AD7: 0.7791 | AE7: 0.754 | AF7: 0.7312 | AG7: 0.7128 | AH7: 0.7008 | AI7: 0.6658 | AJ7: 0.6516 | AL7: 1M | AM7: =C7*(1+(((2-3*O7^2)/24*AA7^2)+(O7*AA7*C7/4))*0.0833333333333333) -> 0.54684506 | AN7: =D7*(1+(((2-3*P7^2)/24*AB7^2)+(P7*AB7*D7/4))*0.0833333333333333) -> 0.52682781 | AO7: =E7*(1+(((2-3*Q7^2)/24*AC7^2)+(Q7*AC7*E7/4))*0.0833333333333333) -> 0.5203048 | AP7: =F7*(1+(((2-3*R7^2)/24*AD7^2)+(R7*AD7*F7/4))*0.0833333333333333) -> 0.4921014 | AQ7: =G7*(1+(((2-3*S7^2)/24*AE7^2)+(S7*AE7*G7/4))*0.0833333333333333) -> 0.4847573 | AR7: =H7*(1+(((2-3*T7^2)/24*AF7^2)+(T7*AF7*H7/4))*0.0833333333333333) -> 0.46470322 | AS7: =I7*(1+(((2-3*U7^2)/24*AG7^2)+(U7*AG7*I7/4))*0.0833333333333333) -> 0.44196516 | AT7: =J7*(1+(((2-3*V7^2)/24*AH7^2)+(V7*AH7*J7/4))*0.0833333333333333) -> 0.43432319 | ... AV7: =L7*(1+(((2-3*X7^2)/24*AJ7^2)+(X7*AJ7*L7/4))*0.0833333333333333) -> 0.39943809
B8: 3M | C8: 0.5361 | D8: 0.5141 | E8: 0.501 | F8: 0.4746 | G8: 0.4579 | H8: 0.4441 | I8: 0.4369 | J8: 0.4152 | K8: 0.3963 | L8: 0.385 | N8: 3M | O8: -0.3315 | P8: -0.3151 | Q8: -0.2858 | R8: -0.2682 | S8: -0.2579 | T8: -0.2318 | U8: -0.2134 | V8: -0.1869 | W8: -0.1704 | X8: -0.1598 | Z8: 3M | AA8: 0.8374 | AB8: 0.7979 | AC8: 0.7817 | AD8: 0.7663 | AE8: 0.7319 | AF8: 0.7164 | AG8: 0.6852 | AH8: 0.6756 | AI8: 0.6553 | AJ8: 0.6292 | AL8: 3M | AM8: =C8*(1+(((2-3*O8^2)/24*AA8^2)+(O8*AA8*C8/4))*0.25) -> 0.53765454 | AN8: =D8*(1+(((2-3*P8^2)/24*AB8^2)+(P8*AB8*D8/4))*0.25) -> 0.5157501 | AO8: =E8*(1+(((2-3*Q8^2)/24*AC8^2)+(Q8*AC8*E8/4))*0.25) -> 0.5030917 | AP8: =F8*(1+(((2-3*R8^2)/24*AD8^2)+(R8*AD8*F8/4))*0.25) -> 0.47688634 | AQ8: =G8*(1+(((2-3*S8^2)/24*AE8^2)+(S8*AE8*G8/4))*0.25) -> 0.46002674 | AR8: =H8*(1+(((2-3*T8^2)/24*AF8^2)+(T8*AF8*H8/4))*0.25) -> 0.44641876 | AS8: =I8*(1+(((2-3*U8^2)/24*AG8^2)+(U8*AG8*I8/4))*0.25) -> 0.43913707 | AT8: =J8*(1+(((2-3*V8^2)/24*AH8^2)+(V8*AH8*J8/4))*0.25) -> 0.41758081 | ... AV8: =L8*(1+(((2-3*X8^2)/24*AJ8^2)+(X8*AJ8*L8/4))*0.25) -> 0.38712229
B9: 6M | C9: 0.5242 | D9: 0.4963 | E9: 0.4872 | F9: 0.4686 | G9: 0.4516 | H9: 0.4325 | I9: 0.4235 | J9: 0.4089 | K9: 0.3828 | L9: 0.3699 | N9: 6M | O9: -0.3199 | P9: -0.2876 | Q9: -0.2693 | R9: -0.2429 | S9: -0.2269 | T9: -0.2182 | U9: -0.1967 | V9: -0.1716 | W9: -0.1651 | X9: -0.1369 | Z9: 6M | AA9: 0.7989 | AB9: 0.7757 | AC9: 0.7523 | AD9: 0.7443 | AE9: 0.7093 | AF9: 0.6894 | AG9: 0.67 | AH9: 0.6574 | AI9: 0.6194 | AJ9: 0.6045 | AL9: 6M | AM9: =C9*(1+(((2-3*O9^2)/24*AA9^2)+(O9*AA9*C9/4))*0.5) -> 0.52722206 | AN9: =D9*(1+(((2-3*P9^2)/24*AB9^2)+(P9*AB9*D9/4))*0.5) -> 0.50033027 | AO9: =E9*(1+(((2-3*Q9^2)/24*AC9^2)+(Q9*AC9*E9/4))*0.5) -> 0.49142801 | AP9: =F9*(1+(((2-3*R9^2)/24*AD9^2)+(R9*AD9*F9/4))*0.5) -> 0.47349686 | AQ9: =G9*(1+(((2-3*S9^2)/24*AE9^2)+(S9*AE9*G9/4))*0.5) -> 0.45623289 | AR9: =H9*(1+(((2-3*T9^2)/24*AF9^2)+(T9*AF9*H9/4))*0.5) -> 0.43693584 | AS9: =I9*(1+(((2-3*U9^2)/24*AG9^2)+(U9*AG9*I9/4))*0.5) -> 0.42800691 | AT9: =J9*(1+(((2-3*V9^2)/24*AH9^2)+(V9*AH9*J9/4))*0.5) -> 0.41358023 | ... AV9: =L9*(1+(((2-3*X9^2)/24*AJ9^2)+(X9*AJ9*L9/4))*0.5) -> 0.37395831
B10: 1Y | C10: 0.501 | D10: 0.491 | E10: 0.4731 | F10: 0.4573 | G10: 0.4289 | H10: 0.415 | I10: 0.3972 | J10: 0.391 | K10: 0.3758 | L10: 0.343 | N10: 1Y | O10: -0.2981 | P10: -0.2776 | Q10: -0.2581 | R10: -0.2336 | S10: -0.2121 | T10: -0.1992 | U10: -0.1849 | V10: -0.1572 | W10: -0.1387 | X10: -0.1153 | Z10: 1Y | AA10: 0.7924 | AB10: 0.7649 | AC10: 0.7392 | AD10: 0.719 | AE10: 0.698 | AF10: 0.6633 | AG10: 0.658 | AH10: 0.6334 | AI10: 0.613 | AJ10: 0.5893 | AL10: 1Y | AM10: =C10*(1+(((2-3*O10^2)/24*AA10^2)+(O10*AA10*C10/4))*1) -> 0.50889791 | AN10: =D10*(1+(((2-3*P10^2)/24*AB10^2)+(P10*AB10*D10/4))*1) -> 0.49937444 | AO10: =E10*(1+(((2-3*Q10^2)/24*AC10^2)+(Q10*AC10*E10/4))*1) -> 0.48181419 | AP10: =F10*(1+(((2-3*R10^2)/24*AD10^2)+(R10*AD10*F10/4))*1) -> 0.46660696 | AQ10: =G10*(1+(((2-3*S10^2)/24*AE10^2)+(S10*AE10*G10/4))*1) -> 0.43832998 | AR10: =H10*(1+(((2-3*T10^2)/24*AF10^2)+(T10*AF10*H10/4))*1) -> 0.42362088 | AS10: =I10*(1+(((2-3*U10^2)/24*AG10^2)+(U10*AG10*I10/4))*1) -> 0.40599751 | AT10: =J10*(1+(((2-3*V10^2)/24*AH10^2)+(V10*AH10*J10/4))*1) -> 0.39978212 | ... AV10: =L10*(1+(((2-3*X10^2)/24*AJ10^2)+(X10*AJ10*L10/4))*1) -> 0.35072987
B11: 2Y | C11: 0.4812 | D11: 0.4646 | E11: 0.4421 | F11: 0.436 | G11: 0.4079 | H11: 0.3913 | I11: 0.3775 | J11: 0.3599 | K11: 0.3468 | L11: 0.3244 | N11: 2Y | O11: -0.2822 | P11: -0.2598 | Q11: -0.2413 | R11: -0.2166 | S11: -0.2039 | T11: -0.1675 | U11: -0.1533 | V11: -0.1431 | W11: -0.1216 | X11: -0.1003 | Z11: 2Y | AA11: 0.7584 | AB11: 0.7313 | AC11: 0.7236 | AD11: 0.7043 | AE11: 0.6715 | AF11: 0.6497 | AG11: 0.6195 | AH11: 0.5976 | AI11: 0.5802 | AJ11: 0.5564 | AL11: 2Y | AM11: =C11*(1+(((2-3*O11^2)/24*AA11^2)+(O11*AA11*C11/4))*2) -> 0.49703978 | AN11: =D11*(1+(((2-3*P11^2)/24*AB11^2)+(P11*AB11*D11/4))*2) -> 0.48131351 | AO11: =E11*(1+(((2-3*Q11^2)/24*AC11^2)+(Q11*AC11*E11/4))*2) -> 0.46024736 | AP11: =F11*(1+(((2-3*R11^2)/24*AD11^2)+(R11*AD11*F11/4))*2) -> 0.45500912 | AQ11: =G11*(1+(((2-3*S11^2)/24*AE11^2)+(S11*AE11*G11/4))*2) -> 0.42525237 | AR11: =H11*(1+(((2-3*T11^2)/24*AF11^2)+(T11*AF11*H11/4))*2) -> 0.4093387 | AS11: =I11*(1+(((2-3*U11^2)/24*AG11^2)+(U11*AG11*I11/4))*2) -> 0.39402813 | AT11: =J11*(1+(((2-3*V11^2)/24*AH11^2)+(V11*AH11*J11/4))*2) -> 0.3751252 | ... AV11: =L11*(1+(((2-3*X11^2)/24*AJ11^2)+(X11*AJ11*L11/4))*2) -> 0.337949
B12: 3Y | C12: 0.4732 | D12: 0.4432 | E12: 0.4238 | F12: 0.4257 | G12: 0.4006 | H12: 0.3763 | I12: 0.3675 | J12: 0.3405 | K12: 0.3339 | L12: 0.3262 | N12: 3Y | O12: -0.2455 | P12: -0.2294 | Q12: -0.2187 | R12: -0.1971 | S12: -0.1817 | T12: -0.1501 | U12: -0.1355 | V12: -0.1111 | W12: -0.1006 | X12: -0.0833 | Z12: 3Y | AA12: 0.7451 | AB12: 0.7264 | AC12: 0.7015 | AD12: 0.6783 | AE12: 0.6564 | AF12: 0.6326 | AG12: 0.6001 | AH12: 0.5837 | AI12: 0.5582 | AJ12: 0.5295 | AL12: 3Y | AM12: =C12*(1+(((2-3*O12^2)/24*AA12^2)+(O12*AA12*C12/4))*3) -> 0.50221984 | AN12: =D12*(1+(((2-3*P12^2)/24*AB12^2)+(P12*AB12*D12/4))*3) -> 0.47250063 | AO12: =E12*(1+(((2-3*Q12^2)/24*AC12^2)+(Q12*AC12*E12/4))*3) -> 0.45153145 | AP12: =F12*(1+(((2-3*R12^2)/24*AD12^2)+(R12*AD12*F12/4))*3) -> 0.45364092 | AQ12: =G12*(1+(((2-3*S12^2)/24*AE12^2)+(S12*AE12*G12/4))*3) -> 0.42725869 | AR12: =H12*(1+(((2-3*T12^2)/24*AF12^2)+(T12*AF12*H12/4))*3) -> 0.40259075 | AS12: =I12*(1+(((2-3*U12^2)/24*AG12^2)+(U12*AG12*I12/4))*3) -> 0.3914384 | AT12: =J12*(1+(((2-3*V12^2)/24*AH12^2)+(V12*AH12*J12/4))*3) -> 0.36332663 | ... AV12: =L12*(1+(((2-3*X12^2)/24*AJ12^2)+(X12*AJ12*L12/4))*3) -> 0.34530624
B13: 5Y | C13: 0.4406 | D13: 0.4289 | E13: 0.4119 | F13: 0.4039 | G13: 0.3925 | H13: 0.3656 | I13: 0.3587 | J13: 0.3431 | K13: 0.3258 | L13: 0.2973 | N13: 5Y | O13: -0.2389 | P13: -0.2194 | Q13: -0.2005 | R13: -0.1809 | S13: -0.1531 | T13: -0.1281 | U13: -0.1099 | V13: -0.0976 | W13: -0.0747 | X13: -0.0523 | Z13: 5Y | AA13: 0.7084 | AB13: 0.6977 | AC13: 0.6804 | AD13: 0.6556 | AE13: 0.6328 | AF13: 0.6051 | AG13: 0.5769 | AH13: 0.5669 | AI13: 0.5355 | AJ13: 0.5227 | AL13: 5Y | AM13: =C13*(1+(((2-3*O13^2)/24*AA13^2)+(O13*AA13*C13/4))*5) -> 0.48377362 | AN13: =D13*(1+(((2-3*P13^2)/24*AB13^2)+(P13*AB13*D13/4))*5) -> 0.47441256 | AO13: =E13*(1+(((2-3*Q13^2)/24*AC13^2)+(Q13*AC13*E13/4))*5) -> 0.45763017 | AP13: =F13*(1+(((2-3*R13^2)/24*AD13^2)+(R13*AD13*F13/4))*5) -> 0.44849862 | AQ13: =G13*(1+(((2-3*S13^2)/24*AE13^2)+(S13*AE13*G13/4))*5) -> 0.43702889 | AR13: =H13*(1+(((2-3*T13^2)/24*AF13^2)+(T13*AF13*H13/4))*5) -> 0.40705248 | AS13: =I13*(1+(((2-3*U13^2)/24*AG13^2)+(U13*AG13*I13/4))*5) -> 0.39734363 | AT13: =J13*(1+(((2-3*V13^2)/24*AH13^2)+(V13*AH13*J13/4))*5) -> 0.38024529 | ... AV13: =L13*(1+(((2-3*X13^2)/24*AJ13^2)+(X13*AJ13*L13/4))*5) -> 0.32798535
B14: 10Y | C14: 0.4428 | D14: 0.4146 | E14: 0.398 | F14: 0.3923 | G14: 0.3712 | H14: 0.3434 | I14: 0.3259 | J14: 0.3097 | K14: 0.3081 | L14: 0.2895 | N14: 10Y | O14: -0.221 | P14: -0.1879 | Q14: -0.1654 | R14: -0.1524 | S14: -0.1391 | T14: -0.1157 | U14: -0.1046 | V14: -0.0875 | W14: -0.0489 | X14: -0.0359 | Z14: 10Y | AA14: 0.695 | AB14: 0.6809 | AC14: 0.6487 | AD14: 0.6352 | AE14: 0.6121 | AF14: 0.5776 | AG14: 0.5561 | AH14: 0.5347 | AI14: 0.5115 | AJ14: 0.4962 | AL14: 10Y | AM14: =C14*(1+(((2-3*O14^2)/24*AA14^2)+(O14*AA14*C14/4))*10) -> 0.53268924 | AN14: =D14*(1+(((2-3*P14^2)/24*AB14^2)+(P14*AB14*D14/4))*10) -> 0.51131867 | AO14: =E14*(1+(((2-3*Q14^2)/24*AC14^2)+(Q14*AC14*E14/4))*10) -> 0.489352 | AP14: =F14*(1+(((2-3*R14^2)/24*AD14^2)+(R14*AD14*F14/4))*10) -> 0.48236331 | AQ14: =G14*(1+(((2-3*S14^2)/24*AE14^2)+(S14*AE14*G14/4))*10) -> 0.45440356 | AR14: =H14*(1+(((2-3*T14^2)/24*AF14^2)+(T14*AF14*H14/4))*10) -> 0.4172528 | AS14: =I14*(1+(((2-3*U14^2)/24*AG14^2)+(U14*AG14*I14/4))*10) -> 0.39306283 | AT14: =J14*(1+(((2-3*V14^2)/24*AH14^2)+(V14*AH14*J14/4))*10) -> 0.37142103 | ... AV14: =L14*(1+(((2-3*X14^2)/24*AJ14^2)+(X14*AJ14*L14/4))*10) -> 0.345052
B15: 20Y | C15: 0.4119 | D15: 0.3984 | E15: 0.376 | F15: 0.3749 | G15: 0.3471 | H15: 0.3325 | I15: 0.3183 | J15: 0.3081 | K15: 0.2817 | L15: 0.275 | N15: 20Y | O15: -0.1944 | P15: -0.1744 | Q15: -0.1551 | R15: -0.1457 | S15: -0.1179 | T15: -0.1036 | U15: -0.0877 | V15: -0.0523 | W15: -0.0454 | X15: -0.02 | Z15: 20Y | AA15: 0.6767 | AB15: 0.6511 | AC15: 0.6243 | AD15: 0.6059 | AE15: 0.5844 | AF15: 0.5668 | AG15: 0.531 | AH15: 0.5179 | AI15: 0.4894 | AJ15: 0.4678 | AL15: 20Y | AM15: =C15*(1+(((2-3*O15^2)/24*AA15^2)+(O15*AA15*C15/4))*20) -> 0.59684836 | AN15: =D15*(1+(((2-3*P15^2)/24*AB15^2)+(P15*AB15*D15/4))*20) -> 0.57693169 | AO15: =E15*(1+(((2-3*Q15^2)/24*AC15^2)+(Q15*AC15*E15/4))*20) -> 0.54298392 | AP15: =F15*(1+(((2-3*R15^2)/24*AD15^2)+(R15*AD15*F15/4))*20) -> 0.53494279 | AQ15: =G15*(1+(((2-3*S15^2)/24*AE15^2)+(S15*AE15*G15/4))*20) -> 0.49904651 | AR15: =H15*(1+(((2-3*T15^2)/24*AF15^2)+(T15*AF15*H15/4))*20) -> 0.47520702 | AS15: =I15*(1+(((2-3*U15^2)/24*AG15^2)+(U15*AG15*I15/4))*20) -> 0.4425641 | AT15: =J15*(1+(((2-3*V15^2)/24*AH15^2)+(V15*AH15*J15/4))*20) -> 0.43241022 | ... AV15: =L15*(1+(((2-3*X15^2)/24*AJ15^2)+(X15*AJ15*L15/4))*20) -> 0.3717023
B16: 30Y | C16: 0.4054 | D16: 0.3835 | E16: 0.3679 | F16: 0.3552 | G16: 0.3416 | H16: 0.3155 | I16: 0.3023 | J16: 0.2834 | K16: 0.2669 | L16: 0.2539 | N16: 30Y | O16: -0.176 | P16: -0.1549 | Q16: -0.1366 | R16: -0.1078 | S16: -0.0932 | T16: -0.0702 | U16: -0.0495 | V16: -0.0437 | W16: -0.0183 | X16: 0.0089 | Z16: 30Y | AA16: 0.6568 | AB16: 0.6205 | AC16: 0.598 | AD16: 0.5822 | AE16: 0.5526 | AF16: 0.5337 | AG16: 0.5081 | AH16: 0.4978 | AI16: 0.4779 | AJ16: 0.4579 | AL16: 30Y | AM16: =C16*(1+(((2-3*O16^2)/24*AA16^2)+(O16*AA16*C16/4))*30) -> 0.67980865 | AN16: =D16*(1+(((2-3*P16^2)/24*AB16^2)+(P16*AB16*D16/4))*30) -> 0.63333314 | AO16: =E16*(1+(((2-3*Q16^2)/24*AC16^2)+(Q16*AC16*E16/4))*30) -> 0.60467785 | AP16: =F16*(1+(((2-3*R16^2)/24*AD16^2)+(R16*AD16*F16/4))*30) -> 0.59155905 | AQ16: =G16*(1+(((2-3*S16^2)/24*AE16^2)+(S16*AE16*G16/4))*30) -> 0.55391162 | AR16: =H16*(1+(((2-3*T16^2)/24*AF16^2)+(T16*AF16*H16/4))*30) -> 0.5105333 | AS16: =I16*(1+(((2-3*U16^2)/24*AG16^2)+(U16*AG16*I16/4))*30) -> 0.47945336 | AT16: =J16*(1+(((2-3*V16^2)/24*AH16^2)+(V16*AH16*J16/4))*30) -> 0.445363 | ... AV16: =L16*(1+(((2-3*X16^2)/24*AJ16^2)+(X16*AJ16*L16/4))*30) -> 0.38894412
A18: Combined = Hagan SABR ATM-vol asymptotic approximation with beta=1 (lognormal): sigma_ATM = alpha*(1+((2-3*rho^2)/24*nu^2+rho*nu*alpha/4)*T). Collapses ATM/RHO/NU into one usable vol surface per scenario.
A20: SECTION 2 - SCENARIO SHOCKS: Per-Param Shock Size + Sensitivity Factor Grid
B21: Shocked(i,j) = Base(i,j) + ScenarioShockSize(param,scenario) x SensitivityFactor(i,j) for ATM/RHO/NU. Combined Effective Vol is then recomputed from the SHOCKED ATM/RHO/NU via the same Hagan formula shown in Section 1 - i.e. the single 'shocked SABR curve' is derived, not separately shocked.
B24: Scenario Shock Size (per param, parallel move applied before sensitivity scaling)
B25: Scenario | C25: ATM | D25: RHO | E25: NU
B26: Scenario 1 | C26: 0.0099 | D26: 0.0057 | E26: 0.0224
B27: Scenario 2 | C27: 0.0125 | D27: 0.0065 | E27: 0.0206
B28: Scenario 3 | C28: 0.012 | D28: 0.0077 | E28: 0.0249
B29: Scenario 4 | C29: 0.0205 | D29: 0.0056 | E29: 0.0233
B30: Scenario 5 | C30: 0.0159 | D30: 0.0125 | E30: 0.0331
B31: Scenario 6 | C31: 0.0178 | D31: 0.0151 | E31: 0.041
B32: Scenario 7 | C32: 0.0263 | D32: 0.0133 | E32: 0.0317
B33: Scenario 8 | C33: 0.0224 | D33: 0.0138 | E33: 0.0338
B34: Scenario 9 | C34: 0.0265 | D34: 0.0127 | E34: 0.0369
B35: Scenario 10 | C35: 0.0316 | D35: 0.0155 | E35: 0.0535
B38: Sensitivity Factor Grid (shared shape across ATM/RHO/NU; applied to all scenarios)
B39: Expiry \ Tenor | C39: 1M | D39: 3M | E39: 6M | F39: 1Y | G39: 2Y | H39: 3Y | I39: 5Y | J39: 10Y | K39: 20Y | L39: 30Y
B40: 1M | C40: 1.601 | D40: 1.518 | E40: 1.42 | F40: 1.34 | G40: 1.237 | H40: 1.137 | I40: 1.09 | J40: 1 | K40: 0.9 | L40: 0.802
B41: 3M | C41: 1.499 | D41: 1.404 | E41: 1.317 | F41: 1.214 | G41: 1.166 | H41: 1.054 | I41: 0.991 | J41: 0.873 | K41: 0.817 | L41: 0.721
B42: 6M | C42: 1.39 | D42: 1.313 | E42: 1.265 | F42: 1.148 | G42: 1.089 | H42: 0.964 | I42: 0.854 | J42: 0.798 | K42: 0.717 | L42: 0.596
B43: 1Y | C43: 1.305 | D43: 1.23 | E43: 1.178 | F43: 1.075 | G43: 0.947 | H43: 0.865 | I43: 0.766 | J43: 0.674 | K43: 0.628 | L43: 0.501
B44: 2Y | C44: 1.244 | D44: 1.147 | E44: 1.041 | F44: 0.984 | G44: 0.858 | H44: 0.799 | I44: 0.677 | J44: 0.605 | K44: 0.503 | L44: 0.416
B45: 3Y | C45: 1.178 | D45: 1.078 | E45: 0.958 | F45: 0.903 | G45: 0.773 | H45: 0.694 | I45: 0.631 | J45: 0.529 | K45: 0.406 | L45: 0.369
B46: 5Y | C46: 1.043 | D46: 0.955 | E46: 0.896 | F46: 0.78 | G46: 0.688 | H46: 0.584 | I46: 0.495 | J46: 0.435 | K46: 0.325 | L46: 0.256
B47: 10Y | C47: 0.962 | D47: 0.877 | E47: 0.818 | F47: 0.699 | G47: 0.614 | H47: 0.542 | I47: 0.411 | J47: 0.319 | K47: 0.275 | L47: 0.179
B48: 20Y | C48: 0.865 | D48: 0.771 | E48: 0.714 | F48: 0.636 | G48: 0.502 | H48: 0.457 | I48: 0.363 | J48: 0.256 | K48: 0.155 | L48: 0.15
B49: 30Y | C49: 0.762 | D49: 0.728 | E49: 0.594 | F49: 0.532 | G49: 0.415 | H49: 0.359 | I49: 0.256 | J49: 0.15 | K49: 0.15 | L49: 0.15
A51: SECTION 3 - SHOCKED SABR SURFACES: ATM, RHO, NU, Combined Effective Vol aligned per scenario (10 scenarios)
A52: Combined block recomputes the Hagan formula from this scenario's SHOCKED ATM/RHO/NU -> a single shocked vol surface per scenario.
A54: SCENARIO 1
B55: Param: ATM | N55: Param: RHO | Z55: Param: NU | AL55: Combined Effective ATM Vol (Hagan approx, beta=1)
B56: Expiry \ Tenor | C56: 1M | D56: 3M | E56: 6M | F56: 1Y | G56: 2Y | H56: 3Y | I56: 5Y | J56: 10Y | K56: 20Y | L56: 30Y | N56: Expiry \ Tenor | O56: 1M | P56: 3M | Q56: 6M | R56: 1Y | S56: 2Y | T56: 3Y | U56: 5Y | V56: 10Y | W56: 20Y | X56: 30Y | Z56: Expiry \ Tenor | AA56: 1M | AB56: 3M | AC56: 6M | AD56: 1Y | AE56: 2Y | AF56: 3Y | AG56: 5Y | AH56: 10Y | AI56: 20Y | AJ56: 30Y | AL56: Expiry \ Tenor | AM56: 1M | AN56: 3M | AO56: 6M | AP56: 1Y | AQ56: 2Y | AR56: 3Y | AS56: 5Y | AT56: 10Y | AU56: 20Y | AV56: 30Y
B57: 1M | C57: =C7+$C$26*C40 -> 0.5623499 | D57: =D7+$C$26*D40 -> 0.5414282 | E57: =E7+$C$26*E40 -> 0.533758 | F57: =F7+$C$26*F40 -> 0.504666 | G57: =G7+$C$26*G40 -> 0.4963463 | H57: =H7+$C$26*H40 -> 0.4752563 | I57: =I7+$C$26*I40 -> 0.451991 | J57: =J7+$C$26*J40 -> 0.4434 | ... L57: =L7+$C$26*L40 -> 0.4066398 | N57: 1M | O57: =O7+$D$26*O40 -> -0.3586 | P57: =P7+$D$26*P40 -> -0.3387 | Q57: =Q7+$D$26*Q40 -> -0.3126 | R57: =R7+$D$26*R40 -> -0.2851 | S57: =S7+$D$26*S40 -> -0.2797 | T57: =T7+$D$26*T40 -> -0.2583 | U57: =U7+$D$26*U40 -> -0.2308 | V57: =V7+$D$26*V40 -> -0.2049 | ... X57: =X7+$D$26*X40 -> -0.1771 | Z57: 1M | AA57: =AA7+$E$26*AA40 -> 0.8595 | AB57: =AB7+$E$26*AB40 -> 0.8187 | AC57: =AC7+$E$26*AC40 -> 0.8127 | AD57: =AD7+$E$26*AD40 -> 0.7791 | AE57: =AE7+$E$26*AE40 -> 0.754 | AF57: =AF7+$E$26*AF40 -> 0.7312 | AG57: =AG7+$E$26*AG40 -> 0.7128 | AH57: =AH7+$E$26*AH40 -> 0.7008 | ... AJ57: =AJ7+$E$26*AJ40 -> 0.6516 | AL57: 1M | AM57: =C57*(1+(((2-3*O57^2)/24*AA57^2)+(O57*AA57*C57/4))*0.0833333333333333) -> 0.56264774 | AN57: =D57*(1+(((2-3*P57^2)/24*AB57^2)+(P57*AB57*D57/4))*0.0833333333333333) -> 0.54182122 | AO57: =E57*(1+(((2-3*Q57^2)/24*AC57^2)+(Q57*AC57*E57/4))*0.0833333333333333) -> 0.53433945 | AP57: =F57*(1+(((2-3*R57^2)/24*AD57^2)+(R57*AD57*F57/4))*0.0833333333333333) -> 0.50535535 | AQ57: =G57*(1+(((2-3*S57^2)/24*AE57^2)+(S57*AE57*G57/4))*0.0833333333333333) -> 0.49699352 | AR57: =H57*(1+(((2-3*T57^2)/24*AF57^2)+(T57*AF57*H57/4))*0.0833333333333333) -> 0.47595553 | AS57: =I57*(1+(((2-3*U57^2)/24*AG57^2)+(U57*AG57*I57/4))*0.0833333333333333) -> 0.45275816 | AT57: =J57*(1+(((2-3*V57^2)/24*AH57^2)+(V57*AH57*J57/4))*0.0833333333333333) -> 0.44422886 | ... AV57: =L57*(1+(((2-3*X57^2)/24*AJ57^2)+(X57*AJ57*L57/4))*0.0833333333333333) -> 0.40738483
B58: 3M | C58: =C8+$C$26*C41 -> 0.5509401 | D58: =D8+$C$26*D41 -> 0.5279996 | E58: =E8+$C$26*E41 -> 0.5140383 | F58: =F8+$C$26*F41 -> 0.4866186 | G58: =G8+$C$26*G41 -> 0.4694434 | H58: =H8+$C$26*H41 -> 0.4545346 | I58: =I8+$C$26*I41 -> 0.4467109 | J58: =J8+$C$26*J41 -> 0.4238427 | ... L58: =L8+$C$26*L41 -> 0.3921379 | N58: 3M | O58: =O8+$D$26*O41 -> -0.3315 | P58: =P8+$D$26*P41 -> -0.3151 | Q58: =Q8+$D$26*Q41 -> -0.2858 | R58: =R8+$D$26*R41 -> -0.2682 | S58: =S8+$D$26*S41 -> -0.2579 | T58: =T8+$D$26*T41 -> -0.2318 | U58: =U8+$D$26*U41 -> -0.2134 | V58: =V8+$D$26*V41 -> -0.1869 | ... X58: =X8+$D$26*X41 -> -0.1598 | Z58: 3M | AA58: =AA8+$E$26*AA41 -> 0.8374 | AB58: =AB8+$E$26*AB41 -> 0.7979 | AC58: =AC8+$E$26*AC41 -> 0.7817 | AD58: =AD8+$E$26*AD41 -> 0.7663 | AE58: =AE8+$E$26*AE41 -> 0.7319 | AF58: =AF8+$E$26*AF41 -> 0.7164 | AG58: =AG8+$E$26*AG41 -> 0.6852 | AH58: =AH8+$E$26*AH41 -> 0.6756 | ... AJ58: =AJ8+$E$26*AJ41 -> 0.6292 | AL58: 3M | AM58: =C58*(1+(((2-3*O58^2)/24*AA58^2)+(O58*AA58*C58/4))*0.25) -> 0.55239582 | AN58: =D58*(1+(((2-3*P58^2)/24*AB58^2)+(P58*AB58*D58/4))*0.25) -> 0.52957899 | AO58: =E58*(1+(((2-3*Q58^2)/24*AC58^2)+(Q58*AC58*E58/4))*0.25) -> 0.51609085 | AP58: =F58*(1+(((2-3*R58^2)/24*AD58^2)+(R58*AD58*F58/4))*0.25) -> 0.48888771 | AQ58: =G58*(1+(((2-3*S58^2)/24*AE58^2)+(S58*AE58*G58/4))*0.25) -> 0.47155982 | AR58: =H58*(1+(((2-3*T58^2)/24*AF58^2)+(T58*AF58*H58/4))*0.25) -> 0.45685862 | AS58: =I58*(1+(((2-3*U58^2)/24*AG58^2)+(U58*AG58*I58/4))*0.25) -> 0.44895815 | AT58: =J58*(1+(((2-3*V58^2)/24*AH58^2)+(V58*AH58*J58/4))*0.25) -> 0.42624416 | ... AV58: =L58*(1+(((2-3*X58^2)/24*AJ58^2)+(X58*AJ58*L58/4))*0.25) -> 0.39428195
B59: 6M | C59: =C9+$C$26*C42 -> 0.537961 | D59: =D9+$C$26*D42 -> 0.5092987 | E59: =E9+$C$26*E42 -> 0.4997235 | F59: =F9+$C$26*F42 -> 0.4799652 | G59: =G9+$C$26*G42 -> 0.4623811 | H59: =H9+$C$26*H42 -> 0.4420436 | I59: =I9+$C$26*I42 -> 0.4319546 | J59: =J9+$C$26*J42 -> 0.4168002 | ... L59: =L9+$C$26*L42 -> 0.3758004 | N59: 6M | O59: =O9+$D$26*O42 -> -0.3199 | P59: =P9+$D$26*P42 -> -0.2876 | Q59: =Q9+$D$26*Q42 -> -0.2693 | R59: =R9+$D$26*R42 -> -0.2429 | S59: =S9+$D$26*S42 -> -0.2269 | T59: =T9+$D$26*T42 -> -0.2182 | U59: =U9+$D$26*U42 -> -0.1967 | V59: =V9+$D$26*V42 -> -0.1716 | ... X59: =X9+$D$26*X42 -> -0.1369 | Z59: 6M | AA59: =AA9+$E$26*AA42 -> 0.7989 | AB59: =AB9+$E$26*AB42 -> 0.7757 | AC59: =AC9+$E$26*AC42 -> 0.7523 | AD59: =AD9+$E$26*AD42 -> 0.7443 | AE59: =AE9+$E$26*AE42 -> 0.7093 | AF59: =AF9+$E$26*AF42 -> 0.6894 | AG59: =AG9+$E$26*AG42 -> 0.67 | AH59: =AH9+$E$26*AH42 -> 0.6574 | ... AJ59: =AJ9+$E$26*AJ42 -> 0.6045 | AL59: 6M | AM59: =C59*(1+(((2-3*O59^2)/24*AA59^2)+(O59*AA59*C59/4))*0.5) -> 0.5408259 | AN59: =D59*(1+(((2-3*P59^2)/24*AB59^2)+(P59*AB59*D59/4))*0.5) -> 0.51324991 | AO59: =E59*(1+(((2-3*Q59^2)/24*AC59^2)+(Q59*AC59*E59/4))*0.5) -> 0.50390171 | AP59: =F59*(1+(((2-3*R59^2)/24*AD59^2)+(R59*AD59*F59/4))*0.5) -> 0.48485755 | AQ59: =G59*(1+(((2-3*S59^2)/24*AE59^2)+(S59*AE59*G59/4))*0.5) -> 0.46702431 | AR59: =H59*(1+(((2-3*T59^2)/24*AF59^2)+(T59*AF59*H59/4))*0.5) -> 0.446498 | AS59: =I59*(1+(((2-3*U59^2)/24*AG59^2)+(U59*AG59*I59/4))*0.5) -> 0.43649133 | AT59: =J59*(1+(((2-3*V59^2)/24*AH59^2)+(V59*AH59*J59/4))*0.5) -> 0.42152442 | ... AV59: =L59*(1+(((2-3*X59^2)/24*AJ59^2)+(X59*AJ59*L59/4))*0.5) -> 0.37990051
B60: 1Y | C60: =C10+$C$26*C43 -> 0.5139195 | D60: =D10+$C$26*D43 -> 0.503177 | E60: =E10+$C$26*E43 -> 0.4847622 | F60: =F10+$C$26*F43 -> 0.4679425 | G60: =G10+$C$26*G43 -> 0.4382753 | H60: =H10+$C$26*H43 -> 0.4235635 | I60: =I10+$C$26*I43 -> 0.4047834 | J60: =J10+$C$26*J43 -> 0.3976726 | ... L60: =L10+$C$26*L43 -> 0.3479599 | N60: 1Y | O60: =O10+$D$26*O43 -> -0.2981 | P60: =P10+$D$26*P43 -> -0.2776 | Q60: =Q10+$D$26*Q43 -> -0.2581 | R60: =R10+$D$26*R43 -> -0.2336 | S60: =S10+$D$26*S43 -> -0.2121 | T60: =T10+$D$26*T43 -> -0.1992 | U60: =U10+$D$26*U43 -> -0.1849 | V60: =V10+$D$26*V43 -> -0.1572 | ... X60: =X10+$D$26*X43 -> -0.1153 | Z60: 1Y | AA60: =AA10+$E$26*AA43 -> 0.7924 | AB60: =AB10+$E$26*AB43 -> 0.7649 | AC60: =AC10+$E$26*AC43 -> 0.7392 | AD60: =AD10+$E$26*AD43 -> 0.719 | AE60: =AE10+$E$26*AE43 -> 0.698 | AF60: =AF10+$E$26*AF43 -> 0.6633 | AG60: =AG10+$E$26*AG43 -> 0.658 | AH60: =AH10+$E$26*AH43 -> 0.6334 | ... AJ60: =AJ10+$E$26*AJ43 -> 0.5893 | AL60: 1Y | AM60: =C60*(1+(((2-3*O60^2)/24*AA60^2)+(O60*AA60*C60/4))*1) -> 0.52162899 | AN60: =D60*(1+(((2-3*P60^2)/24*AB60^2)+(P60*AB60*D60/4))*1) -> 0.51143388 | AO60: =E60*(1+(((2-3*Q60^2)/24*AC60^2)+(Q60*AC60*E60/4))*1) -> 0.49342155 | AP60: =F60*(1+(((2-3*R60^2)/24*AD60^2)+(R60*AD60*F60/4))*1) -> 0.47725695 | AQ60: =G60*(1+(((2-3*S60^2)/24*AE60^2)+(S60*AE60*G60/4))*1) -> 0.44775933 | AR60: =H60*(1+(((2-3*T60^2)/24*AF60^2)+(T60*AF60*H60/4))*1) -> 0.43224246 | AS60: =I60*(1+(((2-3*U60^2)/24*AG60^2)+(U60*AG60*I60/4))*1) -> 0.4136555 | AT60: =J60*(1+(((2-3*V60^2)/24*AH60^2)+(V60*AH60*J60/4))*1) -> 0.40653854 | ... AV60: =L60*(1+(((2-3*X60^2)/24*AJ60^2)+(X60*AJ60*L60/4))*1) -> 0.35577223
B61: 2Y | C61: =C11+$C$26*C44 -> 0.4935156 | D61: =D11+$C$26*D44 -> 0.4759553 | E61: =E11+$C$26*E44 -> 0.4524059 | F61: =F11+$C$26*F44 -> 0.4457416 | G61: =G11+$C$26*G44 -> 0.4163942 | H61: =H11+$C$26*H44 -> 0.3992101 | I61: =I11+$C$26*I44 -> 0.3842023 | J61: =J11+$C$26*J44 -> 0.3658895 | ... L61: =L11+$C$26*L44 -> 0.3285184 | N61: 2Y | O61: =O11+$D$26*O44 -> -0.2822 | P61: =P11+$D$26*P44 -> -0.2598 | Q61: =Q11+$D$26*Q44 -> -0.2413 | R61: =R11+$D$26*R44 -> -0.2166 | S61: =S11+$D$26*S44 -> -0.2039 | T61: =T11+$D$26*T44 -> -0.1675 | U61: =U11+$D$26*U44 -> -0.1533 | V61: =V11+$D$26*V44 -> -0.1431 | ... X61: =X11+$D$26*X44 -> -0.1003 | Z61: 2Y | AA61: =AA11+$E$26*AA44 -> 0.7584 | AB61: =AB11+$E$26*AB44 -> 0.7313 | AC61: =AC11+$E$26*AC44 -> 0.7236 | AD61: =AD11+$E$26*AD44 -> 0.7043 | AE61: =AE11+$E$26*AE44 -> 0.6715 | AF61: =AF11+$E$26*AF44 -> 0.6497 | AG61: =AG11+$E$26*AG44 -> 0.6195 | AH61: =AH11+$E$26*AH44 -> 0.5976 | ... AJ61: =AJ11+$E$26*AJ44 -> 0.5564 | AL61: 2Y | AM61: =C61*(1+(((2-3*O61^2)/24*AA61^2)+(O61*AA61*C61/4))*2) -> 0.50911037 | AN61: =D61*(1+(((2-3*P61^2)/24*AB61^2)+(P61*AB61*D61/4))*2) -> 0.49256389 | AO61: =E61*(1+(((2-3*Q61^2)/24*AC61^2)+(Q61*AC61*E61/4))*2) -> 0.47056926 | AP61: =F61*(1+(((2-3*R61^2)/24*AD61^2)+(R61*AD61*F61/4))*2) -> 0.46484424 | AQ61: =G61*(1+(((2-3*S61^2)/24*AE61^2)+(S61*AE61*G61/4))*2) -> 0.43386578 | AR61: =H61*(1+(((2-3*T61^2)/24*AF61^2)+(T61*AF61*H61/4))*2) -> 0.41744163 | AS61: =I61*(1+(((2-3*U61^2)/24*AG61^2)+(U61*AG61*I61/4))*2) -> 0.4009016 | AT61: =J61*(1+(((2-3*V61^2)/24*AH61^2)+(V61*AH61*J61/4))*2) -> 0.38127438 | ... AV61: =L61*(1+(((2-3*X61^2)/24*AJ61^2)+(X61*AJ61*L61/4))*2) -> 0.34220166
B62: 3Y | C62: =C12+$C$26*C45 -> 0.4848622 | D62: =D12+$C$26*D45 -> 0.4538722 | E62: =E12+$C$26*E45 -> 0.4332842 | F62: =F12+$C$26*F45 -> 0.4346397 | G62: =G12+$C$26*G45 -> 0.4082527 | H62: =H12+$C$26*H45 -> 0.3831706 | I62: =I12+$C$26*I45 -> 0.3737469 | J62: =J12+$C$26*J45 -> 0.3457371 | ... L62: =L12+$C$26*L45 -> 0.3298531 | N62: 3Y | O62: =O12+$D$26*O45 -> -0.2455 | P62: =P12+$D$26*P45 -> -0.2294 | Q62: =Q12+$D$26*Q45 -> -0.2187 | R62: =R12+$D$26*R45 -> -0.1971 | S62: =S12+$D$26*S45 -> -0.1817 | T62: =T12+$D$26*T45 -> -0.1501 | U62: =U12+$D$26*U45 -> -0.1355 | V62: =V12+$D$26*V45 -> -0.1111 | ... X62: =X12+$D$26*X45 -> -0.0833 | Z62: 3Y | AA62: =AA12+$E$26*AA45 -> 0.7451 | AB62: =AB12+$E$26*AB45 -> 0.7264 | AC62: =AC12+$E$26*AC45 -> 0.7015 | AD62: =AD12+$E$26*AD45 -> 0.6783 | AE62: =AE12+$E$26*AE45 -> 0.6564 | AF62: =AF12+$E$26*AF45 -> 0.6326 | AG62: =AG12+$E$26*AG45 -> 0.6001 | AH62: =AH12+$E$26*AH45 -> 0.5837 | ... AJ62: =AJ12+$E$26*AJ45 -> 0.5295 | AL62: 3Y | AM62: =C62*(1+(((2-3*O62^2)/24*AA62^2)+(O62*AA62*C62/4))*3) -> 0.51382148 | AN62: =D62*(1+(((2-3*P62^2)/24*AB62^2)+(P62*AB62*D62/4))*3) -> 0.48327302 | AO62: =E62*(1+(((2-3*Q62^2)/24*AC62^2)+(Q62*AC62*E62/4))*3) -> 0.46116341 | AP62: =F62*(1+(((2-3*R62^2)/24*AD62^2)+(R62*AD62*F62/4))*3) -> 0.46277778 | AQ62: =G62*(1+(((2-3*S62^2)/24*AE62^2)+(S62*AE62*G62/4))*3) -> 0.43514118 | AR62: =H62*(1+(((2-3*T62^2)/24*AF62^2)+(T62*AF62*H62/4))*3) -> 0.40975389 | AS62: =I62*(1+(((2-3*U62^2)/24*AG62^2)+(U62*AG62*I62/4))*3) -> 0.39794982 | AT62: =J62*(1+(((2-3*V62^2)/24*AH62^2)+(V62*AH62*J62/4))*3) -> 0.36882675 | ... AV62: =L62*(1+(((2-3*X62^2)/24*AJ62^2)+(X62*AJ62*L62/4))*3) -> 0.34913344
B63: 5Y | C63: =C13+$C$26*C46 -> 0.4509257 | D63: =D13+$C$26*D46 -> 0.4383545 | E63: =E13+$C$26*E46 -> 0.4207704 | F63: =F13+$C$26*F46 -> 0.411622 | G63: =G13+$C$26*G46 -> 0.3993112 | H63: =H13+$C$26*H46 -> 0.3713816 | I63: =I13+$C$26*I46 -> 0.3636005 | J63: =J13+$C$26*J46 -> 0.3474065 | ... L63: =L13+$C$26*L46 -> 0.2998344 | N63: 5Y | O63: =O13+$D$26*O46 -> -0.2389 | P63: =P13+$D$26*P46 -> -0.2194 | Q63: =Q13+$D$26*Q46 -> -0.2005 | R63: =R13+$D$26*R46 -> -0.1809 | S63: =S13+$D$26*S46 -> -0.1531 | T63: =T13+$D$26*T46 -> -0.1281 | U63: =U13+$D$26*U46 -> -0.1099 | V63: =V13+$D$26*V46 -> -0.0976 | ... X63: =X13+$D$26*X46 -> -0.0523 | Z63: 5Y | AA63: =AA13+$E$26*AA46 -> 0.7084 | AB63: =AB13+$E$26*AB46 -> 0.6977 | AC63: =AC13+$E$26*AC46 -> 0.6804 | AD63: =AD13+$E$26*AD46 -> 0.6556 | AE63: =AE13+$E$26*AE46 -> 0.6328 | AF63: =AF13+$E$26*AF46 -> 0.6051 | AG63: =AG13+$E$26*AG46 -> 0.5769 | AH63: =AH13+$E$26*AH46 -> 0.5669 | ... AJ63: =AJ13+$E$26*AJ46 -> 0.5227 | AL63: 5Y | AM63: =C63*(1+(((2-3*O63^2)/24*AA63^2)+(O63*AA63*C63/4))*5) -> 0.49412613 | AN63: =D63*(1+(((2-3*P63^2)/24*AB63^2)+(P63*AB63*D63/4))*5) -> 0.48407731 | AO63: =E63*(1+(((2-3*Q63^2)/24*AC63^2)+(Q63*AC63*E63/4))*5) -> 0.46684892 | AP63: =F63*(1+(((2-3*R63^2)/24*AD63^2)+(R63*AD63*F63/4))*5) -> 0.45660207 | AQ63: =G63*(1+(((2-3*S63^2)/24*AE63^2)+(S63*AE63*G63/4))*5) -> 0.44428345 | AR63: =H63*(1+(((2-3*T63^2)/24*AF63^2)+(T63*AF63*H63/4))*5) -> 0.41328157 | AS63: =I63*(1+(((2-3*U63^2)/24*AG63^2)+(U63*AG63*I63/4))*5) -> 0.40263086 | AT63: =J63*(1+(((2-3*V63^2)/24*AH63^2)+(V63*AH63*J63/4))*5) -> 0.38491456 | ... AV63: =L63*(1+(((2-3*X63^2)/24*AJ63^2)+(X63*AJ63*L63/4))*5) -> 0.33075537
B64: 10Y | C64: =C14+$C$26*C47 -> 0.4523238 | D64: =D14+$C$26*D47 -> 0.4232823 | E64: =E14+$C$26*E47 -> 0.4060982 | F64: =F14+$C$26*F47 -> 0.3992201 | G64: =G14+$C$26*G47 -> 0.3772786 | H64: =H14+$C$26*H47 -> 0.3487658 | I64: =I14+$C$26*I47 -> 0.3299689 | J64: =J14+$C$26*J47 -> 0.3128581 | ... L64: =L14+$C$26*L47 -> 0.2912721 | N64: 10Y | O64: =O14+$D$26*O47 -> -0.221 | P64: =P14+$D$26*P47 -> -0.1879 | Q64: =Q14+$D$26*Q47 -> -0.1654 | R64: =R14+$D$26*R47 -> -0.1524 | S64: =S14+$D$26*S47 -> -0.1391 | T64: =T14+$D$26*T47 -> -0.1157 | U64: =U14+$D$26*U47 -> -0.1046 | V64: =V14+$D$26*V47 -> -0.0875 | ... X64: =X14+$D$26*X47 -> -0.0359 | Z64: 10Y | AA64: =AA14+$E$26*AA47 -> 0.695 | AB64: =AB14+$E$26*AB47 -> 0.6809 | AC64: =AC14+$E$26*AC47 -> 0.6487 | AD64: =AD14+$E$26*AD47 -> 0.6352 | AE64: =AE14+$E$26*AE47 -> 0.6121 | AF64: =AF14+$E$26*AF47 -> 0.5776 | AG64: =AG14+$E$26*AG47 -> 0.5561 | AH64: =AH14+$E$26*AH47 -> 0.5347 | ... AJ64: =AJ14+$E$26*AJ47 -> 0.4962 | AL64: 10Y | AM64: =C64*(1+(((2-3*O64^2)/24*AA64^2)+(O64*AA64*C64/4))*10) -> 0.54249223 | AN64: =D64*(1+(((2-3*P64^2)/24*AB64^2)+(P64*AB64*D64/4))*10) -> 0.52085091 | AO64: =E64*(1+(((2-3*Q64^2)/24*AC64^2)+(Q64*AC64*E64/4))*10) -> 0.49842682 | AP64: =F64*(1+(((2-3*R64^2)/24*AD64^2)+(R64*AD64*F64/4))*10) -> 0.49020352 | AQ64: =G64*(1+(((2-3*S64^2)/24*AE64^2)+(S64*AE64*G64/4))*10) -> 0.46135651 | AR64: =H64*(1+(((2-3*T64^2)/24*AF64^2)+(T64*AF64*H64/4))*10) -> 0.42345993 | AS64: =I64*(1+(((2-3*U64^2)/24*AG64^2)+(U64*AG64*I64/4))*10) -> 0.39777503 | AT64: =J64*(1+(((2-3*V64^2)/24*AH64^2)+(V64*AH64*J64/4))*10) -> 0.37509295 | ... AV64: =L64*(1+(((2-3*X64^2)/24*AJ64^2)+(X64*AJ64*L64/4))*10) -> 0.34714116
B65: 20Y | C65: =C15+$C$26*C48 -> 0.4204635 | D65: =D15+$C$26*D48 -> 0.4060329 | E65: =E15+$C$26*E48 -> 0.3830686 | F65: =F15+$C$26*F48 -> 0.3811964 | G65: =G15+$C$26*G48 -> 0.3520698 | H65: =H15+$C$26*H48 -> 0.3370243 | I65: =I15+$C$26*I48 -> 0.3218937 | J65: =J15+$C$26*J48 -> 0.3106344 | ... L65: =L15+$C$26*L48 -> 0.276485 | N65: 20Y | O65: =O15+$D$26*O48 -> -0.1944 | P65: =P15+$D$26*P48 -> -0.1744 | Q65: =Q15+$D$26*Q48 -> -0.1551 | R65: =R15+$D$26*R48 -> -0.1457 | S65: =S15+$D$26*S48 -> -0.1179 | T65: =T15+$D$26*T48 -> -0.1036 | U65: =U15+$D$26*U48 -> -0.0877 | V65: =V15+$D$26*V48 -> -0.0523 | ... X65: =X15+$D$26*X48 -> -0.02 | Z65: 20Y | AA65: =AA15+$E$26*AA48 -> 0.6767 | AB65: =AB15+$E$26*AB48 -> 0.6511 | AC65: =AC15+$E$26*AC48 -> 0.6243 | AD65: =AD15+$E$26*AD48 -> 0.6059 | AE65: =AE15+$E$26*AE48 -> 0.5844 | AF65: =AF15+$E$26*AF48 -> 0.5668 | AG65: =AG15+$E$26*AG48 -> 0.531 | AH65: =AH15+$E$26*AH48 -> 0.5179 | ... AJ65: =AJ15+$E$26*AJ48 -> 0.4678 | AL65: 20Y | AM65: =C65*(1+(((2-3*O65^2)/24*AA65^2)+(O65*AA65*C65/4))*20) -> 0.60688866 | AN65: =D65*(1+(((2-3*P65^2)/24*AB65^2)+(P65*AB65*D65/4))*20) -> 0.58622545 | AO65: =E65*(1+(((2-3*Q65^2)/24*AC65^2)+(Q65*AC65*E65/4))*20) -> 0.55188078 | AP65: =F65*(1+(((2-3*R65^2)/24*AD65^2)+(R65*AD65*F65/4))*20) -> 0.54286766 | AQ65: =G65*(1+(((2-3*S65^2)/24*AE65^2)+(S65*AE65*G65/4))*20) -> 0.50558911 | AR65: =H65*(1+(((2-3*T65^2)/24*AF65^2)+(T65*AF65*H65/4))*20) -> 0.48122543 | AS65: =I65*(1+(((2-3*U65^2)/24*AG65^2)+(U65*AG65*I65/4))*20) -> 0.44729143 | AT65: =J65*(1+(((2-3*V65^2)/24*AH65^2)+(V65*AH65*J65/4))*20) -> 0.43586057 | ... AV65: =L65*(1+(((2-3*X65^2)/24*AJ65^2)+(X65*AJ65*L65/4))*20) -> 0.37369029
B66: 30Y | C66: =C16+$C$26*C49 -> 0.4129438 | D66: =D16+$C$26*D49 -> 0.3907072 | E66: =E16+$C$26*E49 -> 0.3737806 | F66: =F16+$C$26*F49 -> 0.3604668 | G66: =G16+$C$26*G49 -> 0.3457085 | H66: =H16+$C$26*H49 -> 0.3190541 | I66: =I16+$C$26*I49 -> 0.3048344 | J66: =J16+$C$26*J49 -> 0.284885 | ... L66: =L16+$C$26*L49 -> 0.255385 | N66: 30Y | O66: =O16+$D$26*O49 -> -0.176 | P66: =P16+$D$26*P49 -> -0.1549 | Q66: =Q16+$D$26*Q49 -> -0.1366 | R66: =R16+$D$26*R49 -> -0.1078 | S66: =S16+$D$26*S49 -> -0.0932 | T66: =T16+$D$26*T49 -> -0.0702 | U66: =U16+$D$26*U49 -> -0.0495 | V66: =V16+$D$26*V49 -> -0.0437 | ... X66: =X16+$D$26*X49 -> 0.0089 | Z66: 30Y | AA66: =AA16+$E$26*AA49 -> 0.6568 | AB66: =AB16+$E$26*AB49 -> 0.6205 | AC66: =AC16+$E$26*AC49 -> 0.598 | AD66: =AD16+$E$26*AD49 -> 0.5822 | AE66: =AE16+$E$26*AE49 -> 0.5526 | AF66: =AF16+$E$26*AF49 -> 0.5337 | AG66: =AG16+$E$26*AG49 -> 0.5081 | AH66: =AH16+$E$26*AH49 -> 0.4978 | ... AJ66: =AJ16+$E$26*AJ49 -> 0.4579 | AL66: 30Y | AM66: =C66*(1+(((2-3*O66^2)/24*AA66^2)+(O66*AA66*C66/4))*30) -> 0.68975796 | AN66: =D66*(1+(((2-3*P66^2)/24*AB66^2)+(P66*AB66*D66/4))*30) -> 0.64320562 | AO66: =E66*(1+(((2-3*Q66^2)/24*AC66^2)+(Q66*AC66*E66/4))*30) -> 0.61299652 | AP66: =F66*(1+(((2-3*R66^2)/24*AD66^2)+(R66*AD66*F66/4))*30) -> 0.59943687 | AQ66: =G66*(1+(((2-3*S66^2)/24*AE66^2)+(S66*AE66*G66/4))*30) -> 0.560025 | AR66: =H66*(1+(((2-3*T66^2)/24*AF66^2)+(T66*AF66*H66/4))*30) -> 0.51596581 | AS66: =I66*(1+(((2-3*U66^2)/24*AG66^2)+(U66*AG66*I66/4))*30) -> 0.48332723 | AT66: =J66*(1+(((2-3*V66^2)/24*AH66^2)+(V66*AH66*J66/4))*30) -> 0.44762766 | ... AV66: =L66*(1+(((2-3*X66^2)/24*AJ66^2)+(X66*AJ66*L66/4))*30) -> 0.39123055
A68: SCENARIO 2
B69: Param: ATM | N69: Param: RHO | Z69: Param: NU | AL69: Combined Effective ATM Vol (Hagan approx, beta=1)
B70: Expiry \ Tenor | C70: 1M | D70: 3M | E70: 6M | F70: 1Y | G70: 2Y | H70: 3Y | I70: 5Y | J70: 10Y | K70: 20Y | L70: 30Y | N70: Expiry \ Tenor | O70: 1M | P70: 3M | Q70: 6M | R70: 1Y | S70: 2Y | T70: 3Y | U70: 5Y | V70: 10Y | W70: 20Y | X70: 30Y | Z70: Expiry \ Tenor | AA70: 1M | AB70: 3M | AC70: 6M | AD70: 1Y | AE70: 2Y | AF70: 3Y | AG70: 5Y | AH70: 10Y | AI70: 20Y | AJ70: 30Y | AL70: Expiry \ Tenor | AM70: 1M | AN70: 3M | AO70: 6M | AP70: 1Y | AQ70: 2Y | AR70: 3Y | AS70: 5Y | AT70: 10Y | AU70: 20Y | AV70: 30Y
B71: 1M | C71: =C7+$C$27*C40 -> 0.5665125 | D71: =D7+$C$27*D40 -> 0.545375 | E71: =E7+$C$27*E40 -> 0.53745 | F71: =F7+$C$27*F40 -> 0.50815 | G71: =G7+$C$27*G40 -> 0.4995625 | H71: =H7+$C$27*H40 -> 0.4782125 | I71: =I7+$C$27*I40 -> 0.454825 | J71: =J7+$C$27*J40 -> 0.446 | ... L71: =L7+$C$27*L40 -> 0.408725 | N71: 1M | O71: =O7+$D$27*O40 -> -0.3586 | P71: =P7+$D$27*P40 -> -0.3387 | Q71: =Q7+$D$27*Q40 -> -0.3126 | R71: =R7+$D$27*R40 -> -0.2851 | S71: =S7+$D$27*S40 -> -0.2797 | T71: =T7+$D$27*T40 -> -0.2583 | U71: =U7+$D$27*U40 -> -0.2308 | V71: =V7+$D$27*V40 -> -0.2049 | ... X71: =X7+$D$27*X40 -> -0.1771 | Z71: 1M | AA71: =AA7+$E$27*AA40 -> 0.8595 | AB71: =AB7+$E$27*AB40 -> 0.8187 | AC71: =AC7+$E$27*AC40 -> 0.8127 | AD71: =AD7+$E$27*AD40 -> 0.7791 | AE71: =AE7+$E$27*AE40 -> 0.754 | AF71: =AF7+$E$27*AF40 -> 0.7312 | AG71: =AG7+$E$27*AG40 -> 0.7128 | AH71: =AH7+$E$27*AH40 -> 0.7008 | ... AJ71: =AJ7+$E$27*AJ40 -> 0.6516 | AL71: 1M | AM71: =C71*(1+(((2-3*O71^2)/24*AA71^2)+(O71*AA71*C71/4))*0.0833333333333333) -> 0.5667974 | AN71: =D71*(1+(((2-3*P71^2)/24*AB71^2)+(P71*AB71*D71/4))*0.0833333333333333) -> 0.54575845 | AO71: =E71*(1+(((2-3*Q71^2)/24*AC71^2)+(Q71*AC71*E71/4))*0.0833333333333333) -> 0.53802497 | AP71: =F71*(1+(((2-3*R71^2)/24*AD71^2)+(R71*AD71*F71/4))*0.0833333333333333) -> 0.50883592 | AQ71: =G71*(1+(((2-3*S71^2)/24*AE71^2)+(S71*AE71*G71/4))*0.0833333333333333) -> 0.50020686 | AR71: =H71*(1+(((2-3*T71^2)/24*AF71^2)+(T71*AF71*H71/4))*0.0833333333333333) -> 0.47891052 | AS71: =I71*(1+(((2-3*U71^2)/24*AG71^2)+(U71*AG71*I71/4))*0.0833333333333333) -> 0.45559255 | AT71: =J71*(1+(((2-3*V71^2)/24*AH71^2)+(V71*AH71*J71/4))*0.0833333333333333) -> 0.44683025 | ... AV71: =L71*(1+(((2-3*X71^2)/24*AJ71^2)+(X71*AJ71*L71/4))*0.0833333333333333) -> 0.4094718
B72: 3M | C72: =C8+$C$27*C41 -> 0.5548375 | D72: =D8+$C$27*D41 -> 0.53165 | E72: =E8+$C$27*E41 -> 0.5174625 | F72: =F8+$C$27*F41 -> 0.489775 | G72: =G8+$C$27*G41 -> 0.472475 | H72: =H8+$C$27*H41 -> 0.457275 | I72: =I8+$C$27*I41 -> 0.4492875 | J72: =J8+$C$27*J41 -> 0.4261125 | ... L72: =L8+$C$27*L41 -> 0.3940125 | N72: 3M | O72: =O8+$D$27*O41 -> -0.3315 | P72: =P8+$D$27*P41 -> -0.3151 | Q72: =Q8+$D$27*Q41 -> -0.2858 | R72: =R8+$D$27*R41 -> -0.2682 | S72: =S8+$D$27*S41 -> -0.2579 | T72: =T8+$D$27*T41 -> -0.2318 | U72: =U8+$D$27*U41 -> -0.2134 | V72: =V8+$D$27*V41 -> -0.1869 | ... X72: =X8+$D$27*X41 -> -0.1598 | Z72: 3M | AA72: =AA8+$E$27*AA41 -> 0.8374 | AB72: =AB8+$E$27*AB41 -> 0.7979 | AC72: =AC8+$E$27*AC41 -> 0.7817 | AD72: =AD8+$E$27*AD41 -> 0.7663 | AE72: =AE8+$E$27*AE41 -> 0.7319 | AF72: =AF8+$E$27*AF41 -> 0.7164 | AG72: =AG8+$E$27*AG41 -> 0.6852 | AH72: =AH8+$E$27*AH41 -> 0.6756 | ... AJ72: =AJ8+$E$27*AJ41 -> 0.6292 | AL72: 3M | AM72: =C72*(1+(((2-3*O72^2)/24*AA72^2)+(O72*AA72*C72/4))*0.25) -> 0.556266 | AN72: =D72*(1+(((2-3*P72^2)/24*AB72^2)+(P72*AB72*D72/4))*0.25) -> 0.53320982 | AO72: =E72*(1+(((2-3*Q72^2)/24*AC72^2)+(Q72*AC72*E72/4))*0.25) -> 0.51950398 | AP72: =F72*(1+(((2-3*R72^2)/24*AD72^2)+(R72*AD72*F72/4))*0.25) -> 0.49203897 | AQ72: =G72*(1+(((2-3*S72^2)/24*AE72^2)+(S72*AE72*G72/4))*0.25) -> 0.47458819 | AR72: =H72*(1+(((2-3*T72^2)/24*AF72^2)+(T72*AF72*H72/4))*0.25) -> 0.45960002 | AS72: =I72*(1+(((2-3*U72^2)/24*AG72^2)+(U72*AG72*I72/4))*0.25) -> 0.45153713 | AT72: =J72*(1+(((2-3*V72^2)/24*AH72^2)+(V72*AH72*J72/4))*0.25) -> 0.42851918 | ... AV72: =L72*(1+(((2-3*X72^2)/24*AJ72^2)+(X72*AJ72*L72/4))*0.25) -> 0.39616216
B73: 6M | C73: =C9+$C$27*C42 -> 0.541575 | D73: =D9+$C$27*D42 -> 0.5127125 | E73: =E9+$C$27*E42 -> 0.5030125 | F73: =F9+$C$27*F42 -> 0.48295 | G73: =G9+$C$27*G42 -> 0.4652125 | H73: =H9+$C$27*H42 -> 0.44455 | I73: =I9+$C$27*I42 -> 0.434175 | J73: =J9+$C$27*J42 -> 0.418875 | ... L73: =L9+$C$27*L42 -> 0.37735 | N73: 6M | O73: =O9+$D$27*O42 -> -0.3199 | P73: =P9+$D$27*P42 -> -0.2876 | Q73: =Q9+$D$27*Q42 -> -0.2693 | R73: =R9+$D$27*R42 -> -0.2429 | S73: =S9+$D$27*S42 -> -0.2269 | T73: =T9+$D$27*T42 -> -0.2182 | U73: =U9+$D$27*U42 -> -0.1967 | V73: =V9+$D$27*V42 -> -0.1716 | ... X73: =X9+$D$27*X42 -> -0.1369 | Z73: 6M | AA73: =AA9+$E$27*AA42 -> 0.7989 | AB73: =AB9+$E$27*AB42 -> 0.7757 | AC73: =AC9+$E$27*AC42 -> 0.7523 | AD73: =AD9+$E$27*AD42 -> 0.7443 | AE73: =AE9+$E$27*AE42 -> 0.7093 | AF73: =AF9+$E$27*AF42 -> 0.6894 | AG73: =AG9+$E$27*AG42 -> 0.67 | AH73: =AH9+$E$27*AH42 -> 0.6574 | ... AJ73: =AJ9+$E$27*AJ42 -> 0.6045 | AL73: 6M | AM73: =C73*(1+(((2-3*O73^2)/24*AA73^2)+(O73*AA73*C73/4))*0.5) -> 0.54439662 | AN73: =D73*(1+(((2-3*P73^2)/24*AB73^2)+(P73*AB73*D73/4))*0.5) -> 0.51664139 | AO73: =E73*(1+(((2-3*Q73^2)/24*AC73^2)+(Q73*AC73*E73/4))*0.5) -> 0.50717631 | AP73: =F73*(1+(((2-3*R73^2)/24*AD73^2)+(R73*AD73*F73/4))*0.5) -> 0.4878402 | AQ73: =G73*(1+(((2-3*S73^2)/24*AE73^2)+(S73*AE73*G73/4))*0.5) -> 0.46985764 | AR73: =H73*(1+(((2-3*T73^2)/24*AF73^2)+(T73*AF73*H73/4))*0.5) -> 0.4490087 | AS73: =I73*(1+(((2-3*U73^2)/24*AG73^2)+(U73*AG73*I73/4))*0.5) -> 0.43871917 | AT73: =J73*(1+(((2-3*V73^2)/24*AH73^2)+(V73*AH73*J73/4))*0.5) -> 0.42361049 | ... AV73: =L73*(1+(((2-3*X73^2)/24*AJ73^2)+(X73*AJ73*L73/4))*0.5) -> 0.38146097
B74: 1Y | C74: =C10+$C$27*C43 -> 0.5173125 | D74: =D10+$C$27*D43 -> 0.506375 | E74: =E10+$C$27*E43 -> 0.487825 | F74: =F10+$C$27*F43 -> 0.4707375 | G74: =G10+$C$27*G43 -> 0.4407375 | H74: =H10+$C$27*H43 -> 0.4258125 | I74: =I10+$C$27*I43 -> 0.406775 | J74: =J10+$C$27*J43 -> 0.399425 | ... L74: =L10+$C$27*L43 -> 0.3492625 | N74: 1Y | O74: =O10+$D$27*O43 -> -0.2981 | P74: =P10+$D$27*P43 -> -0.2776 | Q74: =Q10+$D$27*Q43 -> -0.2581 | R74: =R10+$D$27*R43 -> -0.2336 | S74: =S10+$D$27*S43 -> -0.2121 | T74: =T10+$D$27*T43 -> -0.1992 | U74: =U10+$D$27*U43 -> -0.1849 | V74: =V10+$D$27*V43 -> -0.1572 | ... X74: =X10+$D$27*X43 -> -0.1153 | Z74: 1Y | AA74: =AA10+$E$27*AA43 -> 0.7924 | AB74: =AB10+$E$27*AB43 -> 0.7649 | AC74: =AC10+$E$27*AC43 -> 0.7392 | AD74: =AD10+$E$27*AD43 -> 0.719 | AE74: =AE10+$E$27*AE43 -> 0.698 | AF74: =AF10+$E$27*AF43 -> 0.6633 | AG74: =AG10+$E$27*AG43 -> 0.658 | AH74: =AH10+$E$27*AH43 -> 0.6334 | ... AJ74: =AJ10+$E$27*AJ43 -> 0.5893 | AL74: 1Y | AM74: =C74*(1+(((2-3*O74^2)/24*AA74^2)+(O74*AA74*C74/4))*1) -> 0.52496923 | AN74: =D74*(1+(((2-3*P74^2)/24*AB74^2)+(P74*AB74*D74/4))*1) -> 0.51459839 | AO74: =E74*(1+(((2-3*Q74^2)/24*AC74^2)+(Q74*AC74*E74/4))*1) -> 0.4964678 | AP74: =F74*(1+(((2-3*R74^2)/24*AD74^2)+(R74*AD74*F74/4))*1) -> 0.48005234 | AQ74: =G74*(1+(((2-3*S74^2)/24*AE74^2)+(S74*AE74*G74/4))*1) -> 0.45023465 | AR74: =H74*(1+(((2-3*T74^2)/24*AF74^2)+(T74*AF74*H74/4))*1) -> 0.43450591 | AS74: =I74*(1+(((2-3*U74^2)/24*AG74^2)+(U74*AG74*I74/4))*1) -> 0.41566611 | AT74: =J74*(1+(((2-3*V74^2)/24*AH74^2)+(V74*AH74*J74/4))*1) -> 0.40831258 | ... AV74: =L74*(1+(((2-3*X74^2)/24*AJ74^2)+(X74*AJ74*L74/4))*1) -> 0.35709635
B75: 2Y | C75: =C11+$C$27*C44 -> 0.49675 | D75: =D11+$C$27*D44 -> 0.4789375 | E75: =E11+$C$27*E44 -> 0.4551125 | F75: =F11+$C$27*F44 -> 0.4483 | G75: =G11+$C$27*G44 -> 0.418625 | H75: =H11+$C$27*H44 -> 0.4012875 | I75: =I11+$C$27*I44 -> 0.3859625 | J75: =J11+$C$27*J44 -> 0.3674625 | ... L75: =L11+$C$27*L44 -> 0.3296 | N75: 2Y | O75: =O11+$D$27*O44 -> -0.2822 | P75: =P11+$D$27*P44 -> -0.2598 | Q75: =Q11+$D$27*Q44 -> -0.2413 | R75: =R11+$D$27*R44 -> -0.2166 | S75: =S11+$D$27*S44 -> -0.2039 | T75: =T11+$D$27*T44 -> -0.1675 | U75: =U11+$D$27*U44 -> -0.1533 | V75: =V11+$D$27*V44 -> -0.1431 | ... X75: =X11+$D$27*X44 -> -0.1003 | Z75: 2Y | AA75: =AA11+$E$27*AA44 -> 0.7584 | AB75: =AB11+$E$27*AB44 -> 0.7313 | AC75: =AC11+$E$27*AC44 -> 0.7236 | AD75: =AD11+$E$27*AD44 -> 0.7043 | AE75: =AE11+$E$27*AE44 -> 0.6715 | AF75: =AF11+$E$27*AF44 -> 0.6497 | AG75: =AG11+$E$27*AG44 -> 0.6195 | AH75: =AH11+$E$27*AH44 -> 0.5976 | ... AJ75: =AJ11+$E$27*AJ44 -> 0.5564 | AL75: 2Y | AM75: =C75*(1+(((2-3*O75^2)/24*AA75^2)+(O75*AA75*C75/4))*2) -> 0.51227504 | AN75: =D75*(1+(((2-3*P75^2)/24*AB75^2)+(P75*AB75*D75/4))*2) -> 0.49551448 | AO75: =E75*(1+(((2-3*Q75^2)/24*AC75^2)+(Q75*AC75*E75/4))*2) -> 0.47327698 | AP75: =F75*(1+(((2-3*R75^2)/24*AD75^2)+(R75*AD75*F75/4))*2) -> 0.4674248 | AQ75: =G75*(1+(((2-3*S75^2)/24*AE75^2)+(S75*AE75*G75/4))*2) -> 0.43612626 | AR75: =H75*(1+(((2-3*T75^2)/24*AF75^2)+(T75*AF75*H75/4))*2) -> 0.41956854 | AS75: =I75*(1+(((2-3*U75^2)/24*AG75^2)+(U75*AG75*I75/4))*2) -> 0.40270605 | AT75: =J75*(1+(((2-3*V75^2)/24*AH75^2)+(V75*AH75*J75/4))*2) -> 0.38288881 | ... AV75: =L75*(1+(((2-3*X75^2)/24*AJ75^2)+(X75*AJ75*L75/4))*2) -> 0.34331836
B76: 3Y | C76: =C12+$C$27*C45 -> 0.487925 | D76: =D12+$C$27*D45 -> 0.456675 | E76: =E12+$C$27*E45 -> 0.435775 | F76: =F12+$C$27*F45 -> 0.4369875 | G76: =G12+$C$27*G45 -> 0.4102625 | H76: =H12+$C$27*H45 -> 0.384975 | I76: =I12+$C$27*I45 -> 0.3753875 | J76: =J12+$C$27*J45 -> 0.3471125 | ... L76: =L12+$C$27*L45 -> 0.3308125 | N76: 3Y | O76: =O12+$D$27*O45 -> -0.2455 | P76: =P12+$D$27*P45 -> -0.2294 | Q76: =Q12+$D$27*Q45 -> -0.2187 | R76: =R12+$D$27*R45 -> -0.1971 | S76: =S12+$D$27*S45 -> -0.1817 | T76: =T12+$D$27*T45 -> -0.1501 | U76: =U12+$D$27*U45 -> -0.1355 | V76: =V12+$D$27*V45 -> -0.1111 | ... X76: =X12+$D$27*X45 -> -0.0833 | Z76: 3Y | AA76: =AA12+$E$27*AA45 -> 0.7451 | AB76: =AB12+$E$27*AB45 -> 0.7264 | AC76: =AC12+$E$27*AC45 -> 0.7015 | AD76: =AD12+$E$27*AD45 -> 0.6783 | AE76: =AE12+$E$27*AE45 -> 0.6564 | AF76: =AF12+$E$27*AF45 -> 0.6326 | AG76: =AG12+$E$27*AG45 -> 0.6001 | AH76: =AH12+$E$27*AH45 -> 0.5837 | ... AJ76: =AJ12+$E$27*AJ45 -> 0.5295 | AL76: 3Y | AM76: =C76*(1+(((2-3*O76^2)/24*AA76^2)+(O76*AA76*C76/4))*3) -> 0.51686219 | AN76: =D76*(1+(((2-3*P76^2)/24*AB76^2)+(P76*AB76*D76/4))*3) -> 0.48609741 | AO76: =E76*(1+(((2-3*Q76^2)/24*AC76^2)+(Q76*AC76*E76/4))*3) -> 0.46368959 | AP76: =F76*(1+(((2-3*R76^2)/24*AD76^2)+(R76*AD76*F76/4))*3) -> 0.4651747 | AQ76: =G76*(1+(((2-3*S76^2)/24*AE76^2)+(S76*AE76*G76/4))*3) -> 0.4372096 | AR76: =H76*(1+(((2-3*T76^2)/24*AF76^2)+(T76*AF76*H76/4))*3) -> 0.41163401 | AS76: =I76*(1+(((2-3*U76^2)/24*AG76^2)+(U76*AG76*I76/4))*3) -> 0.39965911 | AT76: =J76*(1+(((2-3*V76^2)/24*AH76^2)+(V76*AH76*J76/4))*3) -> 0.37027079 | ... AV76: =L76*(1+(((2-3*X76^2)/24*AJ76^2)+(X76*AJ76*L76/4))*3) -> 0.35013842
B77: 5Y | C77: =C13+$C$27*C46 -> 0.4536375 | D77: =D13+$C$27*D46 -> 0.4408375 | E77: =E13+$C$27*E46 -> 0.4231 | F77: =F13+$C$27*F46 -> 0.41365 | G77: =G13+$C$27*G46 -> 0.4011 | H77: =H13+$C$27*H46 -> 0.3729 | I77: =I13+$C$27*I46 -> 0.3648875 | J77: =J13+$C$27*J46 -> 0.3485375 | ... L77: =L13+$C$27*L46 -> 0.3005 | N77: 5Y | O77: =O13+$D$27*O46 -> -0.2389 | P77: =P13+$D$27*P46 -> -0.2194 | Q77: =Q13+$D$27*Q46 -> -0.2005 | R77: =R13+$D$27*R46 -> -0.1809 | S77: =S13+$D$27*S46 -> -0.1531 | T77: =T13+$D$27*T46 -> -0.1281 | U77: =U13+$D$27*U46 -> -0.1099 | V77: =V13+$D$27*V46 -> -0.0976 | ... X77: =X13+$D$27*X46 -> -0.0523 | Z77: 5Y | AA77: =AA13+$E$27*AA46 -> 0.7084 | AB77: =AB13+$E$27*AB46 -> 0.6977 | AC77: =AC13+$E$27*AC46 -> 0.6804 | AD77: =AD13+$E$27*AD46 -> 0.6556 | AE77: =AE13+$E$27*AE46 -> 0.6328 | AF77: =AF13+$E$27*AF46 -> 0.6051 | AG77: =AG13+$E$27*AG46 -> 0.5769 | AH77: =AH13+$E$27*AH46 -> 0.5669 | ... AJ77: =AJ13+$E$27*AJ46 -> 0.5227 | AL77: 5Y | AM77: =C77*(1+(((2-3*O77^2)/24*AA77^2)+(O77*AA77*C77/4))*5) -> 0.4968375 | AN77: =D77*(1+(((2-3*P77^2)/24*AB77^2)+(P77*AB77*D77/4))*5) -> 0.48660986 | AO77: =E77*(1+(((2-3*Q77^2)/24*AC77^2)+(Q77*AC77*E77/4))*5) -> 0.46926555 | AP77: =F77*(1+(((2-3*R77^2)/24*AD77^2)+(R77*AD77*F77/4))*5) -> 0.45872732 | AQ77: =G77*(1+(((2-3*S77^2)/24*AE77^2)+(S77*AE77*G77/4))*5) -> 0.44618682 | AR77: =H77*(1+(((2-3*T77^2)/24*AF77^2)+(T77*AF77*H77/4))*5) -> 0.41491641 | AS77: =I77*(1+(((2-3*U77^2)/24*AG77^2)+(U77*AG77*I77/4))*5) -> 0.40401879 | AT77: =J77*(1+(((2-3*V77^2)/24*AH77^2)+(V77*AH77*J77/4))*5) -> 0.3861404 | ... AV77: =L77*(1+(((2-3*X77^2)/24*AJ77^2)+(X77*AJ77*L77/4))*5) -> 0.33148278
B78: 10Y | C78: =C14+$C$27*C47 -> 0.454825 | D78: =D14+$C$27*D47 -> 0.4255625 | E78: =E14+$C$27*E47 -> 0.408225 | F78: =F14+$C$27*F47 -> 0.4010375 | G78: =G14+$C$27*G47 -> 0.378875 | H78: =H14+$C$27*H47 -> 0.350175 | I78: =I14+$C$27*I47 -> 0.3310375 | J78: =J14+$C$27*J47 -> 0.3136875 | ... L78: =L14+$C$27*L47 -> 0.2917375 | N78: 10Y | O78: =O14+$D$27*O47 -> -0.221 | P78: =P14+$D$27*P47 -> -0.1879 | Q78: =Q14+$D$27*Q47 -> -0.1654 | R78: =R14+$D$27*R47 -> -0.1524 | S78: =S14+$D$27*S47 -> -0.1391 | T78: =T14+$D$27*T47 -> -0.1157 | U78: =U14+$D$27*U47 -> -0.1046 | V78: =V14+$D$27*V47 -> -0.0875 | ... X78: =X14+$D$27*X47 -> -0.0359 | Z78: 10Y | AA78: =AA14+$E$27*AA47 -> 0.695 | AB78: =AB14+$E$27*AB47 -> 0.6809 | AC78: =AC14+$E$27*AC47 -> 0.6487 | AD78: =AD14+$E$27*AD47 -> 0.6352 | AE78: =AE14+$E$27*AE47 -> 0.6121 | AF78: =AF14+$E$27*AF47 -> 0.5776 | AG78: =AG14+$E$27*AG47 -> 0.5561 | AH78: =AH14+$E$27*AH47 -> 0.5347 | ... AJ78: =AJ14+$E$27*AJ47 -> 0.4962 | AL78: 10Y | AM78: =C78*(1+(((2-3*O78^2)/24*AA78^2)+(O78*AA78*C78/4))*10) -> 0.5450552 | AN78: =D78*(1+(((2-3*P78^2)/24*AB78^2)+(P78*AB78*D78/4))*10) -> 0.52334634 | AO78: =E78*(1+(((2-3*Q78^2)/24*AC78^2)+(Q78*AC78*E78/4))*10) -> 0.50080427 | AP78: =F78*(1+(((2-3*R78^2)/24*AD78^2)+(R78*AD78*F78/4))*10) -> 0.49225873 | AQ78: =G78*(1+(((2-3*S78^2)/24*AE78^2)+(S78*AE78*G78/4))*10) -> 0.46317993 | AR78: =H78*(1+(((2-3*T78^2)/24*AF78^2)+(T78*AF78*H78/4))*10) -> 0.42508849 | AS78: =I78*(1+(((2-3*U78^2)/24*AG78^2)+(U78*AG78*I78/4))*10) -> 0.39901177 | AT78: =J78*(1+(((2-3*V78^2)/24*AH78^2)+(V78*AH78*J78/4))*10) -> 0.37605691 | ... AV78: =L78*(1+(((2-3*X78^2)/24*AJ78^2)+(X78*AJ78*L78/4))*10) -> 0.34768978
B79: 20Y | C79: =C15+$C$27*C48 -> 0.4227125 | D79: =D15+$C$27*D48 -> 0.4080375 | E79: =E15+$C$27*E48 -> 0.384925 | F79: =F15+$C$27*F48 -> 0.38285 | G79: =G15+$C$27*G48 -> 0.353375 | H79: =H15+$C$27*H48 -> 0.3382125 | I79: =I15+$C$27*I48 -> 0.3228375 | J79: =J15+$C$27*J48 -> 0.3113 | ... L79: =L15+$C$27*L48 -> 0.276875 | N79: 20Y | O79: =O15+$D$27*O48 -> -0.1944 | P79: =P15+$D$27*P48 -> -0.1744 | Q79: =Q15+$D$27*Q48 -> -0.1551 | R79: =R15+$D$27*R48 -> -0.1457 | S79: =S15+$D$27*S48 -> -0.1179 | T79: =T15+$D$27*T48 -> -0.1036 | U79: =U15+$D$27*U48 -> -0.0877 | V79: =V15+$D$27*V48 -> -0.0523 | ... X79: =X15+$D$27*X48 -> -0.02 | Z79: 20Y | AA79: =AA15+$E$27*AA48 -> 0.6767 | AB79: =AB15+$E$27*AB48 -> 0.6511 | AC79: =AC15+$E$27*AC48 -> 0.6243 | AD79: =AD15+$E$27*AD48 -> 0.6059 | AE79: =AE15+$E$27*AE48 -> 0.5844 | AF79: =AF15+$E$27*AF48 -> 0.5668 | AG79: =AG15+$E$27*AG48 -> 0.531 | AH79: =AH15+$E$27*AH48 -> 0.5179 | ... AJ79: =AJ15+$E$27*AJ48 -> 0.4678 | AL79: 20Y | AM79: =C79*(1+(((2-3*O79^2)/24*AA79^2)+(O79*AA79*C79/4))*20) -> 0.60950951 | AN79: =D79*(1+(((2-3*P79^2)/24*AB79^2)+(P79*AB79*D79/4))*20) -> 0.58865527 | AO79: =E79*(1+(((2-3*Q79^2)/24*AC79^2)+(Q79*AC79*E79/4))*20) -> 0.55420931 | AP79: =F79*(1+(((2-3*R79^2)/24*AD79^2)+(R79*AD79*F79/4))*20) -> 0.54494314 | AQ79: =G79*(1+(((2-3*S79^2)/24*AE79^2)+(S79*AE79*G79/4))*20) -> 0.50730454 | AR79: =H79*(1+(((2-3*T79^2)/24*AF79^2)+(T79*AF79*H79/4))*20) -> 0.48280404 | AS79: =I79*(1+(((2-3*U79^2)/24*AG79^2)+(U79*AG79*I79/4))*20) -> 0.44853195 | AT79: =J79*(1+(((2-3*V79^2)/24*AH79^2)+(V79*AH79*J79/4))*20) -> 0.43676643 | ... AV79: =L79*(1+(((2-3*X79^2)/24*AJ79^2)+(X79*AJ79*L79/4))*20) -> 0.37421235
B80: 30Y | C80: =C16+$C$27*C49 -> 0.414925 | D80: =D16+$C$27*D49 -> 0.3926 | E80: =E16+$C$27*E49 -> 0.375325 | F80: =F16+$C$27*F49 -> 0.36185 | G80: =G16+$C$27*G49 -> 0.3467875 | H80: =H16+$C$27*H49 -> 0.3199875 | I80: =I16+$C$27*I49 -> 0.3055 | J80: =J16+$C$27*J49 -> 0.285275 | ... L80: =L16+$C$27*L49 -> 0.255775 | N80: 30Y | O80: =O16+$D$27*O49 -> -0.176 | P80: =P16+$D$27*P49 -> -0.1549 | Q80: =Q16+$D$27*Q49 -> -0.1366 | R80: =R16+$D$27*R49 -> -0.1078 | S80: =S16+$D$27*S49 -> -0.0932 | T80: =T16+$D$27*T49 -> -0.0702 | U80: =U16+$D$27*U49 -> -0.0495 | V80: =V16+$D$27*V49 -> -0.0437 | ... X80: =X16+$D$27*X49 -> 0.0089 | Z80: 30Y | AA80: =AA16+$E$27*AA49 -> 0.6568 | AB80: =AB16+$E$27*AB49 -> 0.6205 | AC80: =AC16+$E$27*AC49 -> 0.598 | AD80: =AD16+$E$27*AD49 -> 0.5822 | AE80: =AE16+$E$27*AE49 -> 0.5526 | AF80: =AF16+$E$27*AF49 -> 0.5337 | AG80: =AG16+$E$27*AG49 -> 0.5081 | AH80: =AH16+$E$27*AH49 -> 0.4978 | ... AJ80: =AJ16+$E$27*AJ49 -> 0.4579 | AL80: 30Y | AM80: =C80*(1+(((2-3*O80^2)/24*AA80^2)+(O80*AA80*C80/4))*30) -> 0.69235454 | AN80: =D80*(1+(((2-3*P80^2)/24*AB80^2)+(P80*AB80*D80/4))*30) -> 0.64578598 | AO80: =E80*(1+(((2-3*Q80^2)/24*AC80^2)+(Q80*AC80*E80/4))*30) -> 0.61517419 | AP80: =F80*(1+(((2-3*R80^2)/24*AD80^2)+(R80*AD80*F80/4))*30) -> 0.60150146 | AQ80: =G80*(1+(((2-3*S80^2)/24*AE80^2)+(S80*AE80*G80/4))*30) -> 0.56162838 | AR80: =H80*(1+(((2-3*T80^2)/24*AF80^2)+(T80*AF80*H80/4))*30) -> 0.51739136 | AS80: =I80*(1+(((2-3*U80^2)/24*AG80^2)+(U80*AG80*I80/4))*30) -> 0.48434421 | AT80: =J80*(1+(((2-3*V80^2)/24*AH80^2)+(V80*AH80*J80/4))*30) -> 0.44822229 | ... AV80: =L80*(1+(((2-3*X80^2)/24*AJ80^2)+(X80*AJ80*L80/4))*30) -> 0.39183105
A82: SCENARIO 3
B83: Param: ATM | N83: Param: RHO | Z83: Param: NU | AL83: Combined Effective ATM Vol (Hagan approx, beta=1)
B84: Expiry \ Tenor | C84: 1M | D84: 3M | E84: 6M | F84: 1Y | G84: 2Y | H84: 3Y | I84: 5Y | J84: 10Y | K84: 20Y | L84: 30Y | N84: Expiry \ Tenor | O84: 1M | P84: 3M | Q84: 6M | R84: 1Y | S84: 2Y | T84: 3Y | U84: 5Y | V84: 10Y | W84: 20Y | X84: 30Y | Z84: Expiry \ Tenor | AA84: 1M | AB84: 3M | AC84: 6M | AD84: 1Y | AE84: 2Y | AF84: 3Y | AG84: 5Y | AH84: 10Y | AI84: 20Y | AJ84: 30Y | AL84: Expiry \ Tenor | AM84: 1M | AN84: 3M | AO84: 6M | AP84: 1Y | AQ84: 2Y | AR84: 3Y | AS84: 5Y | AT84: 10Y | AU84: 20Y | AV84: 30Y
B85: 1M | C85: =C7+$C$28*C40 -> 0.565712 | D85: =D7+$C$28*D40 -> 0.544616 | E85: =E7+$C$28*E40 -> 0.53674 | F85: =F7+$C$28*F40 -> 0.50748 | G85: =G7+$C$28*G40 -> 0.498944 | H85: =H7+$C$28*H40 -> 0.477644 | I85: =I7+$C$28*I40 -> 0.45428 | J85: =J7+$C$28*J40 -> 0.4455 | ... L85: =L7+$C$28*L40 -> 0.408324 | N85: 1M | O85: =O7+$D$28*O40 -> -0.3586 | P85: =P7+$D$28*P40 -> -0.3387 | Q85: =Q7+$D$28*Q40 -> -0.3126 | R85: =R7+$D$28*R40 -> -0.2851 | S85: =S7+$D$28*S40 -> -0.2797 | T85: =T7+$D$28*T40 -> -0.2583 | U85: =U7+$D$28*U40 -> -0.2308 | V85: =V7+$D$28*V40 -> -0.2049 | ... X85: =X7+$D$28*X40 -> -0.1771 | Z85: 1M | AA85: =AA7+$E$28*AA40 -> 0.8595 | AB85: =AB7+$E$28*AB40 -> 0.8187 | AC85: =AC7+$E$28*AC40 -> 0.8127 | AD85: =AD7+$E$28*AD40 -> 0.7791 | AE85: =AE7+$E$28*AE40 -> 0.754 | AF85: =AF7+$E$28*AF40 -> 0.7312 | AG85: =AG7+$E$28*AG40 -> 0.7128 | AH85: =AH7+$E$28*AH40 -> 0.7008 | ... AJ85: =AJ7+$E$28*AJ40 -> 0.6516 | AL85: 1M | AM85: =C85*(1+(((2-3*O85^2)/24*AA85^2)+(O85*AA85*C85/4))*0.0833333333333333) -> 0.56599941 | AN85: =D85*(1+(((2-3*P85^2)/24*AB85^2)+(P85*AB85*D85/4))*0.0833333333333333) -> 0.5450013 | AO85: =E85*(1+(((2-3*Q85^2)/24*AC85^2)+(Q85*AC85*E85/4))*0.0833333333333333) -> 0.53731622 | AP85: =F85*(1+(((2-3*R85^2)/24*AD85^2)+(R85*AD85*F85/4))*0.0833333333333333) -> 0.50816659 | AQ85: =G85*(1+(((2-3*S85^2)/24*AE85^2)+(S85*AE85*G85/4))*0.0833333333333333) -> 0.49958892 | AR85: =H85*(1+(((2-3*T85^2)/24*AF85^2)+(T85*AF85*H85/4))*0.0833333333333333) -> 0.47834226 | AS85: =I85*(1+(((2-3*U85^2)/24*AG85^2)+(U85*AG85*I85/4))*0.0833333333333333) -> 0.45504748 | AT85: =J85*(1+(((2-3*V85^2)/24*AH85^2)+(V85*AH85*J85/4))*0.0833333333333333) -> 0.44632999 | ... AV85: =L85*(1+(((2-3*X85^2)/24*AJ85^2)+(X85*AJ85*L85/4))*0.0833333333333333) -> 0.40907046
B86: 3M | C86: =C8+$C$28*C41 -> 0.554088 | D86: =D8+$C$28*D41 -> 0.530948 | E86: =E8+$C$28*E41 -> 0.516804 | F86: =F8+$C$28*F41 -> 0.489168 | G86: =G8+$C$28*G41 -> 0.471892 | H86: =H8+$C$28*H41 -> 0.456748 | I86: =I8+$C$28*I41 -> 0.448792 | J86: =J8+$C$28*J41 -> 0.425676 | ... L86: =L8+$C$28*L41 -> 0.393652 | N86: 3M | O86: =O8+$D$28*O41 -> -0.3315 | P86: =P8+$D$28*P41 -> -0.3151 | Q86: =Q8+$D$28*Q41 -> -0.2858 | R86: =R8+$D$28*R41 -> -0.2682 | S86: =S8+$D$28*S41 -> -0.2579 | T86: =T8+$D$28*T41 -> -0.2318 | U86: =U8+$D$28*U41 -> -0.2134 | V86: =V8+$D$28*V41 -> -0.1869 | ... X86: =X8+$D$28*X41 -> -0.1598 | Z86: 3M | AA86: =AA8+$E$28*AA41 -> 0.8374 | AB86: =AB8+$E$28*AB41 -> 0.7979 | AC86: =AC8+$E$28*AC41 -> 0.7817 | AD86: =AD8+$E$28*AD41 -> 0.7663 | AE86: =AE8+$E$28*AE41 -> 0.7319 | AF86: =AF8+$E$28*AF41 -> 0.7164 | AG86: =AG8+$E$28*AG41 -> 0.6852 | AH86: =AH8+$E$28*AH41 -> 0.6756 | ... AJ86: =AJ8+$E$28*AJ41 -> 0.6292 | AL86: 3M | AM86: =C86*(1+(((2-3*O86^2)/24*AA86^2)+(O86*AA86*C86/4))*0.25) -> 0.55552178 | AN86: =D86*(1+(((2-3*P86^2)/24*AB86^2)+(P86*AB86*D86/4))*0.25) -> 0.53251161 | AO86: =E86*(1+(((2-3*Q86^2)/24*AC86^2)+(Q86*AC86*E86/4))*0.25) -> 0.51884763 | AP86: =F86*(1+(((2-3*R86^2)/24*AD86^2)+(R86*AD86*F86/4))*0.25) -> 0.49143298 | AQ86: =G86*(1+(((2-3*S86^2)/24*AE86^2)+(S86*AE86*G86/4))*0.25) -> 0.47400583 | AR86: =H86*(1+(((2-3*T86^2)/24*AF86^2)+(T86*AF86*H86/4))*0.25) -> 0.45907284 | AS86: =I86*(1+(((2-3*U86^2)/24*AG86^2)+(U86*AG86*I86/4))*0.25) -> 0.45104118 | AT86: =J86*(1+(((2-3*V86^2)/24*AH86^2)+(V86*AH86*J86/4))*0.25) -> 0.42808169 | ... AV86: =L86*(1+(((2-3*X86^2)/24*AJ86^2)+(X86*AJ86*L86/4))*0.25) -> 0.39580058
B87: 6M | C87: =C9+$C$28*C42 -> 0.54088 | D87: =D9+$C$28*D42 -> 0.512056 | E87: =E9+$C$28*E42 -> 0.50238 | F87: =F9+$C$28*F42 -> 0.482376 | G87: =G9+$C$28*G42 -> 0.464668 | H87: =H9+$C$28*H42 -> 0.444068 | I87: =I9+$C$28*I42 -> 0.433748 | J87: =J9+$C$28*J42 -> 0.418476 | ... L87: =L9+$C$28*L42 -> 0.377052 | N87: 6M | O87: =O9+$D$28*O42 -> -0.3199 | P87: =P9+$D$28*P42 -> -0.2876 | Q87: =Q9+$D$28*Q42 -> -0.2693 | R87: =R9+$D$28*R42 -> -0.2429 | S87: =S9+$D$28*S42 -> -0.2269 | T87: =T9+$D$28*T42 -> -0.2182 | U87: =U9+$D$28*U42 -> -0.1967 | V87: =V9+$D$28*V42 -> -0.1716 | ... X87: =X9+$D$28*X42 -> -0.1369 | Z87: 6M | AA87: =AA9+$E$28*AA42 -> 0.7989 | AB87: =AB9+$E$28*AB42 -> 0.7757 | AC87: =AC9+$E$28*AC42 -> 0.7523 | AD87: =AD9+$E$28*AD42 -> 0.7443 | AE87: =AE9+$E$28*AE42 -> 0.7093 | AF87: =AF9+$E$28*AF42 -> 0.6894 | AG87: =AG9+$E$28*AG42 -> 0.67 | AH87: =AH9+$E$28*AH42 -> 0.6574 | ... AJ87: =AJ9+$E$28*AJ42 -> 0.6045 | AL87: 6M | AM87: =C87*(1+(((2-3*O87^2)/24*AA87^2)+(O87*AA87*C87/4))*0.5) -> 0.54371001 | AN87: =D87*(1+(((2-3*P87^2)/24*AB87^2)+(P87*AB87*D87/4))*0.5) -> 0.51598923 | AO87: =E87*(1+(((2-3*Q87^2)/24*AC87^2)+(Q87*AC87*E87/4))*0.5) -> 0.50654662 | AP87: =F87*(1+(((2-3*R87^2)/24*AD87^2)+(R87*AD87*F87/4))*0.5) -> 0.48726664 | AQ87: =G87*(1+(((2-3*S87^2)/24*AE87^2)+(S87*AE87*G87/4))*0.5) -> 0.4693128 | AR87: =H87*(1+(((2-3*T87^2)/24*AF87^2)+(T87*AF87*H87/4))*0.5) -> 0.44852589 | AS87: =I87*(1+(((2-3*U87^2)/24*AG87^2)+(U87*AG87*I87/4))*0.5) -> 0.43829075 | AT87: =J87*(1+(((2-3*V87^2)/24*AH87^2)+(V87*AH87*J87/4))*0.5) -> 0.42320933 | ... AV87: =L87*(1+(((2-3*X87^2)/24*AJ87^2)+(X87*AJ87*L87/4))*0.5) -> 0.38116088
B88: 1Y | C88: =C10+$C$28*C43 -> 0.51666 | D88: =D10+$C$28*D43 -> 0.50576 | E88: =E10+$C$28*E43 -> 0.487236 | F88: =F10+$C$28*F43 -> 0.4702 | G88: =G10+$C$28*G43 -> 0.440264 | H88: =H10+$C$28*H43 -> 0.42538 | I88: =I10+$C$28*I43 -> 0.406392 | J88: =J10+$C$28*J43 -> 0.399088 | ... L88: =L10+$C$28*L43 -> 0.349012 | N88: 1Y | O88: =O10+$D$28*O43 -> -0.2981 | P88: =P10+$D$28*P43 -> -0.2776 | Q88: =Q10+$D$28*Q43 -> -0.2581 | R88: =R10+$D$28*R43 -> -0.2336 | S88: =S10+$D$28*S43 -> -0.2121 | T88: =T10+$D$28*T43 -> -0.1992 | U88: =U10+$D$28*U43 -> -0.1849 | V88: =V10+$D$28*V43 -> -0.1572 | ... X88: =X10+$D$28*X43 -> -0.1153 | Z88: 1Y | AA88: =AA10+$E$28*AA43 -> 0.7924 | AB88: =AB10+$E$28*AB43 -> 0.7649 | AC88: =AC10+$E$28*AC43 -> 0.7392 | AD88: =AD10+$E$28*AD43 -> 0.719 | AE88: =AE10+$E$28*AE43 -> 0.698 | AF88: =AF10+$E$28*AF43 -> 0.6633 | AG88: =AG10+$E$28*AG43 -> 0.658 | AH88: =AH10+$E$28*AH43 -> 0.6334 | ... AJ88: =AJ10+$E$28*AJ43 -> 0.5893 | AL88: 1Y | AM88: =C88*(1+(((2-3*O88^2)/24*AA88^2)+(O88*AA88*C88/4))*1) -> 0.52432699 | AN88: =D88*(1+(((2-3*P88^2)/24*AB88^2)+(P88*AB88*D88/4))*1) -> 0.51398991 | AO88: =E88*(1+(((2-3*Q88^2)/24*AC88^2)+(Q88*AC88*E88/4))*1) -> 0.49588205 | AP88: =F88*(1+(((2-3*R88^2)/24*AD88^2)+(R88*AD88*F88/4))*1) -> 0.47951481 | AQ88: =G88*(1+(((2-3*S88^2)/24*AE88^2)+(S88*AE88*G88/4))*1) -> 0.44975866 | AR88: =H88*(1+(((2-3*T88^2)/24*AF88^2)+(T88*AF88*H88/4))*1) -> 0.43407066 | AS88: =I88*(1+(((2-3*U88^2)/24*AG88^2)+(U88*AG88*I88/4))*1) -> 0.41527948 | AT88: =J88*(1+(((2-3*V88^2)/24*AH88^2)+(V88*AH88*J88/4))*1) -> 0.40797143 | ... AV88: =L88*(1+(((2-3*X88^2)/24*AJ88^2)+(X88*AJ88*L88/4))*1) -> 0.35684171
B89: 2Y | C89: =C11+$C$28*C44 -> 0.496128 | D89: =D11+$C$28*D44 -> 0.478364 | E89: =E11+$C$28*E44 -> 0.454592 | F89: =F11+$C$28*F44 -> 0.447808 | G89: =G11+$C$28*G44 -> 0.418196 | H89: =H11+$C$28*H44 -> 0.400888 | I89: =I11+$C$28*I44 -> 0.385624 | J89: =J11+$C$28*J44 -> 0.36716 | ... L89: =L11+$C$28*L44 -> 0.329392 | N89: 2Y | O89: =O11+$D$28*O44 -> -0.2822 | P89: =P11+$D$28*P44 -> -0.2598 | Q89: =Q11+$D$28*Q44 -> -0.2413 | R89: =R11+$D$28*R44 -> -0.2166 | S89: =S11+$D$28*S44 -> -0.2039 | T89: =T11+$D$28*T44 -> -0.1675 | U89: =U11+$D$28*U44 -> -0.1533 | V89: =V11+$D$28*V44 -> -0.1431 | ... X89: =X11+$D$28*X44 -> -0.1003 | Z89: 2Y | AA89: =AA11+$E$28*AA44 -> 0.7584 | AB89: =AB11+$E$28*AB44 -> 0.7313 | AC89: =AC11+$E$28*AC44 -> 0.7236 | AD89: =AD11+$E$28*AD44 -> 0.7043 | AE89: =AE11+$E$28*AE44 -> 0.6715 | AF89: =AF11+$E$28*AF44 -> 0.6497 | AG89: =AG11+$E$28*AG44 -> 0.6195 | AH89: =AH11+$E$28*AH44 -> 0.5976 | ... AJ89: =AJ11+$E$28*AJ44 -> 0.5564 | AL89: 2Y | AM89: =C89*(1+(((2-3*O89^2)/24*AA89^2)+(O89*AA89*C89/4))*2) -> 0.51166663 | AN89: =D89*(1+(((2-3*P89^2)/24*AB89^2)+(P89*AB89*D89/4))*2) -> 0.49494719 | AO89: =E89*(1+(((2-3*Q89^2)/24*AC89^2)+(Q89*AC89*E89/4))*2) -> 0.47275637 | AP89: =F89*(1+(((2-3*R89^2)/24*AD89^2)+(R89*AD89*F89/4))*2) -> 0.46692861 | AQ89: =G89*(1+(((2-3*S89^2)/24*AE89^2)+(S89*AE89*G89/4))*2) -> 0.4356916 | AR89: =H89*(1+(((2-3*T89^2)/24*AF89^2)+(T89*AF89*H89/4))*2) -> 0.41915956 | AS89: =I89*(1+(((2-3*U89^2)/24*AG89^2)+(U89*AG89*I89/4))*2) -> 0.40235906 | AT89: =J89*(1+(((2-3*V89^2)/24*AH89^2)+(V89*AH89*J89/4))*2) -> 0.38257836 | ... AV89: =L89*(1+(((2-3*X89^2)/24*AJ89^2)+(X89*AJ89*L89/4))*2) -> 0.34310362
B90: 3Y | C90: =C12+$C$28*C45 -> 0.487336 | D90: =D12+$C$28*D45 -> 0.456136 | E90: =E12+$C$28*E45 -> 0.435296 | F90: =F12+$C$28*F45 -> 0.436536 | G90: =G12+$C$28*G45 -> 0.409876 | H90: =H12+$C$28*H45 -> 0.384628 | I90: =I12+$C$28*I45 -> 0.375072 | J90: =J12+$C$28*J45 -> 0.346848 | ... L90: =L12+$C$28*L45 -> 0.330628 | N90: 3Y | O90: =O12+$D$28*O45 -> -0.2455 | P90: =P12+$D$28*P45 -> -0.2294 | Q90: =Q12+$D$28*Q45 -> -0.2187 | R90: =R12+$D$28*R45 -> -0.1971 | S90: =S12+$D$28*S45 -> -0.1817 | T90: =T12+$D$28*T45 -> -0.1501 | U90: =U12+$D$28*U45 -> -0.1355 | V90: =V12+$D$28*V45 -> -0.1111 | ... X90: =X12+$D$28*X45 -> -0.0833 | Z90: 3Y | AA90: =AA12+$E$28*AA45 -> 0.7451 | AB90: =AB12+$E$28*AB45 -> 0.7264 | AC90: =AC12+$E$28*AC45 -> 0.7015 | AD90: =AD12+$E$28*AD45 -> 0.6783 | AE90: =AE12+$E$28*AE45 -> 0.6564 | AF90: =AF12+$E$28*AF45 -> 0.6326 | AG90: =AG12+$E$28*AG45 -> 0.6001 | AH90: =AH12+$E$28*AH45 -> 0.5837 | ... AJ90: =AJ12+$E$28*AJ45 -> 0.5295 | AL90: 3Y | AM90: =C90*(1+(((2-3*O90^2)/24*AA90^2)+(O90*AA90*C90/4))*3) -> 0.51627764 | AN90: =D90*(1+(((2-3*P90^2)/24*AB90^2)+(P90*AB90*D90/4))*3) -> 0.48555441 | AO90: =E90*(1+(((2-3*Q90^2)/24*AC90^2)+(Q90*AC90*E90/4))*3) -> 0.46320389 | AP90: =F90*(1+(((2-3*R90^2)/24*AD90^2)+(R90*AD90*F90/4))*3) -> 0.46471384 | AQ90: =G90*(1+(((2-3*S90^2)/24*AE90^2)+(S90*AE90*G90/4))*3) -> 0.43681188 | AR90: =H90*(1+(((2-3*T90^2)/24*AF90^2)+(T90*AF90*H90/4))*3) -> 0.41127248 | AS90: =I90*(1+(((2-3*U90^2)/24*AG90^2)+(U90*AG90*I90/4))*3) -> 0.39933043 | AT90: =J90*(1+(((2-3*V90^2)/24*AH90^2)+(V90*AH90*J90/4))*3) -> 0.3699931 | ... AV90: =L90*(1+(((2-3*X90^2)/24*AJ90^2)+(X90*AJ90*L90/4))*3) -> 0.34994516
B91: 5Y | C91: =C13+$C$28*C46 -> 0.453116 | D91: =D13+$C$28*D46 -> 0.44036 | E91: =E13+$C$28*E46 -> 0.422652 | F91: =F13+$C$28*F46 -> 0.41326 | G91: =G13+$C$28*G46 -> 0.400756 | H91: =H13+$C$28*H46 -> 0.372608 | I91: =I13+$C$28*I46 -> 0.36464 | J91: =J13+$C$28*J46 -> 0.34832 | ... L91: =L13+$C$28*L46 -> 0.300372 | N91: 5Y | O91: =O13+$D$28*O46 -> -0.2389 | P91: =P13+$D$28*P46 -> -0.2194 | Q91: =Q13+$D$28*Q46 -> -0.2005 | R91: =R13+$D$28*R46 -> -0.1809 | S91: =S13+$D$28*S46 -> -0.1531 | T91: =T13+$D$28*T46 -> -0.1281 | U91: =U13+$D$28*U46 -> -0.1099 | V91: =V13+$D$28*V46 -> -0.0976 | ... X91: =X13+$D$28*X46 -> -0.0523 | Z91: 5Y | AA91: =AA13+$E$28*AA46 -> 0.7084 | AB91: =AB13+$E$28*AB46 -> 0.6977 | AC91: =AC13+$E$28*AC46 -> 0.6804 | AD91: =AD13+$E$28*AD46 -> 0.6556 | AE91: =AE13+$E$28*AE46 -> 0.6328 | AF91: =AF13+$E$28*AF46 -> 0.6051 | AG91: =AG13+$E$28*AG46 -> 0.5769 | AH91: =AH13+$E$28*AH46 -> 0.5669 | ... AJ91: =AJ13+$E$28*AJ46 -> 0.5227 | AL91: 5Y | AM91: =C91*(1+(((2-3*O91^2)/24*AA91^2)+(O91*AA91*C91/4))*5) -> 0.49631632 | AN91: =D91*(1+(((2-3*P91^2)/24*AB91^2)+(P91*AB91*D91/4))*5) -> 0.48612301 | AO91: =E91*(1+(((2-3*Q91^2)/24*AC91^2)+(Q91*AC91*E91/4))*5) -> 0.46880096 | AP91: =F91*(1+(((2-3*R91^2)/24*AD91^2)+(R91*AD91*F91/4))*5) -> 0.45831871 | AQ91: =G91*(1+(((2-3*S91^2)/24*AE91^2)+(S91*AE91*G91/4))*5) -> 0.44582085 | AR91: =H91*(1+(((2-3*T91^2)/24*AF91^2)+(T91*AF91*H91/4))*5) -> 0.41460206 | AS91: =I91*(1+(((2-3*U91^2)/24*AG91^2)+(U91*AG91*I91/4))*5) -> 0.4037519 | AT91: =J91*(1+(((2-3*V91^2)/24*AH91^2)+(V91*AH91*J91/4))*5) -> 0.38590468 | ... AV91: =L91*(1+(((2-3*X91^2)/24*AJ91^2)+(X91*AJ91*L91/4))*5) -> 0.33134289
B92: 10Y | C92: =C14+$C$28*C47 -> 0.454344 | D92: =D14+$C$28*D47 -> 0.425124 | E92: =E14+$C$28*E47 -> 0.407816 | F92: =F14+$C$28*F47 -> 0.400688 | G92: =G14+$C$28*G47 -> 0.378568 | H92: =H14+$C$28*H47 -> 0.349904 | I92: =I14+$C$28*I47 -> 0.330832 | J92: =J14+$C$28*J47 -> 0.313528 | ... L92: =L14+$C$28*L47 -> 0.291648 | N92: 10Y | O92: =O14+$D$28*O47 -> -0.221 | P92: =P14+$D$28*P47 -> -0.1879 | Q92: =Q14+$D$28*Q47 -> -0.1654 | R92: =R14+$D$28*R47 -> -0.1524 | S92: =S14+$D$28*S47 -> -0.1391 | T92: =T14+$D$28*T47 -> -0.1157 | U92: =U14+$D$28*U47 -> -0.1046 | V92: =V14+$D$28*V47 -> -0.0875 | ... X92: =X14+$D$28*X47 -> -0.0359 | Z92: 10Y | AA92: =AA14+$E$28*AA47 -> 0.695 | AB92: =AB14+$E$28*AB47 -> 0.6809 | AC92: =AC14+$E$28*AC47 -> 0.6487 | AD92: =AD14+$E$28*AD47 -> 0.6352 | AE92: =AE14+$E$28*AE47 -> 0.6121 | AF92: =AF14+$E$28*AF47 -> 0.5776 | AG92: =AG14+$E$28*AG47 -> 0.5561 | AH92: =AH14+$E$28*AH47 -> 0.5347 | ... AJ92: =AJ14+$E$28*AJ47 -> 0.4962 | AL92: 10Y | AM92: =C92*(1+(((2-3*O92^2)/24*AA92^2)+(O92*AA92*C92/4))*10) -> 0.5445627 | AN92: =D92*(1+(((2-3*P92^2)/24*AB92^2)+(P92*AB92*D92/4))*10) -> 0.52286671 | AO92: =E92*(1+(((2-3*Q92^2)/24*AC92^2)+(Q92*AC92*E92/4))*10) -> 0.50034726 | AP92: =F92*(1+(((2-3*R92^2)/24*AD92^2)+(R92*AD92*F92/4))*10) -> 0.49186362 | AQ92: =G92*(1+(((2-3*S92^2)/24*AE92^2)+(S92*AE92*G92/4))*10) -> 0.46282935 | AR92: =H92*(1+(((2-3*T92^2)/24*AF92^2)+(T92*AF92*H92/4))*10) -> 0.42477536 | AS92: =I92*(1+(((2-3*U92^2)/24*AG92^2)+(U92*AG92*I92/4))*10) -> 0.39877396 | AT92: =J92*(1+(((2-3*V92^2)/24*AH92^2)+(V92*AH92*J92/4))*10) -> 0.37587154 | ... AV92: =L92*(1+(((2-3*X92^2)/24*AJ92^2)+(X92*AJ92*L92/4))*10) -> 0.34758428
B93: 20Y | C93: =C15+$C$28*C48 -> 0.42228 | D93: =D15+$C$28*D48 -> 0.407652 | E93: =E15+$C$28*E48 -> 0.384568 | F93: =F15+$C$28*F48 -> 0.382532 | G93: =G15+$C$28*G48 -> 0.353124 | H93: =H15+$C$28*H48 -> 0.337984 | I93: =I15+$C$28*I48 -> 0.322656 | J93: =J15+$C$28*J48 -> 0.311172 | ... L93: =L15+$C$28*L48 -> 0.2768 | N93: 20Y | O93: =O15+$D$28*O48 -> -0.1944 | P93: =P15+$D$28*P48 -> -0.1744 | Q93: =Q15+$D$28*Q48 -> -0.1551 | R93: =R15+$D$28*R48 -> -0.1457 | S93: =S15+$D$28*S48 -> -0.1179 | T93: =T15+$D$28*T48 -> -0.1036 | U93: =U15+$D$28*U48 -> -0.0877 | V93: =V15+$D$28*V48 -> -0.0523 | ... X93: =X15+$D$28*X48 -> -0.02 | Z93: 20Y | AA93: =AA15+$E$28*AA48 -> 0.6767 | AB93: =AB15+$E$28*AB48 -> 0.6511 | AC93: =AC15+$E$28*AC48 -> 0.6243 | AD93: =AD15+$E$28*AD48 -> 0.6059 | AE93: =AE15+$E$28*AE48 -> 0.5844 | AF93: =AF15+$E$28*AF48 -> 0.5668 | AG93: =AG15+$E$28*AG48 -> 0.531 | AH93: =AH15+$E$28*AH48 -> 0.5179 | ... AJ93: =AJ15+$E$28*AJ48 -> 0.4678 | AL93: 20Y | AM93: =C93*(1+(((2-3*O93^2)/24*AA93^2)+(O93*AA93*C93/4))*20) -> 0.60900601 | AN93: =D93*(1+(((2-3*P93^2)/24*AB93^2)+(P93*AB93*D93/4))*20) -> 0.58818835 | AO93: =E93*(1+(((2-3*Q93^2)/24*AC93^2)+(Q93*AC93*E93/4))*20) -> 0.55376177 | AP93: =F93*(1+(((2-3*R93^2)/24*AD93^2)+(R93*AD93*F93/4))*20) -> 0.5445442 | AQ93: =G93*(1+(((2-3*S93^2)/24*AE93^2)+(S93*AE93*G93/4))*20) -> 0.50697474 | AR93: =H93*(1+(((2-3*T93^2)/24*AF93^2)+(T93*AF93*H93/4))*20) -> 0.48250052 | AS93: =I93*(1+(((2-3*U93^2)/24*AG93^2)+(U93*AG93*I93/4))*20) -> 0.44829342 | AT93: =J93*(1+(((2-3*V93^2)/24*AH93^2)+(V93*AH93*J93/4))*20) -> 0.43659223 | ... AV93: =L93*(1+(((2-3*X93^2)/24*AJ93^2)+(X93*AJ93*L93/4))*20) -> 0.37411195
B94: 30Y | C94: =C16+$C$28*C49 -> 0.414544 | D94: =D16+$C$28*D49 -> 0.392236 | E94: =E16+$C$28*E49 -> 0.375028 | F94: =F16+$C$28*F49 -> 0.361584 | G94: =G16+$C$28*G49 -> 0.34658 | H94: =H16+$C$28*H49 -> 0.319808 | I94: =I16+$C$28*I49 -> 0.305372 | J94: =J16+$C$28*J49 -> 0.2852 | ... L94: =L16+$C$28*L49 -> 0.2557 | N94: 30Y | O94: =O16+$D$28*O49 -> -0.176 | P94: =P16+$D$28*P49 -> -0.1549 | Q94: =Q16+$D$28*Q49 -> -0.1366 | R94: =R16+$D$28*R49 -> -0.1078 | S94: =S16+$D$28*S49 -> -0.0932 | T94: =T16+$D$28*T49 -> -0.0702 | U94: =U16+$D$28*U49 -> -0.0495 | V94: =V16+$D$28*V49 -> -0.0437 | ... X94: =X16+$D$28*X49 -> 0.0089 | Z94: 30Y | AA94: =AA16+$E$28*AA49 -> 0.6568 | AB94: =AB16+$E$28*AB49 -> 0.6205 | AC94: =AC16+$E$28*AC49 -> 0.598 | AD94: =AD16+$E$28*AD49 -> 0.5822 | AE94: =AE16+$E$28*AE49 -> 0.5526 | AF94: =AF16+$E$28*AF49 -> 0.5337 | AG94: =AG16+$E$28*AG49 -> 0.5081 | AH94: =AH16+$E$28*AH49 -> 0.4978 | ... AJ94: =AJ16+$E$28*AJ49 -> 0.4579 | AL94: 30Y | AM94: =C94*(1+(((2-3*O94^2)/24*AA94^2)+(O94*AA94*C94/4))*30) -> 0.69185573 | AN94: =D94*(1+(((2-3*P94^2)/24*AB94^2)+(P94*AB94*D94/4))*30) -> 0.64529016 | AO94: =E94*(1+(((2-3*Q94^2)/24*AC94^2)+(Q94*AC94*E94/4))*30) -> 0.61475564 | AP94: =F94*(1+(((2-3*R94^2)/24*AD94^2)+(R94*AD94*F94/4))*30) -> 0.60110456 | AQ94: =G94*(1+(((2-3*S94^2)/24*AE94^2)+(S94*AE94*G94/4))*30) -> 0.56132011 | AR94: =H94*(1+(((2-3*T94^2)/24*AF94^2)+(T94*AF94*H94/4))*30) -> 0.51711725 | AS94: =I94*(1+(((2-3*U94^2)/24*AG94^2)+(U94*AG94*I94/4))*30) -> 0.48414865 | AT94: =J94*(1+(((2-3*V94^2)/24*AH94^2)+(V94*AH94*J94/4))*30) -> 0.44810795 | ... AV94: =L94*(1+(((2-3*X94^2)/24*AJ94^2)+(X94*AJ94*L94/4))*30) -> 0.39171557
A96: SCENARIO 4
B97: Param: ATM | N97: Param: RHO | Z97: Param: NU | AL97: Combined Effective ATM Vol (Hagan approx, beta=1)
B98: Expiry \ Tenor | C98: 1M | D98: 3M | E98: 6M | F98: 1Y | G98: 2Y | H98: 3Y | I98: 5Y | J98: 10Y | K98: 20Y | L98: 30Y | N98: Expiry \ Tenor | O98: 1M | P98: 3M | Q98: 6M | R98: 1Y | S98: 2Y | T98: 3Y | U98: 5Y | V98: 10Y | W98: 20Y | X98: 30Y | Z98: Expiry \ Tenor | AA98: 1M | AB98: 3M | AC98: 6M | AD98: 1Y | AE98: 2Y | AF98: 3Y | AG98: 5Y | AH98: 10Y | AI98: 20Y | AJ98: 30Y | AL98: Expiry \ Tenor | AM98: 1M | AN98: 3M | AO98: 6M | AP98: 1Y | AQ98: 2Y | AR98: 3Y | AS98: 5Y | AT98: 10Y | AU98: 20Y | AV98: 30Y
B99: 1M | C99: =C7+$C$29*C40 -> 0.5793205 | D99: =D7+$C$29*D40 -> 0.557519 | E99: =E7+$C$29*E40 -> 0.54881 | F99: =F7+$C$29*F40 -> 0.51887 | G99: =G7+$C$29*G40 -> 0.5094585 | H99: =H7+$C$29*H40 -> 0.4873085 | I99: =I7+$C$29*I40 -> 0.463545 | J99: =J7+$C$29*J40 -> 0.454 | ... L99: =L7+$C$29*L40 -> 0.415141 | N99: 1M | O99: =O7+$D$29*O40 -> -0.3586 | P99: =P7+$D$29*P40 -> -0.3387 | Q99: =Q7+$D$29*Q40 -> -0.3126 | R99: =R7+$D$29*R40 -> -0.2851 | S99: =S7+$D$29*S40 -> -0.2797 | T99: =T7+$D$29*T40 -> -0.2583 | U99: =U7+$D$29*U40 -> -0.2308 | V99: =V7+$D$29*V40 -> -0.2049 | ... X99: =X7+$D$29*X40 -> -0.1771 | Z99: 1M | AA99: =AA7+$E$29*AA40 -> 0.8595 | AB99: =AB7+$E$29*AB40 -> 0.8187 | AC99: =AC7+$E$29*AC40 -> 0.8127 | AD99: =AD7+$E$29*AD40 -> 0.7791 | AE99: =AE7+$E$29*AE40 -> 0.754 | AF99: =AF7+$E$29*AF40 -> 0.7312 | AG99: =AG7+$E$29*AG40 -> 0.7128 | AH99: =AH7+$E$29*AH40 -> 0.7008 | ... AJ99: =AJ7+$E$29*AJ40 -> 0.6516 | AL99: 1M | AM99: =C99*(1+(((2-3*O99^2)/24*AA99^2)+(O99*AA99*C99/4))*0.0833333333333333) -> 0.5795642 | AN99: =D99*(1+(((2-3*P99^2)/24*AB99^2)+(P99*AB99*D99/4))*0.0833333333333333) -> 0.55787187 | AO99: =E99*(1+(((2-3*Q99^2)/24*AC99^2)+(Q99*AC99*E99/4))*0.0833333333333333) -> 0.54936412 | AP99: =F99*(1+(((2-3*R99^2)/24*AD99^2)+(R99*AD99*F99/4))*0.0833333333333333) -> 0.51954465 | AQ99: =G99*(1+(((2-3*S99^2)/24*AE99^2)+(S99*AE99*G99/4))*0.0833333333333333) -> 0.51009347 | AR99: =H99*(1+(((2-3*T99^2)/24*AF99^2)+(T99*AF99*H99/4))*0.0833333333333333) -> 0.48800235 | AS99: =I99*(1+(((2-3*U99^2)/24*AG99^2)+(U99*AG99*I99/4))*0.0833333333333333) -> 0.46431341 | AT99: =J99*(1+(((2-3*V99^2)/24*AH99^2)+(V99*AH99*J99/4))*0.0833333333333333) -> 0.45483428 | ... AV99: =L99*(1+(((2-3*X99^2)/24*AJ99^2)+(X99*AJ99*L99/4))*0.0833333333333333) -> 0.41589312
B100: 3M | C100: =C8+$C$29*C41 -> 0.5668295 | D100: =D8+$C$29*D41 -> 0.542882 | E100: =E8+$C$29*E41 -> 0.5279985 | F100: =F8+$C$29*F41 -> 0.499487 | G100: =G8+$C$29*G41 -> 0.481803 | H100: =H8+$C$29*H41 -> 0.465707 | I100: =I8+$C$29*I41 -> 0.4572155 | J100: =J8+$C$29*J41 -> 0.4330965 | ... L100: =L8+$C$29*L41 -> 0.3997805 | N100: 3M | O100: =O8+$D$29*O41 -> -0.3315 | P100: =P8+$D$29*P41 -> -0.3151 | Q100: =Q8+$D$29*Q41 -> -0.2858 | R100: =R8+$D$29*R41 -> -0.2682 | S100: =S8+$D$29*S41 -> -0.2579 | T100: =T8+$D$29*T41 -> -0.2318 | U100: =U8+$D$29*U41 -> -0.2134 | V100: =V8+$D$29*V41 -> -0.1869 | ... X100: =X8+$D$29*X41 -> -0.1598 | Z100: 3M | AA100: =AA8+$E$29*AA41 -> 0.8374 | AB100: =AB8+$E$29*AB41 -> 0.7979 | AC100: =AC8+$E$29*AC41 -> 0.7817 | AD100: =AD8+$E$29*AD41 -> 0.7663 | AE100: =AE8+$E$29*AE41 -> 0.7319 | AF100: =AF8+$E$29*AF41 -> 0.7164 | AG100: =AG8+$E$29*AG41 -> 0.6852 | AH100: =AH8+$E$29*AH41 -> 0.6756 | ... AJ100: =AJ8+$E$29*AJ41 -> 0.6292 | AL100: 3M | AM100: =C100*(1+(((2-3*O100^2)/24*AA100^2)+(O100*AA100*C100/4))*0.25) -> 0.56817094 | AN100: =D100*(1+(((2-3*P100^2)/24*AB100^2)+(P100*AB100*D100/4))*0.25) -> 0.54437896 | AO100: =E100*(1+(((2-3*Q100^2)/24*AC100^2)+(Q100*AC100*E100/4))*0.25) -> 0.53000387 | AP100: =F100*(1+(((2-3*R100^2)/24*AD100^2)+(R100*AD100*F100/4))*0.25) -> 0.50173355 | AQ100: =G100*(1+(((2-3*S100^2)/24*AE100^2)+(S100*AE100*G100/4))*0.25) -> 0.48390489 | AR100: =H100*(1+(((2-3*T100^2)/24*AF100^2)+(T100*AF100*H100/4))*0.25) -> 0.46803414 | AS100: =I100*(1+(((2-3*U100^2)/24*AG100^2)+(U100*AG100*I100/4))*0.25) -> 0.4594717 | AT100: =J100*(1+(((2-3*V100^2)/24*AH100^2)+(V100*AH100*J100/4))*0.25) -> 0.43551876 | ... AV100: =L100*(1+(((2-3*X100^2)/24*AJ100^2)+(X100*AJ100*L100/4))*0.25) -> 0.40194714
B101: 6M | C101: =C9+$C$29*C42 -> 0.552695 | D101: =D9+$C$29*D42 -> 0.5232165 | E101: =E9+$C$29*E42 -> 0.5131325 | F101: =F9+$C$29*F42 -> 0.492134 | G101: =G9+$C$29*G42 -> 0.4739245 | H101: =H9+$C$29*H42 -> 0.452262 | I101: =I9+$C$29*I42 -> 0.441007 | J101: =J9+$C$29*J42 -> 0.425259 | ... L101: =L9+$C$29*L42 -> 0.382118 | N101: 6M | O101: =O9+$D$29*O42 -> -0.3199 | P101: =P9+$D$29*P42 -> -0.2876 | Q101: =Q9+$D$29*Q42 -> -0.2693 | R101: =R9+$D$29*R42 -> -0.2429 | S101: =S9+$D$29*S42 -> -0.2269 | T101: =T9+$D$29*T42 -> -0.2182 | U101: =U9+$D$29*U42 -> -0.1967 | V101: =V9+$D$29*V42 -> -0.1716 | ... X101: =X9+$D$29*X42 -> -0.1369 | Z101: 6M | AA101: =AA9+$E$29*AA42 -> 0.7989 | AB101: =AB9+$E$29*AB42 -> 0.7757 | AC101: =AC9+$E$29*AC42 -> 0.7523 | AD101: =AD9+$E$29*AD42 -> 0.7443 | AE101: =AE9+$E$29*AE42 -> 0.7093 | AF101: =AF9+$E$29*AF42 -> 0.6894 | AG101: =AG9+$E$29*AG42 -> 0.67 | AH101: =AH9+$E$29*AH42 -> 0.6574 | ... AJ101: =AJ9+$E$29*AJ42 -> 0.6045 | AL101: 6M | AM101: =C101*(1+(((2-3*O101^2)/24*AA101^2)+(O101*AA101*C101/4))*0.5) -> 0.55537822 | AN101: =D101*(1+(((2-3*P101^2)/24*AB101^2)+(P101*AB101*D101/4))*0.5) -> 0.52707262 | AO101: =E101*(1+(((2-3*Q101^2)/24*AC101^2)+(Q101*AC101*E101/4))*0.5) -> 0.51724858 | AP101: =F101*(1+(((2-3*R101^2)/24*AD101^2)+(R101*AD101*F101/4))*0.5) -> 0.49701505 | AQ101: =G101*(1+(((2-3*S101^2)/24*AE101^2)+(S101*AE101*G101/4))*0.5) -> 0.47857357 | AR101: =H101*(1+(((2-3*T101^2)/24*AF101^2)+(T101*AF101*H101/4))*0.5) -> 0.45673247 | AS101: =I101*(1+(((2-3*U101^2)/24*AG101^2)+(U101*AG101*I101/4))*0.5) -> 0.44557304 | AT101: =J101*(1+(((2-3*V101^2)/24*AH101^2)+(V101*AH101*J101/4))*0.5) -> 0.43002838 | ... AV101: =L101*(1+(((2-3*X101^2)/24*AJ101^2)+(X101*AJ101*L101/4))*0.5) -> 0.38626206
B102: 1Y | C102: =C10+$C$29*C43 -> 0.5277525 | D102: =D10+$C$29*D43 -> 0.516215 | E102: =E10+$C$29*E43 -> 0.497249 | F102: =F10+$C$29*F43 -> 0.4793375 | G102: =G10+$C$29*G43 -> 0.4483135 | H102: =H10+$C$29*H43 -> 0.4327325 | I102: =I10+$C$29*I43 -> 0.412903 | J102: =J10+$C$29*J43 -> 0.404817 | ... L102: =L10+$C$29*L43 -> 0.3532705 | N102: 1Y | O102: =O10+$D$29*O43 -> -0.2981 | P102: =P10+$D$29*P43 -> -0.2776 | Q102: =Q10+$D$29*Q43 -> -0.2581 | R102: =R10+$D$29*R43 -> -0.2336 | S102: =S10+$D$29*S43 -> -0.2121 | T102: =T10+$D$29*T43 -> -0.1992 | U102: =U10+$D$29*U43 -> -0.1849 | V102: =V10+$D$29*V43 -> -0.1572 | ... X102: =X10+$D$29*X43 -> -0.1153 | Z102: 1Y | AA102: =AA10+$E$29*AA43 -> 0.7924 | AB102: =AB10+$E$29*AB43 -> 0.7649 | AC102: =AC10+$E$29*AC43 -> 0.7392 | AD102: =AD10+$E$29*AD43 -> 0.719 | AE102: =AE10+$E$29*AE43 -> 0.698 | AF102: =AF10+$E$29*AF43 -> 0.6633 | AG102: =AG10+$E$29*AG43 -> 0.658 | AH102: =AH10+$E$29*AH43 -> 0.6334 | ... AJ102: =AJ10+$E$29*AJ43 -> 0.5893 | AL102: 1Y | AM102: =C102*(1+(((2-3*O102^2)/24*AA102^2)+(O102*AA102*C102/4))*1) -> 0.53523839 | AN102: =D102*(1+(((2-3*P102^2)/24*AB102^2)+(P102*AB102*D102/4))*1) -> 0.52432855 | AO102: =E102*(1+(((2-3*Q102^2)/24*AC102^2)+(Q102*AC102*E102/4))*1) -> 0.50583525 | AP102: =F102*(1+(((2-3*R102^2)/24*AD102^2)+(R102*AD102*F102/4))*1) -> 0.48864942 | AQ102: =G102*(1+(((2-3*S102^2)/24*AE102^2)+(S102*AE102*G102/4))*1) -> 0.45784819 | AR102: =H102*(1+(((2-3*T102^2)/24*AF102^2)+(T102*AF102*H102/4))*1) -> 0.44146827 | AS102: =I102*(1+(((2-3*U102^2)/24*AG102^2)+(U102*AG102*I102/4))*1) -> 0.4218511 | AT102: =J102*(1+(((2-3*V102^2)/24*AH102^2)+(V102*AH102*J102/4))*1) -> 0.41377023 | ... AV102: =L102*(1+(((2-3*X102^2)/24*AJ102^2)+(X102*AJ102*L102/4))*1) -> 0.36117019
B103: 2Y | C103: =C11+$C$29*C44 -> 0.506702 | D103: =D11+$C$29*D44 -> 0.4881135 | E103: =E11+$C$29*E44 -> 0.4634405 | F103: =F11+$C$29*F44 -> 0.456172 | G103: =G11+$C$29*G44 -> 0.425489 | H103: =H11+$C$29*H44 -> 0.4076795 | I103: =I11+$C$29*I44 -> 0.3913785 | J103: =J11+$C$29*J44 -> 0.3723025 | ... L103: =L11+$C$29*L44 -> 0.332928 | N103: 2Y | O103: =O11+$D$29*O44 -> -0.2822 | P103: =P11+$D$29*P44 -> -0.2598 | Q103: =Q11+$D$29*Q44 -> -0.2413 | R103: =R11+$D$29*R44 -> -0.2166 | S103: =S11+$D$29*S44 -> -0.2039 | T103: =T11+$D$29*T44 -> -0.1675 | U103: =U11+$D$29*U44 -> -0.1533 | V103: =V11+$D$29*V44 -> -0.1431 | ... X103: =X11+$D$29*X44 -> -0.1003 | Z103: 2Y | AA103: =AA11+$E$29*AA44 -> 0.7584 | AB103: =AB11+$E$29*AB44 -> 0.7313 | AC103: =AC11+$E$29*AC44 -> 0.7236 | AD103: =AD11+$E$29*AD44 -> 0.7043 | AE103: =AE11+$E$29*AE44 -> 0.6715 | AF103: =AF11+$E$29*AF44 -> 0.6497 | AG103: =AG11+$E$29*AG44 -> 0.6195 | AH103: =AH11+$E$29*AH44 -> 0.5976 | ... AJ103: =AJ11+$E$29*AJ44 -> 0.5564 | AL103: 2Y | AM103: =C103*(1+(((2-3*O103^2)/24*AA103^2)+(O103*AA103*C103/4))*2) -> 0.52199845 | AN103: =D103*(1+(((2-3*P103^2)/24*AB103^2)+(P103*AB103*D103/4))*2) -> 0.5045826 | AO103: =E103*(1+(((2-3*Q103^2)/24*AC103^2)+(Q103*AC103*E103/4))*2) -> 0.48160043 | AP103: =F103*(1+(((2-3*R103^2)/24*AD103^2)+(R103*AD103*F103/4))*2) -> 0.47535872 | AQ103: =G103*(1+(((2-3*S103^2)/24*AE103^2)+(S103*AE103*G103/4))*2) -> 0.44307728 | AR103: =H103*(1+(((2-3*T103^2)/24*AF103^2)+(T103*AF103*H103/4))*2) -> 0.42610994 | AS103: =I103*(1+(((2-3*U103^2)/24*AG103^2)+(U103*AG103*I103/4))*2) -> 0.40825635 | AT103: =J103*(1+(((2-3*V103^2)/24*AH103^2)+(V103*AH103*J103/4))*2) -> 0.38785494 | ... AV103: =L103*(1+(((2-3*X103^2)/24*AJ103^2)+(X103*AJ103*L103/4))*2) -> 0.34675396
B104: 3Y | C104: =C12+$C$29*C45 -> 0.497349 | D104: =D12+$C$29*D45 -> 0.465299 | E104: =E12+$C$29*E45 -> 0.443439 | F104: =F12+$C$29*F45 -> 0.4442115 | G104: =G12+$C$29*G45 -> 0.4164465 | H104: =H12+$C$29*H45 -> 0.390527 | I104: =I12+$C$29*I45 -> 0.3804355 | J104: =J12+$C$29*J45 -> 0.3513445 | ... L104: =L12+$C$29*L45 -> 0.3337645 | N104: 3Y | O104: =O12+$D$29*O45 -> -0.2455 | P104: =P12+$D$29*P45 -> -0.2294 | Q104: =Q12+$D$29*Q45 -> -0.2187 | R104: =R12+$D$29*R45 -> -0.1971 | S104: =S12+$D$29*S45 -> -0.1817 | T104: =T12+$D$29*T45 -> -0.1501 | U104: =U12+$D$29*U45 -> -0.1355 | V104: =V12+$D$29*V45 -> -0.1111 | ... X104: =X12+$D$29*X45 -> -0.0833 | Z104: 3Y | AA104: =AA12+$E$29*AA45 -> 0.7451 | AB104: =AB12+$E$29*AB45 -> 0.7264 | AC104: =AC12+$E$29*AC45 -> 0.7015 | AD104: =AD12+$E$29*AD45 -> 0.6783 | AE104: =AE12+$E$29*AE45 -> 0.6564 | AF104: =AF12+$E$29*AF45 -> 0.6326 | AG104: =AG12+$E$29*AG45 -> 0.6001 | AH104: =AH12+$E$29*AH45 -> 0.5837 | ... AJ104: =AJ12+$E$29*AJ45 -> 0.5295 | AL104: 3Y | AM104: =C104*(1+(((2-3*O104^2)/24*AA104^2)+(O104*AA104*C104/4))*3) -> 0.52620208 | AN104: =D104*(1+(((2-3*P104^2)/24*AB104^2)+(P104*AB104*D104/4))*3) -> 0.49477553 | AO104: =E104*(1+(((2-3*Q104^2)/24*AC104^2)+(Q104*AC104*E104/4))*3) -> 0.47145348 | AP104: =F104*(1+(((2-3*R104^2)/24*AD104^2)+(R104*AD104*F104/4))*3) -> 0.47254291 | AQ104: =G104*(1+(((2-3*S104^2)/24*AE104^2)+(S104*AE104*G104/4))*3) -> 0.44356942 | AR104: =H104*(1+(((2-3*T104^2)/24*AF104^2)+(T104*AF104*H104/4))*3) -> 0.41741607 | AS104: =I104*(1+(((2-3*U104^2)/24*AG104^2)+(U104*AG104*I104/4))*3) -> 0.40491638 | AT104: =J104*(1+(((2-3*V104^2)/24*AH104^2)+(V104*AH104*J104/4))*3) -> 0.37471282 | ... AV104: =L104*(1+(((2-3*X104^2)/24*AJ104^2)+(X104*AJ104*L104/4))*3) -> 0.35323028
B105: 5Y | C105: =C13+$C$29*C46 -> 0.4619815 | D105: =D13+$C$29*D46 -> 0.4484775 | E105: =E13+$C$29*E46 -> 0.430268 | F105: =F13+$C$29*F46 -> 0.41989 | G105: =G13+$C$29*G46 -> 0.406604 | H105: =H13+$C$29*H46 -> 0.377572 | I105: =I13+$C$29*I46 -> 0.3688475 | J105: =J13+$C$29*J46 -> 0.3520175 | ... L105: =L13+$C$29*L46 -> 0.302548 | N105: 5Y | O105: =O13+$D$29*O46 -> -0.2389 | P105: =P13+$D$29*P46 -> -0.2194 | Q105: =Q13+$D$29*Q46 -> -0.2005 | R105: =R13+$D$29*R46 -> -0.1809 | S105: =S13+$D$29*S46 -> -0.1531 | T105: =T13+$D$29*T46 -> -0.1281 | U105: =U13+$D$29*U46 -> -0.1099 | V105: =V13+$D$29*V46 -> -0.0976 | ... X105: =X13+$D$29*X46 -> -0.0523 | Z105: 5Y | AA105: =AA13+$E$29*AA46 -> 0.7084 | AB105: =AB13+$E$29*AB46 -> 0.6977 | AC105: =AC13+$E$29*AC46 -> 0.6804 | AD105: =AD13+$E$29*AD46 -> 0.6556 | AE105: =AE13+$E$29*AE46 -> 0.6328 | AF105: =AF13+$E$29*AF46 -> 0.6051 | AG105: =AG13+$E$29*AG46 -> 0.5769 | AH105: =AH13+$E$29*AH46 -> 0.5669 | ... AJ105: =AJ13+$E$29*AJ46 -> 0.5227 | AL105: 5Y | AM105: =C105*(1+(((2-3*O105^2)/24*AA105^2)+(O105*AA105*C105/4))*5) -> 0.50516064 | AN105: =D105*(1+(((2-3*P105^2)/24*AB105^2)+(P105*AB105*D105/4))*5) -> 0.4943875 | AO105: =E105*(1+(((2-3*Q105^2)/24*AC105^2)+(Q105*AC105*E105/4))*5) -> 0.47668974 | AP105: =F105*(1+(((2-3*R105^2)/24*AD105^2)+(R105*AD105*F105/4))*5) -> 0.46525889 | AQ105: =G105*(1+(((2-3*S105^2)/24*AE105^2)+(S105*AE105*G105/4))*5) -> 0.45203849 | AR105: =H105*(1+(((2-3*T105^2)/24*AF105^2)+(T105*AF105*H105/4))*5) -> 0.41994391 | AS105: =I105*(1+(((2-3*U105^2)/24*AG105^2)+(U105*AG105*I105/4))*5) -> 0.40828771 | AT105: =J105*(1+(((2-3*V105^2)/24*AH105^2)+(V105*AH105*J105/4))*5) -> 0.38991113 | ... AV105: =L105*(1+(((2-3*X105^2)/24*AJ105^2)+(X105*AJ105*L105/4))*5) -> 0.33372076
B106: 10Y | C106: =C14+$C$29*C47 -> 0.462521 | D106: =D14+$C$29*D47 -> 0.4325785 | E106: =E14+$C$29*E47 -> 0.414769 | F106: =F14+$C$29*F47 -> 0.4066295 | G106: =G14+$C$29*G47 -> 0.383787 | H106: =H14+$C$29*H47 -> 0.354511 | I106: =I14+$C$29*I47 -> 0.3343255 | J106: =J14+$C$29*J47 -> 0.3162395 | ... L106: =L14+$C$29*L47 -> 0.2931695 | N106: 10Y | O106: =O14+$D$29*O47 -> -0.221 | P106: =P14+$D$29*P47 -> -0.1879 | Q106: =Q14+$D$29*Q47 -> -0.1654 | R106: =R14+$D$29*R47 -> -0.1524 | S106: =S14+$D$29*S47 -> -0.1391 | T106: =T14+$D$29*T47 -> -0.1157 | U106: =U14+$D$29*U47 -> -0.1046 | V106: =V14+$D$29*V47 -> -0.0875 | ... X106: =X14+$D$29*X47 -> -0.0359 | Z106: 10Y | AA106: =AA14+$E$29*AA47 -> 0.695 | AB106: =AB14+$E$29*AB47 -> 0.6809 | AC106: =AC14+$E$29*AC47 -> 0.6487 | AD106: =AD14+$E$29*AD47 -> 0.6352 | AE106: =AE14+$E$29*AE47 -> 0.6121 | AF106: =AF14+$E$29*AF47 -> 0.5776 | AG106: =AG14+$E$29*AG47 -> 0.5561 | AH106: =AH14+$E$29*AH47 -> 0.5347 | ... AJ106: =AJ14+$E$29*AJ47 -> 0.4962 | AL106: 10Y | AM106: =C106*(1+(((2-3*O106^2)/24*AA106^2)+(O106*AA106*C106/4))*10) -> 0.55291114 | AN106: =D106*(1+(((2-3*P106^2)/24*AB106^2)+(P106*AB106*D106/4))*10) -> 0.5310037 | AO106: =E106*(1+(((2-3*Q106^2)/24*AC106^2)+(Q106*AC106*E106/4))*10) -> 0.50810429 | AP106: =F106*(1+(((2-3*R106^2)/24*AD106^2)+(R106*AD106*F106/4))*10) -> 0.4985724 | AQ106: =G106*(1+(((2-3*S106^2)/24*AE106^2)+(S106*AE106*G106/4))*10) -> 0.46878364 | AR106: =H106*(1+(((2-3*T106^2)/24*AF106^2)+(T106*AF106*H106/4))*10) -> 0.43009529 | AS106: =I106*(1+(((2-3*U106^2)/24*AG106^2)+(U106*AG106*I106/4))*10) -> 0.40281507 | AT106: =J106*(1+(((2-3*V106^2)/24*AH106^2)+(V106*AH106*J106/4))*10) -> 0.37902192 | ... AV106: =L106*(1+(((2-3*X106^2)/24*AJ106^2)+(X106*AJ106*L106/4))*10) -> 0.34937773
